Workbook
Name Prix_Base_Primera: 'Lot 4 - BPU Drom-Com'!$AC$1111
Name Prix_Base_Primera: 'Lot 4 - BPU Location'!$AA$1111
Name Prix_Base_Primera: 'Lot 4 - Bordereau de prix'!$AC$1112
Name Prix_Cache_HF20: 'Lot 4 - BPU Drom-Com'!$AC$1091
Name Prix_Cache_HF20: 'Lot 4 - BPU Location'!$AA$1091
Name Prix_Cache_HF20: 'Lot 4 - Bordereau de prix'!$AC$1092
Name Prix_Cache_HF20H: 'Lot 4 - BPU Drom-Com'!$AC$1074
Name Prix_Cache_HF20H: 'Lot 4 - BPU Location'!$AA$1074
Name Prix_Cache_HF20H: 'Lot 4 - Bordereau de prix'!$AC$1075
Name Prix_Cache_HF40: 'Lot 4 - BPU Drom-Com'!$AC$1030
Name Prix_Cache_HF40: 'Lot 4 - BPU Location'!$AA$1030
Name Prix_Cache_HF40: 'Lot 4 - Bordereau de prix'!$AC$1031
Name Prix_chassis_A6010: 'Lot 4 - BPU Drom-Com'!$O$1056
Name Prix_chassis_A6010: 'Lot 4 - BPU Location'!$O$1056
Name Prix_chassis_A6010: 'Lot 4 - Bordereau de prix'!$O$1057
Name Prix_Chassis_HF20: 'Lot 4 - BPU Drom-Com'!$AC$1017
Name Prix_Chassis_HF20: 'Lot 4 - BPU Location'!$AA$1017
Name Prix_Chassis_HF20: 'Lot 4 - Bordereau de prix'!$AC$1018
Name Prix_chassis_HF40: 'Lot 4 - BPU Drom-Com'!$AC$1029
Name Prix_chassis_HF40: 'Lot 4 - BPU Location'!$AA$1029
Name Prix_chassis_HF40: 'Lot 4 - Bordereau de prix'!$AC$1030
Name Prix_Ctrl_A9K: 'Lot 4 - BPU Drom-Com'!$AC$1073
Name Prix_Ctrl_A9K: 'Lot 4 - BPU Location'!$AA$1073
Name Prix_Ctrl_A9K: 'Lot 4 - Bordereau de prix'!$AC$1074
Name Prix_Ctrl_Primera: 'Lot 4 - BPU Drom-Com'!$AC$1043
Name Prix_Ctrl_Primera: 'Lot 4 - BPU Location'!$AA$1043
Name Prix_Ctrl_Primera: 'Lot 4 - Bordereau de prix'!$AC$1044
Name Prix_diques_23TB_A6k: 'Lot 4 - BPU Drom-Com'!$AC$1060
Name Prix_diques_23TB_A6k: 'Lot 4 - BPU Location'!$AA$1060
Name Prix_diques_23TB_A6k: 'Lot 4 - Bordereau de prix'!$AC$1061
Name Prix_Disques_21TB_HF20: 'Lot 4 - BPU Drom-Com'!$AC$1018
Name Prix_Disques_21TB_HF20: 'Lot 4 - BPU Location'!$AA$1018
Name Prix_Disques_21TB_HF20: 'Lot 4 - Bordereau de prix'!$AC$1019
Name Prix_Disques_42TB_HF40: 'Lot 4 - BPU Drom-Com'!$AC$1032
Name Prix_Disques_42TB_HF40: 'Lot 4 - BPU Location'!$AA$1032
Name Prix_Disques_42TB_HF40: 'Lot 4 - Bordereau de prix'!$AC$1033
Name Prix_Power_Alletra6k: 'Lot 4 - BPU Drom-Com'!$AC$1062
Name Prix_Power_Alletra6k: 'Lot 4 - BPU Location'!$AA$1062
Name Prix_Power_Alletra6k: 'Lot 4 - Bordereau de prix'!$AC$1063
Name Prix_SSD_Primera: 'Lot 4 - BPU Drom-Com'!$AC$1044
Name Prix_SSD_Primera: 'Lot 4 - BPU Location'!$AA$1044
Name Prix_SSD_Primera: 'Lot 4 - Bordereau de prix'!$AC$1045
Name Prix_Support_11TB_HF20H: 'Lot 4 - BPU Drom-Com'!$AC$1010
Name Prix_Support_11TB_HF20H: 'Lot 4 - BPU Location'!$AA$1010
Name Prix_Support_11TB_HF20H: 'Lot 4 - Bordereau de prix'!$AC$1011
Name Prix_Support_21TB_HF20: 'Lot 4 - BPU Drom-Com'!$AC$1024
Name Prix_Support_21TB_HF20: 'Lot 4 - BPU Location'!$AA$1024
Name Prix_Support_21TB_HF20: 'Lot 4 - Bordereau de prix'!$AC$1025
Name Prix_Support_42TB_HF40: 'Lot 4 - BPU Drom-Com'!$AC$1038
Name Prix_Support_42TB_HF40: 'Lot 4 - BPU Location'!$AA$1038
Name Prix_Support_42TB_HF40: 'Lot 4 - Bordereau de prix'!$AC$1039
Name Prix_Support_Alletra610: 'Lot 4 - BPU Drom-Com'!$O$1067
Name Prix_Support_Alletra610: 'Lot 4 - BPU Location'!$O$1067
Name Prix_Support_Alletra610: 'Lot 4 - Bordereau de prix'!$O$1068
Name Prix_Support_Base_Primera: 'Lot 4 - BPU Drom-Com'!$AC$1049
Name Prix_Support_Base_Primera: 'Lot 4 - BPU Location'!$AA$1049
Name Prix_Support_Base_Primera: 'Lot 4 - Bordereau de prix'!$AC$1050
Name Prix_Support_cache_HF20: 'Lot 4 - BPU Drom-Com'!$AC$1025
Name Prix_Support_cache_HF20: 'Lot 4 - BPU Location'!$AA$1025
Name Prix_Support_cache_HF20: 'Lot 4 - Bordereau de prix'!$AC$1026

Sheet Suivi de version
B2: Mise à jour Février 2022
B3: o Version initiale validée le 10/09/2021
B4: N1 V2 | C4: Ajoût numéros de références manquantes sur Descriptifs et prix existants
C5: Baisses de prix sur 2 références suites à erreurs typographiques
C6: Ajout (sans impact prix) de references logisitique de prises de rdv commandes sur toutes les configurations
C7: Correction de commentaires et descriptif suite à erreurs typographiques
C8: Ajout de passage de HDD vers SSD
A9: 44497 | B9: V3 | C9: Ajoût numéros de références manquantes sur Descriptifs et prix existants
C10: Baisse de prix sur 1 référence suite à erreur typographique
C11: Hausse de prix sur 1 référence suite à erreur typographique
C12: Changement de références logistique de l'interieur à quai/porte
C13: Ajout de passage livraison à l'interieur à 0€
C14: Ajout des references de prise de rdv a 1€
C15: Ajout des references livraison a l'etage a 1€
C16: Baisse de 2€ sur les configuration pour refleter ce surcout eventuel
C17: Suppression du cordon electrique par defaut
C18: Ajout des cordons 0,7m et 2m à 1€
C19: Baisse de 1€ sur les configuration pour refleter ce surcout eventuel
C20: Ajout des serveurs Intel Gen10+
C21: Ajout des serveurs AMD Gen10 +V2
... C28: Suppressions des ajouts impossible (cad avec passage uniquement)
A30: 44623 | B30: V4 | C30: Ajoût numéros de références manquantes sur Descriptifs et prix existants
C31: Correction de prix d'ajout ou passage pour respect prix passage (prix ajout - prix passage)
C32: Ajout de lignes support Nimble manquantes
C33: Ajout/Suppression/Mise à jour de reference SSD/Nvme obsoletes d'ici 3 mois
C34: Integration des SKUS HPE VMWare EDUC
C35: Integration des SKUS HPE MS EDUC
C36: Integration des SKUS Support 6 / 7 ans sur certaines references produits
C37: Ajout CPUs
C38: Suppression : Categorie 2 Options pour mutualisation
C39: Equilibrage de la ram des bundle par remplacement de barrette DIMM 16Go/32Go par 32Go/64Go avec répercution prix passage sur bundle
C40: Simplification des configurations Apollo 6500 avec configurations non éclatés (chassis et serveur) : prix final respecté avec logique ajout/passage
C41: Ajout Chassis Apollo Gen10+ Intel avec suppression de passage AMD avec Intel : prix final respecté avec logique ajout/passage
C42: Suppression temporaire des options sans garanti 5 ans embarqué (Nimble, Primera, Commutateurs,…)
A44: 44704 | B44: v5 | C44: Suppression des Ctrl RAID + disques durs des configurations (dégression des prix en conséquence)
C45: Ajout des rails kits dans les configurations (prise en compte dans prix bundle)
C46: Ajout derniers serveurs Gen10+ (ML30, DL20, Apollo 4200)
C47: Ajout Stockage Alletra, Qumulo
C48: Ajout références produit générique pour simplification BPU
C49: Ajout références stockage et réseau avec 5 ans intégrés
C50: Application de la clause euro/dollar
C51: Suppression de références obsolètes
C52: Réintroduction des options temporairement supprimées avec intégration prix support 5 ans dans le prix du produit
C53: Réintroduction des barettes DIMM 16Go
C54: Suppression des configurations Apollo 2000 de 4 nœuds pleins
C55: Ajout de chassis Apollo 2000 vides
C56: Ajout de lames Apollo 2000 unitaires
... C61: Introduction BPU Location

Sheet Lot 4 - Bordereau de prix
A4: Bordereau de prix unitaires
A6: DésignationDescription des matériels | B6: Référence constructeur (le cas échéant) | C6: HPE SKU | D6: Quantités | E6: Column1 | F6: TARIFS en €HT | G6: Ancien Tarif | H6: Delta
A7: CATEGORIE 1 : Serveurs Edge ou Standard
A8: Désignation/Description des matériels | B8: Référence constructeur (le cas échéant) | C8: Numéro de référence | D8: Quantités | F8: TARIFS en €HT | G8: TARIFS en €HT
A9: Cat1 Conf1 Microserver | B9: HPE ProLiant MicroServer Gen10+ | C9: P16005-421 | F9: 488.24 | G9: 488.24 | H9: =IF(ISNUMBER(F9),ROUND(F9-G9,2),"") -> 0
A10: Serveur tour Ultra Micro mono-socket | B10: HPE ProLiant MicroServer Gen10 Plus G5420 2-core 1P 8GB-U S100i 4LFF-NHP 180W External PS Server | C10: P16005-421 | D10: 1 | H10: =IF(ISNUMBER(F10),ROUND(F10-G10,2),"")
A11: 1 disque de 1 To 6G SATA 7.2K 3,5 pouces (LFF) Non Hot Plug | B11: HPE 1TB SATA 6G Entry 7.2K LFF (3.5in) RW 1yr Wty HDD | C11: 843266-B21 | D11: 1 | H11: =IF(ISNUMBER(F11),ROUND(F11-G11,2),"")
A12: Kit pour carte d'administration HPE iLO | B12: HPE MicroServer Gen10 Plus iLO Enablement Kit | C12: P13788-B21 | D12: 1 | H12: =IF(ISNUMBER(F12),ROUND(F12-G12,2),"")
A13: Carte d'administration HPE iLO avec API RESTful compatible IPMI v2.0 et Redfish. Licence en version Advanced avec toutes les options activées | B13: HPE iLO Advanced 1-server License with 1yr Support on iLO Licensed Features | C13: 512485-B21 | D13: 1 | H13: =IF(ISNUMBER(F13),ROUND(F13-G13,2),"")
A14: Livraison devant la porte | B14: Livraison devant la porte | C14: AC114A | D14: 1 | H14: =IF(ISNUMBER(F14),ROUND(F14-G14,2),"")
A15: Garantie 5 ans J+1 | B15: HPE 5Y Tech Care Basic Service | C15: HU4B2A5 | D15: 1 | H15: =IF(ISNUMBER(F15),ROUND(F15-G15,2),"")
A16: Garantie 5 ans J+1 ILO | B16: HPE iLO AdvPack NonBL Support | C16: HU4B2A5#7X4 | D16: 1 | H16: =IF(ISNUMBER(F16),ROUND(F16-G16,2),"")
A17: Garantie 5 ans J+1 châssis | B17: HPE Microserver Gen10 Plus Support | C17: HU4B2A5#YKX | D17: 1 | H17: =IF(ISNUMBER(F17),ROUND(F17-G17,2),"")
H18: =IF(ISNUMBER(F18),ROUND(F18-G18,2),"")
A19: Cat1 Conf5 DL20 Gen10 plus | B19: HPE ProLiant DL20 Gen10+ | C19: P44109-B21 | F19: 302.89 | G19: 302.89 | H19: =IF(ISNUMBER(F19),ROUND(F19-G19,2),"") -> 0
A20: Serveur rack standard 1U mono-socket INTEL | B20: HPE DL20 Gen10+ 2LFF NHP CTO Svr | C20: P44109-B21 | D20: 1 | H20: =IF(ISNUMBER(F20),ROUND(F20-G20,2),"")
A21: Processeur 64 bits Intel Xeon E-2314 (2,8 GHz de base / 4,50 Ghz Turbo / 4 cœurs / 4 threads / 8 Mo Smart Cache / 65 W PDT | B21: Intel Xeon E-2314 2.8GHz 4-core 65W FIO Processor for HPE | C21: P45248-B21 | D21: 1 | H21: =IF(ISNUMBER(F21),ROUND(F21-G21,2),"")
A22: 1 barrette mémoire HPE Standard DDR4 2666 MHz UDIMM de 16 Go (soit 4 Go ECC par cœur) | B22: HPE 16GB (1x16GB) Single Rank x8 DDR4-3200 CAS-22-22-22 Unbuffered Standard Memory Kit | C22: P43019-B21 | D22: 1 | H22: =IF(ISNUMBER(F22),ROUND(F22-G22,2),"")
A23: 1 cage pour emplacement PCI | B23: HPE ProLiant DL20 Gen10 Plus x8/x8 LP FIO Riser Kit | C23: P46114-B21 | D23: 1 | H23: =IF(ISNUMBER(F23),ROUND(F23-G23,2),"")
A24: Alimentation 290W certifiée 80Plus Platinium | B24: HPE DL20 Gen10 Plat 290W FIO PSU Kit | C24: P21649-B21 | D24: 1 | H24: =IF(ISNUMBER(F24),ROUND(F24-G24,2),"")
A25: Carte d'administration HPE iLO avec API RESTful compatible IPMI v2.0 et Redfish. Licence en version Advanced avec toutes les options activées | B25: HPE iLO Adv 1-svr Lic 1yr Support | C25: 512485-B21 | D25: 1 | H25: =IF(ISNUMBER(F25),ROUND(F25-G25,2),"")
A26: Suppresion du cable electrique par defaut | B26: HPE Remove Standard Power Cords | C26: 469774-409 | D26: 1 | H26: =IF(ISNUMBER(F26),ROUND(F26-G26,2),"")
A27: 1 kit de rail pour rack | B27: HPE 1U Short Friction Rail Kit | C27: 775612-B21 | D27: 1 | H27: =IF(ISNUMBER(F27),ROUND(F27-G27,2),"")
A28: Livraison devant la porte | B28: Livraison devant la porte | C28: AC111A | D28: 1 | H28: =IF(ISNUMBER(F28),ROUND(F28-G28,2),"")
A29: Garantie 5 ans J+1 | B29: HPE 5Y Tech Care Basic Service | C29: HU4B2A5 | D29: 1 | H29: =IF(ISNUMBER(F29),ROUND(F29-G29,2),"")
A30: Garantie 5 ans J+1 ILO | B30: HPE iLO AdvPack NonBL Support | C30: HU4B2A5#7X4 | D30: 1 | H30: =IF(ISNUMBER(F30),ROUND(F30-G30,2),"")
A31: Garantie 5 ans J+1 châssis | B31: HPE ProLiant DL20 Gen10+ Support | C31: HU4B2A5#ZX1 | D31: 1 | H31: =IF(ISNUMBER(F31),ROUND(F31-G31,2),"")
H32: =IF(ISNUMBER(F32),ROUND(F32-G32,2),"")
A33: Cat1 Conf2 DL325 Gen10 plus | B33: HPE ProLiant DL325 Gen10+ | C33: P18606-B21 | F33: 674.1 | G33: 674.1 | H33: =IF(ISNUMBER(F33),ROUND(F33-G33,2),"") -> 0
A34: Serveur rack standard 1U mono-socket AMD | B34: HPE DL325 Gen10+ CTO Svr | C34: P18606-B21 | D34: 1 | H34: =IF(ISNUMBER(F34),ROUND(F34-G34,2),"")
A35: Processeur 64 bits AMD EPYC 7232P (3,1 GHz de base / 3,2 Ghz Boost / 8 cœurs / 16 threads / 32 Mo cache L3 / 120 W PDT) | B35: HPE DL325 Gen10+ AMD EPYC 7232P FIO Kit | C35: P19634-L21 | D35: 1 | H35: =IF(ISNUMBER(F35),ROUND(F35-G35,2),"")
A36: 1 barrette mémoire HPE DDR4 2933 MHz RDIMM de 32 Go (soit 4 Go ECC par cœur) | B36: HPE 32GB 2Rx4 PC4-3200AA-R Smart Kit | C36: P07646-B21 | D36: 1 | H36: =IF(ISNUMBER(F36),ROUND(F36-G36,2),"")
A37: 1 cage Disque LFF | B37: HPE DL325 Gen10+ 4LFF LP FIO Cage Kit | C37: P15525-B21 | D37: 1 | H37: =IF(ISNUMBER(F37),ROUND(F37-G37,2),"")
A38: 2 ports Ethernet Gigabit intégrés | B38: Marvell QL41132HQRJ Ethernet 10Gb 2-port BASE-T OCP3 Adapter for HPE | C38: P10103-B21 | D38: 1 | H38: =IF(ISNUMBER(F38),ROUND(F38-G38,2),"")
A39: alimentation HPE FlexSlot de 800W certifiée 80PLUS Titanium | B39: HPE 800W FS Ti Ht Plg LH Pwr Sply Kit | C39: 865438-B21 | D39: 1 | H39: =IF(ISNUMBER(F39),ROUND(F39-G39,2),"")
A40: Carte d'administration HPE iLO avec API RESTful compatible IPMI v2.0 et Redfish. Licence en version Advanced avec toutes les options activées | B40: HPE iLO Adv 1-svr Lic 1yr Support | C40: 512485-B21 | D40: 1 | H40: =IF(ISNUMBER(F40),ROUND(F40-G40,2),"")
A41: 1 kit de câbles pour SATA LFF | B41: HPE DL325 Gen10 Plus LFF SATA FIO Cable Kit | C41: P15903-B21 | D41: 1 | H41: =IF(ISNUMBER(F41),ROUND(F41-G41,2),"")
A42: 1 kit de rail pour rack | B42: HPE DL325 Gen10 Plus 1075mm Easy Install Rail Kit | C42: P18544-B21 | D42: 1 | H42: =IF(ISNUMBER(F42),ROUND(F42-G42,2),"")
A43: Suppresion du cable electrique par defaut | B43: HPE Remove Standard Power Cords | C43: 469774-409 | D43: 1 | H43: =IF(ISNUMBER(F43),ROUND(F43-G43,2),"")
A44: Livraison devant la porte | B44: Livraison devant la porte | C44: AC114A | D44: 1 | H44: =IF(ISNUMBER(F44),ROUND(F44-G44,2),"")
A45: Garantie 5 ans J+1 | B45: HPE 5Y Tech Care Basic Service | C45: HU4B2A5 | D45: 1 | H45: =IF(ISNUMBER(F45),ROUND(F45-G45,2),"")
... A47: Garantie 5 ans J+1 châssis | B47: HPE DL325 GEN10 PLUS Supp | C47: HU4B2A5#YL0 | D47: 1 | H47: =IF(ISNUMBER(F47),ROUND(F47-G47,2),"")
H48: =IF(ISNUMBER(F48),ROUND(F48-G48,2),"")
A49: Cat1 Conf3 Edge EL300 | B49: HPE EL300 v2 | C49: P25828-B21 | F49: 1666.29 | G49: 1666.29 | H49: =IF(ISNUMBER(F49),ROUND(F49-G49,2),"") -> 0
A50: Serveur de type Edge | B50: HPE EL300 v2 Converged Edge System | C50: P25828-B21 | D50: 1 | H50: =IF(ISNUMBER(F50),ROUND(F50-G50,2),"")
A51: Processeur 64 bits Intel Core i5-7300U (2.6GHz/2-core/15W) | B51: Intel Core i5-7300U FIO Basic Kit EL300 | C51: P25834-B21 | D51: 1 | H51: =IF(ISNUMBER(F51),ROUND(F51-G51,2),"")
A52: 1 barrette mémoire HPE DDR4 2666 MHz RDIMM de 8 Go (soit 4 Go ECC par cœur) | B52: HPE EL 8GB 2Rx8 DDR4-2400V-R FIO Kit | C52: P09176-B21 | D52: 1 | H52: =IF(ISNUMBER(F52),ROUND(F52-G52,2),"")
A53: 1 disque SSD de 120 Go 6G SATA M.2 2,5 pouces (SFF) | B53: HPE EL 120GB SATA RI M.2 2242 PLP MV SSD | C53: P44366-B21 | D53: 1 | H53: =IF(ISNUMBER(F53),ROUND(F53-G53,2),"")
A54: Kit pour cage disque M.2 | B54: HPE EL300 SFF to M.2 Enable Kit | C54: P04054-B21 | D54: 1 | H54: =IF(ISNUMBER(F54),ROUND(F54-G54,2),"")
A55: Kit carte mère pour alimentation continue | B55: HPE EL300 12VDC FIO Transfer Board | C55: P08120-B21 | D55: 1 | H55: =IF(ISNUMBER(F55),ROUND(F55-G55,2),"")
A56: alimentation de 80W | B56: HPE EL300 80W 12VDC Power Supply | C56: P08641-B21 | D56: 1 | H56: =IF(ISNUMBER(F56),ROUND(F56-G56,2),"")
A57: Kit carte mère pour compatibilité processeur Intel i5 | B57: HPE EL300 v2 FIO Carrier Board | C57: P25835-B21 | D57: 1 | H57: =IF(ISNUMBER(F57),ROUND(F57-G57,2),"")
A58: Carte d'administration iSM spécifique aux matériels Edge. Licence en version Advanced | B58: HPE EL300 iSM Adv 3yr 24x7 Sup/Upd E-LTU | C58: R1P49AAE | D58: 1 | H58: =IF(ISNUMBER(F58),ROUND(F58-G58,2),"")
A59: Cable Electrique | B59: HPE C13 - CEE-VII EU 250V 10Amp 1.83m Power Cord | C59: AF568A | D59: 1 | H59: =IF(ISNUMBER(F59),ROUND(F59-G59,2),"")
A60: Livraison devant la porte | B60: Livraison devant la porte | C60: AC111A | D60: 1 | H60: =IF(ISNUMBER(F60),ROUND(F60-G60,2),"")
A61: Garantie 5 ans J+1 | B61: HPE 5Y Tech Care Basic Service | C61: HU4B2A5 | D61: 1 | H61: =IF(ISNUMBER(F61),ROUND(F61-G61,2),"")
... A63: Garantie 5 ans J+1 | B63: HPE Edgeline ISM Advanced Support | C63: HU4B2A5#XP9 | D63: 1 | H63: =IF(ISNUMBER(F63),ROUND(F63-G63,2),"")
H64: =IF(ISNUMBER(F64),ROUND(F64-G64,2),"")
A65: Cat1 Conf6 Tour ML30 Gen10 plus | B65: HPE ProLiant ML30 Gen10+ | C65: P44723-B21 | F65: 721.84 | G65: 721.84 | H65: =IF(ISNUMBER(F65),ROUND(F65-G65,2),"") -> 0
A66: Serveur de type tour | B66: HPE ProLiant ML30 Gen10 Plus 4LFF Non-hot Plug Configure-to-order Server | C66: P44723-B21 | D66: 1 | H66: =IF(ISNUMBER(F66),ROUND(F66-G66,2),"")
A67: Processeur 64 bits Intel Xeon E-2314 (2,8 GHz de base / 4,50 Ghz Turbo / 4 cœurs / 4 threads / 8 Mo Smart Cache / 65 W PDT | B67: Intel Xeon E-2314 2.8GHz 4-core 65W FIO Processor for HPE | C67: P45248-B21 | D67: 1 | H67: =IF(ISNUMBER(F67),ROUND(F67-G67,2),"")
A68: 1 barrette mémoire HPE Standard DDR4 2666 MHz UDIMM de 16 Go (soit 4 Go ECC par cœur) | B68: HPE 16GB (1x16GB) Single Rank x8 DDR4-3200 CAS-22-22-22 Unbuffered Standard Memory Kit | C68: P43019-B21 | D68: 1 | H68: =IF(ISNUMBER(F68),ROUND(F68-G68,2),"")
A69: Alimentation 500W certifiée 80Plus Platinium | B69: HPE 500W FS Plat Ht Plg LH Pwr Sply Kit | C69: 865408-B21 | D69: 1 | H69: =IF(ISNUMBER(F69),ROUND(F69-G69,2),"")
A70: Carte d'administration HPE iLO avec API RESTful compatible IPMI v2.0 et Redfish. Licence en version Advanced avec toutes les options activées | B70: HPE iLO Adv 1-svr Lic 1yr Support | C70: 512485-B21 | D70: 1 | H70: =IF(ISNUMBER(F70),ROUND(F70-G70,2),"")
A71: Kit d'alimentation redondante | B71: HPE ML30 Gen10+ 4U RPS Enablement Kit | C71: P45209-B21 | D71: 1 | H71: =IF(ISNUMBER(F71),ROUND(F71-G71,2),"")
A72: Kit Ventilateur | B72: HPE ML30 Gen10 Front PCI Fan and Baffle Kit | C72: P06303-B21 | D72: 1 | H72: =IF(ISNUMBER(F72),ROUND(F72-G72,2),"")
A73: Suppresion du cable electrique par defaut | B73: HPE Remove Standard Power Cords | C73: 469774-409 | D73: 1 | H73: =IF(ISNUMBER(F73),ROUND(F73-G73,2),"")
A74: Livraison devant la porte | B74: Livraison devant la porte | C74: AC111A | D74: 1 | H74: =IF(ISNUMBER(F74),ROUND(F74-G74,2),"")
A75: Garantie 5 ans J+1 | B75: HPE 5Y Tech Care Basic Service | C75: HU4B2A5 | D75: 1 | H75: =IF(ISNUMBER(F75),ROUND(F75-G75,2),"")
A76: Garantie 5 ans J+1 ILO | B76: HPE iLO AdvPack NonBL Support | C76: HU4B2A5#7X4 | D76: 1 | H76: =IF(ISNUMBER(F76),ROUND(F76-G76,2),"")
A77: Garantie 5 ans J+1 châssis | B77: HPE ProLiant ML30 Gen10+ Support | C77: HU4B2A5#ZNB | D77: 1 | H77: =IF(ISNUMBER(F77),ROUND(F77-G77,2),"")
H78: =IF(ISNUMBER(F78),ROUND(F78-G78,2),"")
A79: CATEGORIE 1 : extensions et périphériques associés, extensions de garantie, installation, etc. | H79: =IF(ISNUMBER(F79),ROUND(F79-G79,2),"")
A80: Désignation/Description des matériels | B80: Référence constructeur (le cas échéant) | C80: Numéro de référence | D80: Quantités | F80: TARIFS en €HT | G80: TARIFS en €HT | H80: =IF(ISNUMBER(F80),ROUND(F80-G80,2),"")
A81: Ces extensions sont propres a cette categorie. Les extensions communes sont factorisés dans le chapitre Categorie 1 a 4 : extensions | H81: =IF(ISNUMBER(F81),ROUND(F81-G81,2),"")
A82: Ajout d'une barrette mémoire DDR4-2666 UDIMM 8 Go | B82: HPE 8GB 1Rx8 PC4-2666V-E STND Kit | C82: 879505-B21 | F82: 46.2 | G82: 46.2 | H82: =IF(ISNUMBER(F82),ROUND(F82-G82,2),"") -> 0
B83: HPE 8GB 1Rx8 PC4-3200AA-E STND Kit | C83: P43016-B21 | F83: 46.2 | G83: 46.2 | H83: =IF(ISNUMBER(F83),ROUND(F83-G83,2),"") -> 0
A84: Ajout d'une barrette mémoire DDR4-2666/3200 UDIMM 16 Go | B84: HPE 16GB 2Rx8 PC4-2666V-E STND Kit | C84: 879507-B21 | F84: 79.8 | G84: 79.8 | H84: =IF(ISNUMBER(F84),ROUND(F84-G84,2),"") -> 0
B85: HPE 16GB 1Rx8 PC4-3200AA-E STND Kit | C85: P43019-B21 | F85: 79.8 | G85: 79.8 | H85: =IF(ISNUMBER(F85),ROUND(F85-G85,2),"") -> 0
H86: =IF(ISNUMBER(F86),ROUND(F86-G86,2),"")
A87: Cat1 Configuration n°1: Serveur tour Ultra Micro mono-socket | H87: =IF(ISNUMBER(F87),ROUND(F87-G87,2),"")
A88: Disque durs rotatifs additionnels | H88: =IF(ISNUMBER(F88),ROUND(F88-G88,2),"")
A89: Ajout d'un disque dur SATA 7.2K LFF de 1 To Non HotPlug | B89: HPE 1TB SATA 7.2K LFF RW MV HDD | C89: 801882-B21 | F89: 94.5 | G89: 94.5 | H89: =IF(ISNUMBER(F89),ROUND(F89-G89,2),"") -> 0
A90: Ajout d'un disque dur SATA 7.2K LFF de 4 To Non HotPlug | B90: HPE 4TB SATA 7.2K LFF RW MV HDD | C90: 801888-B21 | F90: 118.65 | G90: 118.65 | H90: =IF(ISNUMBER(F90),ROUND(F90-G90,2),"") -> 0
A91: Autres extensions matérielles | H91: =IF(ISNUMBER(F91),ROUND(F91-G91,2),"")
A92: Ajout d'un kit de conversion LFF Non-hot Plug vers SFF Non-hot Plug | B92: HPE MicroServer Gen10 SFF NHP SATA Converter Kit | C92: 870213-B21 | F92: 5.25 | G92: 5.25 | H92: =IF(ISNUMBER(F92),ROUND(F92-G92,2),"") -> 0
A93: Extensions de garanties | H93: =IF(ISNUMBER(F93),ROUND(F93-G93,2),"")
A94: Microserver | H94: =IF(ISNUMBER(F94),ROUND(F94-G94,2),"")
A95: Passage à support 5 ans intervention j+1 (9x5) avec retention de disque | B95: Tech Care Basic DMR 5Y (J+1 9x5) | C95: Passage vers HU4B3A5#YKX | F95: 19 | G95: 19 | H95: =IF(ISNUMBER(F95),ROUND(F95-G95,2),"") -> 0
A96: Passage à support 5 ans intervention h+4 (24h/24h, 7j/7j) | B96: Tech Care Essential 5Y (4H 24X7) | C96: Passage vers HU4A6A5#YKX | F96: 26 | G96: 26 | H96: =IF(ISNUMBER(F96),ROUND(F96-G96,2),"") -> 0
A97: Passage à support 5 ans intervention h+4 (24h/24h, 7j/7j) avec retention de Disque | B97: Tech Care Essential 5Y DMR (4H 24X7) | C97: Passage vers HU4A7A5#YKX | F97: 35 | G97: 35 | H97: =IF(ISNUMBER(F97),ROUND(F97-G97,2),"") -> 0
A98: Passage à support 6 ans intervention J+1 (Heures ouvrées, jours ouvrés) | B98: HPE 6Y TC Basis SVC | C98: Passage vers HU4B2A6#YKX | F98: 5 | G98: 5 | H98: =IF(ISNUMBER(F98),ROUND(F98-G98,2),"") -> 0
A99: Passage à support 6 ans intervention h+4 (24h/24h, 7j/7j) | B99: HPE 6Y Tech Care Essential SVC | C99: Passage vers HU4A6A6#YKX | F99: 110 | G99: 110 | H99: =IF(ISNUMBER(F99),ROUND(F99-G99,2),"") -> 0
A100: Passage à support 7 ans intervention J+1 (Heures ouvrées, jours ouvrés) | B100: HPE 7Y Tech Care Basis SVC | C100: Passage vers HU4B2A7#YKX | F100: 10 | G100: 10 | H100: =IF(ISNUMBER(F100),ROUND(F100-G100,2),"") -> 0
A101: Passage à support 7 ans intervention h+4 (24h/24h, 7j/7j) | B101: HPE 7Y Tech Care Essential SVC | C101: Passage vers HU4A6A7#YKX | F101: 167 | G101: 167 | H101: =IF(ISNUMBER(F101),ROUND(F101-G101,2),"") -> 0
A102: Passage à support 5 ans intervention j+1 (9x5) avec retention de disque | B102: Tech Care Basic DMR 5Y (J+1 9x5) | C102: Passage vers HU4B3A5#ZX1 | F102: 19 | G102: 19 | H102: =IF(ISNUMBER(F102),ROUND(F102-G102,2),"") -> 0
A103: Passage à support 5 ans intervention h+4 (24h/24h, 7j/7j) | B103: Tech Care Essential 5Y (4H 24X7) | C103: Passage vers HU4A6A5#ZX1 | F103: 26 | G103: 26 | H103: =IF(ISNUMBER(F103),ROUND(F103-G103,2),"") -> 0
A104: Passage à support 5 ans intervention h+4 (24h/24h, 7j/7j) avec retention de Disque | B104: Tech Care Essential 5Y DMR (4H 24X7) | C104: Passage vers HU4A7A5#ZX1 | F104: 35 | G104: 35 | H104: =IF(ISNUMBER(F104),ROUND(F104-G104,2),"") -> 0
A105: Passage à support 6 ans intervention J+1 (Heures ouvrées, jours ouvrés) | B105: HPE 6Y TC Basis SVC | C105: Passage vers HU4B2A6#ZX1 | F105: 5 | G105: 5 | H105: =IF(ISNUMBER(F105),ROUND(F105-G105,2),"") -> 0
A106: Passage à support 6 ans intervention h+4 (24h/24h, 7j/7j) | B106: HPE 6Y Tech Care Essential SVC | C106: Passage vers HU4A6A6#ZX1 | F106: 110 | G106: 110 | H106: =IF(ISNUMBER(F106),ROUND(F106-G106,2),"") -> 0
...

Sheet Lot 4 - BPU Location
H1: COEFFICIENTS LOCATIF
H2: ='Loc Coefficients Crédit-Bail'!D2 -> 0.26392451 | I2: ='Loc Coefficients Crédit-Bail'!E2 -> 0.13385372 | J2: ='Loc Coefficients Crédit-Bail'!F2 -> 0.091350624 | K2: ='Loc Coefficients Crédit-Bail'!G2 -> 0.070256845
H3: CREDIT-BAIL | L3: LOCATION
A4: Bordereau de prix unitaires | H4: 1 an | I4: 2 ans | J4: 3 ans | K4: 4 ans | L4: 1 an | N4: 2 ans | P4: 3 ans | R4: 4 ans
H5: 4 Trimestres | I5: 8 Trimestres | J5: 12 Trimestres | K5: 16 Trimestres | L5: 4 trimestres | N5: 8 trimestres | P5: 12 trimestres | R5: 16 trimestres
A6: DésignationDescription des matériels | B6: Référence constructeur (le cas échéant) | C6: HPE SKU | D6: Quantités | E6: Column1 | F6: TARIFS en €HT | G6: Références de Location | H6: Loyer Trimestriel €HT | I6: Loyer Trimestriel €HT | J6: Loyer Trimestriel €HT | K6: Loyer Trimestriel €HT | L6: Coefficient Locatif | M6: Loyer Trimestriel €HT | N6: Coefficient Locatif | O6: Loyer Trimestriel €HT | P6: Coefficient Locatif | Q6: Loyer Trimestriel €HT | R6: Coefficient Locatif | S6: Loyer Trimestriel €HT
A7: CATEGORIE 1 : Serveurs Edge ou Standard | H7: =IF(ISNUMBER($F7),ROUND($F7*H$2,2),"") | I7: =IF(ISNUMBER($F7),ROUND($F7*I$2,2),"") | J7: =IF(ISNUMBER($F7),ROUND($F7*J$2,2),"") | K7: =IF(ISNUMBER($F7),ROUND($F7*K$2,2),"") | L7: =IF(ISNUMBER(F7),IF(LEFT(A7,3)="Cat",VLOOKUP(A7,'Loc Configurations Seules'!R:U,4,FALSE),VLOOKUP(G7,'Loc Coefficients Location'!A:D,4,FALSE)),"") | M7: =IF(ISNUMBER(L7),L7*$F7,"") | N7: =IF(ISNUMBER(F7),IF(LEFT(A7,3)="Cat",VLOOKUP(A7,'Loc Configurations Seules'!R:V,5,FALSE),VLOOKUP(G7,'Loc Coefficients Location'!A:E,5,FALSE)),"") | O7: =IF(ISNUMBER(N7),N7*$F7,"") | P7: =IF(ISNUMBER(F7),IF(LEFT(A7,3)="Cat",VLOOKUP(A7,'Loc Configurations Seules'!R:W,6,FALSE),VLOOKUP(G7,'Loc Coefficients Location'!A:F,6,FALSE)),"") | Q7: =IF(ISNUMBER(P7),P7*$F7,"") | R7: =IF(ISNUMBER(F7),IF(LEFT(A7,3)="Cat",VLOOKUP(A7,'Loc Configurations Seules'!R:X,7,FALSE),VLOOKUP(G7,'Loc Coefficients Location'!A:G,7,FALSE)),"") | S7: =IF(ISNUMBER(R7),R7*$F7,"")
A8: Désignation/Description des matériels | B8: Référence constructeur (le cas échéant) | C8: Numéro de référence | D8: Quantités | F8: TARIFS en €HT | H8: =IF(ISNUMBER($F8),ROUND($F8*H$2,2),"") | I8: =IF(ISNUMBER($F8),ROUND($F8*I$2,2),"") | J8: =IF(ISNUMBER($F8),ROUND($F8*J$2,2),"") | K8: =IF(ISNUMBER($F8),ROUND($F8*K$2,2),"") | L8: =IF(ISNUMBER(F8),IF(LEFT(A8,3)="Cat",VLOOKUP(A8,'Loc Configurations Seules'!R:U,4,FALSE),VLOOKUP(G8,'Loc Coefficients Location'!A:D,4,FALSE)),"") | M8: =IF(ISNUMBER(L8),L8*$F8,"") | N8: =IF(ISNUMBER(F8),IF(LEFT(A8,3)="Cat",VLOOKUP(A8,'Loc Configurations Seules'!R:V,5,FALSE),VLOOKUP(G8,'Loc Coefficients Location'!A:E,5,FALSE)),"") | O8: =IF(ISNUMBER(N8),N8*$F8,"") | P8: =IF(ISNUMBER(F8),IF(LEFT(A8,3)="Cat",VLOOKUP(A8,'Loc Configurations Seules'!R:W,6,FALSE),VLOOKUP(G8,'Loc Coefficients Location'!A:F,6,FALSE)),"") | Q8: =IF(ISNUMBER(P8),P8*$F8,"") | R8: =IF(ISNUMBER(F8),IF(LEFT(A8,3)="Cat",VLOOKUP(A8,'Loc Configurations Seules'!R:X,7,FALSE),VLOOKUP(G8,'Loc Coefficients Location'!A:G,7,FALSE)),"") | S8: =IF(ISNUMBER(R8),R8*$F8,"")
A9: Cat1 Conf1 Microserver | B9: HPE ProLiant MicroServer Gen10+ | C9: P16005-421 | F9: 488.24 | H9: =IF(ISNUMBER($F9),ROUND($F9*H$2,2),"") -> 128.86 | I9: =IF(ISNUMBER($F9),ROUND($F9*I$2,2),"") -> 65.35 | J9: =IF(ISNUMBER($F9),ROUND($F9*J$2,2),"") -> 44.6 | K9: =IF(ISNUMBER($F9),ROUND($F9*K$2,2),"") -> 34.3 | L9: =IF(ISNUMBER(F9),IF(LEFT(A9,3)="Cat",VLOOKUP(A9,'Loc Configurations Seules'!R:U,4,FALSE),VLOOKUP(G9,'Loc Coefficients Location'!A:D,4,FALSE)),"") -> 0.188 | M9: =IF(ISNUMBER(L9),L9*$F9,"") -> 91.78912 | N9: =IF(ISNUMBER(F9),IF(LEFT(A9,3)="Cat",VLOOKUP(A9,'Loc Configurations Seules'!R:V,5,FALSE),VLOOKUP(G9,'Loc Coefficients Location'!A:E,5,FALSE)),"") -> 0.0997 | O9: =IF(ISNUMBER(N9),N9*$F9,"") -> 48.677528 | P9: =IF(ISNUMBER(F9),IF(LEFT(A9,3)="Cat",VLOOKUP(A9,'Loc Configurations Seules'!R:W,6,FALSE),VLOOKUP(G9,'Loc Coefficients Location'!A:F,6,FALSE)),"") -> 0.0757 | Q9: =IF(ISNUMBER(P9),P9*$F9,"") -> 36.959768 | R9: =IF(ISNUMBER(F9),IF(LEFT(A9,3)="Cat",VLOOKUP(A9,'Loc Configurations Seules'!R:X,7,FALSE),VLOOKUP(G9,'Loc Coefficients Location'!A:G,7,FALSE)),"") -> 0.0634 | S9: =IF(ISNUMBER(R9),R9*$F9,"") -> 30.954416
A10: Serveur tour Ultra Micro mono-socket | B10: HPE ProLiant MicroServer Gen10 Plus G5420 2-core 1P 8GB-U S100i 4LFF-NHP 180W External PS Server | C10: P16005-421 | D10: 1 | G10: PC_SE/PLX86 | H10: =IF(ISNUMBER($F10),ROUND($F10*H$2,2),"") | I10: =IF(ISNUMBER($F10),ROUND($F10*I$2,2),"") | J10: =IF(ISNUMBER($F10),ROUND($F10*J$2,2),"") | K10: =IF(ISNUMBER($F10),ROUND($F10*K$2,2),"") | L10: =IF(ISNUMBER(F10),IF(LEFT(A10,3)="Cat",VLOOKUP(A10,'Loc Configurations Seules'!R:U,4,FALSE),VLOOKUP(G10,'Loc Coefficients Location'!A:D,4,FALSE)),"") | M10: =IF(ISNUMBER(L10),L10*$F10,"") | N10: =IF(ISNUMBER(F10),IF(LEFT(A10,3)="Cat",VLOOKUP(A10,'Loc Configurations Seules'!R:V,5,FALSE),VLOOKUP(G10,'Loc Coefficients Location'!A:E,5,FALSE)),"") | O10: =IF(ISNUMBER(N10),N10*$F10,"") | P10: =IF(ISNUMBER(F10),IF(LEFT(A10,3)="Cat",VLOOKUP(A10,'Loc Configurations Seules'!R:W,6,FALSE),VLOOKUP(G10,'Loc Coefficients Location'!A:F,6,FALSE)),"") | Q10: =IF(ISNUMBER(P10),P10*$F10,"") | R10: =IF(ISNUMBER(F10),IF(LEFT(A10,3)="Cat",VLOOKUP(A10,'Loc Configurations Seules'!R:X,7,FALSE),VLOOKUP(G10,'Loc Coefficients Location'!A:G,7,FALSE)),"") | S10: =IF(ISNUMBER(R10),R10*$F10,"")
A11: 1 disque de 1 To 6G SATA 7.2K 3,5 pouces (LFF) Non Hot Plug | B11: HPE 1TB SATA 6G Entry 7.2K LFF (3.5in) RW 1yr Wty HDD | C11: 843266-B21 | D11: 1 | G11: Store/PRIMERA | H11: =IF(ISNUMBER($F11),ROUND($F11*H$2,2),"") | I11: =IF(ISNUMBER($F11),ROUND($F11*I$2,2),"") | J11: =IF(ISNUMBER($F11),ROUND($F11*J$2,2),"") | K11: =IF(ISNUMBER($F11),ROUND($F11*K$2,2),"") | L11: =IF(ISNUMBER(F11),IF(LEFT(A11,3)="Cat",VLOOKUP(A11,'Loc Configurations Seules'!R:U,4,FALSE),VLOOKUP(G11,'Loc Coefficients Location'!A:D,4,FALSE)),"") | M11: =IF(ISNUMBER(L11),L11*$F11,"") | N11: =IF(ISNUMBER(F11),IF(LEFT(A11,3)="Cat",VLOOKUP(A11,'Loc Configurations Seules'!R:V,5,FALSE),VLOOKUP(G11,'Loc Coefficients Location'!A:E,5,FALSE)),"") | O11: =IF(ISNUMBER(N11),N11*$F11,"") | P11: =IF(ISNUMBER(F11),IF(LEFT(A11,3)="Cat",VLOOKUP(A11,'Loc Configurations Seules'!R:W,6,FALSE),VLOOKUP(G11,'Loc Coefficients Location'!A:F,6,FALSE)),"") | Q11: =IF(ISNUMBER(P11),P11*$F11,"") | R11: =IF(ISNUMBER(F11),IF(LEFT(A11,3)="Cat",VLOOKUP(A11,'Loc Configurations Seules'!R:X,7,FALSE),VLOOKUP(G11,'Loc Coefficients Location'!A:G,7,FALSE)),"") | S11: =IF(ISNUMBER(R11),R11*$F11,"")
A12: Kit pour carte d'administration HPE iLO | B12: HPE MicroServer Gen10 Plus iLO Enablement Kit | C12: P13788-B21 | D12: 1 | G12: SOFT/MAINT | H12: =IF(ISNUMBER($F12),ROUND($F12*H$2,2),"") | I12: =IF(ISNUMBER($F12),ROUND($F12*I$2,2),"") | J12: =IF(ISNUMBER($F12),ROUND($F12*J$2,2),"") | K12: =IF(ISNUMBER($F12),ROUND($F12*K$2,2),"") | L12: =IF(ISNUMBER(F12),IF(LEFT(A12,3)="Cat",VLOOKUP(A12,'Loc Configurations Seules'!R:U,4,FALSE),VLOOKUP(G12,'Loc Coefficients Location'!A:D,4,FALSE)),"") | M12: =IF(ISNUMBER(L12),L12*$F12,"") | N12: =IF(ISNUMBER(F12),IF(LEFT(A12,3)="Cat",VLOOKUP(A12,'Loc Configurations Seules'!R:V,5,FALSE),VLOOKUP(G12,'Loc Coefficients Location'!A:E,5,FALSE)),"") | O12: =IF(ISNUMBER(N12),N12*$F12,"") | P12: =IF(ISNUMBER(F12),IF(LEFT(A12,3)="Cat",VLOOKUP(A12,'Loc Configurations Seules'!R:W,6,FALSE),VLOOKUP(G12,'Loc Coefficients Location'!A:F,6,FALSE)),"") | Q12: =IF(ISNUMBER(P12),P12*$F12,"") | R12: =IF(ISNUMBER(F12),IF(LEFT(A12,3)="Cat",VLOOKUP(A12,'Loc Configurations Seules'!R:X,7,FALSE),VLOOKUP(G12,'Loc Coefficients Location'!A:G,7,FALSE)),"") | S12: =IF(ISNUMBER(R12),R12*$F12,"")
A13: Carte d'administration HPE iLO avec API RESTful compatible IPMI v2.0 et Redfish. Licence en version Advanced avec toutes les options activées | B13: HPE iLO Advanced 1-server License with 1yr Support on iLO Licensed Features | C13: 512485-B21 | D13: 1 | G13: PC_SE/PLX86 | H13: =IF(ISNUMBER($F13),ROUND($F13*H$2,2),"") | I13: =IF(ISNUMBER($F13),ROUND($F13*I$2,2),"") | J13: =IF(ISNUMBER($F13),ROUND($F13*J$2,2),"") | K13: =IF(ISNUMBER($F13),ROUND($F13*K$2,2),"") | L13: =IF(ISNUMBER(F13),IF(LEFT(A13,3)="Cat",VLOOKUP(A13,'Loc Configurations Seules'!R:U,4,FALSE),VLOOKUP(G13,'Loc Coefficients Location'!A:D,4,FALSE)),"") | M13: =IF(ISNUMBER(L13),L13*$F13,"") | N13: =IF(ISNUMBER(F13),IF(LEFT(A13,3)="Cat",VLOOKUP(A13,'Loc Configurations Seules'!R:V,5,FALSE),VLOOKUP(G13,'Loc Coefficients Location'!A:E,5,FALSE)),"") | O13: =IF(ISNUMBER(N13),N13*$F13,"") | P13: =IF(ISNUMBER(F13),IF(LEFT(A13,3)="Cat",VLOOKUP(A13,'Loc Configurations Seules'!R:W,6,FALSE),VLOOKUP(G13,'Loc Coefficients Location'!A:F,6,FALSE)),"") | Q13: =IF(ISNUMBER(P13),P13*$F13,"") | R13: =IF(ISNUMBER(F13),IF(LEFT(A13,3)="Cat",VLOOKUP(A13,'Loc Configurations Seules'!R:X,7,FALSE),VLOOKUP(G13,'Loc Coefficients Location'!A:G,7,FALSE)),"") | S13: =IF(ISNUMBER(R13),R13*$F13,"")
A14: Livraison devant la porte | B14: Livraison devant la porte | C14: AC114A | D14: 1 | G14: SOFT/MAINT | H14: =IF(ISNUMBER($F14),ROUND($F14*H$2,2),"") | I14: =IF(ISNUMBER($F14),ROUND($F14*I$2,2),"") | J14: =IF(ISNUMBER($F14),ROUND($F14*J$2,2),"") | K14: =IF(ISNUMBER($F14),ROUND($F14*K$2,2),"") | L14: =IF(ISNUMBER(F14),IF(LEFT(A14,3)="Cat",VLOOKUP(A14,'Loc Configurations Seules'!R:U,4,FALSE),VLOOKUP(G14,'Loc Coefficients Location'!A:D,4,FALSE)),"") | M14: =IF(ISNUMBER(L14),L14*$F14,"") | N14: =IF(ISNUMBER(F14),IF(LEFT(A14,3)="Cat",VLOOKUP(A14,'Loc Configurations Seules'!R:V,5,FALSE),VLOOKUP(G14,'Loc Coefficients Location'!A:E,5,FALSE)),"") | O14: =IF(ISNUMBER(N14),N14*$F14,"") | P14: =IF(ISNUMBER(F14),IF(LEFT(A14,3)="Cat",VLOOKUP(A14,'Loc Configurations Seules'!R:W,6,FALSE),VLOOKUP(G14,'Loc Coefficients Location'!A:F,6,FALSE)),"") | Q14: =IF(ISNUMBER(P14),P14*$F14,"") | R14: =IF(ISNUMBER(F14),IF(LEFT(A14,3)="Cat",VLOOKUP(A14,'Loc Configurations Seules'!R:X,7,FALSE),VLOOKUP(G14,'Loc Coefficients Location'!A:G,7,FALSE)),"") | S14: =IF(ISNUMBER(R14),R14*$F14,"")
A15: Garantie 5 ans J+1 | B15: HPE 5Y Tech Care Basic Service | C15: HU4B2A5 | D15: 1 | G15: SOFT/MAINT | H15: =IF(ISNUMBER($F15),ROUND($F15*H$2,2),"") | I15: =IF(ISNUMBER($F15),ROUND($F15*I$2,2),"") | J15: =IF(ISNUMBER($F15),ROUND($F15*J$2,2),"") | K15: =IF(ISNUMBER($F15),ROUND($F15*K$2,2),"")
A16: Garantie 5 ans J+1 ILO | B16: HPE iLO AdvPack NonBL Support | C16: HU4B2A5#7X4 | D16: 1 | G16: SOFT/MAINT | H16: =IF(ISNUMBER($F16),ROUND($F16*H$2,2),"") | I16: =IF(ISNUMBER($F16),ROUND($F16*I$2,2),"") | J16: =IF(ISNUMBER($F16),ROUND($F16*J$2,2),"") | K16: =IF(ISNUMBER($F16),ROUND($F16*K$2,2),"")
A17: Garantie 5 ans J+1 châssis | B17: HPE Microserver Gen10 Plus Support | C17: HU4B2A5#YKX | D17: 1 | G17: SOFT/MAINT | H17: =IF(ISNUMBER($F17),ROUND($F17*H$2,2),"") | I17: =IF(ISNUMBER($F17),ROUND($F17*I$2,2),"") | J17: =IF(ISNUMBER($F17),ROUND($F17*J$2,2),"") | K17: =IF(ISNUMBER($F17),ROUND($F17*K$2,2),"")
H18: =IF(ISNUMBER($F18),ROUND($F18*H$2,2),"") | I18: =IF(ISNUMBER($F18),ROUND($F18*I$2,2),"") | J18: =IF(ISNUMBER($F18),ROUND($F18*J$2,2),"") | K18: =IF(ISNUMBER($F18),ROUND($F18*K$2,2),"") | L18: =IF(ISNUMBER(F18),IF(LEFT(A18,3)="Cat",VLOOKUP(A18,'Loc Configurations Seules'!R:U,4,FALSE),VLOOKUP(G18,'Loc Coefficients Location'!A:D,4,FALSE)),"") | M18: =IF(ISNUMBER(L18),L18*$F18,"") | N18: =IF(ISNUMBER(F18),IF(LEFT(A18,3)="Cat",VLOOKUP(A18,'Loc Configurations Seules'!R:V,5,FALSE),VLOOKUP(G18,'Loc Coefficients Location'!A:E,5,FALSE)),"") | O18: =IF(ISNUMBER(N18),N18*$F18,"") | P18: =IF(ISNUMBER(F18),IF(LEFT(A18,3)="Cat",VLOOKUP(A18,'Loc Configurations Seules'!R:W,6,FALSE),VLOOKUP(G18,'Loc Coefficients Location'!A:F,6,FALSE)),"") | Q18: =IF(ISNUMBER(P18),P18*$F18,"") | R18: =IF(ISNUMBER(F18),IF(LEFT(A18,3)="Cat",VLOOKUP(A18,'Loc Configurations Seules'!R:X,7,FALSE),VLOOKUP(G18,'Loc Coefficients Location'!A:G,7,FALSE)),"") | S18: =IF(ISNUMBER(R18),R18*$F18,"")
A19: Cat1 Conf5 DL20 Gen10 plus | B19: HPE ProLiant DL20 Gen10+ | C19: P44109-B21 | F19: 302.89 | H19: =IF(ISNUMBER($F19),ROUND($F19*H$2,2),"") -> 79.94 | I19: =IF(ISNUMBER($F19),ROUND($F19*I$2,2),"") -> 40.54 | J19: =IF(ISNUMBER($F19),ROUND($F19*J$2,2),"") -> 27.67 | K19: =IF(ISNUMBER($F19),ROUND($F19*K$2,2),"") -> 21.28 | L19: =IF(ISNUMBER(F19),IF(LEFT(A19,3)="Cat",VLOOKUP(A19,'Loc Configurations Seules'!R:U,4,FALSE),VLOOKUP(G19,'Loc Coefficients Location'!A:D,4,FALSE)),"") -> 0.2129 | M19: =IF(ISNUMBER(L19),L19*$F19,"") -> 64.485281 | N19: =IF(ISNUMBER(F19),IF(LEFT(A19,3)="Cat",VLOOKUP(A19,'Loc Configurations Seules'!R:V,5,FALSE),VLOOKUP(G19,'Loc Coefficients Location'!A:E,5,FALSE)),"") -> 0.1109 | O19: =IF(ISNUMBER(N19),N19*$F19,"") -> 33.590501 | P19: =IF(ISNUMBER(F19),IF(LEFT(A19,3)="Cat",VLOOKUP(A19,'Loc Configurations Seules'!R:W,6,FALSE),VLOOKUP(G19,'Loc Coefficients Location'!A:F,6,FALSE)),"") -> 0.0808 | Q19: =IF(ISNUMBER(P19),P19*$F19,"") -> 24.473512 | R19: =IF(ISNUMBER(F19),IF(LEFT(A19,3)="Cat",VLOOKUP(A19,'Loc Configurations Seules'!R:X,7,FALSE),VLOOKUP(G19,'Loc Coefficients Location'!A:G,7,FALSE)),"") -> 0.0657 | S19: =IF(ISNUMBER(R19),R19*$F19,"") -> 19.899873
A20: Serveur rack standard 1U mono-socket INTEL | B20: HPE DL20 Gen10+ 2LFF NHP CTO Svr | C20: P44109-B21 | D20: 1 | G20: PC_SE/PLX86 | H20: =IF(ISNUMBER($F20),ROUND($F20*H$2,2),"") | I20: =IF(ISNUMBER($F20),ROUND($F20*I$2,2),"") | J20: =IF(ISNUMBER($F20),ROUND($F20*J$2,2),"") | K20: =IF(ISNUMBER($F20),ROUND($F20*K$2,2),"") | L20: =IF(ISNUMBER(F20),IF(LEFT(A20,3)="Cat",VLOOKUP(A20,'Loc Configurations Seules'!R:U,4,FALSE),VLOOKUP(G20,'Loc Coefficients Location'!A:D,4,FALSE)),"") | M20: =IF(ISNUMBER(L20),L20*$F20,"") | N20: =IF(ISNUMBER(F20),IF(LEFT(A20,3)="Cat",VLOOKUP(A20,'Loc Configurations Seules'!R:V,5,FALSE),VLOOKUP(G20,'Loc Coefficients Location'!A:E,5,FALSE)),"") | O20: =IF(ISNUMBER(N20),N20*$F20,"") | P20: =IF(ISNUMBER(F20),IF(LEFT(A20,3)="Cat",VLOOKUP(A20,'Loc Configurations Seules'!R:W,6,FALSE),VLOOKUP(G20,'Loc Coefficients Location'!A:F,6,FALSE)),"") | Q20: =IF(ISNUMBER(P20),P20*$F20,"") | R20: =IF(ISNUMBER(F20),IF(LEFT(A20,3)="Cat",VLOOKUP(A20,'Loc Configurations Seules'!R:X,7,FALSE),VLOOKUP(G20,'Loc Coefficients Location'!A:G,7,FALSE)),"") | S20: =IF(ISNUMBER(R20),R20*$F20,"")
A21: Processeur 64 bits Intel Xeon E-2314 (2,8 GHz de base / 4,50 Ghz Turbo / 4 cœurs / 4 threads / 8 Mo Smart Cache / 65 W PDT | B21: Intel Xeon E-2314 2.8GHz 4-core 65W FIO Processor for HPE | C21: P45248-B21 | D21: 1 | G21: PC_SE/PLX86 | H21: =IF(ISNUMBER($F21),ROUND($F21*H$2,2),"") | I21: =IF(ISNUMBER($F21),ROUND($F21*I$2,2),"") | J21: =IF(ISNUMBER($F21),ROUND($F21*J$2,2),"") | K21: =IF(ISNUMBER($F21),ROUND($F21*K$2,2),"") | L21: =IF(ISNUMBER(F21),IF(LEFT(A21,3)="Cat",VLOOKUP(A21,'Loc Configurations Seules'!R:U,4,FALSE),VLOOKUP(G21,'Loc Coefficients Location'!A:D,4,FALSE)),"") | M21: =IF(ISNUMBER(L21),L21*$F21,"") | N21: =IF(ISNUMBER(F21),IF(LEFT(A21,3)="Cat",VLOOKUP(A21,'Loc Configurations Seules'!R:V,5,FALSE),VLOOKUP(G21,'Loc Coefficients Location'!A:E,5,FALSE)),"") | O21: =IF(ISNUMBER(N21),N21*$F21,"") | P21: =IF(ISNUMBER(F21),IF(LEFT(A21,3)="Cat",VLOOKUP(A21,'Loc Configurations Seules'!R:W,6,FALSE),VLOOKUP(G21,'Loc Coefficients Location'!A:F,6,FALSE)),"") | Q21: =IF(ISNUMBER(P21),P21*$F21,"") | R21: =IF(ISNUMBER(F21),IF(LEFT(A21,3)="Cat",VLOOKUP(A21,'Loc Configurations Seules'!R:X,7,FALSE),VLOOKUP(G21,'Loc Coefficients Location'!A:G,7,FALSE)),"") | S21: =IF(ISNUMBER(R21),R21*$F21,"")
A22: 1 barrette mémoire HPE Standard DDR4 2666 MHz UDIMM de 16 Go (soit 4 Go ECC par cœur) | B22: HPE 16GB (1x16GB) Single Rank x8 DDR4-3200 CAS-22-22-22 Unbuffered Standard Memory Kit | C22: P43019-B21 | D22: 1 | G22: PC_SE/PLX86 | H22: =IF(ISNUMBER($F22),ROUND($F22*H$2,2),"") | I22: =IF(ISNUMBER($F22),ROUND($F22*I$2,2),"") | J22: =IF(ISNUMBER($F22),ROUND($F22*J$2,2),"") | K22: =IF(ISNUMBER($F22),ROUND($F22*K$2,2),"") | L22: =IF(ISNUMBER(F22),IF(LEFT(A22,3)="Cat",VLOOKUP(A22,'Loc Configurations Seules'!R:U,4,FALSE),VLOOKUP(G22,'Loc Coefficients Location'!A:D,4,FALSE)),"") | M22: =IF(ISNUMBER(L22),L22*$F22,"") | N22: =IF(ISNUMBER(F22),IF(LEFT(A22,3)="Cat",VLOOKUP(A22,'Loc Configurations Seules'!R:V,5,FALSE),VLOOKUP(G22,'Loc Coefficients Location'!A:E,5,FALSE)),"") | O22: =IF(ISNUMBER(N22),N22*$F22,"") | P22: =IF(ISNUMBER(F22),IF(LEFT(A22,3)="Cat",VLOOKUP(A22,'Loc Configurations Seules'!R:W,6,FALSE),VLOOKUP(G22,'Loc Coefficients Location'!A:F,6,FALSE)),"") | Q22: =IF(ISNUMBER(P22),P22*$F22,"") | R22: =IF(ISNUMBER(F22),IF(LEFT(A22,3)="Cat",VLOOKUP(A22,'Loc Configurations Seules'!R:X,7,FALSE),VLOOKUP(G22,'Loc Coefficients Location'!A:G,7,FALSE)),"") | S22: =IF(ISNUMBER(R22),R22*$F22,"")
A23: 1 cage pour emplacement PCI | B23: HPE ProLiant DL20 Gen10 Plus x8/x8 LP FIO Riser Kit | C23: P46114-B21 | D23: 1 | G23: PC_SE/PLX86 | H23: =IF(ISNUMBER($F23),ROUND($F23*H$2,2),"") | I23: =IF(ISNUMBER($F23),ROUND($F23*I$2,2),"") | J23: =IF(ISNUMBER($F23),ROUND($F23*J$2,2),"") | K23: =IF(ISNUMBER($F23),ROUND($F23*K$2,2),"") | L23: =IF(ISNUMBER(F23),IF(LEFT(A23,3)="Cat",VLOOKUP(A23,'Loc Configurations Seules'!R:U,4,FALSE),VLOOKUP(G23,'Loc Coefficients Location'!A:D,4,FALSE)),"") | M23: =IF(ISNUMBER(L23),L23*$F23,"") | N23: =IF(ISNUMBER(F23),IF(LEFT(A23,3)="Cat",VLOOKUP(A23,'Loc Configurations Seules'!R:V,5,FALSE),VLOOKUP(G23,'Loc Coefficients Location'!A:E,5,FALSE)),"") | O23: =IF(ISNUMBER(N23),N23*$F23,"") | P23: =IF(ISNUMBER(F23),IF(LEFT(A23,3)="Cat",VLOOKUP(A23,'Loc Configurations Seules'!R:W,6,FALSE),VLOOKUP(G23,'Loc Coefficients Location'!A:F,6,FALSE)),"") | Q23: =IF(ISNUMBER(P23),P23*$F23,"") | R23: =IF(ISNUMBER(F23),IF(LEFT(A23,3)="Cat",VLOOKUP(A23,'Loc Configurations Seules'!R:X,7,FALSE),VLOOKUP(G23,'Loc Coefficients Location'!A:G,7,FALSE)),"") | S23: =IF(ISNUMBER(R23),R23*$F23,"")
A24: Alimentation 290W certifiée 80Plus Platinium | B24: HPE DL20 Gen10 Plat 290W FIO PSU Kit | C24: P21649-B21 | D24: 1 | G24: SOFT/MAINT | H24: =IF(ISNUMBER($F24),ROUND($F24*H$2,2),"") | I24: =IF(ISNUMBER($F24),ROUND($F24*I$2,2),"") | J24: =IF(ISNUMBER($F24),ROUND($F24*J$2,2),"") | K24: =IF(ISNUMBER($F24),ROUND($F24*K$2,2),"") | L24: =IF(ISNUMBER(F24),IF(LEFT(A24,3)="Cat",VLOOKUP(A24,'Loc Configurations Seules'!R:U,4,FALSE),VLOOKUP(G24,'Loc Coefficients Location'!A:D,4,FALSE)),"") | M24: =IF(ISNUMBER(L24),L24*$F24,"") | N24: =IF(ISNUMBER(F24),IF(LEFT(A24,3)="Cat",VLOOKUP(A24,'Loc Configurations Seules'!R:V,5,FALSE),VLOOKUP(G24,'Loc Coefficients Location'!A:E,5,FALSE)),"") | O24: =IF(ISNUMBER(N24),N24*$F24,"") | P24: =IF(ISNUMBER(F24),IF(LEFT(A24,3)="Cat",VLOOKUP(A24,'Loc Configurations Seules'!R:W,6,FALSE),VLOOKUP(G24,'Loc Coefficients Location'!A:F,6,FALSE)),"") | Q24: =IF(ISNUMBER(P24),P24*$F24,"") | R24: =IF(ISNUMBER(F24),IF(LEFT(A24,3)="Cat",VLOOKUP(A24,'Loc Configurations Seules'!R:X,7,FALSE),VLOOKUP(G24,'Loc Coefficients Location'!A:G,7,FALSE)),"") | S24: =IF(ISNUMBER(R24),R24*$F24,"")
A25: Carte d'administration HPE iLO avec API RESTful compatible IPMI v2.0 et Redfish. Licence en version Advanced avec toutes les options activées | B25: HPE iLO Adv 1-svr Lic 1yr Support | C25: 512485-B21 | D25: 1 | G25: PC_SE/PLX86 | H25: =IF(ISNUMBER($F25),ROUND($F25*H$2,2),"") | I25: =IF(ISNUMBER($F25),ROUND($F25*I$2,2),"") | J25: =IF(ISNUMBER($F25),ROUND($F25*J$2,2),"") | K25: =IF(ISNUMBER($F25),ROUND($F25*K$2,2),"") | L25: =IF(ISNUMBER(F25),IF(LEFT(A25,3)="Cat",VLOOKUP(A25,'Loc Configurations Seules'!R:U,4,FALSE),VLOOKUP(G25,'Loc Coefficients Location'!A:D,4,FALSE)),"") | M25: =IF(ISNUMBER(L25),L25*$F25,"") | N25: =IF(ISNUMBER(F25),IF(LEFT(A25,3)="Cat",VLOOKUP(A25,'Loc Configurations Seules'!R:V,5,FALSE),VLOOKUP(G25,'Loc Coefficients Location'!A:E,5,FALSE)),"") | O25: =IF(ISNUMBER(N25),N25*$F25,"") | P25: =IF(ISNUMBER(F25),IF(LEFT(A25,3)="Cat",VLOOKUP(A25,'Loc Configurations Seules'!R:W,6,FALSE),VLOOKUP(G25,'Loc Coefficients Location'!A:F,6,FALSE)),"") | Q25: =IF(ISNUMBER(P25),P25*$F25,"") | R25: =IF(ISNUMBER(F25),IF(LEFT(A25,3)="Cat",VLOOKUP(A25,'Loc Configurations Seules'!R:X,7,FALSE),VLOOKUP(G25,'Loc Coefficients Location'!A:G,7,FALSE)),"") | S25: =IF(ISNUMBER(R25),R25*$F25,"")
A26: Suppresion du cable electrique par defaut | B26: HPE Remove Standard Power Cords | C26: 469774-409 | D26: 1 | G26: PC_SE/PLX86 | H26: =IF(ISNUMBER($F26),ROUND($F26*H$2,2),"") | I26: =IF(ISNUMBER($F26),ROUND($F26*I$2,2),"") | J26: =IF(ISNUMBER($F26),ROUND($F26*J$2,2),"") | K26: =IF(ISNUMBER($F26),ROUND($F26*K$2,2),"") | L26: =IF(ISNUMBER(F26),IF(LEFT(A26,3)="Cat",VLOOKUP(A26,'Loc Configurations Seules'!R:U,4,FALSE),VLOOKUP(G26,'Loc Coefficients Location'!A:D,4,FALSE)),"") | M26: =IF(ISNUMBER(L26),L26*$F26,"") | N26: =IF(ISNUMBER(F26),IF(LEFT(A26,3)="Cat",VLOOKUP(A26,'Loc Configurations Seules'!R:V,5,FALSE),VLOOKUP(G26,'Loc Coefficients Location'!A:E,5,FALSE)),"") | O26: =IF(ISNUMBER(N26),N26*$F26,"") | P26: =IF(ISNUMBER(F26),IF(LEFT(A26,3)="Cat",VLOOKUP(A26,'Loc Configurations Seules'!R:W,6,FALSE),VLOOKUP(G26,'Loc Coefficients Location'!A:F,6,FALSE)),"") | Q26: =IF(ISNUMBER(P26),P26*$F26,"") | R26: =IF(ISNUMBER(F26),IF(LEFT(A26,3)="Cat",VLOOKUP(A26,'Loc Configurations Seules'!R:X,7,FALSE),VLOOKUP(G26,'Loc Coefficients Location'!A:G,7,FALSE)),"") | S26: =IF(ISNUMBER(R26),R26*$F26,"")
A27: 1 kit de rail pour rack | B27: HPE 1U Short Friction Rail Kit | C27: 775612-B21 | D27: 1 | G27: SOFT/MAINT | H27: =IF(ISNUMBER($F27),ROUND($F27*H$2,2),"") | I27: =IF(ISNUMBER($F27),ROUND($F27*I$2,2),"") | J27: =IF(ISNUMBER($F27),ROUND($F27*J$2,2),"") | K27: =IF(ISNUMBER($F27),ROUND($F27*K$2,2),"") | L27: =IF(ISNUMBER(F27),IF(LEFT(A27,3)="Cat",VLOOKUP(A27,'Loc Configurations Seules'!R:U,4,FALSE),VLOOKUP(G27,'Loc Coefficients Location'!A:D,4,FALSE)),"") | M27: =IF(ISNUMBER(L27),L27*$F27,"") | N27: =IF(ISNUMBER(F27),IF(LEFT(A27,3)="Cat",VLOOKUP(A27,'Loc Configurations Seules'!R:V,5,FALSE),VLOOKUP(G27,'Loc Coefficients Location'!A:E,5,FALSE)),"") | O27: =IF(ISNUMBER(N27),N27*$F27,"") | P27: =IF(ISNUMBER(F27),IF(LEFT(A27,3)="Cat",VLOOKUP(A27,'Loc Configurations Seules'!R:W,6,FALSE),VLOOKUP(G27,'Loc Coefficients Location'!A:F,6,FALSE)),"") | Q27: =IF(ISNUMBER(P27),P27*$F27,"") | R27: =IF(ISNUMBER(F27),IF(LEFT(A27,3)="Cat",VLOOKUP(A27,'Loc Configurations Seules'!R:X,7,FALSE),VLOOKUP(G27,'Loc Coefficients Location'!A:G,7,FALSE)),"") | S27: =IF(ISNUMBER(R27),R27*$F27,"")
A28: Livraison devant la porte | B28: Livraison devant la porte | C28: AC111A | D28: 1 | G28: SOFT/MAINT | H28: =IF(ISNUMBER($F28),ROUND($F28*H$2,2),"") | I28: =IF(ISNUMBER($F28),ROUND($F28*I$2,2),"") | J28: =IF(ISNUMBER($F28),ROUND($F28*J$2,2),"") | K28: =IF(ISNUMBER($F28),ROUND($F28*K$2,2),"") | L28: =IF(ISNUMBER(F28),IF(LEFT(A28,3)="Cat",VLOOKUP(A28,'Loc Configurations Seules'!R:U,4,FALSE),VLOOKUP(G28,'Loc Coefficients Location'!A:D,4,FALSE)),"") | M28: =IF(ISNUMBER(L28),L28*$F28,"") | N28: =IF(ISNUMBER(F28),IF(LEFT(A28,3)="Cat",VLOOKUP(A28,'Loc Configurations Seules'!R:V,5,FALSE),VLOOKUP(G28,'Loc Coefficients Location'!A:E,5,FALSE)),"") | O28: =IF(ISNUMBER(N28),N28*$F28,"") | P28: =IF(ISNUMBER(F28),IF(LEFT(A28,3)="Cat",VLOOKUP(A28,'Loc Configurations Seules'!R:W,6,FALSE),VLOOKUP(G28,'Loc Coefficients Location'!A:F,6,FALSE)),"") | Q28: =IF(ISNUMBER(P28),P28*$F28,"") | R28: =IF(ISNUMBER(F28),IF(LEFT(A28,3)="Cat",VLOOKUP(A28,'Loc Configurations Seules'!R:X,7,FALSE),VLOOKUP(G28,'Loc Coefficients Location'!A:G,7,FALSE)),"") | S28: =IF(ISNUMBER(R28),R28*$F28,"")
A29: Garantie 5 ans J+1 | B29: HPE 5Y Tech Care Basic Service | C29: HU4B2A5 | D29: 1 | G29: SOFT/MAINT | H29: =IF(ISNUMBER($F29),ROUND($F29*H$2,2),"") | I29: =IF(ISNUMBER($F29),ROUND($F29*I$2,2),"") | J29: =IF(ISNUMBER($F29),ROUND($F29*J$2,2),"") | K29: =IF(ISNUMBER($F29),ROUND($F29*K$2,2),"")
A30: Garantie 5 ans J+1 ILO | B30: HPE iLO AdvPack NonBL Support | C30: HU4B2A5#7X4 | D30: 1 | G30: SOFT/MAINT | H30: =IF(ISNUMBER($F30),ROUND($F30*H$2,2),"") | I30: =IF(ISNUMBER($F30),ROUND($F30*I$2,2),"") | J30: =IF(ISNUMBER($F30),ROUND($F30*J$2,2),"") | K30: =IF(ISNUMBER($F30),ROUND($F30*K$2,2),"")
A31: Garantie 5 ans J+1 châssis | B31: HPE ProLiant DL20 Gen10+ Support | C31: HU4B2A5#ZX1 | D31: 1 | G31: SOFT/MAINT | H31: =IF(ISNUMBER($F31),ROUND($F31*H$2,2),"") | I31: =IF(ISNUMBER($F31),ROUND($F31*I$2,2),"") | J31: =IF(ISNUMBER($F31),ROUND($F31*J$2,2),"") | K31: =IF(ISNUMBER($F31),ROUND($F31*K$2,2),"")
H32: =IF(ISNUMBER($F32),ROUND($F32*H$2,2),"") | I32: =IF(ISNUMBER($F32),ROUND($F32*I$2,2),"") | J32: =IF(ISNUMBER($F32),ROUND($F32*J$2,2),"") | K32: =IF(ISNUMBER($F32),ROUND($F32*K$2,2),"") | L32: =IF(ISNUMBER(F32),IF(LEFT(A32,3)="Cat",VLOOKUP(A32,'Loc Configurations Seules'!R:U,4,FALSE),VLOOKUP(G32,'Loc Coefficients Location'!A:D,4,FALSE)),"") | M32: =IF(ISNUMBER(L32),L32*$F32,"") | N32: =IF(ISNUMBER(F32),IF(LEFT(A32,3)="Cat",VLOOKUP(A32,'Loc Configurations Seules'!R:V,5,FALSE),VLOOKUP(G32,'Loc Coefficients Location'!A:E,5,FALSE)),"") | O32: =IF(ISNUMBER(N32),N32*$F32,"") | P32: =IF(ISNUMBER(F32),IF(LEFT(A32,3)="Cat",VLOOKUP(A32,'Loc Configurations Seules'!R:W,6,FALSE),VLOOKUP(G32,'Loc Coefficients Location'!A:F,6,FALSE)),"") | Q32: =IF(ISNUMBER(P32),P32*$F32,"") | R32: =IF(ISNUMBER(F32),IF(LEFT(A32,3)="Cat",VLOOKUP(A32,'Loc Configurations Seules'!R:X,7,FALSE),VLOOKUP(G32,'Loc Coefficients Location'!A:G,7,FALSE)),"") | S32: =IF(ISNUMBER(R32),R32*$F32,"")
A33: Cat1 Conf2 DL325 Gen10 plus | B33: HPE ProLiant DL325 Gen10+ | C33: P18606-B21 | F33: 674.1 | H33: =IF(ISNUMBER($F33),ROUND($F33*H$2,2),"") -> 177.91 | I33: =IF(ISNUMBER($F33),ROUND($F33*I$2,2),"") -> 90.23 | J33: =IF(ISNUMBER($F33),ROUND($F33*J$2,2),"") -> 61.58 | K33: =IF(ISNUMBER($F33),ROUND($F33*K$2,2),"") -> 47.36 | L33: =IF(ISNUMBER(F33),IF(LEFT(A33,3)="Cat",VLOOKUP(A33,'Loc Configurations Seules'!R:U,4,FALSE),VLOOKUP(G33,'Loc Coefficients Location'!A:D,4,FALSE)),"") -> 0.2046 | M33: =IF(ISNUMBER(L33),L33*$F33,"") -> 137.92086 | N33: =IF(ISNUMBER(F33),IF(LEFT(A33,3)="Cat",VLOOKUP(A33,'Loc Configurations Seules'!R:V,5,FALSE),VLOOKUP(G33,'Loc Coefficients Location'!A:E,5,FALSE)),"") -> 0.1072 | O33: =IF(ISNUMBER(N33),N33*$F33,"") -> 72.26352 | P33: =IF(ISNUMBER(F33),IF(LEFT(A33,3)="Cat",VLOOKUP(A33,'Loc Configurations Seules'!R:W,6,FALSE),VLOOKUP(G33,'Loc Coefficients Location'!A:F,6,FALSE)),"") -> 0.0791 | Q33: =IF(ISNUMBER(P33),P33*$F33,"") -> 53.32131 | R33: =IF(ISNUMBER(F33),IF(LEFT(A33,3)="Cat",VLOOKUP(A33,'Loc Configurations Seules'!R:X,7,FALSE),VLOOKUP(G33,'Loc Coefficients Location'!A:G,7,FALSE)),"") -> 0.0649 | S33: =IF(ISNUMBER(R33),R33*$F33,"") -> 43.74909
A34: Serveur rack standard 1U mono-socket AMD | B34: HPE DL325 Gen10+ CTO Svr | C34: P18606-B21 | D34: 1 | G34: PC_SE/PLX86 | H34: =IF(ISNUMBER($F34),ROUND($F34*H$2,2),"") | I34: =IF(ISNUMBER($F34),ROUND($F34*I$2,2),"") | J34: =IF(ISNUMBER($F34),ROUND($F34*J$2,2),"") | K34: =IF(ISNUMBER($F34),ROUND($F34*K$2,2),"") | L34: =IF(ISNUMBER(F34),IF(LEFT(A34,3)="Cat",VLOOKUP(A34,'Loc Configurations Seules'!R:U,4,FALSE),VLOOKUP(G34,'Loc Coefficients Location'!A:D,4,FALSE)),"") | M34: =IF(ISNUMBER(L34),L34*$F34,"") | N34: =IF(ISNUMBER(F34),IF(LEFT(A34,3)="Cat",VLOOKUP(A34,'Loc Configurations Seules'!R:V,5,FALSE),VLOOKUP(G34,'Loc Coefficients Location'!A:E,5,FALSE)),"") | O34: =IF(ISNUMBER(N34),N34*$F34,"") | P34: =IF(ISNUMBER(F34),IF(LEFT(A34,3)="Cat",VLOOKUP(A34,'Loc Configurations Seules'!R:W,6,FALSE),VLOOKUP(G34,'Loc Coefficients Location'!A:F,6,FALSE)),"") | Q34: =IF(ISNUMBER(P34),P34*$F34,"") | R34: =IF(ISNUMBER(F34),IF(LEFT(A34,3)="Cat",VLOOKUP(A34,'Loc Configurations Seules'!R:X,7,FALSE),VLOOKUP(G34,'Loc Coefficients Location'!A:G,7,FALSE)),"") | S34: =IF(ISNUMBER(R34),R34*$F34,"")
A35: Processeur 64 bits AMD EPYC 7232P (3,1 GHz de base / 3,2 Ghz Boost / 8 cœurs / 16 threads / 32 Mo cache L3 / 120 W PDT) | B35: HPE DL325 Gen10+ AMD EPYC 7232P FIO Kit | C35: P19634-L21 | D35: 1 | G35: PC_SE/PLX86 | H35: =IF(ISNUMBER($F35),ROUND($F35*H$2,2),"") | I35: =IF(ISNUMBER($F35),ROUND($F35*I$2,2),"") | J35: =IF(ISNUMBER($F35),ROUND($F35*J$2,2),"") | K35: =IF(ISNUMBER($F35),ROUND($F35*K$2,2),"") | L35: =IF(ISNUMBER(F35),IF(LEFT(A35,3)="Cat",VLOOKUP(A35,'Loc Configurations Seules'!R:U,4,FALSE),VLOOKUP(G35,'Loc Coefficients Location'!A:D,4,FALSE)),"") | M35: =IF(ISNUMBER(L35),L35*$F35,"") | N35: =IF(ISNUMBER(F35),IF(LEFT(A35,3)="Cat",VLOOKUP(A35,'Loc Configurations Seules'!R:V,5,FALSE),VLOOKUP(G35,'Loc Coefficients Location'!A:E,5,FALSE)),"") | O35: =IF(ISNUMBER(N35),N35*$F35,"") | P35: =IF(ISNUMBER(F35),IF(LEFT(A35,3)="Cat",VLOOKUP(A35,'Loc Configurations Seules'!R:W,6,FALSE),VLOOKUP(G35,'Loc Coefficients Location'!A:F,6,FALSE)),"") | Q35: =IF(ISNUMBER(P35),P35*$F35,"") | R35: =IF(ISNUMBER(F35),IF(LEFT(A35,3)="Cat",VLOOKUP(A35,'Loc Configurations Seules'!R:X,7,FALSE),VLOOKUP(G35,'Loc Coefficients Location'!A:G,7,FALSE)),"") | S35: =IF(ISNUMBER(R35),R35*$F35,"")
A36: 1 barrette mémoire HPE DDR4 2933 MHz RDIMM de 32 Go (soit 4 Go ECC par cœur) | B36: HPE 32GB 2Rx4 PC4-3200AA-R Smart Kit | C36: P07646-B21 | D36: 1 | G36: PC_SE/PLX86 | H36: =IF(ISNUMBER($F36),ROUND($F36*H$2,2),"") | I36: =IF(ISNUMBER($F36),ROUND($F36*I$2,2),"") | J36: =IF(ISNUMBER($F36),ROUND($F36*J$2,2),"") | K36: =IF(ISNUMBER($F36),ROUND($F36*K$2,2),"") | L36: =IF(ISNUMBER(F36),IF(LEFT(A36,3)="Cat",VLOOKUP(A36,'Loc Configurations Seules'!R:U,4,FALSE),VLOOKUP(G36,'Loc Coefficients Location'!A:D,4,FALSE)),"") | M36: =IF(ISNUMBER(L36),L36*$F36,"") | N36: =IF(ISNUMBER(F36),IF(LEFT(A36,3)="Cat",VLOOKUP(A36,'Loc Configurations Seules'!R:V,5,FALSE),VLOOKUP(G36,'Loc Coefficients Location'!A:E,5,FALSE)),"") | O36: =IF(ISNUMBER(N36),N36*$F36,"") | P36: =IF(ISNUMBER(F36),IF(LEFT(A36,3)="Cat",VLOOKUP(A36,'Loc Configurations Seules'!R:W,6,FALSE),VLOOKUP(G36,'Loc Coefficients Location'!A:F,6,FALSE)),"") | Q36: =IF(ISNUMBER(P36),P36*$F36,"") | R36: =IF(ISNUMBER(F36),IF(LEFT(A36,3)="Cat",VLOOKUP(A36,'Loc Configurations Seules'!R:X,7,FALSE),VLOOKUP(G36,'Loc Coefficients Location'!A:G,7,FALSE)),"") | S36: =IF(ISNUMBER(R36),R36*$F36,"")
A37: 1 cage Disque LFF | B37: HPE DL325 Gen10+ 4LFF LP FIO Cage Kit | C37: P15525-B21 | D37: 1 | G37: PC_SE/PLX86 | H37: =IF(ISNUMBER($F37),ROUND($F37*H$2,2),"") | I37: =IF(ISNUMBER($F37),ROUND($F37*I$2,2),"") | J37: =IF(ISNUMBER($F37),ROUND($F37*J$2,2),"") | K37: =IF(ISNUMBER($F37),ROUND($F37*K$2,2),"") | L37: =IF(ISNUMBER(F37),IF(LEFT(A37,3)="Cat",VLOOKUP(A37,'Loc Configurations Seules'!R:U,4,FALSE),VLOOKUP(G37,'Loc Coefficients Location'!A:D,4,FALSE)),"") | M37: =IF(ISNUMBER(L37),L37*$F37,"") | N37: =IF(ISNUMBER(F37),IF(LEFT(A37,3)="Cat",VLOOKUP(A37,'Loc Configurations Seules'!R:V,5,FALSE),VLOOKUP(G37,'Loc Coefficients Location'!A:E,5,FALSE)),"") | O37: =IF(ISNUMBER(N37),N37*$F37,"") | P37: =IF(ISNUMBER(F37),IF(LEFT(A37,3)="Cat",VLOOKUP(A37,'Loc Configurations Seules'!R:W,6,FALSE),VLOOKUP(G37,'Loc Coefficients Location'!A:F,6,FALSE)),"") | Q37: =IF(ISNUMBER(P37),P37*$F37,"") | R37: =IF(ISNUMBER(F37),IF(LEFT(A37,3)="Cat",VLOOKUP(A37,'Loc Configurations Seules'!R:X,7,FALSE),VLOOKUP(G37,'Loc Coefficients Location'!A:G,7,FALSE)),"") | S37: =IF(ISNUMBER(R37),R37*$F37,"")
A38: 2 ports Ethernet Gigabit intégrés | B38: Marvell QL41132HQRJ Ethernet 10Gb 2-port BASE-T OCP3 Adapter for HPE | C38: P10103-B21 | D38: 1 | G38: PC_SE/PLX86 | H38: =IF(ISNUMBER($F38),ROUND($F38*H$2,2),"") | I38: =IF(ISNUMBER($F38),ROUND($F38*I$2,2),"") | J38: =IF(ISNUMBER($F38),ROUND($F38*J$2,2),"") | K38: =IF(ISNUMBER($F38),ROUND($F38*K$2,2),"") | L38: =IF(ISNUMBER(F38),IF(LEFT(A38,3)="Cat",VLOOKUP(A38,'Loc Configurations Seules'!R:U,4,FALSE),VLOOKUP(G38,'Loc Coefficients Location'!A:D,4,FALSE)),"") | M38: =IF(ISNUMBER(L38),L38*$F38,"") | N38: =IF(ISNUMBER(F38),IF(LEFT(A38,3)="Cat",VLOOKUP(A38,'Loc Configurations Seules'!R:V,5,FALSE),VLOOKUP(G38,'Loc Coefficients Location'!A:E,5,FALSE)),"") | O38: =IF(ISNUMBER(N38),N38*$F38,"") | P38: =IF(ISNUMBER(F38),IF(LEFT(A38,3)="Cat",VLOOKUP(A38,'Loc Configurations Seules'!R:W,6,FALSE),VLOOKUP(G38,'Loc Coefficients Location'!A:F,6,FALSE)),"") | Q38: =IF(ISNUMBER(P38),P38*$F38,"") | R38: =IF(ISNUMBER(F38),IF(LEFT(A38,3)="Cat",VLOOKUP(A38,'Loc Configurations Seules'!R:X,7,FALSE),VLOOKUP(G38,'Loc Coefficients Location'!A:G,7,FALSE)),"") | S38: =IF(ISNUMBER(R38),R38*$F38,"")
A39: alimentation HPE FlexSlot de 800W certifiée 80PLUS Titanium | B39: HPE 800W FS Ti Ht Plg LH Pwr Sply Kit | C39: 865438-B21 | D39: 1 | G39: PC_SE/PLX86 | H39: =IF(ISNUMBER($F39),ROUND($F39*H$2,2),"") | I39: =IF(ISNUMBER($F39),ROUND($F39*I$2,2),"") | J39: =IF(ISNUMBER($F39),ROUND($F39*J$2,2),"") | K39: =IF(ISNUMBER($F39),ROUND($F39*K$2,2),"") | L39: =IF(ISNUMBER(F39),IF(LEFT(A39,3)="Cat",VLOOKUP(A39,'Loc Configurations Seules'!R:U,4,FALSE),VLOOKUP(G39,'Loc Coefficients Location'!A:D,4,FALSE)),"") | M39: =IF(ISNUMBER(L39),L39*$F39,"") | N39: =IF(ISNUMBER(F39),IF(LEFT(A39,3)="Cat",VLOOKUP(A39,'Loc Configurations Seules'!R:V,5,FALSE),VLOOKUP(G39,'Loc Coefficients Location'!A:E,5,FALSE)),"") | O39: =IF(ISNUMBER(N39),N39*$F39,"") | P39: =IF(ISNUMBER(F39),IF(LEFT(A39,3)="Cat",VLOOKUP(A39,'Loc Configurations Seules'!R:W,6,FALSE),VLOOKUP(G39,'Loc Coefficients Location'!A:F,6,FALSE)),"") | Q39: =IF(ISNUMBER(P39),P39*$F39,"") | R39: =IF(ISNUMBER(F39),IF(LEFT(A39,3)="Cat",VLOOKUP(A39,'Loc Configurations Seules'!R:X,7,FALSE),VLOOKUP(G39,'Loc Coefficients Location'!A:G,7,FALSE)),"") | S39: =IF(ISNUMBER(R39),R39*$F39,"")
A40: Carte d'administration HPE iLO avec API RESTful compatible IPMI v2.0 et Redfish. Licence en version Advanced avec toutes les options activées | B40: HPE iLO Adv 1-svr Lic 1yr Support | C40: 512485-B21 | D40: 1 | G40: PC_SE/PLX86 | H40: =IF(ISNUMBER($F40),ROUND($F40*H$2,2),"") | I40: =IF(ISNUMBER($F40),ROUND($F40*I$2,2),"") | J40: =IF(ISNUMBER($F40),ROUND($F40*J$2,2),"") | K40: =IF(ISNUMBER($F40),ROUND($F40*K$2,2),"") | L40: =IF(ISNUMBER(F40),IF(LEFT(A40,3)="Cat",VLOOKUP(A40,'Loc Configurations Seules'!R:U,4,FALSE),VLOOKUP(G40,'Loc Coefficients Location'!A:D,4,FALSE)),"") | M40: =IF(ISNUMBER(L40),L40*$F40,"") | N40: =IF(ISNUMBER(F40),IF(LEFT(A40,3)="Cat",VLOOKUP(A40,'Loc Configurations Seules'!R:V,5,FALSE),VLOOKUP(G40,'Loc Coefficients Location'!A:E,5,FALSE)),"") | O40: =IF(ISNUMBER(N40),N40*$F40,"") | P40: =IF(ISNUMBER(F40),IF(LEFT(A40,3)="Cat",VLOOKUP(A40,'Loc Configurations Seules'!R:W,6,FALSE),VLOOKUP(G40,'Loc Coefficients Location'!A:F,6,FALSE)),"") | Q40: =IF(ISNUMBER(P40),P40*$F40,"") | R40: =IF(ISNUMBER(F40),IF(LEFT(A40,3)="Cat",VLOOKUP(A40,'Loc Configurations Seules'!R:X,7,FALSE),VLOOKUP(G40,'Loc Coefficients Location'!A:G,7,FALSE)),"") | S40: =IF(ISNUMBER(R40),R40*$F40,"")
A41: 1 kit de câbles pour SATA LFF | B41: HPE DL325 Gen10 Plus LFF SATA FIO Cable Kit | C41: P15903-B21 | D41: 1 | G41: PC_SE/PLX86 | H41: =IF(ISNUMBER($F41),ROUND($F41*H$2,2),"") | I41: =IF(ISNUMBER($F41),ROUND($F41*I$2,2),"") | J41: =IF(ISNUMBER($F41),ROUND($F41*J$2,2),"") | K41: =IF(ISNUMBER($F41),ROUND($F41*K$2,2),"") | L41: =IF(ISNUMBER(F41),IF(LEFT(A41,3)="Cat",VLOOKUP(A41,'Loc Configurations Seules'!R:U,4,FALSE),VLOOKUP(G41,'Loc Coefficients Location'!A:D,4,FALSE)),"") | M41: =IF(ISNUMBER(L41),L41*$F41,"") | N41: =IF(ISNUMBER(F41),IF(LEFT(A41,3)="Cat",VLOOKUP(A41,'Loc Configurations Seules'!R:V,5,FALSE),VLOOKUP(G41,'Loc Coefficients Location'!A:E,5,FALSE)),"") | O41: =IF(ISNUMBER(N41),N41*$F41,"") | P41: =IF(ISNUMBER(F41),IF(LEFT(A41,3)="Cat",VLOOKUP(A41,'Loc Configurations Seules'!R:W,6,FALSE),VLOOKUP(G41,'Loc Coefficients Location'!A:F,6,FALSE)),"") | Q41: =IF(ISNUMBER(P41),P41*$F41,"") | R41: =IF(ISNUMBER(F41),IF(LEFT(A41,3)="Cat",VLOOKUP(A41,'Loc Configurations Seules'!R:X,7,FALSE),VLOOKUP(G41,'Loc Coefficients Location'!A:G,7,FALSE)),"") | S41: =IF(ISNUMBER(R41),R41*$F41,"")
A42: 1 kit de rail pour rack | B42: HPE DL325 Gen10 Plus 1075mm Easy Install Rail Kit | C42: P18544-B21 | D42: 1 | G42: PC_SE/PLX86 | H42: =IF(ISNUMBER($F42),ROUND($F42*H$2,2),"") | I42: =IF(ISNUMBER($F42),ROUND($F42*I$2,2),"") | J42: =IF(ISNUMBER($F42),ROUND($F42*J$2,2),"") | K42: =IF(ISNUMBER($F42),ROUND($F42*K$2,2),"") | L42: =IF(ISNUMBER(F42),IF(LEFT(A42,3)="Cat",VLOOKUP(A42,'Loc Configurations Seules'!R:U,4,FALSE),VLOOKUP(G42,'Loc Coefficients Location'!A:D,4,FALSE)),"") | M42: =IF(ISNUMBER(L42),L42*$F42,"") | N42: =IF(ISNUMBER(F42),IF(LEFT(A42,3)="Cat",VLOOKUP(A42,'Loc Configurations Seules'!R:V,5,FALSE),VLOOKUP(G42,'Loc Coefficients Location'!A:E,5,FALSE)),"") | O42: =IF(ISNUMBER(N42),N42*$F42,"") | P42: =IF(ISNUMBER(F42),IF(LEFT(A42,3)="Cat",VLOOKUP(A42,'Loc Configurations Seules'!R:W,6,FALSE),VLOOKUP(G42,'Loc Coefficients Location'!A:F,6,FALSE)),"") | Q42: =IF(ISNUMBER(P42),P42*$F42,"") | R42: =IF(ISNUMBER(F42),IF(LEFT(A42,3)="Cat",VLOOKUP(A42,'Loc Configurations Seules'!R:X,7,FALSE),VLOOKUP(G42,'Loc Coefficients Location'!A:G,7,FALSE)),"") | S42: =IF(ISNUMBER(R42),R42*$F42,"")
A43: Suppresion du cable electrique par defaut | B43: HPE Remove Standard Power Cords | C43: 469774-409 | D43: 1 | G43: PC_SE/PLX86 | H43: =IF(ISNUMBER($F43),ROUND($F43*H$2,2),"") | I43: =IF(ISNUMBER($F43),ROUND($F43*I$2,2),"") | J43: =IF(ISNUMBER($F43),ROUND($F43*J$2,2),"") | K43: =IF(ISNUMBER($F43),ROUND($F43*K$2,2),"") | L43: =IF(ISNUMBER(F43),IF(LEFT(A43,3)="Cat",VLOOKUP(A43,'Loc Configurations Seules'!R:U,4,FALSE),VLOOKUP(G43,'Loc Coefficients Location'!A:D,4,FALSE)),"") | M43: =IF(ISNUMBER(L43),L43*$F43,"") | N43: =IF(ISNUMBER(F43),IF(LEFT(A43,3)="Cat",VLOOKUP(A43,'Loc Configurations Seules'!R:V,5,FALSE),VLOOKUP(G43,'Loc Coefficients Location'!A:E,5,FALSE)),"") | O43: =IF(ISNUMBER(N43),N43*$F43,"") | P43: =IF(ISNUMBER(F43),IF(LEFT(A43,3)="Cat",VLOOKUP(A43,'Loc Configurations Seules'!R:W,6,FALSE),VLOOKUP(G43,'Loc Coefficients Location'!A:F,6,FALSE)),"") | Q43: =IF(ISNUMBER(P43),P43*$F43,"") | R43: =IF(ISNUMBER(F43),IF(LEFT(A43,3)="Cat",VLOOKUP(A43,'Loc Configurations Seules'!R:X,7,FALSE),VLOOKUP(G43,'Loc Coefficients Location'!A:G,7,FALSE)),"") | S43: =IF(ISNUMBER(R43),R43*$F43,"")
A44: Livraison devant la porte | B44: Livraison devant la porte | C44: AC114A | D44: 1 | G44: SOFT/MAINT | H44: =IF(ISNUMBER($F44),ROUND($F44*H$2,2),"") | I44: =IF(ISNUMBER($F44),ROUND($F44*I$2,2),"") | J44: =IF(ISNUMBER($F44),ROUND($F44*J$2,2),"") | K44: =IF(ISNUMBER($F44),ROUND($F44*K$2,2),"") | L44: =IF(ISNUMBER(F44),IF(LEFT(A44,3)="Cat",VLOOKUP(A44,'Loc Configurations Seules'!R:U,4,FALSE),VLOOKUP(G44,'Loc Coefficients Location'!A:D,4,FALSE)),"") | M44: =IF(ISNUMBER(L44),L44*$F44,"") | N44: =IF(ISNUMBER(F44),IF(LEFT(A44,3)="Cat",VLOOKUP(A44,'Loc Configurations Seules'!R:V,5,FALSE),VLOOKUP(G44,'Loc Coefficients Location'!A:E,5,FALSE)),"") | O44: =IF(ISNUMBER(N44),N44*$F44,"") | P44: =IF(ISNUMBER(F44),IF(LEFT(A44,3)="Cat",VLOOKUP(A44,'Loc Configurations Seules'!R:W,6,FALSE),VLOOKUP(G44,'Loc Coefficients Location'!A:F,6,FALSE)),"") | Q44: =IF(ISNUMBER(P44),P44*$F44,"") | R44: =IF(ISNUMBER(F44),IF(LEFT(A44,3)="Cat",VLOOKUP(A44,'Loc Configurations Seules'!R:X,7,FALSE),VLOOKUP(G44,'Loc Coefficients Location'!A:G,7,FALSE)),"") | S44: =IF(ISNUMBER(R44),R44*$F44,"")
A45: Garantie 5 ans J+1 | B45: HPE 5Y Tech Care Basic Service | C45: HU4B2A5 | D45: 1 | G45: SOFT/MAINT | H45: =IF(ISNUMBER($F45),ROUND($F45*H$2,2),"") | I45: =IF(ISNUMBER($F45),ROUND($F45*I$2,2),"") | J45: =IF(ISNUMBER($F45),ROUND($F45*J$2,2),"") | K45: =IF(ISNUMBER($F45),ROUND($F45*K$2,2),"")
A46: Garantie 5 ans J+1 ILO | B46: HPE iLO AdvPack NonBL Support | C46: HU4B2A5#7X4 | D46: 1 | G46: SOFT/MAINT | H46: =IF(ISNUMBER($F46),ROUND($F46*H$2,2),"") | I46: =IF(ISNUMBER($F46),ROUND($F46*I$2,2),"") | J46: =IF(ISNUMBER($F46),ROUND($F46*J$2,2),"") | K46: =IF(ISNUMBER($F46),ROUND($F46*K$2,2),"")
A47: Garantie 5 ans J+1 châssis | B47: HPE DL325 GEN10 PLUS Supp | C47: HU4B2A5#YL0 | D47: 1 | G47: SOFT/MAINT | H47: =IF(ISNUMBER($F47),ROUND($F47*H$2,2),"") | I47: =IF(ISNUMBER($F47),ROUND($F47*I$2,2),"") | J47: =IF(ISNUMBER($F47),ROUND($F47*J$2,2),"") | K47: =IF(ISNUMBER($F47),ROUND($F47*K$2,2),"")
H48: =IF(ISNUMBER($F48),ROUND($F48*H$2,2),"") | I48: =IF(ISNUMBER($F48),ROUND($F48*I$2,2),"") | J48: =IF(ISNUMBER($F48),ROUND($F48*J$2,2),"") | K48: =IF(ISNUMBER($F48),ROUND($F48*K$2,2),"") | L48: =IF(ISNUMBER(F48),IF(LEFT(A48,3)="Cat",VLOOKUP(A48,'Loc Configurations Seules'!R:U,4,FALSE),VLOOKUP(G48,'Loc Coefficients Location'!A:D,4,FALSE)),"") | M48: =IF(ISNUMBER(L48),L48*$F48,"") | N48: =IF(ISNUMBER(F48),IF(LEFT(A48,3)="Cat",VLOOKUP(A48,'Loc Configurations Seules'!R:V,5,FALSE),VLOOKUP(G48,'Loc Coefficients Location'!A:E,5,FALSE)),"") | O48: =IF(ISNUMBER(N48),N48*$F48,"") | P48: =IF(ISNUMBER(F48),IF(LEFT(A48,3)="Cat",VLOOKUP(A48,'Loc Configurations Seules'!R:W,6,FALSE),VLOOKUP(G48,'Loc Coefficients Location'!A:F,6,FALSE)),"") | Q48: =IF(ISNUMBER(P48),P48*$F48,"") | R48: =IF(ISNUMBER(F48),IF(LEFT(A48,3)="Cat",VLOOKUP(A48,'Loc Configurations Seules'!R:X,7,FALSE),VLOOKUP(G48,'Loc Coefficients Location'!A:G,7,FALSE)),"") | S48: =IF(ISNUMBER(R48),R48*$F48,"")
A49: Cat1 Conf3 Edge EL300 | B49: HPE EL300 v2 | C49: P25828-B21 | F49: 1666.29 | H49: =IF(ISNUMBER($F49),ROUND($F49*H$2,2),"") -> 439.77 | I49: =IF(ISNUMBER($F49),ROUND($F49*I$2,2),"") -> 223.04 | J49: =IF(ISNUMBER($F49),ROUND($F49*J$2,2),"") -> 152.22 | K49: =IF(ISNUMBER($F49),ROUND($F49*K$2,2),"") -> 117.07 | L49: =IF(ISNUMBER(F49),IF(LEFT(A49,3)="Cat",VLOOKUP(A49,'Loc Configurations Seules'!R:U,4,FALSE),VLOOKUP(G49,'Loc Coefficients Location'!A:D,4,FALSE)),"") -> 0.2207 | M49: =IF(ISNUMBER(L49),L49*$F49,"") -> 367.7502 | N49: =IF(ISNUMBER(F49),IF(LEFT(A49,3)="Cat",VLOOKUP(A49,'Loc Configurations Seules'!R:V,5,FALSE),VLOOKUP(G49,'Loc Coefficients Location'!A:E,5,FALSE)),"") -> 0.1151 | O49: =IF(ISNUMBER(N49),N49*$F49,"") -> 191.78998 | P49: =IF(ISNUMBER(F49),IF(LEFT(A49,3)="Cat",VLOOKUP(A49,'Loc Configurations Seules'!R:W,6,FALSE),VLOOKUP(G49,'Loc Coefficients Location'!A:F,6,FALSE)),"") -> 0.082 | Q49: =IF(ISNUMBER(P49),P49*$F49,"") -> 136.63578 | R49: =IF(ISNUMBER(F49),IF(LEFT(A49,3)="Cat",VLOOKUP(A49,'Loc Configurations Seules'!R:X,7,FALSE),VLOOKUP(G49,'Loc Coefficients Location'!A:G,7,FALSE)),"") -> 0.0662 | S49: =IF(ISNUMBER(R49),R49*$F49,"") -> 110.3084
A50: Serveur de type Edge | B50: HPE EL300 v2 Converged Edge System | C50: P25828-B21 | D50: 1 | G50: PC_SE/EDGE | H50: =IF(ISNUMBER($F50),ROUND($F50*H$2,2),"") | I50: =IF(ISNUMBER($F50),ROUND($F50*I$2,2),"") | J50: =IF(ISNUMBER($F50),ROUND($F50*J$2,2),"") | K50: =IF(ISNUMBER($F50),ROUND($F50*K$2,2),"") | L50: =IF(ISNUMBER(F50),IF(LEFT(A50,3)="Cat",VLOOKUP(A50,'Loc Configurations Seules'!R:U,4,FALSE),VLOOKUP(G50,'Loc Coefficients Location'!A:D,4,FALSE)),"") | M50: =IF(ISNUMBER(L50),L50*$F50,"") | N50: =IF(ISNUMBER(F50),IF(LEFT(A50,3)="Cat",VLOOKUP(A50,'Loc Configurations Seules'!R:V,5,FALSE),VLOOKUP(G50,'Loc Coefficients Location'!A:E,5,FALSE)),"") | O50: =IF(ISNUMBER(N50),N50*$F50,"") | P50: =IF(ISNUMBER(F50),IF(LEFT(A50,3)="Cat",VLOOKUP(A50,'Loc Configurations Seules'!R:W,6,FALSE),VLOOKUP(G50,'Loc Coefficients Location'!A:F,6,FALSE)),"") | Q50: =IF(ISNUMBER(P50),P50*$F50,"") | R50: =IF(ISNUMBER(F50),IF(LEFT(A50,3)="Cat",VLOOKUP(A50,'Loc Configurations Seules'!R:X,7,FALSE),VLOOKUP(G50,'Loc Coefficients Location'!A:G,7,FALSE)),"") | S50: =IF(ISNUMBER(R50),R50*$F50,"")
A51: Processeur 64 bits Intel Core i5-7300U (2.6GHz/2-core/15W) | B51: Intel Core i5-7300U FIO Basic Kit EL300 | C51: P25834-B21 | D51: 1 | G51: PC_SE/EDGE | H51: =IF(ISNUMBER($F51),ROUND($F51*H$2,2),"") | I51: =IF(ISNUMBER($F51),ROUND($F51*I$2,2),"") | J51: =IF(ISNUMBER($F51),ROUND($F51*J$2,2),"") | K51: =IF(ISNUMBER($F51),ROUND($F51*K$2,2),"") | L51: =IF(ISNUMBER(F51),IF(LEFT(A51,3)="Cat",VLOOKUP(A51,'Loc Configurations Seules'!R:U,4,FALSE),VLOOKUP(G51,'Loc Coefficients Location'!A:D,4,FALSE)),"") | M51: =IF(ISNUMBER(L51),L51*$F51,"") | N51: =IF(ISNUMBER(F51),IF(LEFT(A51,3)="Cat",VLOOKUP(A51,'Loc Configurations Seules'!R:V,5,FALSE),VLOOKUP(G51,'Loc Coefficients Location'!A:E,5,FALSE)),"") | O51: =IF(ISNUMBER(N51),N51*$F51,"") | P51: =IF(ISNUMBER(F51),IF(LEFT(A51,3)="Cat",VLOOKUP(A51,'Loc Configurations Seules'!R:W,6,FALSE),VLOOKUP(G51,'Loc Coefficients Location'!A:F,6,FALSE)),"") | Q51: =IF(ISNUMBER(P51),P51*$F51,"") | R51: =IF(ISNUMBER(F51),IF(LEFT(A51,3)="Cat",VLOOKUP(A51,'Loc Configurations Seules'!R:X,7,FALSE),VLOOKUP(G51,'Loc Coefficients Location'!A:G,7,FALSE)),"") | S51: =IF(ISNUMBER(R51),R51*$F51,"")
A52: 1 barrette mémoire HPE DDR4 2666 MHz RDIMM de 8 Go (soit 4 Go ECC par cœur) | B52: HPE EL 8GB 2Rx8 DDR4-2400V-R FIO Kit | C52: P09176-B21 | D52: 1 | G52: PC_SE/EDGE | H52: =IF(ISNUMBER($F52),ROUND($F52*H$2,2),"") | I52: =IF(ISNUMBER($F52),ROUND($F52*I$2,2),"") | J52: =IF(ISNUMBER($F52),ROUND($F52*J$2,2),"") | K52: =IF(ISNUMBER($F52),ROUND($F52*K$2,2),"") | L52: =IF(ISNUMBER(F52),IF(LEFT(A52,3)="Cat",VLOOKUP(A52,'Loc Configurations Seules'!R:U,4,FALSE),VLOOKUP(G52,'Loc Coefficients Location'!A:D,4,FALSE)),"") | M52: =IF(ISNUMBER(L52),L52*$F52,"") | N52: =IF(ISNUMBER(F52),IF(LEFT(A52,3)="Cat",VLOOKUP(A52,'Loc Configurations Seules'!R:V,5,FALSE),VLOOKUP(G52,'Loc Coefficients Location'!A:E,5,FALSE)),"") | O52: =IF(ISNUMBER(N52),N52*$F52,"") | P52: =IF(ISNUMBER(F52),IF(LEFT(A52,3)="Cat",VLOOKUP(A52,'Loc Configurations Seules'!R:W,6,FALSE),VLOOKUP(G52,'Loc Coefficients Location'!A:F,6,FALSE)),"") | Q52: =IF(ISNUMBER(P52),P52*$F52,"") | R52: =IF(ISNUMBER(F52),IF(LEFT(A52,3)="Cat",VLOOKUP(A52,'Loc Configurations Seules'!R:X,7,FALSE),VLOOKUP(G52,'Loc Coefficients Location'!A:G,7,FALSE)),"") | S52: =IF(ISNUMBER(R52),R52*$F52,"")
A53: 1 disque SSD de 120 Go 6G SATA M.2 2,5 pouces (SFF) | B53: HPE EL 120GB SATA RI M.2 2242 PLP MV SSD | C53: P44366-B21 | D53: 1 | G53: PC_SE/EDGE | H53: =IF(ISNUMBER($F53),ROUND($F53*H$2,2),"") | I53: =IF(ISNUMBER($F53),ROUND($F53*I$2,2),"") | J53: =IF(ISNUMBER($F53),ROUND($F53*J$2,2),"") | K53: =IF(ISNUMBER($F53),ROUND($F53*K$2,2),"") | L53: =IF(ISNUMBER(F53),IF(LEFT(A53,3)="Cat",VLOOKUP(A53,'Loc Configurations Seules'!R:U,4,FALSE),VLOOKUP(G53,'Loc Coefficients Location'!A:D,4,FALSE)),"") | M53: =IF(ISNUMBER(L53),L53*$F53,"") | N53: =IF(ISNUMBER(F53),IF(LEFT(A53,3)="Cat",VLOOKUP(A53,'Loc Configurations Seules'!R:V,5,FALSE),VLOOKUP(G53,'Loc Coefficients Location'!A:E,5,FALSE)),"") | O53: =IF(ISNUMBER(N53),N53*$F53,"") | P53: =IF(ISNUMBER(F53),IF(LEFT(A53,3)="Cat",VLOOKUP(A53,'Loc Configurations Seules'!R:W,6,FALSE),VLOOKUP(G53,'Loc Coefficients Location'!A:F,6,FALSE)),"") | Q53: =IF(ISNUMBER(P53),P53*$F53,"") | R53: =IF(ISNUMBER(F53),IF(LEFT(A53,3)="Cat",VLOOKUP(A53,'Loc Configurations Seules'!R:X,7,FALSE),VLOOKUP(G53,'Loc Coefficients Location'!A:G,7,FALSE)),"") | S53: =IF(ISNUMBER(R53),R53*$F53,"")
A54: Kit pour cage disque M.2 | B54: HPE EL300 SFF to M.2 Enable Kit | C54: P04054-B21 | D54: 1 | G54: PC_SE/EDGE | H54: =IF(ISNUMBER($F54),ROUND($F54*H$2,2),"") | I54: =IF(ISNUMBER($F54),ROUND($F54*I$2,2),"") | J54: =IF(ISNUMBER($F54),ROUND($F54*J$2,2),"") | K54: =IF(ISNUMBER($F54),ROUND($F54*K$2,2),"") | L54: =IF(ISNUMBER(F54),IF(LEFT(A54,3)="Cat",VLOOKUP(A54,'Loc Configurations Seules'!R:U,4,FALSE),VLOOKUP(G54,'Loc Coefficients Location'!A:D,4,FALSE)),"") | M54: =IF(ISNUMBER(L54),L54*$F54,"") | N54: =IF(ISNUMBER(F54),IF(LEFT(A54,3)="Cat",VLOOKUP(A54,'Loc Configurations Seules'!R:V,5,FALSE),VLOOKUP(G54,'Loc Coefficients Location'!A:E,5,FALSE)),"") | O54: =IF(ISNUMBER(N54),N54*$F54,"") | P54: =IF(ISNUMBER(F54),IF(LEFT(A54,3)="Cat",VLOOKUP(A54,'Loc Configurations Seules'!R:W,6,FALSE),VLOOKUP(G54,'Loc Coefficients Location'!A:F,6,FALSE)),"") | Q54: =IF(ISNUMBER(P54),P54*$F54,"") | R54: =IF(ISNUMBER(F54),IF(LEFT(A54,3)="Cat",VLOOKUP(A54,'Loc Configurations Seules'!R:X,7,FALSE),VLOOKUP(G54,'Loc Coefficients Location'!A:G,7,FALSE)),"") | S54: =IF(ISNUMBER(R54),R54*$F54,"")
A55: Kit carte mère pour alimentation continue | B55: HPE EL300 12VDC FIO Transfer Board | C55: P08120-B21 | D55: 1 | G55: PC_SE/EDGE | H55: =IF(ISNUMBER($F55),ROUND($F55*H$2,2),"") | I55: =IF(ISNUMBER($F55),ROUND($F55*I$2,2),"") | J55: =IF(ISNUMBER($F55),ROUND($F55*J$2,2),"") | K55: =IF(ISNUMBER($F55),ROUND($F55*K$2,2),"") | L55: =IF(ISNUMBER(F55),IF(LEFT(A55,3)="Cat",VLOOKUP(A55,'Loc Configurations Seules'!R:U,4,FALSE),VLOOKUP(G55,'Loc Coefficients Location'!A:D,4,FALSE)),"") | M55: =IF(ISNUMBER(L55),L55*$F55,"") | N55: =IF(ISNUMBER(F55),IF(LEFT(A55,3)="Cat",VLOOKUP(A55,'Loc Configurations Seules'!R:V,5,FALSE),VLOOKUP(G55,'Loc Coefficients Location'!A:E,5,FALSE)),"") | O55: =IF(ISNUMBER(N55),N55*$F55,"") | P55: =IF(ISNUMBER(F55),IF(LEFT(A55,3)="Cat",VLOOKUP(A55,'Loc Configurations Seules'!R:W,6,FALSE),VLOOKUP(G55,'Loc Coefficients Location'!A:F,6,FALSE)),"") | Q55: =IF(ISNUMBER(P55),P55*$F55,"") | R55: =IF(ISNUMBER(F55),IF(LEFT(A55,3)="Cat",VLOOKUP(A55,'Loc Configurations Seules'!R:X,7,FALSE),VLOOKUP(G55,'Loc Coefficients Location'!A:G,7,FALSE)),"") | S55: =IF(ISNUMBER(R55),R55*$F55,"")
A56: alimentation de 80W | B56: HPE EL300 80W 12VDC Power Supply | C56: P08641-B21 | D56: 1 | G56: PC_SE/EDGE | H56: =IF(ISNUMBER($F56),ROUND($F56*H$2,2),"") | I56: =IF(ISNUMBER($F56),ROUND($F56*I$2,2),"") | J56: =IF(ISNUMBER($F56),ROUND($F56*J$2,2),"") | K56: =IF(ISNUMBER($F56),ROUND($F56*K$2,2),"") | L56: =IF(ISNUMBER(F56),IF(LEFT(A56,3)="Cat",VLOOKUP(A56,'Loc Configurations Seules'!R:U,4,FALSE),VLOOKUP(G56,'Loc Coefficients Location'!A:D,4,FALSE)),"") | M56: =IF(ISNUMBER(L56),L56*$F56,"") | N56: =IF(ISNUMBER(F56),IF(LEFT(A56,3)="Cat",VLOOKUP(A56,'Loc Configurations Seules'!R:V,5,FALSE),VLOOKUP(G56,'Loc Coefficients Location'!A:E,5,FALSE)),"") | O56: =IF(ISNUMBER(N56),N56*$F56,"") | P56: =IF(ISNUMBER(F56),IF(LEFT(A56,3)="Cat",VLOOKUP(A56,'Loc Configurations Seules'!R:W,6,FALSE),VLOOKUP(G56,'Loc Coefficients Location'!A:F,6,FALSE)),"") | Q56: =IF(ISNUMBER(P56),P56*$F56,"") | R56: =IF(ISNUMBER(F56),IF(LEFT(A56,3)="Cat",VLOOKUP(A56,'Loc Configurations Seules'!R:X,7,FALSE),VLOOKUP(G56,'Loc Coefficients Location'!A:G,7,FALSE)),"") | S56: =IF(ISNUMBER(R56),R56*$F56,"")
A57: Kit carte mère pour compatibilité processeur Intel i5 | B57: HPE EL300 v2 FIO Carrier Board | C57: P25835-B21 | D57: 1 | G57: SOFTCOST | H57: =IF(ISNUMBER($F57),ROUND($F57*H$2,2),"") | I57: =IF(ISNUMBER($F57),ROUND($F57*I$2,2),"") | J57: =IF(ISNUMBER($F57),ROUND($F57*J$2,2),"") | K57: =IF(ISNUMBER($F57),ROUND($F57*K$2,2),"") | L57: =IF(ISNUMBER(F57),IF(LEFT(A57,3)="Cat",VLOOKUP(A57,'Loc Configurations Seules'!R:U,4,FALSE),VLOOKUP(G57,'Loc Coefficients Location'!A:D,4,FALSE)),"") | M57: =IF(ISNUMBER(L57),L57*$F57,"") | N57: =IF(ISNUMBER(F57),IF(LEFT(A57,3)="Cat",VLOOKUP(A57,'Loc Configurations Seules'!R:V,5,FALSE),VLOOKUP(G57,'Loc Coefficients Location'!A:E,5,FALSE)),"") | O57: =IF(ISNUMBER(N57),N57*$F57,"") | P57: =IF(ISNUMBER(F57),IF(LEFT(A57,3)="Cat",VLOOKUP(A57,'Loc Configurations Seules'!R:W,6,FALSE),VLOOKUP(G57,'Loc Coefficients Location'!A:F,6,FALSE)),"") | Q57: =IF(ISNUMBER(P57),P57*$F57,"") | R57: =IF(ISNUMBER(F57),IF(LEFT(A57,3)="Cat",VLOOKUP(A57,'Loc Configurations Seules'!R:X,7,FALSE),VLOOKUP(G57,'Loc Coefficients Location'!A:G,7,FALSE)),"") | S57: =IF(ISNUMBER(R57),R57*$F57,"")
A58: Carte d'administration iSM spécifique aux matériels Edge. Licence en version Advanced | B58: HPE EL300 iSM Adv 3yr 24x7 Sup/Upd E-LTU | C58: R1P49AAE | D58: 1 | G58: SOFTCOST | H58: =IF(ISNUMBER($F58),ROUND($F58*H$2,2),"") | I58: =IF(ISNUMBER($F58),ROUND($F58*I$2,2),"") | J58: =IF(ISNUMBER($F58),ROUND($F58*J$2,2),"") | K58: =IF(ISNUMBER($F58),ROUND($F58*K$2,2),"") | L58: =IF(ISNUMBER(F58),IF(LEFT(A58,3)="Cat",VLOOKUP(A58,'Loc Configurations Seules'!R:U,4,FALSE),VLOOKUP(G58,'Loc Coefficients Location'!A:D,4,FALSE)),"") | M58: =IF(ISNUMBER(L58),L58*$F58,"") | N58: =IF(ISNUMBER(F58),IF(LEFT(A58,3)="Cat",VLOOKUP(A58,'Loc Configurations Seules'!R:V,5,FALSE),VLOOKUP(G58,'Loc Coefficients Location'!A:E,5,FALSE)),"") | O58: =IF(ISNUMBER(N58),N58*$F58,"") | P58: =IF(ISNUMBER(F58),IF(LEFT(A58,3)="Cat",VLOOKUP(A58,'Loc Configurations Seules'!R:W,6,FALSE),VLOOKUP(G58,'Loc Coefficients Location'!A:F,6,FALSE)),"") | Q58: =IF(ISNUMBER(P58),P58*$F58,"") | R58: =IF(ISNUMBER(F58),IF(LEFT(A58,3)="Cat",VLOOKUP(A58,'Loc Configurations Seules'!R:X,7,FALSE),VLOOKUP(G58,'Loc Coefficients Location'!A:G,7,FALSE)),"") | S58: =IF(ISNUMBER(R58),R58*$F58,"")
A59: Cable Electrique | B59: HPE C13 - CEE-VII EU 250V 10Amp 1.83m Power Cord | C59: AF568A | D59: 1 | G59: PC_SE/PLX86 | H59: =IF(ISNUMBER($F59),ROUND($F59*H$2,2),"") | I59: =IF(ISNUMBER($F59),ROUND($F59*I$2,2),"") | J59: =IF(ISNUMBER($F59),ROUND($F59*J$2,2),"") | K59: =IF(ISNUMBER($F59),ROUND($F59*K$2,2),"") | L59: =IF(ISNUMBER(F59),IF(LEFT(A59,3)="Cat",VLOOKUP(A59,'Loc Configurations Seules'!R:U,4,FALSE),VLOOKUP(G59,'Loc Coefficients Location'!A:D,4,FALSE)),"") | M59: =IF(ISNUMBER(L59),L59*$F59,"") | N59: =IF(ISNUMBER(F59),IF(LEFT(A59,3)="Cat",VLOOKUP(A59,'Loc Configurations Seules'!R:V,5,FALSE),VLOOKUP(G59,'Loc Coefficients Location'!A:E,5,FALSE)),"") | O59: =IF(ISNUMBER(N59),N59*$F59,"") | P59: =IF(ISNUMBER(F59),IF(LEFT(A59,3)="Cat",VLOOKUP(A59,'Loc Configurations Seules'!R:W,6,FALSE),VLOOKUP(G59,'Loc Coefficients Location'!A:F,6,FALSE)),"") | Q59: =IF(ISNUMBER(P59),P59*$F59,"") | R59: =IF(ISNUMBER(F59),IF(LEFT(A59,3)="Cat",VLOOKUP(A59,'Loc Configurations Seules'!R:X,7,FALSE),VLOOKUP(G59,'Loc Coefficients Location'!A:G,7,FALSE)),"") | S59: =IF(ISNUMBER(R59),R59*$F59,"")
A60: Livraison devant la porte | B60: Livraison devant la porte | C60: AC111A | D60: 1 | G60: SOFT/MAINT | H60: =IF(ISNUMBER($F60),ROUND($F60*H$2,2),"") | I60: =IF(ISNUMBER($F60),ROUND($F60*I$2,2),"") | J60: =IF(ISNUMBER($F60),ROUND($F60*J$2,2),"") | K60: =IF(ISNUMBER($F60),ROUND($F60*K$2,2),"") | L60: =IF(ISNUMBER(F60),IF(LEFT(A60,3)="Cat",VLOOKUP(A60,'Loc Configurations Seules'!R:U,4,FALSE),VLOOKUP(G60,'Loc Coefficients Location'!A:D,4,FALSE)),"") | M60: =IF(ISNUMBER(L60),L60*$F60,"") | N60: =IF(ISNUMBER(F60),IF(LEFT(A60,3)="Cat",VLOOKUP(A60,'Loc Configurations Seules'!R:V,5,FALSE),VLOOKUP(G60,'Loc Coefficients Location'!A:E,5,FALSE)),"") | O60: =IF(ISNUMBER(N60),N60*$F60,"") | P60: =IF(ISNUMBER(F60),IF(LEFT(A60,3)="Cat",VLOOKUP(A60,'Loc Configurations Seules'!R:W,6,FALSE),VLOOKUP(G60,'Loc Coefficients Location'!A:F,6,FALSE)),"") | Q60: =IF(ISNUMBER(P60),P60*$F60,"") | R60: =IF(ISNUMBER(F60),IF(LEFT(A60,3)="Cat",VLOOKUP(A60,'Loc Configurations Seules'!R:X,7,FALSE),VLOOKUP(G60,'Loc Coefficients Location'!A:G,7,FALSE)),"") | S60: =IF(ISNUMBER(R60),R60*$F60,"")
A61: Garantie 5 ans J+1 | B61: HPE 5Y Tech Care Basic Service | C61: HU4B2A5 | D61: 1 | G61: SOFT/MAINT | H61: =IF(ISNUMBER($F61),ROUND($F61*H$2,2),"") | I61: =IF(ISNUMBER($F61),ROUND($F61*I$2,2),"") | J61: =IF(ISNUMBER($F61),ROUND($F61*J$2,2),"") | K61: =IF(ISNUMBER($F61),ROUND($F61*K$2,2),"")
A62: Garantie 5 ans J+1 | B62: HPE Edgeline 300 Support | C62: HU4B2A5#XMU | D62: 1 | G62: SOFT/MAINT | H62: =IF(ISNUMBER($F62),ROUND($F62*H$2,2),"") | I62: =IF(ISNUMBER($F62),ROUND($F62*I$2,2),"") | J62: =IF(ISNUMBER($F62),ROUND($F62*J$2,2),"") | K62: =IF(ISNUMBER($F62),ROUND($F62*K$2,2),"")
A63: Garantie 5 ans J+1 | B63: HPE Edgeline ISM Advanced Support | C63: HU4B2A5#XP9 | D63: 1 | G63: SOFT/MAINT | H63: =IF(ISNUMBER($F63),ROUND($F63*H$2,2),"") | I63: =IF(ISNUMBER($F63),ROUND($F63*I$2,2),"") | J63: =IF(ISNUMBER($F63),ROUND($F63*J$2,2),"") | K63: =IF(ISNUMBER($F63),ROUND($F63*K$2,2),"")
H64: =IF(ISNUMBER($F64),ROUND($F64*H$2,2),"") | I64: =IF(ISNUMBER($F64),ROUND($F64*I$2,2),"") | J64: =IF(ISNUMBER($F64),ROUND($F64*J$2,2),"") | K64: =IF(ISNUMBER($F64),ROUND($F64*K$2,2),"") | L64: =IF(ISNUMBER(F64),IF(LEFT(A64,3)="Cat",VLOOKUP(A64,'Loc Configurations Seules'!R:U,4,FALSE),VLOOKUP(G64,'Loc Coefficients Location'!A:D,4,FALSE)),"") | M64: =IF(ISNUMBER(L64),L64*$F64,"") | N64: =IF(ISNUMBER(F64),IF(LEFT(A64,3)="Cat",VLOOKUP(A64,'Loc Configurations Seules'!R:V,5,FALSE),VLOOKUP(G64,'Loc Coefficients Location'!A:E,5,FALSE)),"") | O64: =IF(ISNUMBER(N64),N64*$F64,"") | P64: =IF(ISNUMBER(F64),IF(LEFT(A64,3)="Cat",VLOOKUP(A64,'Loc Configurations Seules'!R:W,6,FALSE),VLOOKUP(G64,'Loc Coefficients Location'!A:F,6,FALSE)),"") | Q64: =IF(ISNUMBER(P64),P64*$F64,"") | R64: =IF(ISNUMBER(F64),IF(LEFT(A64,3)="Cat",VLOOKUP(A64,'Loc Configurations Seules'!R:X,7,FALSE),VLOOKUP(G64,'Loc Coefficients Location'!A:G,7,FALSE)),"") | S64: =IF(ISNUMBER(R64),R64*$F64,"")
A65: Cat1 Conf6 Tour ML30 Gen10 plus | B65: HPE ProLiant ML30 Gen10+ | C65: P44723-B21 | F65: 721.84 | H65: =IF(ISNUMBER($F65),ROUND($F65*H$2,2),"") -> 190.51 | I65: =IF(ISNUMBER($F65),ROUND($F65*I$2,2),"") -> 96.62 | J65: =IF(ISNUMBER($F65),ROUND($F65*J$2,2),"") -> 65.94 | K65: =IF(ISNUMBER($F65),ROUND($F65*K$2,2),"") -> 50.71 | L65: =IF(ISNUMBER(F65),IF(LEFT(A65,3)="Cat",VLOOKUP(A65,'Loc Configurations Seules'!R:U,4,FALSE),VLOOKUP(G65,'Loc Coefficients Location'!A:D,4,FALSE)),"") -> 0.2004 | M65: =IF(ISNUMBER(L65),L65*$F65,"") -> 144.65674 | N65: =IF(ISNUMBER(F65),IF(LEFT(A65,3)="Cat",VLOOKUP(A65,'Loc Configurations Seules'!R:V,5,FALSE),VLOOKUP(G65,'Loc Coefficients Location'!A:E,5,FALSE)),"") -> 0.1053 | O65: =IF(ISNUMBER(N65),N65*$F65,"") -> 76.009752 | P65: =IF(ISNUMBER(F65),IF(LEFT(A65,3)="Cat",VLOOKUP(A65,'Loc Configurations Seules'!R:W,6,FALSE),VLOOKUP(G65,'Loc Coefficients Location'!A:F,6,FALSE)),"") -> 0.0783 | Q65: =IF(ISNUMBER(P65),P65*$F65,"") -> 56.520072 | R65: =IF(ISNUMBER(F65),IF(LEFT(A65,3)="Cat",VLOOKUP(A65,'Loc Configurations Seules'!R:X,7,FALSE),VLOOKUP(G65,'Loc Coefficients Location'!A:G,7,FALSE)),"") -> 0.0645 | S65: =IF(ISNUMBER(R65),R65*$F65,"") -> 46.55868
A66: Serveur de type tour | B66: HPE ProLiant ML30 Gen10 Plus 4LFF Non-hot Plug Configure-to-order Server | C66: P44723-B21 | D66: 1 | G66: PC_SE/PLX86 | H66: =IF(ISNUMBER($F66),ROUND($F66*H$2,2),"") | I66: =IF(ISNUMBER($F66),ROUND($F66*I$2,2),"") | J66: =IF(ISNUMBER($F66),ROUND($F66*J$2,2),"") | K66: =IF(ISNUMBER($F66),ROUND($F66*K$2,2),"") | L66: =IF(ISNUMBER(F66),IF(LEFT(A66,3)="Cat",VLOOKUP(A66,'Loc Configurations Seules'!R:U,4,FALSE),VLOOKUP(G66,'Loc Coefficients Location'!A:D,4,FALSE)),"") | M66: =IF(ISNUMBER(L66),L66*$F66,"") | N66: =IF(ISNUMBER(F66),IF(LEFT(A66,3)="Cat",VLOOKUP(A66,'Loc Configurations Seules'!R:V,5,FALSE),VLOOKUP(G66,'Loc Coefficients Location'!A:E,5,FALSE)),"") | O66: =IF(ISNUMBER(N66),N66*$F66,"") | P66: =IF(ISNUMBER(F66),IF(LEFT(A66,3)="Cat",VLOOKUP(A66,'Loc Configurations Seules'!R:W,6,FALSE),VLOOKUP(G66,'Loc Coefficients Location'!A:F,6,FALSE)),"") | Q66: =IF(ISNUMBER(P66),P66*$F66,"") | R66: =IF(ISNUMBER(F66),IF(LEFT(A66,3)="Cat",VLOOKUP(A66,'Loc Configurations Seules'!R:X,7,FALSE),VLOOKUP(G66,'Loc Coefficients Location'!A:G,7,FALSE)),"") | S66: =IF(ISNUMBER(R66),R66*$F66,"")
A67: Processeur 64 bits Intel Xeon E-2314 (2,8 GHz de base / 4,50 Ghz Turbo / 4 cœurs / 4 threads / 8 Mo Smart Cache / 65 W PDT | B67: Intel Xeon E-2314 2.8GHz 4-core 65W FIO Processor for HPE | C67: P45248-B21 | D67: 1 | G67: PC_SE/PLX86 | H67: =IF(ISNUMBER($F67),ROUND($F67*H$2,2),"") | I67: =IF(ISNUMBER($F67),ROUND($F67*I$2,2),"") | J67: =IF(ISNUMBER($F67),ROUND($F67*J$2,2),"") | K67: =IF(ISNUMBER($F67),ROUND($F67*K$2,2),"") | L67: =IF(ISNUMBER(F67),IF(LEFT(A67,3)="Cat",VLOOKUP(A67,'Loc Configurations Seules'!R:U,4,FALSE),VLOOKUP(G67,'Loc Coefficients Location'!A:D,4,FALSE)),"") | M67: =IF(ISNUMBER(L67),L67*$F67,"") | N67: =IF(ISNUMBER(F67),IF(LEFT(A67,3)="Cat",VLOOKUP(A67,'Loc Configurations Seules'!R:V,5,FALSE),VLOOKUP(G67,'Loc Coefficients Location'!A:E,5,FALSE)),"") | O67: =IF(ISNUMBER(N67),N67*$F67,"") | P67: =IF(ISNUMBER(F67),IF(LEFT(A67,3)="Cat",VLOOKUP(A67,'Loc Configurations Seules'!R:W,6,FALSE),VLOOKUP(G67,'Loc Coefficients Location'!A:F,6,FALSE)),"") | Q67: =IF(ISNUMBER(P67),P67*$F67,"") | R67: =IF(ISNUMBER(F67),IF(LEFT(A67,3)="Cat",VLOOKUP(A67,'Loc Configurations Seules'!R:X,7,FALSE),VLOOKUP(G67,'Loc Coefficients Location'!A:G,7,FALSE)),"") | S67: =IF(ISNUMBER(R67),R67*$F67,"")
A68: 1 barrette mémoire HPE Standard DDR4 2666 MHz UDIMM de 16 Go (soit 4 Go ECC par cœur) | B68: HPE 16GB (1x16GB) Single Rank x8 DDR4-3200 CAS-22-22-22 Unbuffered Standard Memory Kit | C68: P43019-B21 | D68: 1 | G68: PC_SE/PLX86 | H68: =IF(ISNUMBER($F68),ROUND($F68*H$2,2),"") | I68: =IF(ISNUMBER($F68),ROUND($F68*I$2,2),"") | J68: =IF(ISNUMBER($F68),ROUND($F68*J$2,2),"") | K68: =IF(ISNUMBER($F68),ROUND($F68*K$2,2),"") | L68: =IF(ISNUMBER(F68),IF(LEFT(A68,3)="Cat",VLOOKUP(A68,'Loc Configurations Seules'!R:U,4,FALSE),VLOOKUP(G68,'Loc Coefficients Location'!A:D,4,FALSE)),"") | M68: =IF(ISNUMBER(L68),L68*$F68,"") | N68: =IF(ISNUMBER(F68),IF(LEFT(A68,3)="Cat",VLOOKUP(A68,'Loc Configurations Seules'!R:V,5,FALSE),VLOOKUP(G68,'Loc Coefficients Location'!A:E,5,FALSE)),"") | O68: =IF(ISNUMBER(N68),N68*$F68,"") | P68: =IF(ISNUMBER(F68),IF(LEFT(A68,3)="Cat",VLOOKUP(A68,'Loc Configurations Seules'!R:W,6,FALSE),VLOOKUP(G68,'Loc Coefficients Location'!A:F,6,FALSE)),"") | Q68: =IF(ISNUMBER(P68),P68*$F68,"") | R68: =IF(ISNUMBER(F68),IF(LEFT(A68,3)="Cat",VLOOKUP(A68,'Loc Configurations Seules'!R:X,7,FALSE),VLOOKUP(G68,'Loc Coefficients Location'!A:G,7,FALSE)),"") | S68: =IF(ISNUMBER(R68),R68*$F68,"")
A69: Alimentation 500W certifiée 80Plus Platinium | B69: HPE 500W FS Plat Ht Plg LH Pwr Sply Kit | C69: 865408-B21 | D69: 1 | G69: PC_SE/PLX86 | H69: =IF(ISNUMBER($F69),ROUND($F69*H$2,2),"") | I69: =IF(ISNUMBER($F69),ROUND($F69*I$2,2),"") | J69: =IF(ISNUMBER($F69),ROUND($F69*J$2,2),"") | K69: =IF(ISNUMBER($F69),ROUND($F69*K$2,2),"") | L69: =IF(ISNUMBER(F69),IF(LEFT(A69,3)="Cat",VLOOKUP(A69,'Loc Configurations Seules'!R:U,4,FALSE),VLOOKUP(G69,'Loc Coefficients Location'!A:D,4,FALSE)),"") | M69: =IF(ISNUMBER(L69),L69*$F69,"") | N69: =IF(ISNUMBER(F69),IF(LEFT(A69,3)="Cat",VLOOKUP(A69,'Loc Configurations Seules'!R:V,5,FALSE),VLOOKUP(G69,'Loc Coefficients Location'!A:E,5,FALSE)),"") | O69: =IF(ISNUMBER(N69),N69*$F69,"") | P69: =IF(ISNUMBER(F69),IF(LEFT(A69,3)="Cat",VLOOKUP(A69,'Loc Configurations Seules'!R:W,6,FALSE),VLOOKUP(G69,'Loc Coefficients Location'!A:F,6,FALSE)),"") | Q69: =IF(ISNUMBER(P69),P69*$F69,"") | R69: =IF(ISNUMBER(F69),IF(LEFT(A69,3)="Cat",VLOOKUP(A69,'Loc Configurations Seules'!R:X,7,FALSE),VLOOKUP(G69,'Loc Coefficients Location'!A:G,7,FALSE)),"") | S69: =IF(ISNUMBER(R69),R69*$F69,"")
A70: Carte d'administration HPE iLO avec API RESTful compatible IPMI v2.0 et Redfish. Licence en version Advanced avec toutes les options activées | B70: HPE iLO Adv 1-svr Lic 1yr Support | C70: 512485-B21 | D70: 1 | G70: PC_SE/PLX86 | H70: =IF(ISNUMBER($F70),ROUND($F70*H$2,2),"") | I70: =IF(ISNUMBER($F70),ROUND($F70*I$2,2),"") | J70: =IF(ISNUMBER($F70),ROUND($F70*J$2,2),"") | K70: =IF(ISNUMBER($F70),ROUND($F70*K$2,2),"") | L70: =IF(ISNUMBER(F70),IF(LEFT(A70,3)="Cat",VLOOKUP(A70,'Loc Configurations Seules'!R:U,4,FALSE),VLOOKUP(G70,'Loc Coefficients Location'!A:D,4,FALSE)),"") | M70: =IF(ISNUMBER(L70),L70*$F70,"") | N70: =IF(ISNUMBER(F70),IF(LEFT(A70,3)="Cat",VLOOKUP(A70,'Loc Configurations Seules'!R:V,5,FALSE),VLOOKUP(G70,'Loc Coefficients Location'!A:E,5,FALSE)),"") | O70: =IF(ISNUMBER(N70),N70*$F70,"") | P70: =IF(ISNUMBER(F70),IF(LEFT(A70,3)="Cat",VLOOKUP(A70,'Loc Configurations Seules'!R:W,6,FALSE),VLOOKUP(G70,'Loc Coefficients Location'!A:F,6,FALSE)),"") | Q70: =IF(ISNUMBER(P70),P70*$F70,"") | R70: =IF(ISNUMBER(F70),IF(LEFT(A70,3)="Cat",VLOOKUP(A70,'Loc Configurations Seules'!R:X,7,FALSE),VLOOKUP(G70,'Loc Coefficients Location'!A:G,7,FALSE)),"") | S70: =IF(ISNUMBER(R70),R70*$F70,"")
A71: Kit d'alimentation redondante | B71: HPE ML30 Gen10+ 4U RPS Enablement Kit | C71: P45209-B21 | D71: 1 | G71: PC_SE/PLX86 | H71: =IF(ISNUMBER($F71),ROUND($F71*H$2,2),"") | I71: =IF(ISNUMBER($F71),ROUND($F71*I$2,2),"") | J71: =IF(ISNUMBER($F71),ROUND($F71*J$2,2),"") | K71: =IF(ISNUMBER($F71),ROUND($F71*K$2,2),"") | L71: =IF(ISNUMBER(F71),IF(LEFT(A71,3)="Cat",VLOOKUP(A71,'Loc Configurations Seules'!R:U,4,FALSE),VLOOKUP(G71,'Loc Coefficients Location'!A:D,4,FALSE)),"") | M71: =IF(ISNUMBER(L71),L71*$F71,"") | N71: =IF(ISNUMBER(F71),IF(LEFT(A71,3)="Cat",VLOOKUP(A71,'Loc Configurations Seules'!R:V,5,FALSE),VLOOKUP(G71,'Loc Coefficients Location'!A:E,5,FALSE)),"") | O71: =IF(ISNUMBER(N71),N71*$F71,"") | P71: =IF(ISNUMBER(F71),IF(LEFT(A71,3)="Cat",VLOOKUP(A71,'Loc Configurations Seules'!R:W,6,FALSE),VLOOKUP(G71,'Loc Coefficients Location'!A:F,6,FALSE)),"") | Q71: =IF(ISNUMBER(P71),P71*$F71,"") | R71: =IF(ISNUMBER(F71),IF(LEFT(A71,3)="Cat",VLOOKUP(A71,'Loc Configurations Seules'!R:X,7,FALSE),VLOOKUP(G71,'Loc Coefficients Location'!A:G,7,FALSE)),"") | S71: =IF(ISNUMBER(R71),R71*$F71,"")
A72: Kit Ventilateur | B72: HPE ML30 Gen10 Front PCI Fan and Baffle Kit | C72: P06303-B21 | D72: 1 | G72: PC_SE/PLX86 | H72: =IF(ISNUMBER($F72),ROUND($F72*H$2,2),"") | I72: =IF(ISNUMBER($F72),ROUND($F72*I$2,2),"") | J72: =IF(ISNUMBER($F72),ROUND($F72*J$2,2),"") | K72: =IF(ISNUMBER($F72),ROUND($F72*K$2,2),"") | L72: =IF(ISNUMBER(F72),IF(LEFT(A72,3)="Cat",VLOOKUP(A72,'Loc Configurations Seules'!R:U,4,FALSE),VLOOKUP(G72,'Loc Coefficients Location'!A:D,4,FALSE)),"") | M72: =IF(ISNUMBER(L72),L72*$F72,"") | N72: =IF(ISNUMBER(F72),IF(LEFT(A72,3)="Cat",VLOOKUP(A72,'Loc Configurations Seules'!R:V,5,FALSE),VLOOKUP(G72,'Loc Coefficients Location'!A:E,5,FALSE)),"") | O72: =IF(ISNUMBER(N72),N72*$F72,"") | P72: =IF(ISNUMBER(F72),IF(LEFT(A72,3)="Cat",VLOOKUP(A72,'Loc Configurations Seules'!R:W,6,FALSE),VLOOKUP(G72,'Loc Coefficients Location'!A:F,6,FALSE)),"") | Q72: =IF(ISNUMBER(P72),P72*$F72,"") | R72: =IF(ISNUMBER(F72),IF(LEFT(A72,3)="Cat",VLOOKUP(A72,'Loc Configurations Seules'!R:X,7,FALSE),VLOOKUP(G72,'Loc Coefficients Location'!A:G,7,FALSE)),"") | S72: =IF(ISNUMBER(R72),R72*$F72,"")
A73: Suppresion du cable electrique par defaut | B73: HPE Remove Standard Power Cords | C73: 469774-409 | D73: 1 | G73: PC_SE/PLX86 | H73: =IF(ISNUMBER($F73),ROUND($F73*H$2,2),"") | I73: =IF(ISNUMBER($F73),ROUND($F73*I$2,2),"") | J73: =IF(ISNUMBER($F73),ROUND($F73*J$2,2),"") | K73: =IF(ISNUMBER($F73),ROUND($F73*K$2,2),"") | L73: =IF(ISNUMBER(F73),IF(LEFT(A73,3)="Cat",VLOOKUP(A73,'Loc Configurations Seules'!R:U,4,FALSE),VLOOKUP(G73,'Loc Coefficients Location'!A:D,4,FALSE)),"") | M73: =IF(ISNUMBER(L73),L73*$F73,"") | N73: =IF(ISNUMBER(F73),IF(LEFT(A73,3)="Cat",VLOOKUP(A73,'Loc Configurations Seules'!R:V,5,FALSE),VLOOKUP(G73,'Loc Coefficients Location'!A:E,5,FALSE)),"") | O73: =IF(ISNUMBER(N73),N73*$F73,"") | P73: =IF(ISNUMBER(F73),IF(LEFT(A73,3)="Cat",VLOOKUP(A73,'Loc Configurations Seules'!R:W,6,FALSE),VLOOKUP(G73,'Loc Coefficients Location'!A:F,6,FALSE)),"") | Q73: =IF(ISNUMBER(P73),P73*$F73,"") | R73: =IF(ISNUMBER(F73),IF(LEFT(A73,3)="Cat",VLOOKUP(A73,'Loc Configurations Seules'!R:X,7,FALSE),VLOOKUP(G73,'Loc Coefficients Location'!A:G,7,FALSE)),"") | S73: =IF(ISNUMBER(R73),R73*$F73,"")
A74: Livraison devant la porte | B74: Livraison devant la porte | C74: AC111A | D74: 1 | G74: SOFT/MAINT | H74: =IF(ISNUMBER($F74),ROUND($F74*H$2,2),"") | I74: =IF(ISNUMBER($F74),ROUND($F74*I$2,2),"") | J74: =IF(ISNUMBER($F74),ROUND($F74*J$2,2),"") | K74: =IF(ISNUMBER($F74),ROUND($F74*K$2,2),"") | L74: =IF(ISNUMBER(F74),IF(LEFT(A74,3)="Cat",VLOOKUP(A74,'Loc Configurations Seules'!R:U,4,FALSE),VLOOKUP(G74,'Loc Coefficients Location'!A:D,4,FALSE)),"") | M74: =IF(ISNUMBER(L74),L74*$F74,"") | N74: =IF(ISNUMBER(F74),IF(LEFT(A74,3)="Cat",VLOOKUP(A74,'Loc Configurations Seules'!R:V,5,FALSE),VLOOKUP(G74,'Loc Coefficients Location'!A:E,5,FALSE)),"") | O74: =IF(ISNUMBER(N74),N74*$F74,"") | P74: =IF(ISNUMBER(F74),IF(LEFT(A74,3)="Cat",VLOOKUP(A74,'Loc Configurations Seules'!R:W,6,FALSE),VLOOKUP(G74,'Loc Coefficients Location'!A:F,6,FALSE)),"") | Q74: =IF(ISNUMBER(P74),P74*$F74,"") | R74: =IF(ISNUMBER(F74),IF(LEFT(A74,3)="Cat",VLOOKUP(A74,'Loc Configurations Seules'!R:X,7,FALSE),VLOOKUP(G74,'Loc Coefficients Location'!A:G,7,FALSE)),"") | S74: =IF(ISNUMBER(R74),R74*$F74,"")
A75: Garantie 5 ans J+1 | B75: HPE 5Y Tech Care Basic Service | C75: HU4B2A5 | D75: 1 | G75: SOFT/MAINT | H75: =IF(ISNUMBER($F75),ROUND($F75*H$2,2),"") | I75: =IF(ISNUMBER($F75),ROUND($F75*I$2,2),"") | J75: =IF(ISNUMBER($F75),ROUND($F75*J$2,2),"") | K75: =IF(ISNUMBER($F75),ROUND($F75*K$2,2),"")
A76: Garantie 5 ans J+1 ILO | B76: HPE iLO AdvPack NonBL Support | C76: HU4B2A5#7X4 | D76: 1 | G76: SOFT/MAINT | H76: =IF(ISNUMBER($F76),ROUND($F76*H$2,2),"") | I76: =IF(ISNUMBER($F76),ROUND($F76*I$2,2),"") | J76: =IF(ISNUMBER($F76),ROUND($F76*J$2,2),"") | K76: =IF(ISNUMBER($F76),ROUND($F76*K$2,2),"")
A77: Garantie 5 ans J+1 châssis | B77: HPE ProLiant ML30 Gen10+ Support | C77: HU4B2A5#ZNB | D77: 1 | G77: SOFT/MAINT | H77: =IF(ISNUMBER($F77),ROUND($F77*H$2,2),"") | I77: =IF(ISNUMBER($F77),ROUND($F77*I$2,2),"") | J77: =IF(ISNUMBER($F77),ROUND($F77*J$2,2),"") | K77: =IF(ISNUMBER($F77),ROUND($F77*K$2,2),"")
H78: =IF(ISNUMBER($F78),ROUND($F78*H$2,2),"") | I78: =IF(ISNUMBER($F78),ROUND($F78*I$2,2),"") | J78: =IF(ISNUMBER($F78),ROUND($F78*J$2,2),"") | K78: =IF(ISNUMBER($F78),ROUND($F78*K$2,2),"") | L78: =IF(ISNUMBER(F78),IF(LEFT(A78,3)="Cat",VLOOKUP(A78,'Loc Configurations Seules'!R:U,4,FALSE),VLOOKUP(G78,'Loc Coefficients Location'!A:D,4,FALSE)),"") | M78: =IF(ISNUMBER(L78),L78*$F78,"") | N78: =IF(ISNUMBER(F78),IF(LEFT(A78,3)="Cat",VLOOKUP(A78,'Loc Configurations Seules'!R:V,5,FALSE),VLOOKUP(G78,'Loc Coefficients Location'!A:E,5,FALSE)),"") | O78: =IF(ISNUMBER(N78),N78*$F78,"") | P78: =IF(ISNUMBER(F78),IF(LEFT(A78,3)="Cat",VLOOKUP(A78,'Loc Configurations Seules'!R:W,6,FALSE),VLOOKUP(G78,'Loc Coefficients Location'!A:F,6,FALSE)),"") | Q78: =IF(ISNUMBER(P78),P78*$F78,"") | R78: =IF(ISNUMBER(F78),IF(LEFT(A78,3)="Cat",VLOOKUP(A78,'Loc Configurations Seules'!R:X,7,FALSE),VLOOKUP(G78,'Loc Coefficients Location'!A:G,7,FALSE)),"") | S78: =IF(ISNUMBER(R78),R78*$F78,"")
A79: CATEGORIE 1 : extensions et périphériques associés, extensions de garantie, installation, etc. | H79: =IF(ISNUMBER($F79),ROUND($F79*H$2,2),"") | I79: =IF(ISNUMBER($F79),ROUND($F79*I$2,2),"") | J79: =IF(ISNUMBER($F79),ROUND($F79*J$2,2),"") | K79: =IF(ISNUMBER($F79),ROUND($F79*K$2,2),"") | L79: =IF(ISNUMBER(F79),IF(LEFT(A79,3)="Cat",VLOOKUP(A79,'Loc Configurations Seules'!R:U,4,FALSE),VLOOKUP(G79,'Loc Coefficients Location'!A:D,4,FALSE)),"") | M79: =IF(ISNUMBER(L79),L79*$F79,"") | N79: =IF(ISNUMBER(F79),IF(LEFT(A79,3)="Cat",VLOOKUP(A79,'Loc Configurations Seules'!R:V,5,FALSE),VLOOKUP(G79,'Loc Coefficients Location'!A:E,5,FALSE)),"") | O79: =IF(ISNUMBER(N79),N79*$F79,"") | P79: =IF(ISNUMBER(F79),IF(LEFT(A79,3)="Cat",VLOOKUP(A79,'Loc Configurations Seules'!R:W,6,FALSE),VLOOKUP(G79,'Loc Coefficients Location'!A:F,6,FALSE)),"") | Q79: =IF(ISNUMBER(P79),P79*$F79,"") | R79: =IF(ISNUMBER(F79),IF(LEFT(A79,3)="Cat",VLOOKUP(A79,'Loc Configurations Seules'!R:X,7,FALSE),VLOOKUP(G79,'Loc Coefficients Location'!A:G,7,FALSE)),"") | S79: =IF(ISNUMBER(R79),R79*$F79,"")
A80: Désignation/Description des matériels | B80: Référence constructeur (le cas échéant) | C80: Numéro de référence | D80: Quantités | F80: TARIFS en €HT | H80: =IF(ISNUMBER($F80),ROUND($F80*H$2,2),"") | I80: =IF(ISNUMBER($F80),ROUND($F80*I$2,2),"") | J80: =IF(ISNUMBER($F80),ROUND($F80*J$2,2),"") | K80: =IF(ISNUMBER($F80),ROUND($F80*K$2,2),"") | L80: =IF(ISNUMBER(F80),IF(LEFT(A80,3)="Cat",VLOOKUP(A80,'Loc Configurations Seules'!R:U,4,FALSE),VLOOKUP(G80,'Loc Coefficients Location'!A:D,4,FALSE)),"") | M80: =IF(ISNUMBER(L80),L80*$F80,"") | N80: =IF(ISNUMBER(F80),IF(LEFT(A80,3)="Cat",VLOOKUP(A80,'Loc Configurations Seules'!R:V,5,FALSE),VLOOKUP(G80,'Loc Coefficients Location'!A:E,5,FALSE)),"") | O80: =IF(ISNUMBER(N80),N80*$F80,"") | P80: =IF(ISNUMBER(F80),IF(LEFT(A80,3)="Cat",VLOOKUP(A80,'Loc Configurations Seules'!R:W,6,FALSE),VLOOKUP(G80,'Loc Coefficients Location'!A:F,6,FALSE)),"") | Q80: =IF(ISNUMBER(P80),P80*$F80,"") | R80: =IF(ISNUMBER(F80),IF(LEFT(A80,3)="Cat",VLOOKUP(A80,'Loc Configurations Seules'!R:X,7,FALSE),VLOOKUP(G80,'Loc Coefficients Location'!A:G,7,FALSE)),"") | S80: =IF(ISNUMBER(R80),R80*$F80,"")
A81: Ces extensions sont propres a cette categorie. Les extensions communes sont factorisés dans le chapitre Categorie 1 a 4 : extensions | H81: =IF(ISNUMBER($F81),ROUND($F81*H$2,2),"") | I81: =IF(ISNUMBER($F81),ROUND($F81*I$2,2),"") | J81: =IF(ISNUMBER($F81),ROUND($F81*J$2,2),"") | K81: =IF(ISNUMBER($F81),ROUND($F81*K$2,2),"") | L81: =IF(ISNUMBER(F81),IF(LEFT(A81,3)="Cat",VLOOKUP(A81,'Loc Configurations Seules'!R:U,4,FALSE),VLOOKUP(G81,'Loc Coefficients Location'!A:D,4,FALSE)),"") | M81: =IF(ISNUMBER(L81),L81*$F81,"") | N81: =IF(ISNUMBER(F81),IF(LEFT(A81,3)="Cat",VLOOKUP(A81,'Loc Configurations Seules'!R:V,5,FALSE),VLOOKUP(G81,'Loc Coefficients Location'!A:E,5,FALSE)),"") | O81: =IF(ISNUMBER(N81),N81*$F81,"") | P81: =IF(ISNUMBER(F81),IF(LEFT(A81,3)="Cat",VLOOKUP(A81,'Loc Configurations Seules'!R:W,6,FALSE),VLOOKUP(G81,'Loc Coefficients Location'!A:F,6,FALSE)),"") | Q81: =IF(ISNUMBER(P81),P81*$F81,"") | R81: =IF(ISNUMBER(F81),IF(LEFT(A81,3)="Cat",VLOOKUP(A81,'Loc Configurations Seules'!R:X,7,FALSE),VLOOKUP(G81,'Loc Coefficients Location'!A:G,7,FALSE)),"") | S81: =IF(ISNUMBER(R81),R81*$F81,"")
A82: Ajout d'une barrette mémoire DDR4-2666 UDIMM 8 Go | B82: HPE 8GB 1Rx8 PC4-2666V-E STND Kit | C82: 879505-B21 | F82: 46.2 | G82: PC_SE/PLX86 | H82: =IF(ISNUMBER($F82),ROUND($F82*H$2,2),"") -> 12.19 | I82: =IF(ISNUMBER($F82),ROUND($F82*I$2,2),"") -> 6.18 | J82: =IF(ISNUMBER($F82),ROUND($F82*J$2,2),"") -> 4.22 | K82: =IF(ISNUMBER($F82),ROUND($F82*K$2,2),"") -> 3.25 | L82: =IF(ISNUMBER(F82),IF(LEFT(A82,3)="Cat",VLOOKUP(A82,'Loc Configurations Seules'!R:U,4,FALSE),VLOOKUP(G82,'Loc Coefficients Location'!A:D,4,FALSE)),"") -> 0.18651532 | M82: =IF(ISNUMBER(L82),L82*$F82,"") -> 8.6170079 | N82: =IF(ISNUMBER(F82),IF(LEFT(A82,3)="Cat",VLOOKUP(A82,'Loc Configurations Seules'!R:V,5,FALSE),VLOOKUP(G82,'Loc Coefficients Location'!A:E,5,FALSE)),"") -> 0.099038653 | O82: =IF(ISNUMBER(N82),N82*$F82,"") -> 4.5755858 | P82: =IF(ISNUMBER(F82),IF(LEFT(A82,3)="Cat",VLOOKUP(A82,'Loc Configurations Seules'!R:W,6,FALSE),VLOOKUP(G82,'Loc Coefficients Location'!A:F,6,FALSE)),"") -> 0.07542178 | Q82: =IF(ISNUMBER(P82),P82*$F82,"") -> 3.4844862 | R82: =IF(ISNUMBER(F82),IF(LEFT(A82,3)="Cat",VLOOKUP(A82,'Loc Configurations Seules'!R:X,7,FALSE),VLOOKUP(G82,'Loc Coefficients Location'!A:G,7,FALSE)),"") -> 0.063273484 | S82: =IF(ISNUMBER(R82),R82*$F82,"") -> 2.923235
B83: HPE 8GB 1Rx8 PC4-3200AA-E STND Kit | C83: P43016-B21 | F83: 46.2 | G83: PC_SE/PLX86 | H83: =IF(ISNUMBER($F83),ROUND($F83*H$2,2),"") -> 12.19 | I83: =IF(ISNUMBER($F83),ROUND($F83*I$2,2),"") -> 6.18 | J83: =IF(ISNUMBER($F83),ROUND($F83*J$2,2),"") -> 4.22 | K83: =IF(ISNUMBER($F83),ROUND($F83*K$2,2),"") -> 3.25 | L83: =IF(ISNUMBER(F83),IF(LEFT(A83,3)="Cat",VLOOKUP(A83,'Loc Configurations Seules'!R:U,4,FALSE),VLOOKUP(G83,'Loc Coefficients Location'!A:D,4,FALSE)),"") -> 0.18651532 | M83: =IF(ISNUMBER(L83),L83*$F83,"") -> 8.6170079 | N83: =IF(ISNUMBER(F83),IF(LEFT(A83,3)="Cat",VLOOKUP(A83,'Loc Configurations Seules'!R:V,5,FALSE),VLOOKUP(G83,'Loc Coefficients Location'!A:E,5,FALSE)),"") -> 0.099038653 | O83: =IF(ISNUMBER(N83),N83*$F83,"") -> 4.5755858 | P83: =IF(ISNUMBER(F83),IF(LEFT(A83,3)="Cat",VLOOKUP(A83,'Loc Configurations Seules'!R:W,6,FALSE),VLOOKUP(G83,'Loc Coefficients Location'!A:F,6,FALSE)),"") -> 0.07542178 | Q83: =IF(ISNUMBER(P83),P83*$F83,"") -> 3.4844862 | R83: =IF(ISNUMBER(F83),IF(LEFT(A83,3)="Cat",VLOOKUP(A83,'Loc Configurations Seules'!R:X,7,FALSE),VLOOKUP(G83,'Loc Coefficients Location'!A:G,7,FALSE)),"") -> 0.063273484 | S83: =IF(ISNUMBER(R83),R83*$F83,"") -> 2.923235
A84: Ajout d'une barrette mémoire DDR4-2666/3200 UDIMM 16 Go | B84: HPE 16GB 2Rx8 PC4-2666V-E STND Kit | C84: 879507-B21 | F84: 79.8 | G84: PC_SE/PLX86 | H84: =IF(ISNUMBER($F84),ROUND($F84*H$2,2),"") -> 21.06 | I84: =IF(ISNUMBER($F84),ROUND($F84*I$2,2),"") -> 10.68 | J84: =IF(ISNUMBER($F84),ROUND($F84*J$2,2),"") -> 7.29 | K84: =IF(ISNUMBER($F84),ROUND($F84*K$2,2),"") -> 5.61 | L84: =IF(ISNUMBER(F84),IF(LEFT(A84,3)="Cat",VLOOKUP(A84,'Loc Configurations Seules'!R:U,4,FALSE),VLOOKUP(G84,'Loc Coefficients Location'!A:D,4,FALSE)),"") -> 0.18651532 | M84: =IF(ISNUMBER(L84),L84*$F84,"") -> 14.883923 | N84: =IF(ISNUMBER(F84),IF(LEFT(A84,3)="Cat",VLOOKUP(A84,'Loc Configurations Seules'!R:V,5,FALSE),VLOOKUP(G84,'Loc Coefficients Location'!A:E,5,FALSE)),"") -> 0.099038653 | O84: =IF(ISNUMBER(N84),N84*$F84,"") -> 7.9032845 | P84: =IF(ISNUMBER(F84),IF(LEFT(A84,3)="Cat",VLOOKUP(A84,'Loc Configurations Seules'!R:W,6,FALSE),VLOOKUP(G84,'Loc Coefficients Location'!A:F,6,FALSE)),"") -> 0.07542178 | Q84: =IF(ISNUMBER(P84),P84*$F84,"") -> 6.018658 | R84: =IF(ISNUMBER(F84),IF(LEFT(A84,3)="Cat",VLOOKUP(A84,'Loc Configurations Seules'!R:X,7,FALSE),VLOOKUP(G84,'Loc Coefficients Location'!A:G,7,FALSE)),"") -> 0.063273484 | S84: =IF(ISNUMBER(R84),R84*$F84,"") -> 5.049224
B85: HPE 16GB 1Rx8 PC4-3200AA-E STND Kit | C85: P43019-B21 | F85: 79.8 | G85: PC_SE/PLX86 | H85: =IF(ISNUMBER($F85),ROUND($F85*H$2,2),"") -> 21.06 | I85: =IF(ISNUMBER($F85),ROUND($F85*I$2,2),"") -> 10.68 | J85: =IF(ISNUMBER($F85),ROUND($F85*J$2,2),"") -> 7.29 | K85: =IF(ISNUMBER($F85),ROUND($F85*K$2,2),"") -> 5.61 | L85: =IF(ISNUMBER(F85),IF(LEFT(A85,3)="Cat",VLOOKUP(A85,'Loc Configurations Seules'!R:U,4,FALSE),VLOOKUP(G85,'Loc Coefficients Location'!A:D,4,FALSE)),"") -> 0.18651532 | M85: =IF(ISNUMBER(L85),L85*$F85,"") -> 14.883923 | N85: =IF(ISNUMBER(F85),IF(LEFT(A85,3)="Cat",VLOOKUP(A85,'Loc Configurations Seules'!R:V,5,FALSE),VLOOKUP(G85,'Loc Coefficients Location'!A:E,5,FALSE)),"") -> 0.099038653 | O85: =IF(ISNUMBER(N85),N85*$F85,"") -> 7.9032845 | P85: =IF(ISNUMBER(F85),IF(LEFT(A85,3)="Cat",VLOOKUP(A85,'Loc Configurations Seules'!R:W,6,FALSE),VLOOKUP(G85,'Loc Coefficients Location'!A:F,6,FALSE)),"") -> 0.07542178 | Q85: =IF(ISNUMBER(P85),P85*$F85,"") -> 6.018658 | R85: =IF(ISNUMBER(F85),IF(LEFT(A85,3)="Cat",VLOOKUP(A85,'Loc Configurations Seules'!R:X,7,FALSE),VLOOKUP(G85,'Loc Coefficients Location'!A:G,7,FALSE)),"") -> 0.063273484 | S85: =IF(ISNUMBER(R85),R85*$F85,"") -> 5.049224
H86: =IF(ISNUMBER($F86),ROUND($F86*H$2,2),"") | I86: =IF(ISNUMBER($F86),ROUND($F86*I$2,2),"") | J86: =IF(ISNUMBER($F86),ROUND($F86*J$2,2),"") | K86: =IF(ISNUMBER($F86),ROUND($F86*K$2,2),"") | L86: =IF(ISNUMBER(F86),IF(LEFT(A86,3)="Cat",VLOOKUP(A86,'Loc Configurations Seules'!R:U,4,FALSE),VLOOKUP(G86,'Loc Coefficients Location'!A:D,4,FALSE)),"") | M86: =IF(ISNUMBER(L86),L86*$F86,"") | N86: =IF(ISNUMBER(F86),IF(LEFT(A86,3)="Cat",VLOOKUP(A86,'Loc Configurations Seules'!R:V,5,FALSE),VLOOKUP(G86,'Loc Coefficients Location'!A:E,5,FALSE)),"") | O86: =IF(ISNUMBER(N86),N86*$F86,"") | P86: =IF(ISNUMBER(F86),IF(LEFT(A86,3)="Cat",VLOOKUP(A86,'Loc Configurations Seules'!R:W,6,FALSE),VLOOKUP(G86,'Loc Coefficients Location'!A:F,6,FALSE)),"") | Q86: =IF(ISNUMBER(P86),P86*$F86,"") | R86: =IF(ISNUMBER(F86),IF(LEFT(A86,3)="Cat",VLOOKUP(A86,'Loc Configurations Seules'!R:X,7,FALSE),VLOOKUP(G86,'Loc Coefficients Location'!A:G,7,FALSE)),"") | S86: =IF(ISNUMBER(R86),R86*$F86,"")
A87: Cat1 Configuration n°1: Serveur tour Ultra Micro mono-socket | H87: =IF(ISNUMBER($F87),ROUND($F87*H$2,2),"") | I87: =IF(ISNUMBER($F87),ROUND($F87*I$2,2),"") | J87: =IF(ISNUMBER($F87),ROUND($F87*J$2,2),"") | K87: =IF(ISNUMBER($F87),ROUND($F87*K$2,2),"") | L87: =IF(ISNUMBER(F87),IF(LEFT(A87,3)="Cat",VLOOKUP(A87,'Loc Configurations Seules'!R:U,4,FALSE),VLOOKUP(G87,'Loc Coefficients Location'!A:D,4,FALSE)),"") | M87: =IF(ISNUMBER(L87),L87*$F87,"") | N87: =IF(ISNUMBER(F87),IF(LEFT(A87,3)="Cat",VLOOKUP(A87,'Loc Configurations Seules'!R:V,5,FALSE),VLOOKUP(G87,'Loc Coefficients Location'!A:E,5,FALSE)),"") | O87: =IF(ISNUMBER(N87),N87*$F87,"") | P87: =IF(ISNUMBER(F87),IF(LEFT(A87,3)="Cat",VLOOKUP(A87,'Loc Configurations Seules'!R:W,6,FALSE),VLOOKUP(G87,'Loc Coefficients Location'!A:F,6,FALSE)),"") | Q87: =IF(ISNUMBER(P87),P87*$F87,"") | R87: =IF(ISNUMBER(F87),IF(LEFT(A87,3)="Cat",VLOOKUP(A87,'Loc Configurations Seules'!R:X,7,FALSE),VLOOKUP(G87,'Loc Coefficients Location'!A:G,7,FALSE)),"") | S87: =IF(ISNUMBER(R87),R87*$F87,"")
A88: Disque durs rotatifs additionnels | H88: =IF(ISNUMBER($F88),ROUND($F88*H$2,2),"") | I88: =IF(ISNUMBER($F88),ROUND($F88*I$2,2),"") | J88: =IF(ISNUMBER($F88),ROUND($F88*J$2,2),"") | K88: =IF(ISNUMBER($F88),ROUND($F88*K$2,2),"") | L88: =IF(ISNUMBER(F88),IF(LEFT(A88,3)="Cat",VLOOKUP(A88,'Loc Configurations Seules'!R:U,4,FALSE),VLOOKUP(G88,'Loc Coefficients Location'!A:D,4,FALSE)),"") | M88: =IF(ISNUMBER(L88),L88*$F88,"") | N88: =IF(ISNUMBER(F88),IF(LEFT(A88,3)="Cat",VLOOKUP(A88,'Loc Configurations Seules'!R:V,5,FALSE),VLOOKUP(G88,'Loc Coefficients Location'!A:E,5,FALSE)),"") | O88: =IF(ISNUMBER(N88),N88*$F88,"") | P88: =IF(ISNUMBER(F88),IF(LEFT(A88,3)="Cat",VLOOKUP(A88,'Loc Configurations Seules'!R:W,6,FALSE),VLOOKUP(G88,'Loc Coefficients Location'!A:F,6,FALSE)),"") | Q88: =IF(ISNUMBER(P88),P88*$F88,"") | R88: =IF(ISNUMBER(F88),IF(LEFT(A88,3)="Cat",VLOOKUP(A88,'Loc Configurations Seules'!R:X,7,FALSE),VLOOKUP(G88,'Loc Coefficients Location'!A:G,7,FALSE)),"") | S88: =IF(ISNUMBER(R88),R88*$F88,"")
A89: Ajout d'un disque dur SATA 7.2K LFF de 1 To Non HotPlug | B89: HPE 1TB SATA 7.2K LFF RW MV HDD | C89: 801882-B21 | F89: 94.5 | G89: PC_SE/PLX86 | H89: =IF(ISNUMBER($F89),ROUND($F89*H$2,2),"") -> 24.94 | I89: =IF(ISNUMBER($F89),ROUND($F89*I$2,2),"") -> 12.65 | J89: =IF(ISNUMBER($F89),ROUND($F89*J$2,2),"") -> 8.63 | K89: =IF(ISNUMBER($F89),ROUND($F89*K$2,2),"") -> 6.64 | L89: =IF(ISNUMBER(F89),IF(LEFT(A89,3)="Cat",VLOOKUP(A89,'Loc Configurations Seules'!R:U,4,FALSE),VLOOKUP(G89,'Loc Coefficients Location'!A:D,4,FALSE)),"") -> 0.18651532 | M89: =IF(ISNUMBER(L89),L89*$F89,"") -> 17.625698 | N89: =IF(ISNUMBER(F89),IF(LEFT(A89,3)="Cat",VLOOKUP(A89,'Loc Configurations Seules'!R:V,5,FALSE),VLOOKUP(G89,'Loc Coefficients Location'!A:E,5,FALSE)),"") -> 0.099038653 | O89: =IF(ISNUMBER(N89),N89*$F89,"") -> 9.3591527 | P89: =IF(ISNUMBER(F89),IF(LEFT(A89,3)="Cat",VLOOKUP(A89,'Loc Configurations Seules'!R:W,6,FALSE),VLOOKUP(G89,'Loc Coefficients Location'!A:F,6,FALSE)),"") -> 0.07542178 | Q89: =IF(ISNUMBER(P89),P89*$F89,"") -> 7.1273582 | R89: =IF(ISNUMBER(F89),IF(LEFT(A89,3)="Cat",VLOOKUP(A89,'Loc Configurations Seules'!R:X,7,FALSE),VLOOKUP(G89,'Loc Coefficients Location'!A:G,7,FALSE)),"") -> 0.063273484 | S89: =IF(ISNUMBER(R89),R89*$F89,"") -> 5.9793442
A90: Ajout d'un disque dur SATA 7.2K LFF de 4 To Non HotPlug | B90: HPE 4TB SATA 7.2K LFF RW MV HDD | C90: 801888-B21 | F90: 118.65 | G90: PC_SE/PLX86 | H90: =IF(ISNUMBER($F90),ROUND($F90*H$2,2),"") -> 31.31 | I90: =IF(ISNUMBER($F90),ROUND($F90*I$2,2),"") -> 15.88 | J90: =IF(ISNUMBER($F90),ROUND($F90*J$2,2),"") -> 10.84 | K90: =IF(ISNUMBER($F90),ROUND($F90*K$2,2),"") -> 8.34 | L90: =IF(ISNUMBER(F90),IF(LEFT(A90,3)="Cat",VLOOKUP(A90,'Loc Configurations Seules'!R:U,4,FALSE),VLOOKUP(G90,'Loc Coefficients Location'!A:D,4,FALSE)),"") -> 0.18651532 | M90: =IF(ISNUMBER(L90),L90*$F90,"") -> 22.130043 | N90: =IF(ISNUMBER(F90),IF(LEFT(A90,3)="Cat",VLOOKUP(A90,'Loc Configurations Seules'!R:V,5,FALSE),VLOOKUP(G90,'Loc Coefficients Location'!A:E,5,FALSE)),"") -> 0.099038653 | O90: =IF(ISNUMBER(N90),N90*$F90,"") -> 11.750936 | P90: =IF(ISNUMBER(F90),IF(LEFT(A90,3)="Cat",VLOOKUP(A90,'Loc Configurations Seules'!R:W,6,FALSE),VLOOKUP(G90,'Loc Coefficients Location'!A:F,6,FALSE)),"") -> 0.07542178 | Q90: =IF(ISNUMBER(P90),P90*$F90,"") -> 8.9487941 | R90: =IF(ISNUMBER(F90),IF(LEFT(A90,3)="Cat",VLOOKUP(A90,'Loc Configurations Seules'!R:X,7,FALSE),VLOOKUP(G90,'Loc Coefficients Location'!A:G,7,FALSE)),"") -> 0.063273484 | S90: =IF(ISNUMBER(R90),R90*$F90,"") -> 7.5073989
A91: Autres extensions matérielles | H91: =IF(ISNUMBER($F91),ROUND($F91*H$2,2),"") | I91: =IF(ISNUMBER($F91),ROUND($F91*I$2,2),"") | J91: =IF(ISNUMBER($F91),ROUND($F91*J$2,2),"") | K91: =IF(ISNUMBER($F91),ROUND($F91*K$2,2),"") | L91: =IF(ISNUMBER(F91),IF(LEFT(A91,3)="Cat",VLOOKUP(A91,'Loc Configurations Seules'!R:U,4,FALSE),VLOOKUP(G91,'Loc Coefficients Location'!A:D,4,FALSE)),"") | M91: =IF(ISNUMBER(L91),L91*$F91,"") | N91: =IF(ISNUMBER(F91),IF(LEFT(A91,3)="Cat",VLOOKUP(A91,'Loc Configurations Seules'!R:V,5,FALSE),VLOOKUP(G91,'Loc Coefficients Location'!A:E,5,FALSE)),"") | O91: =IF(ISNUMBER(N91),N91*$F91,"") | P91: =IF(ISNUMBER(F91),IF(LEFT(A91,3)="Cat",VLOOKUP(A91,'Loc Configurations Seules'!R:W,6,FALSE),VLOOKUP(G91,'Loc Coefficients Location'!A:F,6,FALSE)),"") | Q91: =IF(ISNUMBER(P91),P91*$F91,"") | R91: =IF(ISNUMBER(F91),IF(LEFT(A91,3)="Cat",VLOOKUP(A91,'Loc Configurations Seules'!R:X,7,FALSE),VLOOKUP(G91,'Loc Coefficients Location'!A:G,7,FALSE)),"") | S91: =IF(ISNUMBER(R91),R91*$F91,"")
A92: Ajout d'un kit de conversion LFF Non-hot Plug vers SFF Non-hot Plug | B92: HPE MicroServer Gen10 SFF NHP SATA Converter Kit | C92: 870213-B21 | F92: 5.25 | G92: PC_SE/PLX86 | H92: =IF(ISNUMBER($F92),ROUND($F92*H$2,2),"") -> 1.39 | I92: =IF(ISNUMBER($F92),ROUND($F92*I$2,2),"") -> 0.7 | J92: =IF(ISNUMBER($F92),ROUND($F92*J$2,2),"") -> 0.48 | K92: =IF(ISNUMBER($F92),ROUND($F92*K$2,2),"") -> 0.37 | L92: =IF(ISNUMBER(F92),IF(LEFT(A92,3)="Cat",VLOOKUP(A92,'Loc Configurations Seules'!R:U,4,FALSE),VLOOKUP(G92,'Loc Coefficients Location'!A:D,4,FALSE)),"") -> 0.18651532 | M92: =IF(ISNUMBER(L92),L92*$F92,"") -> 0.97920545 | N92: =IF(ISNUMBER(F92),IF(LEFT(A92,3)="Cat",VLOOKUP(A92,'Loc Configurations Seules'!R:V,5,FALSE),VLOOKUP(G92,'Loc Coefficients Location'!A:E,5,FALSE)),"") -> 0.099038653 | O92: =IF(ISNUMBER(N92),N92*$F92,"") -> 0.51995293 | P92: =IF(ISNUMBER(F92),IF(LEFT(A92,3)="Cat",VLOOKUP(A92,'Loc Configurations Seules'!R:W,6,FALSE),VLOOKUP(G92,'Loc Coefficients Location'!A:F,6,FALSE)),"") -> 0.07542178 | Q92: =IF(ISNUMBER(P92),P92*$F92,"") -> 0.39596434 | R92: =IF(ISNUMBER(F92),IF(LEFT(A92,3)="Cat",VLOOKUP(A92,'Loc Configurations Seules'!R:X,7,FALSE),VLOOKUP(G92,'Loc Coefficients Location'!A:G,7,FALSE)),"") -> 0.063273484 | S92: =IF(ISNUMBER(R92),R92*$F92,"") -> 0.33218579
A93: Extensions de garanties | H93: =IF(ISNUMBER($F93),ROUND($F93*H$2,2),"") | I93: =IF(ISNUMBER($F93),ROUND($F93*I$2,2),"") | J93: =IF(ISNUMBER($F93),ROUND($F93*J$2,2),"") | K93: =IF(ISNUMBER($F93),ROUND($F93*K$2,2),"") | L93: =IF(ISNUMBER(F93),IF(LEFT(A93,3)="Cat",VLOOKUP(A93,'Loc Configurations Seules'!R:U,4,FALSE),VLOOKUP(G93,'Loc Coefficients Location'!A:D,4,FALSE)),"") | M93: =IF(ISNUMBER(L93),L93*$F93,"") | N93: =IF(ISNUMBER(F93),IF(LEFT(A93,3)="Cat",VLOOKUP(A93,'Loc Configurations Seules'!R:V,5,FALSE),VLOOKUP(G93,'Loc Coefficients Location'!A:E,5,FALSE)),"") | O93: =IF(ISNUMBER(N93),N93*$F93,"") | P93: =IF(ISNUMBER(F93),IF(LEFT(A93,3)="Cat",VLOOKUP(A93,'Loc Configurations Seules'!R:W,6,FALSE),VLOOKUP(G93,'Loc Coefficients Location'!A:F,6,FALSE)),"") | Q93: =IF(ISNUMBER(P93),P93*$F93,"") | R93: =IF(ISNUMBER(F93),IF(LEFT(A93,3)="Cat",VLOOKUP(A93,'Loc Configurations Seules'!R:X,7,FALSE),VLOOKUP(G93,'Loc Coefficients Location'!A:G,7,FALSE)),"") | S93: =IF(ISNUMBER(R93),R93*$F93,"")
A94: Microserver | H94: =IF(ISNUMBER($F94),ROUND($F94*H$2,2),"") | I94: =IF(ISNUMBER($F94),ROUND($F94*I$2,2),"") | J94: =IF(ISNUMBER($F94),ROUND($F94*J$2,2),"") | K94: =IF(ISNUMBER($F94),ROUND($F94*K$2,2),"") | L94: =IF(ISNUMBER(F94),IF(LEFT(A94,3)="Cat",VLOOKUP(A94,'Loc Configurations Seules'!R:U,4,FALSE),VLOOKUP(G94,'Loc Coefficients Location'!A:D,4,FALSE)),"") | M94: =IF(ISNUMBER(L94),L94*$F94,"") | N94: =IF(ISNUMBER(F94),IF(LEFT(A94,3)="Cat",VLOOKUP(A94,'Loc Configurations Seules'!R:V,5,FALSE),VLOOKUP(G94,'Loc Coefficients Location'!A:E,5,FALSE)),"") | O94: =IF(ISNUMBER(N94),N94*$F94,"") | P94: =IF(ISNUMBER(F94),IF(LEFT(A94,3)="Cat",VLOOKUP(A94,'Loc Configurations Seules'!R:W,6,FALSE),VLOOKUP(G94,'Loc Coefficients Location'!A:F,6,FALSE)),"") | Q94: =IF(ISNUMBER(P94),P94*$F94,"") | R94: =IF(ISNUMBER(F94),IF(LEFT(A94,3)="Cat",VLOOKUP(A94,'Loc Configurations Seules'!R:X,7,FALSE),VLOOKUP(G94,'Loc Coefficients Location'!A:G,7,FALSE)),"") | S94: =IF(ISNUMBER(R94),R94*$F94,"")
A95: Passage à support 5 ans intervention j+1 (9x5) avec retention de disque | B95: Tech Care Basic DMR 5Y (J+1 9x5) | C95: Passage vers HU4B3A5#YKX | F95: 19 | G95: SOFT/MAINT | H95: =IF(ISNUMBER($F95),ROUND($F95*H$2,2),"") -> 5.01 | I95: =IF(ISNUMBER($F95),ROUND($F95*I$2,2),"") -> 2.54 | J95: =IF(ISNUMBER($F95),ROUND($F95*J$2,2),"") -> 1.74 | K95: =IF(ISNUMBER($F95),ROUND($F95*K$2,2),"") -> 1.33
A96: Passage à support 5 ans intervention h+4 (24h/24h, 7j/7j) | B96: Tech Care Essential 5Y (4H 24X7) | C96: Passage vers HU4A6A5#YKX | F96: 26 | G96: SOFT/MAINT | H96: =IF(ISNUMBER($F96),ROUND($F96*H$2,2),"") -> 6.86 | I96: =IF(ISNUMBER($F96),ROUND($F96*I$2,2),"") -> 3.48 | J96: =IF(ISNUMBER($F96),ROUND($F96*J$2,2),"") -> 2.38 | K96: =IF(ISNUMBER($F96),ROUND($F96*K$2,2),"") -> 1.83
A97: Passage à support 5 ans intervention h+4 (24h/24h, 7j/7j) avec retention de Disque | B97: Tech Care Essential 5Y DMR (4H 24X7) | C97: Passage vers HU4A7A5#YKX | F97: 35 | G97: SOFT/MAINT | H97: =IF(ISNUMBER($F97),ROUND($F97*H$2,2),"") -> 9.24 | I97: =IF(ISNUMBER($F97),ROUND($F97*I$2,2),"") -> 4.68 | J97: =IF(ISNUMBER($F97),ROUND($F97*J$2,2),"") -> 3.2 | K97: =IF(ISNUMBER($F97),ROUND($F97*K$2,2),"") -> 2.46
A98: Passage à support 6 ans intervention J+1 (Heures ouvrées, jours ouvrés) | B98: HPE 6Y TC Basis SVC | C98: Passage vers HU4B2A6#YKX | F98: 5 | G98: SOFT/MAINT | H98: =IF(ISNUMBER($F98),ROUND($F98*H$2,2),"") -> 1.32 | I98: =IF(ISNUMBER($F98),ROUND($F98*I$2,2),"") -> 0.67 | J98: =IF(ISNUMBER($F98),ROUND($F98*J$2,2),"") -> 0.46 | K98: =IF(ISNUMBER($F98),ROUND($F98*K$2,2),"") -> 0.35
A99: Passage à support 6 ans intervention h+4 (24h/24h, 7j/7j) | B99: HPE 6Y Tech Care Essential SVC | C99: Passage vers HU4A6A6#YKX | F99: 110 | G99: SOFT/MAINT | H99: =IF(ISNUMBER($F99),ROUND($F99*H$2,2),"") -> 29.03 | I99: =IF(ISNUMBER($F99),ROUND($F99*I$2,2),"") -> 14.72 | J99: =IF(ISNUMBER($F99),ROUND($F99*J$2,2),"") -> 10.05 | K99: =IF(ISNUMBER($F99),ROUND($F99*K$2,2),"") -> 7.73
A100: Passage à support 7 ans intervention J+1 (Heures ouvrées, jours ouvrés) | B100: HPE 7Y Tech Care Basis SVC | C100: Passage vers HU4B2A7#YKX | F100: 10 | G100: SOFT/MAINT | H100: =IF(ISNUMBER($F100),ROUND($F100*H$2,2),"") -> 2.64 | I100: =IF(ISNUMBER($F100),ROUND($F100*I$2,2),"") -> 1.34 | J100: =IF(ISNUMBER($F100),ROUND($F100*J$2,2),"") -> 0.91 | K100: =IF(ISNUMBER($F100),ROUND($F100*K$2,2),"") -> 0.7
...

Sheet Loc Configurations Seules
F1: COEFFICIENTS LOCATIF
F2: 0.2639 | G2: 0.1339 | H2: 0.0914 | I2: 0.0703
F3: CREDIT-BAIL | J3: LOCATION
F4: 1 an | G4: 2 ans | H4: 3 ans | I4: 4 ans | J4: 1 an | L4: 2 ans | N4: 3 ans | P4: 4 ans | U4: 1 an | V4: 2 ans | W4: 3 ans | X4: 4 ans
F5: 4 Trimestres | G5: 8 Trimestres | H5: 12 Trimestres | I5: 16 Trimestres | J5: 4 trimestres | L5: 8 trimestres | N5: 12 trimestres | P5: 16 trimestres | U5: 4 trimestres | V5: 8 trimestres | W5: 12 trimestres | X5: 16 trimestres
A6: Désignation/Description des matériels | B6: Référence constructeur (le cas échéant) | C6: Numéro de référence | D6: Quantités | E6: TARIFS en €HT | F6: Loyer Trimestriel €HT | J6: Coefficient Locatif | K6: Loyer Trimestriel €HT | L6: Coefficient Locatif | M6: Loyer Trimestriel €HT | N6: Coefficient Locatif | O6: Loyer Trimestriel €HT | P6: Coefficient Locatif | Q6: Loyer Trimestriel €HT | R6: Désignation/Description des matériels | U6: Coefficient Locatif | V6: Coefficient Locatif | W6: Coefficient Locatif | X6: Coefficient Locatif
A7: Cat1 Conf1 Microserver | B7: =VLOOKUP(A7,'Lot 4 - Bordereau de prix'!A:B,2,FALSE) -> HPE ProLiant MicroServer Gen10+ | C7: =VLOOKUP(A7,'Lot 4 - Bordereau de prix'!A:C,3,FALSE) -> P16005-421 | D7: 1 | E7: =VLOOKUP(A7,'Lot 4 - Bordereau de prix'!A:F,6,FALSE) -> 488.24 | F7: =ROUND($E7*F$2,2) -> 128.85 | G7: =ROUND($E7*G$2,2) -> 65.38 | H7: =ROUND($E7*H$2,2) -> 44.63 | I7: =ROUND($E7*I$2,2) -> 34.32 | J7: =U7 -> 0.188 | K7: =$E7*J7 -> 91.78912 | L7: =V7 -> 0.0997 | M7: =$E7*L7 -> 48.677528 | N7: =W7 -> 0.0757 | O7: =$E7*N7 -> 36.959768 | P7: =X7 -> 0.0634 | Q7: =$E7*P7 -> 30.954416 | R7: Cat1 Conf1 Microserver | U7: 0.188 | V7: 0.0997 | W7: 0.0757 | X7: 0.0634
A8: Cat1 Conf5 DL20 Gen10 plus | B8: =VLOOKUP(A8,'Lot 4 - Bordereau de prix'!A:B,2,FALSE) -> HPE ProLiant DL20 Gen10+ | C8: =VLOOKUP(A8,'Lot 4 - Bordereau de prix'!A:C,3,FALSE) -> P44109-B21 | D8: 1 | E8: =VLOOKUP(A8,'Lot 4 - Bordereau de prix'!A:F,6,FALSE) -> 302.89 | F8: =ROUND($E8*F$2,2) -> 79.93 | G8: =ROUND($E8*G$2,2) -> 40.56 | H8: =ROUND($E8*H$2,2) -> 27.68 | I8: =ROUND($E8*I$2,2) -> 21.29 | J8: =U8 -> 0.2129 | K8: =$E8*J8 -> 64.485281 | L8: =V8 -> 0.1109 | M8: =$E8*L8 -> 33.590501 | N8: =W8 -> 0.0808 | O8: =$E8*N8 -> 24.473512 | P8: =X8 -> 0.0657 | Q8: =$E8*P8 -> 19.899873 | R8: Cat1 Conf5 DL20 Gen10 plus | U8: 0.2129 | V8: 0.1109 | W8: 0.0808 | X8: 0.0657
A9: Cat1 Conf2 DL325 Gen10 plus | B9: =VLOOKUP(A9,'Lot 4 - Bordereau de prix'!A:B,2,FALSE) -> HPE ProLiant DL325 Gen10+ | C9: =VLOOKUP(A9,'Lot 4 - Bordereau de prix'!A:C,3,FALSE) -> P18606-B21 | D9: 1 | E9: =VLOOKUP(A9,'Lot 4 - Bordereau de prix'!A:F,6,FALSE) -> 674.1 | F9: =ROUND($E9*F$2,2) -> 177.89 | G9: =ROUND($E9*G$2,2) -> 90.26 | H9: =ROUND($E9*H$2,2) -> 61.61 | I9: =ROUND($E9*I$2,2) -> 47.39 | J9: =U9 -> 0.2046 | K9: =$E9*J9 -> 137.92086 | L9: =V9 -> 0.1072 | M9: =$E9*L9 -> 72.26352 | N9: =W9 -> 0.0791 | O9: =$E9*N9 -> 53.32131 | P9: =X9 -> 0.0649 | Q9: =$E9*P9 -> 43.74909 | R9: Cat1 Conf2 DL325 Gen10 plus | U9: 0.2046 | V9: 0.1072 | W9: 0.0791 | X9: 0.0649
A10: Cat1 Conf3 Edge EL300 | B10: =VLOOKUP(A10,'Lot 4 - Bordereau de prix'!A:B,2,FALSE) -> HPE EL300 v2 | C10: =VLOOKUP(A10,'Lot 4 - Bordereau de prix'!A:C,3,FALSE) -> P25828-B21 | D10: 1 | E10: =VLOOKUP(A10,'Lot 4 - Bordereau de prix'!A:F,6,FALSE) -> 1666.29 | F10: =ROUND($E10*F$2,2) -> 439.73 | G10: =ROUND($E10*G$2,2) -> 223.12 | H10: =ROUND($E10*H$2,2) -> 152.3 | I10: =ROUND($E10*I$2,2) -> 117.14 | J10: =U10 -> 0.2207 | K10: =$E10*J10 -> 367.7502 | L10: =V10 -> 0.1151 | M10: =$E10*L10 -> 191.78998 | N10: =W10 -> 0.082 | O10: =$E10*N10 -> 136.63578 | P10: =X10 -> 0.0662 | Q10: =$E10*P10 -> 110.3084 | R10: Cat1 Conf3 Edge EL300 | U10: 0.2207 | V10: 0.1151 | W10: 0.082 | X10: 0.0662
A11: Cat1 Conf6 Tour ML30 Gen10 plus | B11: =VLOOKUP(A11,'Lot 4 - Bordereau de prix'!A:B,2,FALSE) -> HPE ProLiant ML30 Gen10+ | C11: =VLOOKUP(A11,'Lot 4 - Bordereau de prix'!A:C,3,FALSE) -> P44723-B21 | D11: 1 | E11: =VLOOKUP(A11,'Lot 4 - Bordereau de prix'!A:F,6,FALSE) -> 721.84 | F11: =ROUND($E11*F$2,2) -> 190.49 | G11: =ROUND($E11*G$2,2) -> 96.65 | H11: =ROUND($E11*H$2,2) -> 65.98 | I11: =ROUND($E11*I$2,2) -> 50.75 | J11: =U11 -> 0.2004 | K11: =$E11*J11 -> 144.65674 | L11: =V11 -> 0.1053 | M11: =$E11*L11 -> 76.009752 | N11: =W11 -> 0.0783 | O11: =$E11*N11 -> 56.520072 | P11: =X11 -> 0.0645 | Q11: =$E11*P11 -> 46.55868 | R11: Cat1 Conf6 Tour ML30 Gen10 plus | U11: 0.2004 | V11: 0.1053 | W11: 0.0783 | X11: 0.0645
A12: Cat2 Conf1 DL380 Gen10 | B12: =VLOOKUP(A12,'Lot 4 - Bordereau de prix'!A:B,2,FALSE) -> HPE ProLiant DL380 Gen10 | C12: =VLOOKUP(A12,'Lot 4 - Bordereau de prix'!A:C,3,FALSE) -> 868703-B21 | D12: 1 | E12: =VLOOKUP(A12,'Lot 4 - Bordereau de prix'!A:F,6,FALSE) -> 884.1 | F12: =ROUND($E12*F$2,2) -> 233.31 | G12: =ROUND($E12*G$2,2) -> 118.38 | H12: =ROUND($E12*H$2,2) -> 80.81 | I12: =ROUND($E12*I$2,2) -> 62.15 | J12: =U12 -> 0.2059 | K12: =$E12*J12 -> 182.03619 | L12: =V12 -> 0.1078 | M12: =$E12*L12 -> 95.30598 | N12: =W12 -> 0.0794 | O12: =$E12*N12 -> 70.19754 | P12: =X12 -> 0.065 | Q12: =$E12*P12 -> 57.4665 | R12: Cat2 Conf1 DL380 Gen10 | U12: 0.2059 | V12: 0.1078 | W12: 0.0794 | X12: 0.065
A13: Cat2 Conf5 DL160 Gen10 | B13: =VLOOKUP(A13,'Lot 4 - Bordereau de prix'!A:B,2,FALSE) -> HPE ProLiant DL160 Gen10 | C13: =VLOOKUP(A13,'Lot 4 - Bordereau de prix'!A:C,3,FALSE) -> 878973-B21 | D13: 1 | E13: =VLOOKUP(A13,'Lot 4 - Bordereau de prix'!A:F,6,FALSE) -> 830.54 | F13: =ROUND($E13*F$2,2) -> 219.18 | G13: =ROUND($E13*G$2,2) -> 111.21 | H13: =ROUND($E13*H$2,2) -> 75.91 | I13: =ROUND($E13*I$2,2) -> 58.39 | J13: =U13 -> 0.204 | K13: =$E13*J13 -> 169.43016 | L13: =V13 -> 0.1069 | M13: =$E13*L13 -> 88.784726 | N13: =W13 -> 0.079 | O13: =$E13*N13 -> 65.61266 | P13: =X13 -> 0.0649 | Q13: =$E13*P13 -> 53.902046 | R13: Cat2 Conf5 DL160 Gen10 | U13: 0.204 | V13: 0.1069 | W13: 0.079 | X13: 0.0649
A14: Cat2 Conf2 DL380 Gen10 NC | B14: =VLOOKUP(A14,'Lot 4 - Bordereau de prix'!A:B,2,FALSE) -> HPE ProLiant DL380 Gen10 | C14: =VLOOKUP(A14,'Lot 4 - Bordereau de prix'!A:C,3,FALSE) -> P19720-B21 | D14: 1 | E14: =VLOOKUP(A14,'Lot 4 - Bordereau de prix'!A:F,6,FALSE) -> 988.05 | F14: =ROUND($E14*F$2,2) -> 260.75 | G14: =ROUND($E14*G$2,2) -> 132.3 | H14: =ROUND($E14*H$2,2) -> 90.31 | I14: =ROUND($E14*I$2,2) -> 69.46 | J14: =U14 -> 0.2039 | K14: =$E14*J14 -> 201.46339 | L14: =V14 -> 0.1068 | M14: =$E14*L14 -> 105.52374 | N14: =W14 -> 0.079 | O14: =$E14*N14 -> 78.05595 | P14: =X14 -> 0.0648 | Q14: =$E14*P14 -> 64.02564 | R14: Cat2 Conf2 DL380 Gen10 NC | U14: 0.2039 | V14: 0.1068 | W14: 0.079 | X14: 0.0648
A15: Cat2 Conf6 DL180 Gen10 Intel | B15: =VLOOKUP(A15,'Lot 4 - Bordereau de prix'!A:B,2,FALSE) -> HPE ProLiant DL180 Gen10 | C15: =VLOOKUP(A15,'Lot 4 - Bordereau de prix'!A:C,3,FALSE) -> 879517-B21 | D15: 1 | E15: =VLOOKUP(A15,'Lot 4 - Bordereau de prix'!A:F,6,FALSE) -> 901.94 | F15: =ROUND($E15*F$2,2) -> 238.02 | G15: =ROUND($E15*G$2,2) -> 120.77 | H15: =ROUND($E15*H$2,2) -> 82.44 | I15: =ROUND($E15*I$2,2) -> 63.41 | J15: =U15 -> 0.2055 | K15: =$E15*J15 -> 185.34867 | L15: =V15 -> 0.1076 | M15: =$E15*L15 -> 97.048744 | N15: =W15 -> 0.0793 | O15: =$E15*N15 -> 71.523842 | P15: =X15 -> 0.065 | Q15: =$E15*P15 -> 58.6261 | R15: Cat2 Conf6 DL180 Gen10 Intel | U15: 0.2055 | V15: 0.1076 | W15: 0.0793 | X15: 0.065
A16: Cat2 Conf2 DL385 Gen10 plus | B16: =VLOOKUP(A16,'Lot 4 - Bordereau de prix'!A:B,2,FALSE) -> HPE ProLiant DL385 Gen10+ | C16: =VLOOKUP(A16,'Lot 4 - Bordereau de prix'!A:C,3,FALSE) -> P14278-B21 | D16: 1 | E16: =VLOOKUP(A16,'Lot 4 - Bordereau de prix'!A:F,6,FALSE) -> 1254.79 | F16: =ROUND($E16*F$2,2) -> 331.14 | G16: =ROUND($E16*G$2,2) -> 168.02 | H16: =ROUND($E16*H$2,2) -> 114.69 | I16: =ROUND($E16*I$2,2) -> 88.21 | J16: =U16 -> 0.2008 | K16: =$E16*J16 -> 251.96183 | L16: =V16 -> 0.1054 | M16: =$E16*L16 -> 132.25487 | N16: =W16 -> 0.0784 | O16: =$E16*N16 -> 98.375536 | P16: =X16 -> 0.0646 | Q16: =$E16*P16 -> 81.059434 | R16: Cat2 Conf2 DL385 Gen10 plus | U16: 0.2008 | V16: 0.1054 | W16: 0.0784 | X16: 0.0646
A17: Cat2 Conf7 DL365 Gen10 plus | B17: =VLOOKUP(A17,'Lot 4 - Bordereau de prix'!A:B,2,FALSE) -> HPE ProLiant DL365 Gen10+ | C17: =VLOOKUP(A17,'Lot 4 - Bordereau de prix'!A:C,3,FALSE) -> P38578-B21 | D17: 1 | E17: =VLOOKUP(A17,'Lot 4 - Bordereau de prix'!A:F,6,FALSE) -> 1467.9 | F17: =ROUND($E17*F$2,2) -> 387.38 | G17: =ROUND($E17*G$2,2) -> 196.55 | H17: =ROUND($E17*H$2,2) -> 134.17 | I17: =ROUND($E17*I$2,2) -> 103.19 | J17: =U17 -> 0.1987 | K17: =$E17*J17 -> 291.67173 | L17: =V17 -> 0.1045 | M17: =$E17*L17 -> 153.39555 | N17: =W17 -> 0.0779 | O17: =$E17*N17 -> 114.34941 | P17: =X17 -> 0.0644 | Q17: =$E17*P17 -> 94.53276 | R17: Cat2 Conf7 DL365 Gen10 plus | U17: 0.1987 | V17: 0.1045 | W17: 0.0779 | X17: 0.0644
A18: Cat2 Conf3 DL360 Gen10 | B18: =VLOOKUP(A18,'Lot 4 - Bordereau de prix'!A:B,2,FALSE) -> HPE ProLiant DL360 Gen10 | C18: =VLOOKUP(A18,'Lot 4 - Bordereau de prix'!A:C,3,FALSE) -> P19766-B21 | D18: 1 | E18: =VLOOKUP(A18,'Lot 4 - Bordereau de prix'!A:F,6,FALSE) -> 964.95 | F18: =ROUND($E18*F$2,2) -> 254.65 | G18: =ROUND($E18*G$2,2) -> 129.21 | H18: =ROUND($E18*H$2,2) -> 88.2 | I18: =ROUND($E18*I$2,2) -> 67.84 | J18: =U18 -> 0.2016 | K18: =$E18*J18 -> 194.53392 | L18: =V18 -> 0.1058 | M18: =$E18*L18 -> 102.09171 | N18: =W18 -> 0.0785 | O18: =$E18*N18 -> 75.748575 | P18: =X18 -> 0.0646 | Q18: =$E18*P18 -> 62.33577 | R18: Cat2 Conf3 DL360 Gen10 | U18: 0.2016 | V18: 0.1058 | W18: 0.0785 | X18: 0.0646
... A58: Cat5 Conf11 StorEver MSL 3040 | B58: =VLOOKUP(A58,'Lot 4 - Bordereau de prix'!A:B,2,FALSE) -> StoreEver MSL 3040 | C58: =VLOOKUP(A58,'Lot 4 - Bordereau de prix'!A:C,3,FALSE) -> Q6Q62B | D58: 1 | E58: =VLOOKUP(A58,'Lot 4 - Bordereau de prix'!A:F,6,FALSE) -> 5878.94 | F58: =ROUND($E58*F$2,2) -> 1551.45 | G58: =ROUND($E58*G$2,2) -> 787.19 | H58: =ROUND($E58*H$2,2) -> 537.34 | I58: =ROUND($E58*I$2,2) -> 413.29 | J58: =U58 -> 0.2013 | K58: =$E58*J58 -> 1183.4306 | L58: =V58 -> 0.1057 | M58: =$E58*L58 -> 621.40396 | N58: =W58 -> 0.0799 | O58: =$E58*N58 -> 469.72731 | P58: =X58 -> 0.0663 | Q58: =$E58*P58 -> 389.77372 | R58: Cat5 Conf11 StorEver MSL 3040 | U58: 0.2013 | V58: 0.1057 | W58: 0.0799 | X58: 0.0663

Sheet Loc Coefficients Crédit-Bail
A1: Category | B1: Equipment | C1: Type | D1: LRF12 | E1: LRF24 | F1: LRF36 | G1: LRF48
A2: PC_SE/PLX86 | B2: HPE ISS Servers (Apollo; SGI; Synergy; Superdome Flex; StoreEasy; Non Stop, Cloudline) | C2: Server | D2: 0.26392451 | E2: 0.13385372 | F2: 0.091350624 | G2: 0.070256845
A3: PC_SE/EDGE | B3: Edgeline/Moonshot | C3: Server | D3: 0.26392451 | E3: 0.13385372 | F3: 0.091350624 | G3: 0.070256845
A4: Store/PRIMERA | B4: Primera, Nimble and Alletra Storage Hardware; and Store SAN; includes MSA, Store Virtual, IAP(RISS), Storeonce, BX(VLS) | C4: Storage | D4: 0.26392451 | E4: 0.13385372 | F4: 0.091350624 | G4: 0.070256845
A5: Store/DTL | B5: StoreEver MSL and ESL Tape Libraries | C5: Storage | D5: 0.26392451 | E5: 0.13385372 | F5: 0.091350624 | G5: 0.070256845
A6: Store/Other | B6: 3rd Party Storage (EMC Storage, IBM, Lenovo, Pure Storage, Net App) & NAS Storage Appliance (Cisco NSS, QNAP) | C6: Storage | D6: 0.26392451 | E6: 0.13385372 | F6: 0.091350624 | G6: 0.070256845
A7: Netwo/HPEN | B7: Aruba Data Center Networking, Cisco & Arista | C7: Networking | D7: 0.26392451 | E7: 0.13385372 | F7: 0.091350624 | G7: 0.070256845
A8: Netwo/ARUBA | B8: Aruba Wireless | C8: Networking | D8: 0.26392451 | E8: 0.13385372 | F8: 0.091350624 | G8: 0.070256845
A9: SOFTCOST | B9: soft cost | C9: SOFT | D9: 0.26392451 | E9: 0.13385372 | F9: 0.091350624 | G9: 0.070256845

Sheet Loc Coefficients Location
A1: Category | B1: Equipment | C1: Type | D1: LRF12 | E1: LRF24 | F1: LRF36 | G1: LRF48
A2: PC_SE/PLX86 | B2: HPE ISS Servers (Apollo; SGI; Synergy; Superdome Flex; StoreEasy; Non Stop, Cloudline) | C2: Server | D2: 0.18651532 | E2: 0.099038653 | F2: 0.07542178 | G2: 0.063273484
A3: PC_SE/EDGE | B3: Edgeline/Moonshot | C3: Server | D3: 0.20925315 | E3: 0.11012243 | F3: 0.07949472 | G3: 0.065138183
A4: Store/PRIMERA | B4: Primera, Nimble and Alletra Storage Hardware; and Store SAN; includes MSA, Store Virtual, IAP(RISS), Storeonce, BX(VLS) | C4: Storage | D4: 0.19199024 | E4: 0.10177822 | F4: 0.077378408 | G4: 0.064774233
A5: Store/DTL | B5: StoreEver MSL and ESL Tape Libraries | C5: Storage | D5: 0.18383549 | E5: 0.097804969 | F5: 0.07665341 | G5: 0.065185764
A6: Store/Other | B6: 3rd Party Storage (EMC Storage, IBM, Lenovo, Pure Storage, Net App) & NAS Storage Appliance (Cisco NSS, QNAP) | C6: Storage | D6: 0.22517379 | E6: 0.11793884 | F6: 0.083826377 | G6: 0.068067471
A7: Netwo/HPEN | B7: Aruba Data Center Networking, Cisco & Arista | C7: Networking | D7: 0.1895241 | E7: 0.10104761 | F7: 0.075767585 | G7: 0.06637335
A8: Netwo/ARUBA | B8: Aruba Wireless | C8: Networking | D8: 0.1895241 | E8: 0.10104761 | F8: 0.075767585 | G8: 0.06637335
A9: SOFT/MAINT | B9: soft maint | C9: SOFT | D9: 0.26392451 | E9: 0.13385372 | F9: 0.091350624 | G9: 0.070256845
A10: SOFTCOST | B10: soft cost | C10: SOFT | D10: 0.26392451 | E10: 0.13385372 | F10: 0.091350624 | G10: 0.070256845
A12: Mapping | B12: Equipement
A13: Netwo/ARUBA | B13: Aruba Wireless
A14: Netwo/HPEN | B14: Aruba Data Center Networking, Cisco & Arista
A15: Other/Essen | B15: use parent HW lease rate factor
A16: PC_SE/EDGE | B16: Edgeline/Moonshot
A17: PC_SE/PLX86 | B17: HPE ISS Servers (Apollo; SGI; Synergy; Superdome Flex; StoreEasy; Non Stop, Cloudline)
A18: Store/BURA | B18: Primera, Nimble and Alletra Storage Hardware; and Store SAN; includes MSA, Store Virtual, IAP(RISS), Storeonce, BX(VLS)
A19: Store/DTL | B19: StoreEver MSL and ESL Tape Libraries
A20: Store/DTL2 | B20: StoreEver MSL and ESL Tape Libraries
A21: Store/NAS | B21: 3rd Party Storage (EMC Storage, IBM, Lenovo, Pure Storage, Net App) & NAS Storage Appliance (Cisco NSS, QNAP)
A22: Store/Other | B22: 3rd Party Storage (EMC Storage, IBM, Lenovo, Pure Storage, Net App) & NAS Storage Appliance (Cisco NSS, QNAP)
A23: Store/P10000 | B23: Primera, Nimble and Alletra Storage Hardware; and Store SAN; includes MSA, Store Virtual, IAP(RISS), Storeonce, BX(VLS)
... A25: Store/SAN | B25: Primera, Nimble and Alletra Storage Hardware; and Store SAN; includes MSA, Store Virtual, IAP(RISS), Storeonce, BX(VLS)

Sheet Lot 4 - BPU Drom-Com
G2: Les tarifs indiqués ci-après sont des prix plafonds et sont dégressifs selon les quantités approvisionnées sur une même commande. Le tarif indiqué correspond à un prix de transport DDP maritime. (le transport correspond en moyenne à 1/3 du prix). Les prix contractuels sont les prix des devis de transport fournis par IS2.
A4: Bordereau de prix unitaires | G4: Transport DDP Mer ou Services DROM COM | H4: Transport DDP Mer ou Services DROM COM | I4: Transport DDP Mer ou Services DROM COM | J4: Transport DDP Mer ou Services DROM COM | K4: Transport DDP Mer ou Services DROM COM | L4: Transport DDP Mer ou Services DROM COM | M4: Transport DDP Mer ou Services DROM COM
G5: 0.344 | H5: 0.344 | I5: 0.452 | J5: 0.314 | K5: 0.499 | L5: 0.43 | M5: 0.483
A6: DésignationDescription des matériels | B6: Référence constructeur (le cas échéant) | C6: HPE SKU | D6: Quantités | E6: Column1 | F6: TARIFS en €HT | G6: Guadeloupe | H6: Martinique | I6: Guyane | J6: Réunion | K6: Mayotte | L6: Polynésie | M6: Nouvelle Calédonie | N6: Non Disponible DROMCOM
A7: CATEGORIE 1 : Serveurs Edge ou Standard | G7: =IF($N7,"NA",IF(ISNUMBER($F7),ROUND(($F7*G$5),0),"")) | H7: =IF($N7,"NA",IF(ISNUMBER($F7),ROUND(($F7*H$5),0),"")) | I7: =IF($N7,"NA",IF(ISNUMBER($F7),ROUND(($F7*I$5),0),"")) | J7: =IF($N7,"NA",IF(ISNUMBER($F7),ROUND(($F7*J$5),0),"")) | K7: =IF($N7,"NA",IF(ISNUMBER($F7),ROUND(($F7*K$5),0),"")) | L7: =IF($N7,"NA",IF(ISNUMBER($F7),ROUND(($F7*L$5),0),"")) | M7: =IF($N7,"NA",IF(ISNUMBER($F7),ROUND(($F7*M$5),0),"")) | N7: FALSE
A8: Désignation/Description des matériels | B8: Référence constructeur (le cas échéant) | C8: Numéro de référence | D8: Quantités | F8: TARIFS en €HT | G8: =IF($N8,"NA",IF(ISNUMBER($F8),ROUND(($F8*G$5),0),"")) | H8: =IF($N8,"NA",IF(ISNUMBER($F8),ROUND(($F8*H$5),0),"")) | I8: =IF($N8,"NA",IF(ISNUMBER($F8),ROUND(($F8*I$5),0),"")) | J8: =IF($N8,"NA",IF(ISNUMBER($F8),ROUND(($F8*J$5),0),"")) | K8: =IF($N8,"NA",IF(ISNUMBER($F8),ROUND(($F8*K$5),0),"")) | L8: =IF($N8,"NA",IF(ISNUMBER($F8),ROUND(($F8*L$5),0),"")) | M8: =IF($N8,"NA",IF(ISNUMBER($F8),ROUND(($F8*M$5),0),"")) | N8: FALSE
A9: Cat1 Conf1 Microserver | B9: HPE ProLiant MicroServer Gen10+ | C9: P16005-421 | F9: 488.24 | G9: =IF($N9,"NA",IF(ISNUMBER($F9),ROUND(($F9*G$5),0),"")) -> 168 | H9: =IF($N9,"NA",IF(ISNUMBER($F9),ROUND(($F9*H$5),0),"")) -> 168 | I9: =IF($N9,"NA",IF(ISNUMBER($F9),ROUND(($F9*I$5),0),"")) -> 221 | J9: =IF($N9,"NA",IF(ISNUMBER($F9),ROUND(($F9*J$5),0),"")) -> 153 | K9: =IF($N9,"NA",IF(ISNUMBER($F9),ROUND(($F9*K$5),0),"")) -> 244 | L9: =IF($N9,"NA",IF(ISNUMBER($F9),ROUND(($F9*L$5),0),"")) -> 210 | M9: =IF($N9,"NA",IF(ISNUMBER($F9),ROUND(($F9*M$5),0),"")) -> 236 | N9: FALSE
A10: Serveur tour Ultra Micro mono-socket | B10: HPE ProLiant MicroServer Gen10 Plus G5420 2-core 1P 8GB-U S100i 4LFF-NHP 180W External PS Server | C10: P16005-421 | D10: 1 | G10: =IF($N10,"NA",IF(ISNUMBER($F10),ROUND(($F10*G$5),0),"")) | H10: =IF($N10,"NA",IF(ISNUMBER($F10),ROUND(($F10*H$5),0),"")) | I10: =IF($N10,"NA",IF(ISNUMBER($F10),ROUND(($F10*I$5),0),"")) | J10: =IF($N10,"NA",IF(ISNUMBER($F10),ROUND(($F10*J$5),0),"")) | K10: =IF($N10,"NA",IF(ISNUMBER($F10),ROUND(($F10*K$5),0),"")) | L10: =IF($N10,"NA",IF(ISNUMBER($F10),ROUND(($F10*L$5),0),"")) | M10: =IF($N10,"NA",IF(ISNUMBER($F10),ROUND(($F10*M$5),0),"")) | N10: FALSE
A11: 1 disque de 1 To 6G SATA 7.2K 3,5 pouces (LFF) Non Hot Plug | B11: HPE 1TB SATA 6G Entry 7.2K LFF (3.5in) RW 1yr Wty HDD | C11: 843266-B21 | D11: 1 | G11: =IF($N11,"NA",IF(ISNUMBER($F11),ROUND(($F11*G$5),0),"")) | H11: =IF($N11,"NA",IF(ISNUMBER($F11),ROUND(($F11*H$5),0),"")) | I11: =IF($N11,"NA",IF(ISNUMBER($F11),ROUND(($F11*I$5),0),"")) | J11: =IF($N11,"NA",IF(ISNUMBER($F11),ROUND(($F11*J$5),0),"")) | K11: =IF($N11,"NA",IF(ISNUMBER($F11),ROUND(($F11*K$5),0),"")) | L11: =IF($N11,"NA",IF(ISNUMBER($F11),ROUND(($F11*L$5),0),"")) | M11: =IF($N11,"NA",IF(ISNUMBER($F11),ROUND(($F11*M$5),0),"")) | N11: FALSE
A12: Kit pour carte d'administration HPE iLO | B12: HPE MicroServer Gen10 Plus iLO Enablement Kit | C12: P13788-B21 | D12: 1 | G12: =IF($N12,"NA",IF(ISNUMBER($F12),ROUND(($F12*G$5),0),"")) | H12: =IF($N12,"NA",IF(ISNUMBER($F12),ROUND(($F12*H$5),0),"")) | I12: =IF($N12,"NA",IF(ISNUMBER($F12),ROUND(($F12*I$5),0),"")) | J12: =IF($N12,"NA",IF(ISNUMBER($F12),ROUND(($F12*J$5),0),"")) | K12: =IF($N12,"NA",IF(ISNUMBER($F12),ROUND(($F12*K$5),0),"")) | L12: =IF($N12,"NA",IF(ISNUMBER($F12),ROUND(($F12*L$5),0),"")) | M12: =IF($N12,"NA",IF(ISNUMBER($F12),ROUND(($F12*M$5),0),"")) | N12: FALSE
A13: Carte d'administration HPE iLO avec API RESTful compatible IPMI v2.0 et Redfish. Licence en version Advanced avec toutes les options activées | B13: HPE iLO Advanced 1-server License with 1yr Support on iLO Licensed Features | C13: 512485-B21 | D13: 1 | G13: =IF($N13,"NA",IF(ISNUMBER($F13),ROUND(($F13*G$5),0),"")) | H13: =IF($N13,"NA",IF(ISNUMBER($F13),ROUND(($F13*H$5),0),"")) | I13: =IF($N13,"NA",IF(ISNUMBER($F13),ROUND(($F13*I$5),0),"")) | J13: =IF($N13,"NA",IF(ISNUMBER($F13),ROUND(($F13*J$5),0),"")) | K13: =IF($N13,"NA",IF(ISNUMBER($F13),ROUND(($F13*K$5),0),"")) | L13: =IF($N13,"NA",IF(ISNUMBER($F13),ROUND(($F13*L$5),0),"")) | M13: =IF($N13,"NA",IF(ISNUMBER($F13),ROUND(($F13*M$5),0),"")) | N13: FALSE
A14: Livraison devant la porte | B14: Livraison devant la porte | C14: AC114A | D14: 1 | G14: =IF($N14,"NA",IF(ISNUMBER($F14),ROUND(($F14*G$5),0),"")) | H14: =IF($N14,"NA",IF(ISNUMBER($F14),ROUND(($F14*H$5),0),"")) | I14: =IF($N14,"NA",IF(ISNUMBER($F14),ROUND(($F14*I$5),0),"")) | J14: =IF($N14,"NA",IF(ISNUMBER($F14),ROUND(($F14*J$5),0),"")) | K14: =IF($N14,"NA",IF(ISNUMBER($F14),ROUND(($F14*K$5),0),"")) | L14: =IF($N14,"NA",IF(ISNUMBER($F14),ROUND(($F14*L$5),0),"")) | M14: =IF($N14,"NA",IF(ISNUMBER($F14),ROUND(($F14*M$5),0),"")) | N14: FALSE
A15: Garantie 5 ans J+1 | B15: HPE 5Y Tech Care Basic Service | C15: HU4B2A5 | D15: 1 | G15: =IF($N15,"NA",IF(ISNUMBER($F15),ROUND(($F15*G$5),0),"")) | H15: =IF($N15,"NA",IF(ISNUMBER($F15),ROUND(($F15*H$5),0),"")) | I15: =IF($N15,"NA",IF(ISNUMBER($F15),ROUND(($F15*I$5),0),"")) | J15: =IF($N15,"NA",IF(ISNUMBER($F15),ROUND(($F15*J$5),0),"")) | K15: =IF($N15,"NA",IF(ISNUMBER($F15),ROUND(($F15*K$5),0),"")) | L15: =IF($N15,"NA",IF(ISNUMBER($F15),ROUND(($F15*L$5),0),"")) | M15: =IF($N15,"NA",IF(ISNUMBER($F15),ROUND(($F15*M$5),0),"")) | N15: FALSE
A16: Garantie 5 ans J+1 ILO | B16: HPE iLO AdvPack NonBL Support | C16: HU4B2A5#7X4 | D16: 1 | G16: =IF($N16,"NA",IF(ISNUMBER($F16),ROUND(($F16*G$5),0),"")) | H16: =IF($N16,"NA",IF(ISNUMBER($F16),ROUND(($F16*H$5),0),"")) | I16: =IF($N16,"NA",IF(ISNUMBER($F16),ROUND(($F16*I$5),0),"")) | J16: =IF($N16,"NA",IF(ISNUMBER($F16),ROUND(($F16*J$5),0),"")) | K16: =IF($N16,"NA",IF(ISNUMBER($F16),ROUND(($F16*K$5),0),"")) | L16: =IF($N16,"NA",IF(ISNUMBER($F16),ROUND(($F16*L$5),0),"")) | M16: =IF($N16,"NA",IF(ISNUMBER($F16),ROUND(($F16*M$5),0),"")) | N16: FALSE
A17: Garantie 5 ans J+1 châssis | B17: HPE Microserver Gen10 Plus Support | C17: HU4B2A5#YKX | D17: 1 | G17: =IF($N17,"NA",IF(ISNUMBER($F17),ROUND(($F17*G$5),0),"")) | H17: =IF($N17,"NA",IF(ISNUMBER($F17),ROUND(($F17*H$5),0),"")) | I17: =IF($N17,"NA",IF(ISNUMBER($F17),ROUND(($F17*I$5),0),"")) | J17: =IF($N17,"NA",IF(ISNUMBER($F17),ROUND(($F17*J$5),0),"")) | K17: =IF($N17,"NA",IF(ISNUMBER($F17),ROUND(($F17*K$5),0),"")) | L17: =IF($N17,"NA",IF(ISNUMBER($F17),ROUND(($F17*L$5),0),"")) | M17: =IF($N17,"NA",IF(ISNUMBER($F17),ROUND(($F17*M$5),0),"")) | N17: FALSE
G18: =IF($N18,"NA",IF(ISNUMBER($F18),ROUND(($F18*G$5),0),"")) | H18: =IF($N18,"NA",IF(ISNUMBER($F18),ROUND(($F18*H$5),0),"")) | I18: =IF($N18,"NA",IF(ISNUMBER($F18),ROUND(($F18*I$5),0),"")) | J18: =IF($N18,"NA",IF(ISNUMBER($F18),ROUND(($F18*J$5),0),"")) | K18: =IF($N18,"NA",IF(ISNUMBER($F18),ROUND(($F18*K$5),0),"")) | L18: =IF($N18,"NA",IF(ISNUMBER($F18),ROUND(($F18*L$5),0),"")) | M18: =IF($N18,"NA",IF(ISNUMBER($F18),ROUND(($F18*M$5),0),"")) | N18: FALSE
A19: Cat1 Conf5 DL20 Gen10 plus | B19: HPE ProLiant DL20 Gen10+ | C19: P44109-B21 | F19: 302.89 | G19: =IF($N19,"NA",IF(ISNUMBER($F19),ROUND(($F19*G$5),0),"")) -> 104 | H19: =IF($N19,"NA",IF(ISNUMBER($F19),ROUND(($F19*H$5),0),"")) -> 104 | I19: =IF($N19,"NA",IF(ISNUMBER($F19),ROUND(($F19*I$5),0),"")) -> 137 | J19: =IF($N19,"NA",IF(ISNUMBER($F19),ROUND(($F19*J$5),0),"")) -> 95 | K19: =IF($N19,"NA",IF(ISNUMBER($F19),ROUND(($F19*K$5),0),"")) -> 151 | L19: =IF($N19,"NA",IF(ISNUMBER($F19),ROUND(($F19*L$5),0),"")) -> 130 | M19: =IF($N19,"NA",IF(ISNUMBER($F19),ROUND(($F19*M$5),0),"")) -> 146 | N19: FALSE
A20: Serveur rack standard 1U mono-socket INTEL | B20: HPE DL20 Gen10+ 2LFF NHP CTO Svr | C20: P44109-B21 | D20: 1 | G20: =IF($N20,"NA",IF(ISNUMBER($F20),ROUND(($F20*G$5),0),"")) | H20: =IF($N20,"NA",IF(ISNUMBER($F20),ROUND(($F20*H$5),0),"")) | I20: =IF($N20,"NA",IF(ISNUMBER($F20),ROUND(($F20*I$5),0),"")) | J20: =IF($N20,"NA",IF(ISNUMBER($F20),ROUND(($F20*J$5),0),"")) | K20: =IF($N20,"NA",IF(ISNUMBER($F20),ROUND(($F20*K$5),0),"")) | L20: =IF($N20,"NA",IF(ISNUMBER($F20),ROUND(($F20*L$5),0),"")) | M20: =IF($N20,"NA",IF(ISNUMBER($F20),ROUND(($F20*M$5),0),"")) | N20: FALSE
A21: Processeur 64 bits Intel Xeon E-2314 (2,8 GHz de base / 4,50 Ghz Turbo / 4 cœurs / 4 threads / 8 Mo Smart Cache / 65 W PDT | B21: Intel Xeon E-2314 2.8GHz 4-core 65W FIO Processor for HPE | C21: P45248-B21 | D21: 1 | G21: =IF($N21,"NA",IF(ISNUMBER($F21),ROUND(($F21*G$5),0),"")) | H21: =IF($N21,"NA",IF(ISNUMBER($F21),ROUND(($F21*H$5),0),"")) | I21: =IF($N21,"NA",IF(ISNUMBER($F21),ROUND(($F21*I$5),0),"")) | J21: =IF($N21,"NA",IF(ISNUMBER($F21),ROUND(($F21*J$5),0),"")) | K21: =IF($N21,"NA",IF(ISNUMBER($F21),ROUND(($F21*K$5),0),"")) | L21: =IF($N21,"NA",IF(ISNUMBER($F21),ROUND(($F21*L$5),0),"")) | M21: =IF($N21,"NA",IF(ISNUMBER($F21),ROUND(($F21*M$5),0),"")) | N21: FALSE
A22: 1 barrette mémoire HPE Standard DDR4 2666 MHz UDIMM de 16 Go (soit 4 Go ECC par cœur) | B22: HPE 16GB (1x16GB) Single Rank x8 DDR4-3200 CAS-22-22-22 Unbuffered Standard Memory Kit | C22: P43019-B21 | D22: 1 | G22: =IF($N22,"NA",IF(ISNUMBER($F22),ROUND(($F22*G$5),0),"")) | H22: =IF($N22,"NA",IF(ISNUMBER($F22),ROUND(($F22*H$5),0),"")) | I22: =IF($N22,"NA",IF(ISNUMBER($F22),ROUND(($F22*I$5),0),"")) | J22: =IF($N22,"NA",IF(ISNUMBER($F22),ROUND(($F22*J$5),0),"")) | K22: =IF($N22,"NA",IF(ISNUMBER($F22),ROUND(($F22*K$5),0),"")) | L22: =IF($N22,"NA",IF(ISNUMBER($F22),ROUND(($F22*L$5),0),"")) | M22: =IF($N22,"NA",IF(ISNUMBER($F22),ROUND(($F22*M$5),0),"")) | N22: FALSE
A23: 1 cage pour emplacement PCI | B23: HPE ProLiant DL20 Gen10 Plus x8/x8 LP FIO Riser Kit | C23: P46114-B21 | D23: 1 | G23: =IF($N23,"NA",IF(ISNUMBER($F23),ROUND(($F23*G$5),0),"")) | H23: =IF($N23,"NA",IF(ISNUMBER($F23),ROUND(($F23*H$5),0),"")) | I23: =IF($N23,"NA",IF(ISNUMBER($F23),ROUND(($F23*I$5),0),"")) | J23: =IF($N23,"NA",IF(ISNUMBER($F23),ROUND(($F23*J$5),0),"")) | K23: =IF($N23,"NA",IF(ISNUMBER($F23),ROUND(($F23*K$5),0),"")) | L23: =IF($N23,"NA",IF(ISNUMBER($F23),ROUND(($F23*L$5),0),"")) | M23: =IF($N23,"NA",IF(ISNUMBER($F23),ROUND(($F23*M$5),0),"")) | N23: FALSE
A24: Alimentation 290W certifiée 80Plus Platinium | B24: HPE DL20 Gen10 Plat 290W FIO PSU Kit | C24: P21649-B21 | D24: 1 | G24: =IF($N24,"NA",IF(ISNUMBER($F24),ROUND(($F24*G$5),0),"")) | H24: =IF($N24,"NA",IF(ISNUMBER($F24),ROUND(($F24*H$5),0),"")) | I24: =IF($N24,"NA",IF(ISNUMBER($F24),ROUND(($F24*I$5),0),"")) | J24: =IF($N24,"NA",IF(ISNUMBER($F24),ROUND(($F24*J$5),0),"")) | K24: =IF($N24,"NA",IF(ISNUMBER($F24),ROUND(($F24*K$5),0),"")) | L24: =IF($N24,"NA",IF(ISNUMBER($F24),ROUND(($F24*L$5),0),"")) | M24: =IF($N24,"NA",IF(ISNUMBER($F24),ROUND(($F24*M$5),0),"")) | N24: FALSE
A25: Carte d'administration HPE iLO avec API RESTful compatible IPMI v2.0 et Redfish. Licence en version Advanced avec toutes les options activées | B25: HPE iLO Adv 1-svr Lic 1yr Support | C25: 512485-B21 | D25: 1 | G25: =IF($N25,"NA",IF(ISNUMBER($F25),ROUND(($F25*G$5),0),"")) | H25: =IF($N25,"NA",IF(ISNUMBER($F25),ROUND(($F25*H$5),0),"")) | I25: =IF($N25,"NA",IF(ISNUMBER($F25),ROUND(($F25*I$5),0),"")) | J25: =IF($N25,"NA",IF(ISNUMBER($F25),ROUND(($F25*J$5),0),"")) | K25: =IF($N25,"NA",IF(ISNUMBER($F25),ROUND(($F25*K$5),0),"")) | L25: =IF($N25,"NA",IF(ISNUMBER($F25),ROUND(($F25*L$5),0),"")) | M25: =IF($N25,"NA",IF(ISNUMBER($F25),ROUND(($F25*M$5),0),"")) | N25: FALSE
A26: Suppresion du cable electrique par defaut | B26: HPE Remove Standard Power Cords | C26: 469774-409 | D26: 1 | G26: =IF($N26,"NA",IF(ISNUMBER($F26),ROUND(($F26*G$5),0),"")) | H26: =IF($N26,"NA",IF(ISNUMBER($F26),ROUND(($F26*H$5),0),"")) | I26: =IF($N26,"NA",IF(ISNUMBER($F26),ROUND(($F26*I$5),0),"")) | J26: =IF($N26,"NA",IF(ISNUMBER($F26),ROUND(($F26*J$5),0),"")) | K26: =IF($N26,"NA",IF(ISNUMBER($F26),ROUND(($F26*K$5),0),"")) | L26: =IF($N26,"NA",IF(ISNUMBER($F26),ROUND(($F26*L$5),0),"")) | M26: =IF($N26,"NA",IF(ISNUMBER($F26),ROUND(($F26*M$5),0),"")) | N26: FALSE
A27: 1 kit de rail pour rack | B27: HPE 1U Short Friction Rail Kit | C27: 775612-B21 | D27: 1 | G27: =IF($N27,"NA",IF(ISNUMBER($F27),ROUND(($F27*G$5),0),"")) | H27: =IF($N27,"NA",IF(ISNUMBER($F27),ROUND(($F27*H$5),0),"")) | I27: =IF($N27,"NA",IF(ISNUMBER($F27),ROUND(($F27*I$5),0),"")) | J27: =IF($N27,"NA",IF(ISNUMBER($F27),ROUND(($F27*J$5),0),"")) | K27: =IF($N27,"NA",IF(ISNUMBER($F27),ROUND(($F27*K$5),0),"")) | L27: =IF($N27,"NA",IF(ISNUMBER($F27),ROUND(($F27*L$5),0),"")) | M27: =IF($N27,"NA",IF(ISNUMBER($F27),ROUND(($F27*M$5),0),"")) | N27: FALSE
A28: Livraison devant la porte | B28: Livraison devant la porte | C28: AC111A | D28: 1 | G28: =IF($N28,"NA",IF(ISNUMBER($F28),ROUND(($F28*G$5),0),"")) | H28: =IF($N28,"NA",IF(ISNUMBER($F28),ROUND(($F28*H$5),0),"")) | I28: =IF($N28,"NA",IF(ISNUMBER($F28),ROUND(($F28*I$5),0),"")) | J28: =IF($N28,"NA",IF(ISNUMBER($F28),ROUND(($F28*J$5),0),"")) | K28: =IF($N28,"NA",IF(ISNUMBER($F28),ROUND(($F28*K$5),0),"")) | L28: =IF($N28,"NA",IF(ISNUMBER($F28),ROUND(($F28*L$5),0),"")) | M28: =IF($N28,"NA",IF(ISNUMBER($F28),ROUND(($F28*M$5),0),"")) | N28: FALSE
A29: Garantie 5 ans J+1 | B29: HPE 5Y Tech Care Basic Service | C29: HU4B2A5 | D29: 1 | G29: =IF($N29,"NA",IF(ISNUMBER($F29),ROUND(($F29*G$5),0),"")) | H29: =IF($N29,"NA",IF(ISNUMBER($F29),ROUND(($F29*H$5),0),"")) | I29: =IF($N29,"NA",IF(ISNUMBER($F29),ROUND(($F29*I$5),0),"")) | J29: =IF($N29,"NA",IF(ISNUMBER($F29),ROUND(($F29*J$5),0),"")) | K29: =IF($N29,"NA",IF(ISNUMBER($F29),ROUND(($F29*K$5),0),"")) | L29: =IF($N29,"NA",IF(ISNUMBER($F29),ROUND(($F29*L$5),0),"")) | M29: =IF($N29,"NA",IF(ISNUMBER($F29),ROUND(($F29*M$5),0),"")) | N29: FALSE
A30: Garantie 5 ans J+1 ILO | B30: HPE iLO AdvPack NonBL Support | C30: HU4B2A5#7X4 | D30: 1 | G30: =IF($N30,"NA",IF(ISNUMBER($F30),ROUND(($F30*G$5),0),"")) | H30: =IF($N30,"NA",IF(ISNUMBER($F30),ROUND(($F30*H$5),0),"")) | I30: =IF($N30,"NA",IF(ISNUMBER($F30),ROUND(($F30*I$5),0),"")) | J30: =IF($N30,"NA",IF(ISNUMBER($F30),ROUND(($F30*J$5),0),"")) | K30: =IF($N30,"NA",IF(ISNUMBER($F30),ROUND(($F30*K$5),0),"")) | L30: =IF($N30,"NA",IF(ISNUMBER($F30),ROUND(($F30*L$5),0),"")) | M30: =IF($N30,"NA",IF(ISNUMBER($F30),ROUND(($F30*M$5),0),"")) | N30: FALSE
A31: Garantie 5 ans J+1 châssis | B31: HPE ProLiant DL20 Gen10+ Support | C31: HU4B2A5#ZX1 | D31: 1 | G31: =IF($N31,"NA",IF(ISNUMBER($F31),ROUND(($F31*G$5),0),"")) | H31: =IF($N31,"NA",IF(ISNUMBER($F31),ROUND(($F31*H$5),0),"")) | I31: =IF($N31,"NA",IF(ISNUMBER($F31),ROUND(($F31*I$5),0),"")) | J31: =IF($N31,"NA",IF(ISNUMBER($F31),ROUND(($F31*J$5),0),"")) | K31: =IF($N31,"NA",IF(ISNUMBER($F31),ROUND(($F31*K$5),0),"")) | L31: =IF($N31,"NA",IF(ISNUMBER($F31),ROUND(($F31*L$5),0),"")) | M31: =IF($N31,"NA",IF(ISNUMBER($F31),ROUND(($F31*M$5),0),"")) | N31: FALSE
G32: =IF($N32,"NA",IF(ISNUMBER($F32),ROUND(($F32*G$5),0),"")) | H32: =IF($N32,"NA",IF(ISNUMBER($F32),ROUND(($F32*H$5),0),"")) | I32: =IF($N32,"NA",IF(ISNUMBER($F32),ROUND(($F32*I$5),0),"")) | J32: =IF($N32,"NA",IF(ISNUMBER($F32),ROUND(($F32*J$5),0),"")) | K32: =IF($N32,"NA",IF(ISNUMBER($F32),ROUND(($F32*K$5),0),"")) | L32: =IF($N32,"NA",IF(ISNUMBER($F32),ROUND(($F32*L$5),0),"")) | M32: =IF($N32,"NA",IF(ISNUMBER($F32),ROUND(($F32*M$5),0),"")) | N32: FALSE
A33: Cat1 Conf2 DL325 Gen10 plus | B33: HPE ProLiant DL325 Gen10+ | C33: P18606-B21 | F33: 674.1 | G33: =IF($N33,"NA",IF(ISNUMBER($F33),ROUND(($F33*G$5),0),"")) -> 232 | H33: =IF($N33,"NA",IF(ISNUMBER($F33),ROUND(($F33*H$5),0),"")) -> 232 | I33: =IF($N33,"NA",IF(ISNUMBER($F33),ROUND(($F33*I$5),0),"")) -> 305 | J33: =IF($N33,"NA",IF(ISNUMBER($F33),ROUND(($F33*J$5),0),"")) -> 212 | K33: =IF($N33,"NA",IF(ISNUMBER($F33),ROUND(($F33*K$5),0),"")) -> 336 | L33: =IF($N33,"NA",IF(ISNUMBER($F33),ROUND(($F33*L$5),0),"")) -> 290 | M33: =IF($N33,"NA",IF(ISNUMBER($F33),ROUND(($F33*M$5),0),"")) -> 326 | N33: FALSE
A34: Serveur rack standard 1U mono-socket AMD | B34: HPE DL325 Gen10+ CTO Svr | C34: P18606-B21 | D34: 1 | G34: =IF($N34,"NA",IF(ISNUMBER($F34),ROUND(($F34*G$5),0),"")) | H34: =IF($N34,"NA",IF(ISNUMBER($F34),ROUND(($F34*H$5),0),"")) | I34: =IF($N34,"NA",IF(ISNUMBER($F34),ROUND(($F34*I$5),0),"")) | J34: =IF($N34,"NA",IF(ISNUMBER($F34),ROUND(($F34*J$5),0),"")) | K34: =IF($N34,"NA",IF(ISNUMBER($F34),ROUND(($F34*K$5),0),"")) | L34: =IF($N34,"NA",IF(ISNUMBER($F34),ROUND(($F34*L$5),0),"")) | M34: =IF($N34,"NA",IF(ISNUMBER($F34),ROUND(($F34*M$5),0),"")) | N34: FALSE
A35: Processeur 64 bits AMD EPYC 7232P (3,1 GHz de base / 3,2 Ghz Boost / 8 cœurs / 16 threads / 32 Mo cache L3 / 120 W PDT) | B35: HPE DL325 Gen10+ AMD EPYC 7232P FIO Kit | C35: P19634-L21 | D35: 1 | G35: =IF($N35,"NA",IF(ISNUMBER($F35),ROUND(($F35*G$5),0),"")) | H35: =IF($N35,"NA",IF(ISNUMBER($F35),ROUND(($F35*H$5),0),"")) | I35: =IF($N35,"NA",IF(ISNUMBER($F35),ROUND(($F35*I$5),0),"")) | J35: =IF($N35,"NA",IF(ISNUMBER($F35),ROUND(($F35*J$5),0),"")) | K35: =IF($N35,"NA",IF(ISNUMBER($F35),ROUND(($F35*K$5),0),"")) | L35: =IF($N35,"NA",IF(ISNUMBER($F35),ROUND(($F35*L$5),0),"")) | M35: =IF($N35,"NA",IF(ISNUMBER($F35),ROUND(($F35*M$5),0),"")) | N35: FALSE
A36: 1 barrette mémoire HPE DDR4 2933 MHz RDIMM de 32 Go (soit 4 Go ECC par cœur) | B36: HPE 32GB 2Rx4 PC4-3200AA-R Smart Kit | C36: P07646-B21 | D36: 1 | G36: =IF($N36,"NA",IF(ISNUMBER($F36),ROUND(($F36*G$5),0),"")) | H36: =IF($N36,"NA",IF(ISNUMBER($F36),ROUND(($F36*H$5),0),"")) | I36: =IF($N36,"NA",IF(ISNUMBER($F36),ROUND(($F36*I$5),0),"")) | J36: =IF($N36,"NA",IF(ISNUMBER($F36),ROUND(($F36*J$5),0),"")) | K36: =IF($N36,"NA",IF(ISNUMBER($F36),ROUND(($F36*K$5),0),"")) | L36: =IF($N36,"NA",IF(ISNUMBER($F36),ROUND(($F36*L$5),0),"")) | M36: =IF($N36,"NA",IF(ISNUMBER($F36),ROUND(($F36*M$5),0),"")) | N36: FALSE
A37: 1 cage Disque LFF | B37: HPE DL325 Gen10+ 4LFF LP FIO Cage Kit | C37: P15525-B21 | D37: 1 | G37: =IF($N37,"NA",IF(ISNUMBER($F37),ROUND(($F37*G$5),0),"")) | H37: =IF($N37,"NA",IF(ISNUMBER($F37),ROUND(($F37*H$5),0),"")) | I37: =IF($N37,"NA",IF(ISNUMBER($F37),ROUND(($F37*I$5),0),"")) | J37: =IF($N37,"NA",IF(ISNUMBER($F37),ROUND(($F37*J$5),0),"")) | K37: =IF($N37,"NA",IF(ISNUMBER($F37),ROUND(($F37*K$5),0),"")) | L37: =IF($N37,"NA",IF(ISNUMBER($F37),ROUND(($F37*L$5),0),"")) | M37: =IF($N37,"NA",IF(ISNUMBER($F37),ROUND(($F37*M$5),0),"")) | N37: FALSE
A38: 2 ports Ethernet Gigabit intégrés | B38: Marvell QL41132HQRJ Ethernet 10Gb 2-port BASE-T OCP3 Adapter for HPE | C38: P10103-B21 | D38: 1 | G38: =IF($N38,"NA",IF(ISNUMBER($F38),ROUND(($F38*G$5),0),"")) | H38: =IF($N38,"NA",IF(ISNUMBER($F38),ROUND(($F38*H$5),0),"")) | I38: =IF($N38,"NA",IF(ISNUMBER($F38),ROUND(($F38*I$5),0),"")) | J38: =IF($N38,"NA",IF(ISNUMBER($F38),ROUND(($F38*J$5),0),"")) | K38: =IF($N38,"NA",IF(ISNUMBER($F38),ROUND(($F38*K$5),0),"")) | L38: =IF($N38,"NA",IF(ISNUMBER($F38),ROUND(($F38*L$5),0),"")) | M38: =IF($N38,"NA",IF(ISNUMBER($F38),ROUND(($F38*M$5),0),"")) | N38: FALSE
A39: alimentation HPE FlexSlot de 800W certifiée 80PLUS Titanium | B39: HPE 800W FS Ti Ht Plg LH Pwr Sply Kit | C39: 865438-B21 | D39: 1 | G39: =IF($N39,"NA",IF(ISNUMBER($F39),ROUND(($F39*G$5),0),"")) | H39: =IF($N39,"NA",IF(ISNUMBER($F39),ROUND(($F39*H$5),0),"")) | I39: =IF($N39,"NA",IF(ISNUMBER($F39),ROUND(($F39*I$5),0),"")) | J39: =IF($N39,"NA",IF(ISNUMBER($F39),ROUND(($F39*J$5),0),"")) | K39: =IF($N39,"NA",IF(ISNUMBER($F39),ROUND(($F39*K$5),0),"")) | L39: =IF($N39,"NA",IF(ISNUMBER($F39),ROUND(($F39*L$5),0),"")) | M39: =IF($N39,"NA",IF(ISNUMBER($F39),ROUND(($F39*M$5),0),"")) | N39: FALSE
A40: Carte d'administration HPE iLO avec API RESTful compatible IPMI v2.0 et Redfish. Licence en version Advanced avec toutes les options activées | B40: HPE iLO Adv 1-svr Lic 1yr Support | C40: 512485-B21 | D40: 1 | G40: =IF($N40,"NA",IF(ISNUMBER($F40),ROUND(($F40*G$5),0),"")) | H40: =IF($N40,"NA",IF(ISNUMBER($F40),ROUND(($F40*H$5),0),"")) | I40: =IF($N40,"NA",IF(ISNUMBER($F40),ROUND(($F40*I$5),0),"")) | J40: =IF($N40,"NA",IF(ISNUMBER($F40),ROUND(($F40*J$5),0),"")) | K40: =IF($N40,"NA",IF(ISNUMBER($F40),ROUND(($F40*K$5),0),"")) | L40: =IF($N40,"NA",IF(ISNUMBER($F40),ROUND(($F40*L$5),0),"")) | M40: =IF($N40,"NA",IF(ISNUMBER($F40),ROUND(($F40*M$5),0),"")) | N40: FALSE
A41: 1 kit de câbles pour SATA LFF | B41: HPE DL325 Gen10 Plus LFF SATA FIO Cable Kit | C41: P15903-B21 | D41: 1 | G41: =IF($N41,"NA",IF(ISNUMBER($F41),ROUND(($F41*G$5),0),"")) | H41: =IF($N41,"NA",IF(ISNUMBER($F41),ROUND(($F41*H$5),0),"")) | I41: =IF($N41,"NA",IF(ISNUMBER($F41),ROUND(($F41*I$5),0),"")) | J41: =IF($N41,"NA",IF(ISNUMBER($F41),ROUND(($F41*J$5),0),"")) | K41: =IF($N41,"NA",IF(ISNUMBER($F41),ROUND(($F41*K$5),0),"")) | L41: =IF($N41,"NA",IF(ISNUMBER($F41),ROUND(($F41*L$5),0),"")) | M41: =IF($N41,"NA",IF(ISNUMBER($F41),ROUND(($F41*M$5),0),"")) | N41: FALSE
A42: 1 kit de rail pour rack | B42: HPE DL325 Gen10 Plus 1075mm Easy Install Rail Kit | C42: P18544-B21 | D42: 1 | G42: =IF($N42,"NA",IF(ISNUMBER($F42),ROUND(($F42*G$5),0),"")) | H42: =IF($N42,"NA",IF(ISNUMBER($F42),ROUND(($F42*H$5),0),"")) | I42: =IF($N42,"NA",IF(ISNUMBER($F42),ROUND(($F42*I$5),0),"")) | J42: =IF($N42,"NA",IF(ISNUMBER($F42),ROUND(($F42*J$5),0),"")) | K42: =IF($N42,"NA",IF(ISNUMBER($F42),ROUND(($F42*K$5),0),"")) | L42: =IF($N42,"NA",IF(ISNUMBER($F42),ROUND(($F42*L$5),0),"")) | M42: =IF($N42,"NA",IF(ISNUMBER($F42),ROUND(($F42*M$5),0),"")) | N42: FALSE
A43: Suppresion du cable electrique par defaut | B43: HPE Remove Standard Power Cords | C43: 469774-409 | D43: 1 | G43: =IF($N43,"NA",IF(ISNUMBER($F43),ROUND(($F43*G$5),0),"")) | H43: =IF($N43,"NA",IF(ISNUMBER($F43),ROUND(($F43*H$5),0),"")) | I43: =IF($N43,"NA",IF(ISNUMBER($F43),ROUND(($F43*I$5),0),"")) | J43: =IF($N43,"NA",IF(ISNUMBER($F43),ROUND(($F43*J$5),0),"")) | K43: =IF($N43,"NA",IF(ISNUMBER($F43),ROUND(($F43*K$5),0),"")) | L43: =IF($N43,"NA",IF(ISNUMBER($F43),ROUND(($F43*L$5),0),"")) | M43: =IF($N43,"NA",IF(ISNUMBER($F43),ROUND(($F43*M$5),0),"")) | N43: FALSE
A44: Livraison devant la porte | B44: Livraison devant la porte | C44: AC114A | D44: 1 | G44: =IF($N44,"NA",IF(ISNUMBER($F44),ROUND(($F44*G$5),0),"")) | H44: =IF($N44,"NA",IF(ISNUMBER($F44),ROUND(($F44*H$5),0),"")) | I44: =IF($N44,"NA",IF(ISNUMBER($F44),ROUND(($F44*I$5),0),"")) | J44: =IF($N44,"NA",IF(ISNUMBER($F44),ROUND(($F44*J$5),0),"")) | K44: =IF($N44,"NA",IF(ISNUMBER($F44),ROUND(($F44*K$5),0),"")) | L44: =IF($N44,"NA",IF(ISNUMBER($F44),ROUND(($F44*L$5),0),"")) | M44: =IF($N44,"NA",IF(ISNUMBER($F44),ROUND(($F44*M$5),0),"")) | N44: FALSE
A45: Garantie 5 ans J+1 | B45: HPE 5Y Tech Care Basic Service | C45: HU4B2A5 | D45: 1 | G45: =IF($N45,"NA",IF(ISNUMBER($F45),ROUND(($F45*G$5),0),"")) | H45: =IF($N45,"NA",IF(ISNUMBER($F45),ROUND(($F45*H$5),0),"")) | I45: =IF($N45,"NA",IF(ISNUMBER($F45),ROUND(($F45*I$5),0),"")) | J45: =IF($N45,"NA",IF(ISNUMBER($F45),ROUND(($F45*J$5),0),"")) | K45: =IF($N45,"NA",IF(ISNUMBER($F45),ROUND(($F45*K$5),0),"")) | L45: =IF($N45,"NA",IF(ISNUMBER($F45),ROUND(($F45*L$5),0),"")) | M45: =IF($N45,"NA",IF(ISNUMBER($F45),ROUND(($F45*M$5),0),"")) | N45: FALSE
... A47: Garantie 5 ans J+1 châssis | B47: HPE DL325 GEN10 PLUS Supp | C47: HU4B2A5#YL0 | D47: 1 | G47: =IF($N47,"NA",IF(ISNUMBER($F47),ROUND(($F47*G$5),0),"")) | H47: =IF($N47,"NA",IF(ISNUMBER($F47),ROUND(($F47*H$5),0),"")) | I47: =IF($N47,"NA",IF(ISNUMBER($F47),ROUND(($F47*I$5),0),"")) | J47: =IF($N47,"NA",IF(ISNUMBER($F47),ROUND(($F47*J$5),0),"")) | K47: =IF($N47,"NA",IF(ISNUMBER($F47),ROUND(($F47*K$5),0),"")) | L47: =IF($N47,"NA",IF(ISNUMBER($F47),ROUND(($F47*L$5),0),"")) | M47: =IF($N47,"NA",IF(ISNUMBER($F47),ROUND(($F47*M$5),0),"")) | N47: FALSE
G48: =IF($N48,"NA",IF(ISNUMBER($F48),ROUND(($F48*G$5),0),"")) | H48: =IF($N48,"NA",IF(ISNUMBER($F48),ROUND(($F48*H$5),0),"")) | I48: =IF($N48,"NA",IF(ISNUMBER($F48),ROUND(($F48*I$5),0),"")) | J48: =IF($N48,"NA",IF(ISNUMBER($F48),ROUND(($F48*J$5),0),"")) | K48: =IF($N48,"NA",IF(ISNUMBER($F48),ROUND(($F48*K$5),0),"")) | L48: =IF($N48,"NA",IF(ISNUMBER($F48),ROUND(($F48*L$5),0),"")) | M48: =IF($N48,"NA",IF(ISNUMBER($F48),ROUND(($F48*M$5),0),"")) | N48: FALSE
A49: Cat1 Conf3 Edge EL300 | B49: HPE EL300 v2 | C49: P25828-B21 | F49: 1666.29 | G49: =IF($N49,"NA",IF(ISNUMBER($F49),ROUND(($F49*G$5),0),"")) -> 573 | H49: =IF($N49,"NA",IF(ISNUMBER($F49),ROUND(($F49*H$5),0),"")) -> 573 | I49: =IF($N49,"NA",IF(ISNUMBER($F49),ROUND(($F49*I$5),0),"")) -> 753 | J49: =IF($N49,"NA",IF(ISNUMBER($F49),ROUND(($F49*J$5),0),"")) -> 523 | K49: =IF($N49,"NA",IF(ISNUMBER($F49),ROUND(($F49*K$5),0),"")) -> 831 | L49: =IF($N49,"NA",IF(ISNUMBER($F49),ROUND(($F49*L$5),0),"")) -> 717 | M49: =IF($N49,"NA",IF(ISNUMBER($F49),ROUND(($F49*M$5),0),"")) -> 805 | N49: FALSE
A50: Serveur de type Edge | B50: HPE EL300 v2 Converged Edge System | C50: P25828-B21 | D50: 1 | G50: =IF($N50,"NA",IF(ISNUMBER($F50),ROUND(($F50*G$5),0),"")) | H50: =IF($N50,"NA",IF(ISNUMBER($F50),ROUND(($F50*H$5),0),"")) | I50: =IF($N50,"NA",IF(ISNUMBER($F50),ROUND(($F50*I$5),0),"")) | J50: =IF($N50,"NA",IF(ISNUMBER($F50),ROUND(($F50*J$5),0),"")) | K50: =IF($N50,"NA",IF(ISNUMBER($F50),ROUND(($F50*K$5),0),"")) | L50: =IF($N50,"NA",IF(ISNUMBER($F50),ROUND(($F50*L$5),0),"")) | M50: =IF($N50,"NA",IF(ISNUMBER($F50),ROUND(($F50*M$5),0),"")) | N50: FALSE
A51: Processeur 64 bits Intel Core i5-7300U (2.6GHz/2-core/15W) | B51: Intel Core i5-7300U FIO Basic Kit EL300 | C51: P25834-B21 | D51: 1 | G51: =IF($N51,"NA",IF(ISNUMBER($F51),ROUND(($F51*G$5),0),"")) | H51: =IF($N51,"NA",IF(ISNUMBER($F51),ROUND(($F51*H$5),0),"")) | I51: =IF($N51,"NA",IF(ISNUMBER($F51),ROUND(($F51*I$5),0),"")) | J51: =IF($N51,"NA",IF(ISNUMBER($F51),ROUND(($F51*J$5),0),"")) | K51: =IF($N51,"NA",IF(ISNUMBER($F51),ROUND(($F51*K$5),0),"")) | L51: =IF($N51,"NA",IF(ISNUMBER($F51),ROUND(($F51*L$5),0),"")) | M51: =IF($N51,"NA",IF(ISNUMBER($F51),ROUND(($F51*M$5),0),"")) | N51: FALSE
A52: 1 barrette mémoire HPE DDR4 2666 MHz RDIMM de 8 Go (soit 4 Go ECC par cœur) | B52: HPE EL 8GB 2Rx8 DDR4-2400V-R FIO Kit | C52: P09176-B21 | D52: 1 | G52: =IF($N52,"NA",IF(ISNUMBER($F52),ROUND(($F52*G$5),0),"")) | H52: =IF($N52,"NA",IF(ISNUMBER($F52),ROUND(($F52*H$5),0),"")) | I52: =IF($N52,"NA",IF(ISNUMBER($F52),ROUND(($F52*I$5),0),"")) | J52: =IF($N52,"NA",IF(ISNUMBER($F52),ROUND(($F52*J$5),0),"")) | K52: =IF($N52,"NA",IF(ISNUMBER($F52),ROUND(($F52*K$5),0),"")) | L52: =IF($N52,"NA",IF(ISNUMBER($F52),ROUND(($F52*L$5),0),"")) | M52: =IF($N52,"NA",IF(ISNUMBER($F52),ROUND(($F52*M$5),0),"")) | N52: FALSE
A53: 1 disque SSD de 120 Go 6G SATA M.2 2,5 pouces (SFF) | B53: HPE EL 120GB SATA RI M.2 2242 PLP MV SSD | C53: P44366-B21 | D53: 1 | G53: =IF($N53,"NA",IF(ISNUMBER($F53),ROUND(($F53*G$5),0),"")) | H53: =IF($N53,"NA",IF(ISNUMBER($F53),ROUND(($F53*H$5),0),"")) | I53: =IF($N53,"NA",IF(ISNUMBER($F53),ROUND(($F53*I$5),0),"")) | J53: =IF($N53,"NA",IF(ISNUMBER($F53),ROUND(($F53*J$5),0),"")) | K53: =IF($N53,"NA",IF(ISNUMBER($F53),ROUND(($F53*K$5),0),"")) | L53: =IF($N53,"NA",IF(ISNUMBER($F53),ROUND(($F53*L$5),0),"")) | M53: =IF($N53,"NA",IF(ISNUMBER($F53),ROUND(($F53*M$5),0),"")) | N53: FALSE
A54: Kit pour cage disque M.2 | B54: HPE EL300 SFF to M.2 Enable Kit | C54: P04054-B21 | D54: 1 | G54: =IF($N54,"NA",IF(ISNUMBER($F54),ROUND(($F54*G$5),0),"")) | H54: =IF($N54,"NA",IF(ISNUMBER($F54),ROUND(($F54*H$5),0),"")) | I54: =IF($N54,"NA",IF(ISNUMBER($F54),ROUND(($F54*I$5),0),"")) | J54: =IF($N54,"NA",IF(ISNUMBER($F54),ROUND(($F54*J$5),0),"")) | K54: =IF($N54,"NA",IF(ISNUMBER($F54),ROUND(($F54*K$5),0),"")) | L54: =IF($N54,"NA",IF(ISNUMBER($F54),ROUND(($F54*L$5),0),"")) | M54: =IF($N54,"NA",IF(ISNUMBER($F54),ROUND(($F54*M$5),0),"")) | N54: FALSE
A55: Kit carte mère pour alimentation continue | B55: HPE EL300 12VDC FIO Transfer Board | C55: P08120-B21 | D55: 1 | G55: =IF($N55,"NA",IF(ISNUMBER($F55),ROUND(($F55*G$5),0),"")) | H55: =IF($N55,"NA",IF(ISNUMBER($F55),ROUND(($F55*H$5),0),"")) | I55: =IF($N55,"NA",IF(ISNUMBER($F55),ROUND(($F55*I$5),0),"")) | J55: =IF($N55,"NA",IF(ISNUMBER($F55),ROUND(($F55*J$5),0),"")) | K55: =IF($N55,"NA",IF(ISNUMBER($F55),ROUND(($F55*K$5),0),"")) | L55: =IF($N55,"NA",IF(ISNUMBER($F55),ROUND(($F55*L$5),0),"")) | M55: =IF($N55,"NA",IF(ISNUMBER($F55),ROUND(($F55*M$5),0),"")) | N55: FALSE
A56: alimentation de 80W | B56: HPE EL300 80W 12VDC Power Supply | C56: P08641-B21 | D56: 1 | G56: =IF($N56,"NA",IF(ISNUMBER($F56),ROUND(($F56*G$5),0),"")) | H56: =IF($N56,"NA",IF(ISNUMBER($F56),ROUND(($F56*H$5),0),"")) | I56: =IF($N56,"NA",IF(ISNUMBER($F56),ROUND(($F56*I$5),0),"")) | J56: =IF($N56,"NA",IF(ISNUMBER($F56),ROUND(($F56*J$5),0),"")) | K56: =IF($N56,"NA",IF(ISNUMBER($F56),ROUND(($F56*K$5),0),"")) | L56: =IF($N56,"NA",IF(ISNUMBER($F56),ROUND(($F56*L$5),0),"")) | M56: =IF($N56,"NA",IF(ISNUMBER($F56),ROUND(($F56*M$5),0),"")) | N56: FALSE
A57: Kit carte mère pour compatibilité processeur Intel i5 | B57: HPE EL300 v2 FIO Carrier Board | C57: P25835-B21 | D57: 1 | G57: =IF($N57,"NA",IF(ISNUMBER($F57),ROUND(($F57*G$5),0),"")) | H57: =IF($N57,"NA",IF(ISNUMBER($F57),ROUND(($F57*H$5),0),"")) | I57: =IF($N57,"NA",IF(ISNUMBER($F57),ROUND(($F57*I$5),0),"")) | J57: =IF($N57,"NA",IF(ISNUMBER($F57),ROUND(($F57*J$5),0),"")) | K57: =IF($N57,"NA",IF(ISNUMBER($F57),ROUND(($F57*K$5),0),"")) | L57: =IF($N57,"NA",IF(ISNUMBER($F57),ROUND(($F57*L$5),0),"")) | M57: =IF($N57,"NA",IF(ISNUMBER($F57),ROUND(($F57*M$5),0),"")) | N57: FALSE
A58: Carte d'administration iSM spécifique aux matériels Edge. Licence en version Advanced | B58: HPE EL300 iSM Adv 3yr 24x7 Sup/Upd E-LTU | C58: R1P49AAE | D58: 1 | G58: =IF($N58,"NA",IF(ISNUMBER($F58),ROUND(($F58*G$5),0),"")) -> NA | H58: =IF($N58,"NA",IF(ISNUMBER($F58),ROUND(($F58*H$5),0),"")) -> NA | I58: =IF($N58,"NA",IF(ISNUMBER($F58),ROUND(($F58*I$5),0),"")) -> NA | J58: =IF($N58,"NA",IF(ISNUMBER($F58),ROUND(($F58*J$5),0),"")) -> NA | K58: =IF($N58,"NA",IF(ISNUMBER($F58),ROUND(($F58*K$5),0),"")) -> NA | L58: =IF($N58,"NA",IF(ISNUMBER($F58),ROUND(($F58*L$5),0),"")) -> NA | M58: =IF($N58,"NA",IF(ISNUMBER($F58),ROUND(($F58*M$5),0),"")) -> NA | N58: TRUE
A59: Cable Electrique | B59: HPE C13 - CEE-VII EU 250V 10Amp 1.83m Power Cord | C59: AF568A | D59: 1 | G59: =IF($N59,"NA",IF(ISNUMBER($F59),ROUND(($F59*G$5),0),"")) | H59: =IF($N59,"NA",IF(ISNUMBER($F59),ROUND(($F59*H$5),0),"")) | I59: =IF($N59,"NA",IF(ISNUMBER($F59),ROUND(($F59*I$5),0),"")) | J59: =IF($N59,"NA",IF(ISNUMBER($F59),ROUND(($F59*J$5),0),"")) | K59: =IF($N59,"NA",IF(ISNUMBER($F59),ROUND(($F59*K$5),0),"")) | L59: =IF($N59,"NA",IF(ISNUMBER($F59),ROUND(($F59*L$5),0),"")) | M59: =IF($N59,"NA",IF(ISNUMBER($F59),ROUND(($F59*M$5),0),"")) | N59: FALSE
A60: Livraison devant la porte | B60: Livraison devant la porte | C60: AC111A | D60: 1 | G60: =IF($N60,"NA",IF(ISNUMBER($F60),ROUND(($F60*G$5),0),"")) | H60: =IF($N60,"NA",IF(ISNUMBER($F60),ROUND(($F60*H$5),0),"")) | I60: =IF($N60,"NA",IF(ISNUMBER($F60),ROUND(($F60*I$5),0),"")) | J60: =IF($N60,"NA",IF(ISNUMBER($F60),ROUND(($F60*J$5),0),"")) | K60: =IF($N60,"NA",IF(ISNUMBER($F60),ROUND(($F60*K$5),0),"")) | L60: =IF($N60,"NA",IF(ISNUMBER($F60),ROUND(($F60*L$5),0),"")) | M60: =IF($N60,"NA",IF(ISNUMBER($F60),ROUND(($F60*M$5),0),"")) | N60: FALSE
A61: Garantie 5 ans J+1 | B61: HPE 5Y Tech Care Basic Service | C61: HU4B2A5 | D61: 1 | G61: =IF($N61,"NA",IF(ISNUMBER($F61),ROUND(($F61*G$5),0),"")) | H61: =IF($N61,"NA",IF(ISNUMBER($F61),ROUND(($F61*H$5),0),"")) | I61: =IF($N61,"NA",IF(ISNUMBER($F61),ROUND(($F61*I$5),0),"")) | J61: =IF($N61,"NA",IF(ISNUMBER($F61),ROUND(($F61*J$5),0),"")) | K61: =IF($N61,"NA",IF(ISNUMBER($F61),ROUND(($F61*K$5),0),"")) | L61: =IF($N61,"NA",IF(ISNUMBER($F61),ROUND(($F61*L$5),0),"")) | M61: =IF($N61,"NA",IF(ISNUMBER($F61),ROUND(($F61*M$5),0),"")) | N61: FALSE
... A63: Garantie 5 ans J+1 | B63: HPE Edgeline ISM Advanced Support | C63: HU4B2A5#XP9 | D63: 1 | G63: =IF($N63,"NA",IF(ISNUMBER($F63),ROUND(($F63*G$5),0),"")) | H63: =IF($N63,"NA",IF(ISNUMBER($F63),ROUND(($F63*H$5),0),"")) | I63: =IF($N63,"NA",IF(ISNUMBER($F63),ROUND(($F63*I$5),0),"")) | J63: =IF($N63,"NA",IF(ISNUMBER($F63),ROUND(($F63*J$5),0),"")) | K63: =IF($N63,"NA",IF(ISNUMBER($F63),ROUND(($F63*K$5),0),"")) | L63: =IF($N63,"NA",IF(ISNUMBER($F63),ROUND(($F63*L$5),0),"")) | M63: =IF($N63,"NA",IF(ISNUMBER($F63),ROUND(($F63*M$5),0),"")) | N63: FALSE
G64: =IF($N64,"NA",IF(ISNUMBER($F64),ROUND(($F64*G$5),0),"")) | H64: =IF($N64,"NA",IF(ISNUMBER($F64),ROUND(($F64*H$5),0),"")) | I64: =IF($N64,"NA",IF(ISNUMBER($F64),ROUND(($F64*I$5),0),"")) | J64: =IF($N64,"NA",IF(ISNUMBER($F64),ROUND(($F64*J$5),0),"")) | K64: =IF($N64,"NA",IF(ISNUMBER($F64),ROUND(($F64*K$5),0),"")) | L64: =IF($N64,"NA",IF(ISNUMBER($F64),ROUND(($F64*L$5),0),"")) | M64: =IF($N64,"NA",IF(ISNUMBER($F64),ROUND(($F64*M$5),0),"")) | N64: FALSE
A65: Cat1 Conf6 Tour ML30 Gen10 plus | B65: HPE ProLiant ML30 Gen10+ | C65: P44723-B21 | F65: 721.84 | G65: =IF($N65,"NA",IF(ISNUMBER($F65),ROUND(($F65*G$5),0),"")) -> 248 | H65: =IF($N65,"NA",IF(ISNUMBER($F65),ROUND(($F65*H$5),0),"")) -> 248 | I65: =IF($N65,"NA",IF(ISNUMBER($F65),ROUND(($F65*I$5),0),"")) -> 326 | J65: =IF($N65,"NA",IF(ISNUMBER($F65),ROUND(($F65*J$5),0),"")) -> 227 | K65: =IF($N65,"NA",IF(ISNUMBER($F65),ROUND(($F65*K$5),0),"")) -> 360 | L65: =IF($N65,"NA",IF(ISNUMBER($F65),ROUND(($F65*L$5),0),"")) -> 310 | M65: =IF($N65,"NA",IF(ISNUMBER($F65),ROUND(($F65*M$5),0),"")) -> 349 | N65: FALSE
A66: Serveur de type tour | B66: HPE ProLiant ML30 Gen10 Plus 4LFF Non-hot Plug Configure-to-order Server | C66: P44723-B21 | D66: 1 | G66: =IF($N66,"NA",IF(ISNUMBER($F66),ROUND(($F66*G$5),0),"")) | H66: =IF($N66,"NA",IF(ISNUMBER($F66),ROUND(($F66*H$5),0),"")) | I66: =IF($N66,"NA",IF(ISNUMBER($F66),ROUND(($F66*I$5),0),"")) | J66: =IF($N66,"NA",IF(ISNUMBER($F66),ROUND(($F66*J$5),0),"")) | K66: =IF($N66,"NA",IF(ISNUMBER($F66),ROUND(($F66*K$5),0),"")) | L66: =IF($N66,"NA",IF(ISNUMBER($F66),ROUND(($F66*L$5),0),"")) | M66: =IF($N66,"NA",IF(ISNUMBER($F66),ROUND(($F66*M$5),0),"")) | N66: FALSE
A67: Processeur 64 bits Intel Xeon E-2314 (2,8 GHz de base / 4,50 Ghz Turbo / 4 cœurs / 4 threads / 8 Mo Smart Cache / 65 W PDT | B67: Intel Xeon E-2314 2.8GHz 4-core 65W FIO Processor for HPE | C67: P45248-B21 | D67: 1 | G67: =IF($N67,"NA",IF(ISNUMBER($F67),ROUND(($F67*G$5),0),"")) | H67: =IF($N67,"NA",IF(ISNUMBER($F67),ROUND(($F67*H$5),0),"")) | I67: =IF($N67,"NA",IF(ISNUMBER($F67),ROUND(($F67*I$5),0),"")) | J67: =IF($N67,"NA",IF(ISNUMBER($F67),ROUND(($F67*J$5),0),"")) | K67: =IF($N67,"NA",IF(ISNUMBER($F67),ROUND(($F67*K$5),0),"")) | L67: =IF($N67,"NA",IF(ISNUMBER($F67),ROUND(($F67*L$5),0),"")) | M67: =IF($N67,"NA",IF(ISNUMBER($F67),ROUND(($F67*M$5),0),"")) | N67: FALSE
A68: 1 barrette mémoire HPE Standard DDR4 2666 MHz UDIMM de 16 Go (soit 4 Go ECC par cœur) | B68: HPE 16GB (1x16GB) Single Rank x8 DDR4-3200 CAS-22-22-22 Unbuffered Standard Memory Kit | C68: P43019-B21 | D68: 1 | G68: =IF($N68,"NA",IF(ISNUMBER($F68),ROUND(($F68*G$5),0),"")) | H68: =IF($N68,"NA",IF(ISNUMBER($F68),ROUND(($F68*H$5),0),"")) | I68: =IF($N68,"NA",IF(ISNUMBER($F68),ROUND(($F68*I$5),0),"")) | J68: =IF($N68,"NA",IF(ISNUMBER($F68),ROUND(($F68*J$5),0),"")) | K68: =IF($N68,"NA",IF(ISNUMBER($F68),ROUND(($F68*K$5),0),"")) | L68: =IF($N68,"NA",IF(ISNUMBER($F68),ROUND(($F68*L$5),0),"")) | M68: =IF($N68,"NA",IF(ISNUMBER($F68),ROUND(($F68*M$5),0),"")) | N68: FALSE
A69: Alimentation 500W certifiée 80Plus Platinium | B69: HPE 500W FS Plat Ht Plg LH Pwr Sply Kit | C69: 865408-B21 | D69: 1 | G69: =IF($N69,"NA",IF(ISNUMBER($F69),ROUND(($F69*G$5),0),"")) | H69: =IF($N69,"NA",IF(ISNUMBER($F69),ROUND(($F69*H$5),0),"")) | I69: =IF($N69,"NA",IF(ISNUMBER($F69),ROUND(($F69*I$5),0),"")) | J69: =IF($N69,"NA",IF(ISNUMBER($F69),ROUND(($F69*J$5),0),"")) | K69: =IF($N69,"NA",IF(ISNUMBER($F69),ROUND(($F69*K$5),0),"")) | L69: =IF($N69,"NA",IF(ISNUMBER($F69),ROUND(($F69*L$5),0),"")) | M69: =IF($N69,"NA",IF(ISNUMBER($F69),ROUND(($F69*M$5),0),"")) | N69: FALSE
A70: Carte d'administration HPE iLO avec API RESTful compatible IPMI v2.0 et Redfish. Licence en version Advanced avec toutes les options activées | B70: HPE iLO Adv 1-svr Lic 1yr Support | C70: 512485-B21 | D70: 1 | G70: =IF($N70,"NA",IF(ISNUMBER($F70),ROUND(($F70*G$5),0),"")) | H70: =IF($N70,"NA",IF(ISNUMBER($F70),ROUND(($F70*H$5),0),"")) | I70: =IF($N70,"NA",IF(ISNUMBER($F70),ROUND(($F70*I$5),0),"")) | J70: =IF($N70,"NA",IF(ISNUMBER($F70),ROUND(($F70*J$5),0),"")) | K70: =IF($N70,"NA",IF(ISNUMBER($F70),ROUND(($F70*K$5),0),"")) | L70: =IF($N70,"NA",IF(ISNUMBER($F70),ROUND(($F70*L$5),0),"")) | M70: =IF($N70,"NA",IF(ISNUMBER($F70),ROUND(($F70*M$5),0),"")) | N70: FALSE
A71: Kit d'alimentation redondante | B71: HPE ML30 Gen10+ 4U RPS Enablement Kit | C71: P45209-B21 | D71: 1 | G71: =IF($N71,"NA",IF(ISNUMBER($F71),ROUND(($F71*G$5),0),"")) | H71: =IF($N71,"NA",IF(ISNUMBER($F71),ROUND(($F71*H$5),0),"")) | I71: =IF($N71,"NA",IF(ISNUMBER($F71),ROUND(($F71*I$5),0),"")) | J71: =IF($N71,"NA",IF(ISNUMBER($F71),ROUND(($F71*J$5),0),"")) | K71: =IF($N71,"NA",IF(ISNUMBER($F71),ROUND(($F71*K$5),0),"")) | L71: =IF($N71,"NA",IF(ISNUMBER($F71),ROUND(($F71*L$5),0),"")) | M71: =IF($N71,"NA",IF(ISNUMBER($F71),ROUND(($F71*M$5),0),"")) | N71: FALSE
A72: Kit Ventilateur | B72: HPE ML30 Gen10 Front PCI Fan and Baffle Kit | C72: P06303-B21 | D72: 1 | G72: =IF($N72,"NA",IF(ISNUMBER($F72),ROUND(($F72*G$5),0),"")) | H72: =IF($N72,"NA",IF(ISNUMBER($F72),ROUND(($F72*H$5),0),"")) | I72: =IF($N72,"NA",IF(ISNUMBER($F72),ROUND(($F72*I$5),0),"")) | J72: =IF($N72,"NA",IF(ISNUMBER($F72),ROUND(($F72*J$5),0),"")) | K72: =IF($N72,"NA",IF(ISNUMBER($F72),ROUND(($F72*K$5),0),"")) | L72: =IF($N72,"NA",IF(ISNUMBER($F72),ROUND(($F72*L$5),0),"")) | M72: =IF($N72,"NA",IF(ISNUMBER($F72),ROUND(($F72*M$5),0),"")) | N72: FALSE
A73: Suppresion du cable electrique par defaut | B73: HPE Remove Standard Power Cords | C73: 469774-409 | D73: 1 | G73: =IF($N73,"NA",IF(ISNUMBER($F73),ROUND(($F73*G$5),0),"")) | H73: =IF($N73,"NA",IF(ISNUMBER($F73),ROUND(($F73*H$5),0),"")) | I73: =IF($N73,"NA",IF(ISNUMBER($F73),ROUND(($F73*I$5),0),"")) | J73: =IF($N73,"NA",IF(ISNUMBER($F73),ROUND(($F73*J$5),0),"")) | K73: =IF($N73,"NA",IF(ISNUMBER($F73),ROUND(($F73*K$5),0),"")) | L73: =IF($N73,"NA",IF(ISNUMBER($F73),ROUND(($F73*L$5),0),"")) | M73: =IF($N73,"NA",IF(ISNUMBER($F73),ROUND(($F73*M$5),0),"")) | N73: FALSE
A74: Livraison devant la porte | B74: Livraison devant la porte | C74: AC111A | D74: 1 | G74: =IF($N74,"NA",IF(ISNUMBER($F74),ROUND(($F74*G$5),0),"")) | H74: =IF($N74,"NA",IF(ISNUMBER($F74),ROUND(($F74*H$5),0),"")) | I74: =IF($N74,"NA",IF(ISNUMBER($F74),ROUND(($F74*I$5),0),"")) | J74: =IF($N74,"NA",IF(ISNUMBER($F74),ROUND(($F74*J$5),0),"")) | K74: =IF($N74,"NA",IF(ISNUMBER($F74),ROUND(($F74*K$5),0),"")) | L74: =IF($N74,"NA",IF(ISNUMBER($F74),ROUND(($F74*L$5),0),"")) | M74: =IF($N74,"NA",IF(ISNUMBER($F74),ROUND(($F74*M$5),0),"")) | N74: FALSE
A75: Garantie 5 ans J+1 | B75: HPE 5Y Tech Care Basic Service | C75: HU4B2A5 | D75: 1 | G75: =IF($N75,"NA",IF(ISNUMBER($F75),ROUND(($F75*G$5),0),"")) | H75: =IF($N75,"NA",IF(ISNUMBER($F75),ROUND(($F75*H$5),0),"")) | I75: =IF($N75,"NA",IF(ISNUMBER($F75),ROUND(($F75*I$5),0),"")) | J75: =IF($N75,"NA",IF(ISNUMBER($F75),ROUND(($F75*J$5),0),"")) | K75: =IF($N75,"NA",IF(ISNUMBER($F75),ROUND(($F75*K$5),0),"")) | L75: =IF($N75,"NA",IF(ISNUMBER($F75),ROUND(($F75*L$5),0),"")) | M75: =IF($N75,"NA",IF(ISNUMBER($F75),ROUND(($F75*M$5),0),"")) | N75: FALSE
A76: Garantie 5 ans J+1 ILO | B76: HPE iLO AdvPack NonBL Support | C76: HU4B2A5#7X4 | D76: 1 | G76: =IF($N76,"NA",IF(ISNUMBER($F76),ROUND(($F76*G$5),0),"")) | H76: =IF($N76,"NA",IF(ISNUMBER($F76),ROUND(($F76*H$5),0),"")) | I76: =IF($N76,"NA",IF(ISNUMBER($F76),ROUND(($F76*I$5),0),"")) | J76: =IF($N76,"NA",IF(ISNUMBER($F76),ROUND(($F76*J$5),0),"")) | K76: =IF($N76,"NA",IF(ISNUMBER($F76),ROUND(($F76*K$5),0),"")) | L76: =IF($N76,"NA",IF(ISNUMBER($F76),ROUND(($F76*L$5),0),"")) | M76: =IF($N76,"NA",IF(ISNUMBER($F76),ROUND(($F76*M$5),0),"")) | N76: FALSE
A77: Garantie 5 ans J+1 châssis | B77: HPE ProLiant ML30 Gen10+ Support | C77: HU4B2A5#ZNB | D77: 1 | G77: =IF($N77,"NA",IF(ISNUMBER($F77),ROUND(($F77*G$5),0),"")) | H77: =IF($N77,"NA",IF(ISNUMBER($F77),ROUND(($F77*H$5),0),"")) | I77: =IF($N77,"NA",IF(ISNUMBER($F77),ROUND(($F77*I$5),0),"")) | J77: =IF($N77,"NA",IF(ISNUMBER($F77),ROUND(($F77*J$5),0),"")) | K77: =IF($N77,"NA",IF(ISNUMBER($F77),ROUND(($F77*K$5),0),"")) | L77: =IF($N77,"NA",IF(ISNUMBER($F77),ROUND(($F77*L$5),0),"")) | M77: =IF($N77,"NA",IF(ISNUMBER($F77),ROUND(($F77*M$5),0),"")) | N77: FALSE
G78: =IF($N78,"NA",IF(ISNUMBER($F78),ROUND(($F78*G$5),0),"")) | H78: =IF($N78,"NA",IF(ISNUMBER($F78),ROUND(($F78*H$5),0),"")) | I78: =IF($N78,"NA",IF(ISNUMBER($F78),ROUND(($F78*I$5),0),"")) | J78: =IF($N78,"NA",IF(ISNUMBER($F78),ROUND(($F78*J$5),0),"")) | K78: =IF($N78,"NA",IF(ISNUMBER($F78),ROUND(($F78*K$5),0),"")) | L78: =IF($N78,"NA",IF(ISNUMBER($F78),ROUND(($F78*L$5),0),"")) | M78: =IF($N78,"NA",IF(ISNUMBER($F78),ROUND(($F78*M$5),0),"")) | N78: FALSE
A79: CATEGORIE 1 : extensions et périphériques associés, extensions de garantie, installation, etc. | G79: =IF($N79,"NA",IF(ISNUMBER($F79),ROUND(($F79*G$5),0),"")) | H79: =IF($N79,"NA",IF(ISNUMBER($F79),ROUND(($F79*H$5),0),"")) | I79: =IF($N79,"NA",IF(ISNUMBER($F79),ROUND(($F79*I$5),0),"")) | J79: =IF($N79,"NA",IF(ISNUMBER($F79),ROUND(($F79*J$5),0),"")) | K79: =IF($N79,"NA",IF(ISNUMBER($F79),ROUND(($F79*K$5),0),"")) | L79: =IF($N79,"NA",IF(ISNUMBER($F79),ROUND(($F79*L$5),0),"")) | M79: =IF($N79,"NA",IF(ISNUMBER($F79),ROUND(($F79*M$5),0),"")) | N79: FALSE
A80: Désignation/Description des matériels | B80: Référence constructeur (le cas échéant) | C80: Numéro de référence | D80: Quantités | F80: TARIFS en €HT | G80: =IF($N80,"NA",IF(ISNUMBER($F80),ROUND(($F80*G$5),0),"")) | H80: =IF($N80,"NA",IF(ISNUMBER($F80),ROUND(($F80*H$5),0),"")) | I80: =IF($N80,"NA",IF(ISNUMBER($F80),ROUND(($F80*I$5),0),"")) | J80: =IF($N80,"NA",IF(ISNUMBER($F80),ROUND(($F80*J$5),0),"")) | K80: =IF($N80,"NA",IF(ISNUMBER($F80),ROUND(($F80*K$5),0),"")) | L80: =IF($N80,"NA",IF(ISNUMBER($F80),ROUND(($F80*L$5),0),"")) | M80: =IF($N80,"NA",IF(ISNUMBER($F80),ROUND(($F80*M$5),0),"")) | N80: FALSE
A81: Ces extensions sont propres a cette categorie. Les extensions communes sont factorisés dans le chapitre Categorie 1 a 4 : extensions | G81: =IF($N81,"NA",IF(ISNUMBER($F81),ROUND(($F81*G$5),0),"")) | H81: =IF($N81,"NA",IF(ISNUMBER($F81),ROUND(($F81*H$5),0),"")) | I81: =IF($N81,"NA",IF(ISNUMBER($F81),ROUND(($F81*I$5),0),"")) | J81: =IF($N81,"NA",IF(ISNUMBER($F81),ROUND(($F81*J$5),0),"")) | K81: =IF($N81,"NA",IF(ISNUMBER($F81),ROUND(($F81*K$5),0),"")) | L81: =IF($N81,"NA",IF(ISNUMBER($F81),ROUND(($F81*L$5),0),"")) | M81: =IF($N81,"NA",IF(ISNUMBER($F81),ROUND(($F81*M$5),0),"")) | N81: FALSE
A82: Ajout d'une barrette mémoire DDR4-2666 UDIMM 8 Go | B82: HPE 8GB 1Rx8 PC4-2666V-E STND Kit | C82: 879505-B21 | F82: 46.2 | G82: =IF($N82,"NA",IF(ISNUMBER($F82),ROUND(($F82*G$5),0),"")) -> 16 | H82: =IF($N82,"NA",IF(ISNUMBER($F82),ROUND(($F82*H$5),0),"")) -> 16 | I82: =IF($N82,"NA",IF(ISNUMBER($F82),ROUND(($F82*I$5),0),"")) -> 21 | J82: =IF($N82,"NA",IF(ISNUMBER($F82),ROUND(($F82*J$5),0),"")) -> 15 | K82: =IF($N82,"NA",IF(ISNUMBER($F82),ROUND(($F82*K$5),0),"")) -> 23 | L82: =IF($N82,"NA",IF(ISNUMBER($F82),ROUND(($F82*L$5),0),"")) -> 20 | M82: =IF($N82,"NA",IF(ISNUMBER($F82),ROUND(($F82*M$5),0),"")) -> 22 | N82: FALSE
B83: HPE 8GB 1Rx8 PC4-3200AA-E STND Kit | C83: P43016-B21 | F83: 46.2 | G83: =IF($N83,"NA",IF(ISNUMBER($F83),ROUND(($F83*G$5),0),"")) -> 16 | H83: =IF($N83,"NA",IF(ISNUMBER($F83),ROUND(($F83*H$5),0),"")) -> 16 | I83: =IF($N83,"NA",IF(ISNUMBER($F83),ROUND(($F83*I$5),0),"")) -> 21 | J83: =IF($N83,"NA",IF(ISNUMBER($F83),ROUND(($F83*J$5),0),"")) -> 15 | K83: =IF($N83,"NA",IF(ISNUMBER($F83),ROUND(($F83*K$5),0),"")) -> 23 | L83: =IF($N83,"NA",IF(ISNUMBER($F83),ROUND(($F83*L$5),0),"")) -> 20 | M83: =IF($N83,"NA",IF(ISNUMBER($F83),ROUND(($F83*M$5),0),"")) -> 22 | N83: FALSE
A84: Ajout d'une barrette mémoire DDR4-2666/3200 UDIMM 16 Go | B84: HPE 16GB 2Rx8 PC4-2666V-E STND Kit | C84: 879507-B21 | F84: 79.8 | G84: =IF($N84,"NA",IF(ISNUMBER($F84),ROUND(($F84*G$5),0),"")) -> 27 | H84: =IF($N84,"NA",IF(ISNUMBER($F84),ROUND(($F84*H$5),0),"")) -> 27 | I84: =IF($N84,"NA",IF(ISNUMBER($F84),ROUND(($F84*I$5),0),"")) -> 36 | J84: =IF($N84,"NA",IF(ISNUMBER($F84),ROUND(($F84*J$5),0),"")) -> 25 | K84: =IF($N84,"NA",IF(ISNUMBER($F84),ROUND(($F84*K$5),0),"")) -> 40 | L84: =IF($N84,"NA",IF(ISNUMBER($F84),ROUND(($F84*L$5),0),"")) -> 34 | M84: =IF($N84,"NA",IF(ISNUMBER($F84),ROUND(($F84*M$5),0),"")) -> 39 | N84: FALSE
B85: HPE 16GB 1Rx8 PC4-3200AA-E STND Kit | C85: P43019-B21 | F85: 79.8 | G85: =IF($N85,"NA",IF(ISNUMBER($F85),ROUND(($F85*G$5),0),"")) -> 27 | H85: =IF($N85,"NA",IF(ISNUMBER($F85),ROUND(($F85*H$5),0),"")) -> 27 | I85: =IF($N85,"NA",IF(ISNUMBER($F85),ROUND(($F85*I$5),0),"")) -> 36 | J85: =IF($N85,"NA",IF(ISNUMBER($F85),ROUND(($F85*J$5),0),"")) -> 25 | K85: =IF($N85,"NA",IF(ISNUMBER($F85),ROUND(($F85*K$5),0),"")) -> 40 | L85: =IF($N85,"NA",IF(ISNUMBER($F85),ROUND(($F85*L$5),0),"")) -> 34 | M85: =IF($N85,"NA",IF(ISNUMBER($F85),ROUND(($F85*M$5),0),"")) -> 39 | N85: FALSE
G86: =IF($N86,"NA",IF(ISNUMBER($F86),ROUND(($F86*G$5),0),"")) | H86: =IF($N86,"NA",IF(ISNUMBER($F86),ROUND(($F86*H$5),0),"")) | I86: =IF($N86,"NA",IF(ISNUMBER($F86),ROUND(($F86*I$5),0),"")) | J86: =IF($N86,"NA",IF(ISNUMBER($F86),ROUND(($F86*J$5),0),"")) | K86: =IF($N86,"NA",IF(ISNUMBER($F86),ROUND(($F86*K$5),0),"")) | L86: =IF($N86,"NA",IF(ISNUMBER($F86),ROUND(($F86*L$5),0),"")) | M86: =IF($N86,"NA",IF(ISNUMBER($F86),ROUND(($F86*M$5),0),"")) | N86: FALSE
A87: Cat1 Configuration n°1: Serveur tour Ultra Micro mono-socket | G87: =IF($N87,"NA",IF(ISNUMBER($F87),ROUND(($F87*G$5),0),"")) | H87: =IF($N87,"NA",IF(ISNUMBER($F87),ROUND(($F87*H$5),0),"")) | I87: =IF($N87,"NA",IF(ISNUMBER($F87),ROUND(($F87*I$5),0),"")) | J87: =IF($N87,"NA",IF(ISNUMBER($F87),ROUND(($F87*J$5),0),"")) | K87: =IF($N87,"NA",IF(ISNUMBER($F87),ROUND(($F87*K$5),0),"")) | L87: =IF($N87,"NA",IF(ISNUMBER($F87),ROUND(($F87*L$5),0),"")) | M87: =IF($N87,"NA",IF(ISNUMBER($F87),ROUND(($F87*M$5),0),"")) | N87: FALSE
A88: Disque durs rotatifs additionnels | G88: =IF($N88,"NA",IF(ISNUMBER($F88),ROUND(($F88*G$5),0),"")) | H88: =IF($N88,"NA",IF(ISNUMBER($F88),ROUND(($F88*H$5),0),"")) | I88: =IF($N88,"NA",IF(ISNUMBER($F88),ROUND(($F88*I$5),0),"")) | J88: =IF($N88,"NA",IF(ISNUMBER($F88),ROUND(($F88*J$5),0),"")) | K88: =IF($N88,"NA",IF(ISNUMBER($F88),ROUND(($F88*K$5),0),"")) | L88: =IF($N88,"NA",IF(ISNUMBER($F88),ROUND(($F88*L$5),0),"")) | M88: =IF($N88,"NA",IF(ISNUMBER($F88),ROUND(($F88*M$5),0),"")) | N88: FALSE
A89: Ajout d'un disque dur SATA 7.2K LFF de 1 To Non HotPlug | B89: HPE 1TB SATA 7.2K LFF RW MV HDD | C89: 801882-B21 | F89: 94.5 | G89: =IF($N89,"NA",IF(ISNUMBER($F89),ROUND(($F89*G$5),0),"")) -> 33 | H89: =IF($N89,"NA",IF(ISNUMBER($F89),ROUND(($F89*H$5),0),"")) -> 33 | I89: =IF($N89,"NA",IF(ISNUMBER($F89),ROUND(($F89*I$5),0),"")) -> 43 | J89: =IF($N89,"NA",IF(ISNUMBER($F89),ROUND(($F89*J$5),0),"")) -> 30 | K89: =IF($N89,"NA",IF(ISNUMBER($F89),ROUND(($F89*K$5),0),"")) -> 47 | L89: =IF($N89,"NA",IF(ISNUMBER($F89),ROUND(($F89*L$5),0),"")) -> 41 | M89: =IF($N89,"NA",IF(ISNUMBER($F89),ROUND(($F89*M$5),0),"")) -> 46 | N89: FALSE
A90: Ajout d'un disque dur SATA 7.2K LFF de 4 To Non HotPlug | B90: HPE 4TB SATA 7.2K LFF RW MV HDD | C90: 801888-B21 | F90: 118.65 | G90: =IF($N90,"NA",IF(ISNUMBER($F90),ROUND(($F90*G$5),0),"")) -> 41 | H90: =IF($N90,"NA",IF(ISNUMBER($F90),ROUND(($F90*H$5),0),"")) -> 41 | I90: =IF($N90,"NA",IF(ISNUMBER($F90),ROUND(($F90*I$5),0),"")) -> 54 | J90: =IF($N90,"NA",IF(ISNUMBER($F90),ROUND(($F90*J$5),0),"")) -> 37 | K90: =IF($N90,"NA",IF(ISNUMBER($F90),ROUND(($F90*K$5),0),"")) -> 59 | L90: =IF($N90,"NA",IF(ISNUMBER($F90),ROUND(($F90*L$5),0),"")) -> 51 | M90: =IF($N90,"NA",IF(ISNUMBER($F90),ROUND(($F90*M$5),0),"")) -> 57 | N90: FALSE
A91: Autres extensions matérielles | G91: =IF($N91,"NA",IF(ISNUMBER($F91),ROUND(($F91*G$5),0),"")) | H91: =IF($N91,"NA",IF(ISNUMBER($F91),ROUND(($F91*H$5),0),"")) | I91: =IF($N91,"NA",IF(ISNUMBER($F91),ROUND(($F91*I$5),0),"")) | J91: =IF($N91,"NA",IF(ISNUMBER($F91),ROUND(($F91*J$5),0),"")) | K91: =IF($N91,"NA",IF(ISNUMBER($F91),ROUND(($F91*K$5),0),"")) | L91: =IF($N91,"NA",IF(ISNUMBER($F91),ROUND(($F91*L$5),0),"")) | M91: =IF($N91,"NA",IF(ISNUMBER($F91),ROUND(($F91*M$5),0),"")) | N91: FALSE
A92: Ajout d'un kit de conversion LFF Non-hot Plug vers SFF Non-hot Plug | B92: HPE MicroServer Gen10 SFF NHP SATA Converter Kit | C92: 870213-B21 | F92: 5.25 | G92: =IF($N92,"NA",IF(ISNUMBER($F92),ROUND(($F92*G$5),0),"")) -> 2 | H92: =IF($N92,"NA",IF(ISNUMBER($F92),ROUND(($F92*H$5),0),"")) -> 2 | I92: =IF($N92,"NA",IF(ISNUMBER($F92),ROUND(($F92*I$5),0),"")) -> 2 | J92: =IF($N92,"NA",IF(ISNUMBER($F92),ROUND(($F92*J$5),0),"")) -> 2 | K92: =IF($N92,"NA",IF(ISNUMBER($F92),ROUND(($F92*K$5),0),"")) -> 3 | L92: =IF($N92,"NA",IF(ISNUMBER($F92),ROUND(($F92*L$5),0),"")) -> 2 | M92: =IF($N92,"NA",IF(ISNUMBER($F92),ROUND(($F92*M$5),0),"")) -> 3 | N92: FALSE
A93: Extensions de garanties | G93: =IF($N93,"NA",IF(ISNUMBER($F93),ROUND(($F93*G$5),0),"")) | H93: =IF($N93,"NA",IF(ISNUMBER($F93),ROUND(($F93*H$5),0),"")) | I93: =IF($N93,"NA",IF(ISNUMBER($F93),ROUND(($F93*I$5),0),"")) | J93: =IF($N93,"NA",IF(ISNUMBER($F93),ROUND(($F93*J$5),0),"")) | K93: =IF($N93,"NA",IF(ISNUMBER($F93),ROUND(($F93*K$5),0),"")) | L93: =IF($N93,"NA",IF(ISNUMBER($F93),ROUND(($F93*L$5),0),"")) | M93: =IF($N93,"NA",IF(ISNUMBER($F93),ROUND(($F93*M$5),0),"")) | N93: FALSE
A94: Microserver | G94: =IF($N94,"NA",IF(ISNUMBER($F94),ROUND(($F94*G$5),0),"")) | H94: =IF($N94,"NA",IF(ISNUMBER($F94),ROUND(($F94*H$5),0),"")) | I94: =IF($N94,"NA",IF(ISNUMBER($F94),ROUND(($F94*I$5),0),"")) | J94: =IF($N94,"NA",IF(ISNUMBER($F94),ROUND(($F94*J$5),0),"")) | K94: =IF($N94,"NA",IF(ISNUMBER($F94),ROUND(($F94*K$5),0),"")) | L94: =IF($N94,"NA",IF(ISNUMBER($F94),ROUND(($F94*L$5),0),"")) | M94: =IF($N94,"NA",IF(ISNUMBER($F94),ROUND(($F94*M$5),0),"")) | N94: FALSE
A95: Passage à support 5 ans intervention j+1 (9x5) avec retention de disque | B95: Tech Care Basic DMR 5Y (J+1 9x5) | C95: Passage vers HU4B3A5#YKX | F95: 19 | G95: =IF($N95,"NA",IF(ISNUMBER($F95),ROUND(($F95*G$5),0),"")) -> 7 | H95: =IF($N95,"NA",IF(ISNUMBER($F95),ROUND(($F95*H$5),0),"")) -> 7 | I95: =IF($N95,"NA",IF(ISNUMBER($F95),ROUND(($F95*I$5),0),"")) -> 9 | J95: =IF($N95,"NA",IF(ISNUMBER($F95),ROUND(($F95*J$5),0),"")) -> 6 | K95: =IF($N95,"NA",IF(ISNUMBER($F95),ROUND(($F95*K$5),0),"")) -> 9 | L95: =IF($N95,"NA",IF(ISNUMBER($F95),ROUND(($F95*L$5),0),"")) -> 8 | M95: =IF($N95,"NA",IF(ISNUMBER($F95),ROUND(($F95*M$5),0),"")) -> 9 | N95: FALSE
A96: Passage à support 5 ans intervention h+4 (24h/24h, 7j/7j) | B96: Tech Care Essential 5Y (4H 24X7) | C96: Passage vers HU4A6A5#YKX | F96: 26 | G96: =IF($N96,"NA",IF(ISNUMBER($F96),ROUND(($F96*G$5),0),"")) -> NA | H96: =IF($N96,"NA",IF(ISNUMBER($F96),ROUND(($F96*H$5),0),"")) -> NA | I96: =IF($N96,"NA",IF(ISNUMBER($F96),ROUND(($F96*I$5),0),"")) -> NA | J96: =IF($N96,"NA",IF(ISNUMBER($F96),ROUND(($F96*J$5),0),"")) -> NA | K96: =IF($N96,"NA",IF(ISNUMBER($F96),ROUND(($F96*K$5),0),"")) -> NA | L96: =IF($N96,"NA",IF(ISNUMBER($F96),ROUND(($F96*L$5),0),"")) -> NA | M96: =IF($N96,"NA",IF(ISNUMBER($F96),ROUND(($F96*M$5),0),"")) -> NA | N96: TRUE
A97: Passage à support 5 ans intervention h+4 (24h/24h, 7j/7j) avec retention de Disque | B97: Tech Care Essential 5Y DMR (4H 24X7) | C97: Passage vers HU4A7A5#YKX | F97: 35 | G97: =IF($N97,"NA",IF(ISNUMBER($F97),ROUND(($F97*G$5),0),"")) -> NA | H97: =IF($N97,"NA",IF(ISNUMBER($F97),ROUND(($F97*H$5),0),"")) -> NA | I97: =IF($N97,"NA",IF(ISNUMBER($F97),ROUND(($F97*I$5),0),"")) -> NA | J97: =IF($N97,"NA",IF(ISNUMBER($F97),ROUND(($F97*J$5),0),"")) -> NA | K97: =IF($N97,"NA",IF(ISNUMBER($F97),ROUND(($F97*K$5),0),"")) -> NA | L97: =IF($N97,"NA",IF(ISNUMBER($F97),ROUND(($F97*L$5),0),"")) -> NA | M97: =IF($N97,"NA",IF(ISNUMBER($F97),ROUND(($F97*M$5),0),"")) -> NA | N97: TRUE
A98: Passage à support 6 ans intervention J+1 (Heures ouvrées, jours ouvrés) | B98: HPE 6Y TC Basis SVC | C98: Passage vers HU4B2A6#YKX | F98: 5 | G98: =IF($N98,"NA",IF(ISNUMBER($F98),ROUND(($F98*G$5),0),"")) -> 2 | H98: =IF($N98,"NA",IF(ISNUMBER($F98),ROUND(($F98*H$5),0),"")) -> 2 | I98: =IF($N98,"NA",IF(ISNUMBER($F98),ROUND(($F98*I$5),0),"")) -> 2 | J98: =IF($N98,"NA",IF(ISNUMBER($F98),ROUND(($F98*J$5),0),"")) -> 2 | K98: =IF($N98,"NA",IF(ISNUMBER($F98),ROUND(($F98*K$5),0),"")) -> 2 | L98: =IF($N98,"NA",IF(ISNUMBER($F98),ROUND(($F98*L$5),0),"")) -> 2 | M98: =IF($N98,"NA",IF(ISNUMBER($F98),ROUND(($F98*M$5),0),"")) -> 2 | N98: FALSE
A99: Passage à support 6 ans intervention h+4 (24h/24h, 7j/7j) | B99: HPE 6Y Tech Care Essential SVC | C99: Passage vers HU4A6A6#YKX | F99: 110 | G99: =IF($N99,"NA",IF(ISNUMBER($F99),ROUND(($F99*G$5),0),"")) -> NA | H99: =IF($N99,"NA",IF(ISNUMBER($F99),ROUND(($F99*H$5),0),"")) -> NA | I99: =IF($N99,"NA",IF(ISNUMBER($F99),ROUND(($F99*I$5),0),"")) -> NA | J99: =IF($N99,"NA",IF(ISNUMBER($F99),ROUND(($F99*J$5),0),"")) -> NA | K99: =IF($N99,"NA",IF(ISNUMBER($F99),ROUND(($F99*K$5),0),"")) -> NA | L99: =IF($N99,"NA",IF(ISNUMBER($F99),ROUND(($F99*L$5),0),"")) -> NA | M99: =IF($N99,"NA",IF(ISNUMBER($F99),ROUND(($F99*M$5),0),"")) -> NA | N99: TRUE
A100: Passage à support 7 ans intervention J+1 (Heures ouvrées, jours ouvrés) | B100: HPE 7Y Tech Care Basis SVC | C100: Passage vers HU4B2A7#YKX | F100: 10 | G100: =IF($N100,"NA",IF(ISNUMBER($F100),ROUND(($F100*G$5),0),"")) -> 3 | H100: =IF($N100,"NA",IF(ISNUMBER($F100),ROUND(($F100*H$5),0),"")) -> 3 | I100: =IF($N100,"NA",IF(ISNUMBER($F100),ROUND(($F100*I$5),0),"")) -> 5 | J100: =IF($N100,"NA",IF(ISNUMBER($F100),ROUND(($F100*J$5),0),"")) -> 3 | K100: =IF($N100,"NA",IF(ISNUMBER($F100),ROUND(($F100*K$5),0),"")) -> 5 | L100: =IF($N100,"NA",IF(ISNUMBER($F100),ROUND(($F100*L$5),0),"")) -> 4 | M100: =IF($N100,"NA",IF(ISNUMBER($F100),ROUND(($F100*M$5),0),"")) -> 5 | N100: FALSE
A101: Passage à support 7 ans intervention h+4 (24h/24h, 7j/7j) | B101: HPE 7Y Tech Care Essential SVC | C101: Passage vers HU4A6A7#YKX | F101: 167 | G101: =IF($N101,"NA",IF(ISNUMBER($F101),ROUND(($F101*G$5),0),"")) -> NA | H101: =IF($N101,"NA",IF(ISNUMBER($F101),ROUND(($F101*H$5),0),"")) -> NA | I101: =IF($N101,"NA",IF(ISNUMBER($F101),ROUND(($F101*I$5),0),"")) -> NA | J101: =IF($N101,"NA",IF(ISNUMBER($F101),ROUND(($F101*J$5),0),"")) -> NA | K101: =IF($N101,"NA",IF(ISNUMBER($F101),ROUND(($F101*K$5),0),"")) -> NA | L101: =IF($N101,"NA",IF(ISNUMBER($F101),ROUND(($F101*L$5),0),"")) -> NA | M101: =IF($N101,"NA",IF(ISNUMBER($F101),ROUND(($F101*M$5),0),"")) -> NA | N101: TRUE
A102: Passage à support 5 ans intervention j+1 (9x5) avec retention de disque | B102: Tech Care Basic DMR 5Y (J+1 9x5) | C102: Passage vers HU4B3A5#ZX1 | F102: 19 | G102: =IF($N102,"NA",IF(ISNUMBER($F102),ROUND(($F102*G$5),0),"")) -> 7 | H102: =IF($N102,"NA",IF(ISNUMBER($F102),ROUND(($F102*H$5),0),"")) -> 7 | I102: =IF($N102,"NA",IF(ISNUMBER($F102),ROUND(($F102*I$5),0),"")) -> 9 | J102: =IF($N102,"NA",IF(ISNUMBER($F102),ROUND(($F102*J$5),0),"")) -> 6 | K102: =IF($N102,"NA",IF(ISNUMBER($F102),ROUND(($F102*K$5),0),"")) -> 9 | L102: =IF($N102,"NA",IF(ISNUMBER($F102),ROUND(($F102*L$5),0),"")) -> 8 | M102: =IF($N102,"NA",IF(ISNUMBER($F102),ROUND(($F102*M$5),0),"")) -> 9 | N102: FALSE
A103: Passage à support 5 ans intervention h+4 (24h/24h, 7j/7j) | B103: Tech Care Essential 5Y (4H 24X7) | C103: Passage vers HU4A6A5#ZX1 | F103: 26 | G103: =IF($N103,"NA",IF(ISNUMBER($F103),ROUND(($F103*G$5),0),"")) -> NA | H103: =IF($N103,"NA",IF(ISNUMBER($F103),ROUND(($F103*H$5),0),"")) -> NA | I103: =IF($N103,"NA",IF(ISNUMBER($F103),ROUND(($F103*I$5),0),"")) -> NA | J103: =IF($N103,"NA",IF(ISNUMBER($F103),ROUND(($F103*J$5),0),"")) -> NA | K103: =IF($N103,"NA",IF(ISNUMBER($F103),ROUND(($F103*K$5),0),"")) -> NA | L103: =IF($N103,"NA",IF(ISNUMBER($F103),ROUND(($F103*L$5),0),"")) -> NA | M103: =IF($N103,"NA",IF(ISNUMBER($F103),ROUND(($F103*M$5),0),"")) -> NA | N103: TRUE
A104: Passage à support 5 ans intervention h+4 (24h/24h, 7j/7j) avec retention de Disque | B104: Tech Care Essential 5Y DMR (4H 24X7) | C104: Passage vers HU4A7A5#ZX1 | F104: 35 | G104: =IF($N104,"NA",IF(ISNUMBER($F104),ROUND(($F104*G$5),0),"")) -> NA | H104: =IF($N104,"NA",IF(ISNUMBER($F104),ROUND(($F104*H$5),0),"")) -> NA | I104: =IF($N104,"NA",IF(ISNUMBER($F104),ROUND(($F104*I$5),0),"")) -> NA | J104: =IF($N104,"NA",IF(ISNUMBER($F104),ROUND(($F104*J$5),0),"")) -> NA | K104: =IF($N104,"NA",IF(ISNUMBER($F104),ROUND(($F104*K$5),0),"")) -> NA | L104: =IF($N104,"NA",IF(ISNUMBER($F104),ROUND(($F104*L$5),0),"")) -> NA | M104: =IF($N104,"NA",IF(ISNUMBER($F104),ROUND(($F104*M$5),0),"")) -> NA | N104: TRUE
...
