Workbook

Sheet Suivi de version
B2: Mise à jour Octobre 2023
B3: o Version initiale validée le 10/09/2021
B4: N1 V2 | C4: Ajoût numéros de références manquantes sur Descriptifs et prix existants
C5: Baisses de prix sur 2 références suites à erreurs typographiques
C6: Ajout (sans impact prix) de references logisitique de prises de rdv commandes sur toutes les configurations
C7: Correction de commentaires et descriptif suite à erreurs typographiques
C8: Ajout de passage de HDD vers SSD
A9: 44497 | B9: V3 | C9: Ajoût numéros de références manquantes sur Descriptifs et prix existants
C10: Baisse de prix sur 1 référence suite à erreur typographique
C11: Hausse de prix sur 1 référence suite à erreur typographique
C12: Changement de références logistique de l'interieur à quai/porte
C13: Ajout de passage livraison à l'interieur à 0€
C14: Ajout des references de prise de rdv a 1€
C15: Ajout des references livraison a l'etage a 1€
C16: Baisse de 2€ sur les configuration pour refleter ce surcout eventuel
C17: Suppression du cordon electrique par defaut
C18: Ajout des cordons 0,7m et 2m à 1€
C19: Baisse de 1€ sur les configuration pour refleter ce surcout eventuel
C20: Ajout des serveurs Intel Gen10+
C21: Ajout des serveurs AMD Gen10 +V2
... C28: Suppressions des ajouts impossible (cad avec passage uniquement)
A30: 44623 | B30: V4 | C30: Ajoût numéros de références manquantes sur Descriptifs et prix existants
C31: Correction de prix d'ajout ou passage pour respect prix passage (prix ajout - prix passage)
C32: Ajout de lignes support Nimble manquantes
C33: Ajout/Suppression/Mise à jour de reference SSD/Nvme obsoletes d'ici 3 mois
C34: Integration des SKUS HPE VMWare EDUC
C35: Integration des SKUS HPE MS EDUC
C36: Integration des SKUS Support 6 / 7 ans sur certaines references produits
C37: Ajout CPUs
C38: Suppression : Categorie 2 Options pour mutualisation
C39: Equilibrage de la ram des bundle par remplacement de barrette DIMM 16Go/32Go par 32Go/64Go avec répercution prix passage sur bundle
C40: Simplification des configurations Apollo 6500 avec configurations non éclatés (chassis et serveur) : prix final respecté avec logique ajout/passage
C41: Ajout Chassis Apollo Gen10+ Intel avec suppression de passage AMD avec Intel : prix final respecté avec logique ajout/passage
C42: Suppression temporaire des options sans garanti 5 ans embarqué (Nimble, Primera, Commutateurs,…)
A44: 44704 | B44: v5 | C44: Suppression des Ctrl RAID + disques durs des configurations (dégression des prix en conséquence)
C45: Ajout des rails kits dans les configurations (prise en compte dans prix bundle)
C46: Ajout derniers serveurs Gen10+ (ML30, DL20, Apollo 4200)
C47: Ajout Stockage Alletra, Qumulo
C48: Ajout références produit générique pour simplification BPU
C49: Ajout références stockage et réseau avec 5 ans intégrés
C50: Application de la clause euro/dollar
C51: Suppression de références obsolètes
C52: Réintroduction des options temporairement supprimées avec intégration prix support 5 ans dans le prix du produit
C53: Réintroduction des barettes DIMM 16Go
C54: Suppression des configurations Apollo 2000 de 4 nœuds pleins
C55: Ajout de chassis Apollo 2000 vides
C56: Ajout de lames Apollo 2000 unitaires
... C61: Introduction BPU Location
A62: 45211 | B62: v6 | C62: Application de la clause d'augmentation des prix (premiere depuis Septembre 2021)
C63: Ajout des serveurs Gen11
C64: Ajout du Stockage Alletra 5000
C65: Retrait des gammes obsoletes
C66: Maximum 2 générations de produit par gamme
C67: 1 Seule génération de Stockage pour investissement pérenne
C68: Retrait Nimble et Primera au profit de Alletra 5000, 6000 et 9000
C69: Ajout de la nouvelle Alletra MP (Greenlake for block)
C70: Ajout du Microserveur gen10+V2
C71: Intégration du nouvel outil d'administration centralisé HPE Compute Operation manager dans les configurations de base sans surcoût sauf pour le DL325
C72: Ajout des nouveaux GPU Nvidia et sortie du A100 suite à pénurie annoncée par Nvidia
A73: 45251 | B73: v3 | C73: Remplacement des alimentations Platinium en Titanium pour prise en compte de la réglementation EU Lot9 entrant en vigueur au 01/01/2024
C74: Prise en charge du surcoût par HPE sauf pour l'Apollo 2000 Gen10

Sheet Lot4 - BPU
A2: Désignation Description des matériels | B2: Référence constructeur (le cas échéant) | C2: HPE SKU | D2: Quantités | E2: Tag | F2: TARIFS en €HT
A3: CATEGORIE 1 : Serveurs Edge ou Standard
A4: Désignation/Description des matériels | B4: Référence constructeur (le cas échéant) | C4: Numéro de référence | D4: Quantités | F4: TARIFS en €HT
A6: Cat1 Conf4 Microserver Gen10 Plus v2 | B6: HPE ProLiant MicroServer Gen10 plus v2 | C6: P54644-421 | F6: 573.47
A7: Serveur tour Ultra Micro mono-socket | B7: HPE ProLiant MicroServer Gen10 Plus v2 G6405 2-core 16GB-U VROC 4LFF-NHP 180W External PS Server | C7: P54644-421 | D7: 1
A8: 1 disque de 1 To 6G SATA 7.2K 3,5 pouces (LFF) Non Hot Plug | B8: HPE 1TB SATA 6G Business Critical 7.2K LFF RW 1-year Warranty Multi Vendor HDD | C8: 801882-B21 | D8: 1
A9: Kit pour carte d'administration HPE iLO | B9: HPE MicroServer Gen10 Plus iLO Enablement Kit | C9: P13788-B21 | D9: 1
A10: Carte d'administration HPE iLO avec API RESTful compatible IPMI v2.0 et Redfish. Licence en version Advanced avec toutes les options activées | B10: HPE iLO Advanced 1-server License with 1yr Support on iLO Licensed Features | C10: 512485-B21 | D10: 1
A11: Livraison devant la porte | B11: Livraison devant la porte | C11: AC114A | D11: 1
A12: Garantie 5 ans J+1 | B12: HPE 5 Year Tech Care Basic Service | C12: HU4B2A5 | D12: 1
A13: Garantie 5 ans H+4 ILO | B13: HPE 5 Year Tech Care Essential iLO Advance Non Blade Service | C13: HU4B2A5#7X4 | D13: 1
A14: Garantie 5 ans J+1 châssis | B14: HPE Microserver Gen10 Plus Support | C14: HU4B2A5#YKX | D14: 1
A16: Cat1 Conf5 DL20 Gen10 plus | B16: HPE ProLiant DL20 Gen10 plus | C16: P44109-B21 | F16: 310.47
A17: Serveur rack standard 1U DL20 Gen10+ mono-socket INTEL | B17: HPE DL20 Gen10+ 2LFF NHP CTO Svr | C17: P44109-B21 | D17: 1
A18: Processeur 64 bits Intel Xeon E-2314 (2,8 GHz de base / 4,50 Ghz Turbo / 4 cœurs / 4 threads / 8 Mo Smart Cache / 65W TDP) | B18: Intel Xeon E-2314 FIO CPU for HPE | C18: P45248-B21 | D18: 1
A19: Barrette mémoire de 16GB HPE Standard DDR4-3200 UDIMM | B19: HPE 16GB 1Rx8 PC4-3200AA-E STND Kit | C19: P43019-B21 | D19: 1
A20: 1 cage pour emplacement PCI | B20: HPE DL20 Gen10+ 2x8 LP FIO Riser Kit | C20: P46114-B21 | D20: 1
A21: Alimentation Titanium 800W | B21: HPE 800W FS Ti Ht Plg LH Pwr Sply Kit | C21: 865438-B21 | D21: 1
A22: Activation Alimentation redondante | B22: HPE ProLiant DL20 Gen10 Plus RPS FIO Enablement Kit | C22: P45948-B21 | D22: Cat
A23: Licence iLO en version Advanced avec toutes les options activées | B23: HPE iLO Adv 1-svr Lic 1yr Support | C23: 512485-B21 | D23: 1
A24: Suppression des câbles électriques par défaut | B24: HPE Remove Standard Power Cords | C24: 469774-409 | D24: 1
A25: 1 kit de rail pour rack | B25: HPE 1U Short Friction Rail Kit | C25: 775612-B21 | D25: 1
A26: Livraison devant la porte | B26: HPE Door/dock Small Delivery SVC | C26: AC111A | D26: 1
A27: Support 5 ans H+4 ILO | B27: HPE 5Y TC Ess iLO Adv Non BL SVC | C27: HW2P1E | D27: 1
A28: Garantie 5 ans J+1 châssis | B28: HPE 5Y TC Bas DL20 Gen10 Plus HW SVC | C28: H32ZWE | D28: 1
A31: Cat1 Conf10 DL325 Gen10 plus v2 | B31: HPE ProLiant DL325 Gen10 plus V2 | C31: P38471-B21 | F31: 969.28
A32: Serveur rack standard 1U mono-socket AMD | B32: HPE DL325 G10+ v2 8SFF CTO Svr | C32: P38471-B21 | D32: 1
A33: Processeur 64 bits AMD EPYC 7232P (3,1 GHz de base 8 cœurs / 16 threads) | B33: AMD EPYC 7232P Kit for DL325 Gen10+ v2 | C33: P39738-B21 | D33: 1
A34: Barrette mémoire de 32GB HPE DDR4-3200 RDIMM | B34: HPE 32GB 2Rx4 PC4-3200AA-R Smart Kit | C34: P07646-B21 | D34: 1
A35: Cage disque 8SFF | B35: HPE ProLiant DL325 Gen10 Plus v2 8SFF SAS/SATA BC FIO Backplane Kit | C35: P38473-B21 | D35: 1
A36: 2 ports Ethernet 10GbE Base-T OCP (intégré) | B36: BCM 57416 10GbE 2p BASE-T OCP3 Adptr | C36: P10097-B21 | D36: 1
A37: Alimentation Titanium 800W | B37: HPE 800W FS Ti Ht Plg LH Pwr Sply Kit | C37: 865438-B21 | D37: 1
A38: Licence iLO en version Advanced avec toutes les options activées | B38: HPE iLO Adv 1-svr Lic 1yr Support | C38: 512485-B21 | D38: 1
A39: Outil d'administration | B39: HPE GreenLake COM En 5y Up ProLiant aaS | C39: R7A12AAE | D39: 1
A40: Kit de câble SATA | B40: HPE DL325 G10+ v2 SATA FIO Cbl Kit | C40: P39134-B21 | D40: 1
A41: Kit Ventilateurs Standard | B41: HPE DL325 G10+ v2 Stnd FIO Fan Kit | C41: P41471-B21 | D41: 1
A42: Dissipateurs thermiques Haute Performance | B42: HPE DL325 G10+ v2 High Perf FIO HS Kit | C42: P41197-B21 | D42: 1
A43: Suppression des câbles électriques par défaut | B43: HPE Remove Standard Power Cords | C43: 469774-409 | D43: 1
... A47: Garantie 5 ans J+1 châssis | B47: HPE 5Y TC Bas DL325G10+V2 SVC | C47: HY5G1E | D47: 1
A50: Cat1 Conf6 Tour ML30 Gen10 plus | B50: HPE ProLiant ML30 Gen10 plus | C50: P44723-B21 | F50: 757.93
A51: Serveur de type tour ML30 Gen10 plus | B51: HPE ML30 Gen10+ 4LFF NHP CTO Svr | C51: P44723-B21 | D51: 1
A52: Processeur 64 bits Intel Xeon E-2314 (2,8 GHz de base / 4,50 Ghz Turbo / 4 cœurs / 4 threads / 8 Mo Smart Cache / 65W TDP) | B52: Intel Xeon E-2314 FIO CPU for HPE | C52: P45248-B21 | D52: 1
A53: Barrette mémoire de 16GB HPE Standard DDR4-3200 UDIMM | B53: HPE 16GB 1Rx8 PC4-3200AA-E STND Kit | C53: P43019-B21 | D53: 1
A54: Alimentation Titanium 800W | B54: HPE 800W FS Ti Ht Plg LH Pwr Sply Kit | C54: 865438-B21 | D54: 1
A55: Licence iLO en version Advanced avec toutes les options activées | B55: HPE iLO Adv 1-svr Lic 1yr Support | C55: 512485-B21 | D55: 1
A56: Outil d'administration | B56: HPE GreenLake COM En 5y Up ProLiant aaS | C56: R7A12AAE | D56: 1
A57: Kit d'Alimentation redondante | B57: HPE ML30 Gen10+ 4U RPS Enable Kit | C57: P45209-B21 | D57: 1
A58: Kit Ventilateur | B58: HPE ML30 Gen10 PCI Fan and Baffle Kit | C58: P06303-B21 | D58: 1
A59: Suppression des câbles électriques par défaut | B59: HPE Remove Standard Power Cords | C59: 469774-409 | D59: 1
A60: Livraison devant la porte | B60: HPE Door/dock Small Delivery SVC | C60: AC111A | D60: 1
A61: Support 5 ans H+4 ILO | B61: HPE 5Y TC Ess iLO Adv Non BL SVC | C61: HW2P1E | D61: 1
A62: Garantie 5 ans J+1 châssis | B62: HPE 5Y TC Bas ML30 Gen10 Plus SVC | C62: HS8G6E | D62: 1
A64: Cat1 Conf7 DL160 Gen10 | B64: HPE ProLiant DL160 Gen10 | C64: 878973-B21 | F64: 872.07
A65: Serveur rack 1U évolutif bi-socket INTEL DL160 Gen10 | B65: HPE DL160 Gen10 8SFF CTO Server | C65: 878973-B21 | D65: 1
A66: Processeur 64 bits Intel Xeon Silver 4210R (2,40 GHz de base / 3,20 Ghz Turbo / 10 cœurs / 20 threads / 13,75 Mo Smart Cache / 100W TDP) | B66: Intel Xeon-S 4210R FIO Kit for DL160 G10 | C66: P21191-L21 | D66: 1
A67: Barrette mémoire de 32GB HPE DDR4-2933 RDIMM | B67: HPE 32GB 2Rx4 PC4-2933Y-R Smart Kit | C67: P00924-B21 | D67: 2
A68: 2 ports Ethernet 10Gb BASE-T | B68: HPE Eth 10Gb 2p 568T Mmt Adptr | C68: 866470-B21 | D68: 1
A69: Alimentation Titanium 800W | B69: HPE 800W FS Ti Ht Plg LH Pwr Sply Kit | C69: 865438-B21 | D69: 1
A70: Licence iLO en version Advanced avec toutes les options activées | B70: HPE iLO Adv 1-svr Lic 1yr Support | C70: 512485-B21 | D70: 1
A71: Cable SATA | B71: HPE DL160 G10 8SFF Emb SATA FIO Cbl Kit | C71: 866446-B21 | D71: 1
A72: Kit d'Alimentation redondante | B72: HPE DL160/180 Gen10 RPS Enablement Kit | C72: 866442-B21 | D72: 1
A73: 1 kit de rail pour rack | B73: HPE 1U SFF Easy Install Rail Kit | C73: 734807-B21 | D73: 1
A74: Suppression des câbles électriques par défaut | B74: HPE Remove Standard Power Cords | C74: 469774-409 | D74: 1
A75: Livraison devant la porte | B75: HPE Door/dock Small Delivery SVC | C75: AC111A | D75: 1
A76: Support 5 ans H+4 ILO | B76: HPE 5Y TC Ess iLO Adv Non BL SVC | C76: HW2P1E | D76: 1
A77: Garantie 5 ans J+1 châssis | B77: HPE 5Y TC Bas DL160 Gen10 SVC | C77: HV6T5E | D77: 1
A79: Cat1 Conf9 DL180 Gen10 Intel | B79: HPE ProLiant DL180 Gen10 | C79: 879517-B21 | F79: 947.04
A80: Serveur rack 2U évolutif bi-socket INTEL | B80: HPE DL180 Gen10 8SFF CTO Server | C80: 879517-B21 | D80: 1
A81: Processeur 64 bits Intel Xeon Silver 4210R (2,40 GHz de base / 3,20 Ghz Turbo / 10 cœurs / 20 threads / 13,75 Mo Smart Cache / 100W TDP) | B81: Intel Xeon-S 4210R FIO Kit for DL180 G10 | C81: P21198-L21 | D81: 1
A82: Barrette mémoire de 32GB HPE DDR4-2933 RDIMM | B82: HPE 32GB 2Rx4 PC4-2933Y-R Smart Kit | C82: P00924-B21 | D82: 2
A83: Kit pour emplacement Processeur | B83: HPE DL180 Gen10 CPU1 x8x8x8 Riser Kit | C83: 878484-B21 | D83: 1
A84: 2 ports Ethernet 10Gb BASE-T | B84: HPE Eth 10Gb 2p 568T Mmt Adptr | C84: 866470-B21 | D84: 1
A85: Alimentation Titanium 800W | B85: HPE 800W FS Ti Ht Plg LH Pwr Sply Kit | C85: 865438-B21 | D85: 1
A86: Licence iLO en version Advanced avec toutes les options activées | B86: HPE iLO Adv 1-svr Lic 1yr Support | C86: 512485-B21 | D86: 1
A87: Cable | B87: HPE DL180 G10 SFF Box3 MB/-p FIO Cbl Kit | C87: 879752-B21 | D87: 1
A88: Cage pour Alimentation | B88: HPE DL160/180 Gen10 RPS Enablement Kit | C88: 866442-B21 | D88: 1
A89: Suppression des câbles électriques par défaut | B89: HPE Remove Standard Power Cords | C89: 469774-409 | D89: 1
A90: 1 kit de rail pour rack | B90: HPE 2U SFF Easy Install Rail Kit | C90: 733660-B21 | D90: 1
A91: Livraison devant la porte | B91: HPE Door/dock Medium Delivery SVC | C91: AC114A | D91: 1
... A93: Garantie 5 ans J+1 châssis | B93: HPE 5Y TC Bas DL180 Gen10 SVC | C93: HV6W2E | D93: 1
A95: Cat1 Conf8 Tour ML350 Gen11 | B95: HPE ProLiant ML350 Gen11 | C95: P48405-B21 | F95: 1672.91
A96: Serveur de type tour ML30 Gen10+ | B96: HPE ML350 Gen11 SFF CTO Server | C96: P48405-B21 | D96: 1
A97: Processeur 64 bits Intel Xeon Silver 4410Y (2,0 GHz de base / 12 cœurs / 150W TDP) | B97: INT Xeon-S 4410Y CPU for HPE | C97: P49610-B21 | D97: 1
A98: Barrette mémoire de 32GB HPE DDR5-4800 RDIMM | B98: HPE 32GB 2Rx8 PC5-4800B-R Smart Kit | C98: P43328-B21 | D98: 2
A99: 2 ports Ethernet 10GbE Base-T OCP (intégré) | B99: BCM 57416 10GbE 2p BASE-T OCP3 Adptr | C99: P10097-B21 | D99: 1
A100: Alimentation Titanium 1000W | B100: HPE 1000W FS Ti Ht Plg PS Kit | C100: P03178-B21 | D100: 1
A101: Licence iLO en version Advanced avec toutes les options activées | B101: HPE iLO Adv 1-svr Lic 1yr Support | C101: 512485-B21 | D101: 1
A102: Kit d’activation HPE ProLiant ML350 Gen11 OCP2 | B102: HPE ML350 Gen11 OCP2 Enable Kit | C102: P47231-B21 | D102: 1
A103: Cable SATA | B103: HPE ML350 Gen11 SFF Emb SATA Cbl Kit | C103: P47232-B21 | D103: 1
A104: Kit de dissipateurs thermiques Standard | B104: HPE ML350 Gen11 Stnd Heat Sink Kit | C104: P47223-B21 | D104: 1
A105: Suppression des câbles électriques par défaut | B105: HPE Remove Standard Power Cords | C105: 469774-409 | D105: 1
A106: Outil d'administration | B106: HPE GreenLake COM En 5y Up ProLiant aaS | C106: R7A12AAE | D106: 1
A107: Livraison devant la porte | B107: HPE Door/dock Medium Delivery SVC | C107: AC114A | D107: 1
... A109: Garantie 5 ans J+1 châssis | B109: HPE 5Y TC Bas ML350 Gen 11 HW SVC | C109: H93T8E | D109: 1
A111: CATEGORIE 1 : extensions et périphériques associés, extensions de garantie, installation, etc.
A112: Désignation/Description des matériels | B112: Référence constructeur (le cas échéant) | C112: Numéro de référence | D112: Quantités
A113: Ces extensions sont propres a cette categorie. Les extensions communes sont factorisés dans le chapitre Categorie 1 a 4 : extensions
A114: Ajout d'une barrette mémoire DDR4-2600/3200 UDIMM 8 Go pour DL20 et ML30 | B114: HPE 8GB 1Rx8 PC4-3200AA-E STND Kit | C114: P43016-B21 | F114: 47.36
A115: Ajout d'une barrette mémoire DDR4-2600/3200 UDIMM 16 Go pour DL20 et ML30 | B115: HPE 16GB 1Rx8 PC4-3200AA-E STND Kit | C115: P43019-B21 | F115: 81.8
A117: Cat1 Configuration n°4: Serveur tour Ultra Micro mono-socket
...

Sheet Lot4 - BPU DROM COM
H1: Les tarifs indiqués ci-après sont des prix plafonds et sont dégressifs selon les quantités approvisionnées sur une même commande. Le tarif indiqué correspond à un prix de transport DDP maritime. (le transport correspond en moyenne à 1/3 du prix). Les prix contractuels sont les prix des devis de transport fournis par IS2.
G3: Transport DDP Mer ou Services DROM COM | H3: 0.3526 | I3: 0.3526 | J3: 0.4633 | K3: 0.32185 | L3: 0.511475 | M3: 0.44075 | N3: 0.495075
A4: Désignation Description des matériels | B4: Référence constructeur (le cas échéant) | C4: HPE SKU | D4: Quantités | E4: Tag | F4: TARIFS en €HT | H4: Guadeloupe | I4: Martinique | J4: Guyane | K4: Réunion | L4: Mayotte | M4: Polynésie | N4: Nouvelle Calédonie | O4: Disponible DROMCOM
A5: CATEGORIE 1 : Serveurs Edge ou Standard | H5: =IF(AND(ISNUMBER($F5),$O5),$F5*H$3,"") | I5: =IF(AND(ISNUMBER($F5),$O5),$F5*I$3,"") | J5: =IF(AND(ISNUMBER($F5),$O5),$F5*J$3,"") | K5: =IF(AND(ISNUMBER($F5),$O5),$F5*K$3,"") | L5: =IF(AND(ISNUMBER($F5),$O5),$F5*L$3,"") | M5: =IF(AND(ISNUMBER($F5),$O5),$F5*M$3,"") | N5: =IF(AND(ISNUMBER($F5),$O5),$F5*N$3,"")
A6: Désignation/Description des matériels | B6: Référence constructeur (le cas échéant) | C6: Numéro de référence | D6: Quantités | F6: TARIFS en €HT | H6: =IF(AND(ISNUMBER($F6),$O6),$F6*H$3,"") | I6: =IF(AND(ISNUMBER($F6),$O6),$F6*I$3,"") | J6: =IF(AND(ISNUMBER($F6),$O6),$F6*J$3,"") | K6: =IF(AND(ISNUMBER($F6),$O6),$F6*K$3,"") | L6: =IF(AND(ISNUMBER($F6),$O6),$F6*L$3,"") | M6: =IF(AND(ISNUMBER($F6),$O6),$F6*M$3,"") | N6: =IF(AND(ISNUMBER($F6),$O6),$F6*N$3,"")
H7: =IF(AND(ISNUMBER($F7),$O7),$F7*H$3,"") | I7: =IF(AND(ISNUMBER($F7),$O7),$F7*I$3,"") | J7: =IF(AND(ISNUMBER($F7),$O7),$F7*J$3,"") | K7: =IF(AND(ISNUMBER($F7),$O7),$F7*K$3,"") | L7: =IF(AND(ISNUMBER($F7),$O7),$F7*L$3,"") | M7: =IF(AND(ISNUMBER($F7),$O7),$F7*M$3,"") | N7: =IF(AND(ISNUMBER($F7),$O7),$F7*N$3,"")
A8: Cat1 Conf4 Microserver Gen10 Plus v2 | B8: HPE ProLiant MicroServer Gen10 plus v2 | C8: P54644-421 | F8: 573.47 | H8: =IF(AND(ISNUMBER($F8),$O8),$F8*H$3,"") -> 202.20552 | I8: =IF(AND(ISNUMBER($F8),$O8),$F8*I$3,"") -> 202.20552 | J8: =IF(AND(ISNUMBER($F8),$O8),$F8*J$3,"") -> 265.68865 | K8: =IF(AND(ISNUMBER($F8),$O8),$F8*K$3,"") -> 184.57132 | L8: =IF(AND(ISNUMBER($F8),$O8),$F8*L$3,"") -> 293.31557 | M8: =IF(AND(ISNUMBER($F8),$O8),$F8*M$3,"") -> 252.7569 | N8: =IF(AND(ISNUMBER($F8),$O8),$F8*N$3,"") -> 283.91066 | O8: TRUE
A9: Serveur tour Ultra Micro mono-socket | B9: HPE ProLiant MicroServer Gen10 Plus v2 G6405 2-core 16GB-U VROC 4LFF-NHP 180W External PS Server | C9: P54644-421 | D9: 1 | H9: =IF(AND(ISNUMBER($F9),$O9),$F9*H$3,"") | I9: =IF(AND(ISNUMBER($F9),$O9),$F9*I$3,"") | J9: =IF(AND(ISNUMBER($F9),$O9),$F9*J$3,"") | K9: =IF(AND(ISNUMBER($F9),$O9),$F9*K$3,"") | L9: =IF(AND(ISNUMBER($F9),$O9),$F9*L$3,"") | M9: =IF(AND(ISNUMBER($F9),$O9),$F9*M$3,"") | N9: =IF(AND(ISNUMBER($F9),$O9),$F9*N$3,"")
A10: 1 disque de 1 To 6G SATA 7.2K 3,5 pouces (LFF) Non Hot Plug | B10: HPE 1TB SATA 6G Business Critical 7.2K LFF RW 1-year Warranty Multi Vendor HDD | C10: 801882-B21 | D10: 1 | H10: =IF(AND(ISNUMBER($F10),$O10),$F10*H$3,"") | I10: =IF(AND(ISNUMBER($F10),$O10),$F10*I$3,"") | J10: =IF(AND(ISNUMBER($F10),$O10),$F10*J$3,"") | K10: =IF(AND(ISNUMBER($F10),$O10),$F10*K$3,"") | L10: =IF(AND(ISNUMBER($F10),$O10),$F10*L$3,"") | M10: =IF(AND(ISNUMBER($F10),$O10),$F10*M$3,"") | N10: =IF(AND(ISNUMBER($F10),$O10),$F10*N$3,"")
A11: Kit pour carte d'administration HPE iLO | B11: HPE MicroServer Gen10 Plus iLO Enablement Kit | C11: P13788-B21 | D11: 1 | H11: =IF(AND(ISNUMBER($F11),$O11),$F11*H$3,"") | I11: =IF(AND(ISNUMBER($F11),$O11),$F11*I$3,"") | J11: =IF(AND(ISNUMBER($F11),$O11),$F11*J$3,"") | K11: =IF(AND(ISNUMBER($F11),$O11),$F11*K$3,"") | L11: =IF(AND(ISNUMBER($F11),$O11),$F11*L$3,"") | M11: =IF(AND(ISNUMBER($F11),$O11),$F11*M$3,"") | N11: =IF(AND(ISNUMBER($F11),$O11),$F11*N$3,"")
A12: Carte d'administration HPE iLO avec API RESTful compatible IPMI v2.0 et Redfish. Licence en version Advanced avec toutes les options activées | B12: HPE iLO Advanced 1-server License with 1yr Support on iLO Licensed Features | C12: 512485-B21 | D12: 1 | H12: =IF(AND(ISNUMBER($F12),$O12),$F12*H$3,"") | I12: =IF(AND(ISNUMBER($F12),$O12),$F12*I$3,"") | J12: =IF(AND(ISNUMBER($F12),$O12),$F12*J$3,"") | K12: =IF(AND(ISNUMBER($F12),$O12),$F12*K$3,"") | L12: =IF(AND(ISNUMBER($F12),$O12),$F12*L$3,"") | M12: =IF(AND(ISNUMBER($F12),$O12),$F12*M$3,"") | N12: =IF(AND(ISNUMBER($F12),$O12),$F12*N$3,"")
A13: Livraison devant la porte | B13: Livraison devant la porte | C13: AC114A | D13: 1 | H13: =IF(AND(ISNUMBER($F13),$O13),$F13*H$3,"") | I13: =IF(AND(ISNUMBER($F13),$O13),$F13*I$3,"") | J13: =IF(AND(ISNUMBER($F13),$O13),$F13*J$3,"") | K13: =IF(AND(ISNUMBER($F13),$O13),$F13*K$3,"") | L13: =IF(AND(ISNUMBER($F13),$O13),$F13*L$3,"") | M13: =IF(AND(ISNUMBER($F13),$O13),$F13*M$3,"") | N13: =IF(AND(ISNUMBER($F13),$O13),$F13*N$3,"")
A14: Garantie 5 ans J+1 | B14: HPE 5 Year Tech Care Basic Service | C14: HU4B2A5 | D14: 1 | H14: =IF(AND(ISNUMBER($F14),$O14),$F14*H$3,"") | I14: =IF(AND(ISNUMBER($F14),$O14),$F14*I$3,"") | J14: =IF(AND(ISNUMBER($F14),$O14),$F14*J$3,"") | K14: =IF(AND(ISNUMBER($F14),$O14),$F14*K$3,"") | L14: =IF(AND(ISNUMBER($F14),$O14),$F14*L$3,"") | M14: =IF(AND(ISNUMBER($F14),$O14),$F14*M$3,"") | N14: =IF(AND(ISNUMBER($F14),$O14),$F14*N$3,"")
A15: Garantie 5 ans H+4 ILO | B15: HPE 5 Year Tech Care Essential iLO Advance Non Blade Service | C15: HU4B2A5#7X4 | D15: 1 | H15: =IF(AND(ISNUMBER($F15),$O15),$F15*H$3,"") | I15: =IF(AND(ISNUMBER($F15),$O15),$F15*I$3,"") | J15: =IF(AND(ISNUMBER($F15),$O15),$F15*J$3,"") | K15: =IF(AND(ISNUMBER($F15),$O15),$F15*K$3,"") | L15: =IF(AND(ISNUMBER($F15),$O15),$F15*L$3,"") | M15: =IF(AND(ISNUMBER($F15),$O15),$F15*M$3,"") | N15: =IF(AND(ISNUMBER($F15),$O15),$F15*N$3,"")
A16: Garantie 5 ans J+1 châssis | B16: HPE Microserver Gen10 Plus Support | C16: HU4B2A5#YKX | D16: 1 | H16: =IF(AND(ISNUMBER($F16),$O16),$F16*H$3,"") | I16: =IF(AND(ISNUMBER($F16),$O16),$F16*I$3,"") | J16: =IF(AND(ISNUMBER($F16),$O16),$F16*J$3,"") | K16: =IF(AND(ISNUMBER($F16),$O16),$F16*K$3,"") | L16: =IF(AND(ISNUMBER($F16),$O16),$F16*L$3,"") | M16: =IF(AND(ISNUMBER($F16),$O16),$F16*M$3,"") | N16: =IF(AND(ISNUMBER($F16),$O16),$F16*N$3,"")
H17: =IF(AND(ISNUMBER($F17),$O17),$F17*H$3,"") | I17: =IF(AND(ISNUMBER($F17),$O17),$F17*I$3,"") | J17: =IF(AND(ISNUMBER($F17),$O17),$F17*J$3,"") | K17: =IF(AND(ISNUMBER($F17),$O17),$F17*K$3,"") | L17: =IF(AND(ISNUMBER($F17),$O17),$F17*L$3,"") | M17: =IF(AND(ISNUMBER($F17),$O17),$F17*M$3,"") | N17: =IF(AND(ISNUMBER($F17),$O17),$F17*N$3,"")
A18: Cat1 Conf5 DL20 Gen10 plus | B18: HPE ProLiant DL20 Gen10 plus | C18: P44109-B21 | F18: 310.47 | H18: =IF(AND(ISNUMBER($F18),$O18),$F18*H$3,"") -> 109.47172 | I18: =IF(AND(ISNUMBER($F18),$O18),$F18*I$3,"") -> 109.47172 | J18: =IF(AND(ISNUMBER($F18),$O18),$F18*J$3,"") -> 143.84075 | K18: =IF(AND(ISNUMBER($F18),$O18),$F18*K$3,"") -> 99.924769 | L18: =IF(AND(ISNUMBER($F18),$O18),$F18*L$3,"") -> 158.79764 | M18: =IF(AND(ISNUMBER($F18),$O18),$F18*M$3,"") -> 136.83965 | N18: =IF(AND(ISNUMBER($F18),$O18),$F18*N$3,"") -> 153.70594 | O18: TRUE
A19: Serveur rack standard 1U DL20 Gen10+ mono-socket INTEL | B19: HPE DL20 Gen10+ 2LFF NHP CTO Svr | C19: P44109-B21 | D19: 1 | H19: =IF(AND(ISNUMBER($F19),$O19),$F19*H$3,"") | I19: =IF(AND(ISNUMBER($F19),$O19),$F19*I$3,"") | J19: =IF(AND(ISNUMBER($F19),$O19),$F19*J$3,"") | K19: =IF(AND(ISNUMBER($F19),$O19),$F19*K$3,"") | L19: =IF(AND(ISNUMBER($F19),$O19),$F19*L$3,"") | M19: =IF(AND(ISNUMBER($F19),$O19),$F19*M$3,"") | N19: =IF(AND(ISNUMBER($F19),$O19),$F19*N$3,"")
A20: Processeur 64 bits Intel Xeon E-2314 (2,8 GHz de base / 4,50 Ghz Turbo / 4 cœurs / 4 threads / 8 Mo Smart Cache / 65W TDP) | B20: Intel Xeon E-2314 FIO CPU for HPE | C20: P45248-B21 | D20: 1 | H20: =IF(AND(ISNUMBER($F20),$O20),$F20*H$3,"") | I20: =IF(AND(ISNUMBER($F20),$O20),$F20*I$3,"") | J20: =IF(AND(ISNUMBER($F20),$O20),$F20*J$3,"") | K20: =IF(AND(ISNUMBER($F20),$O20),$F20*K$3,"") | L20: =IF(AND(ISNUMBER($F20),$O20),$F20*L$3,"") | M20: =IF(AND(ISNUMBER($F20),$O20),$F20*M$3,"") | N20: =IF(AND(ISNUMBER($F20),$O20),$F20*N$3,"")
A21: Barrette mémoire de 16GB HPE Standard DDR4-3200 UDIMM | B21: HPE 16GB 1Rx8 PC4-3200AA-E STND Kit | C21: P43019-B21 | D21: 1 | H21: =IF(AND(ISNUMBER($F21),$O21),$F21*H$3,"") | I21: =IF(AND(ISNUMBER($F21),$O21),$F21*I$3,"") | J21: =IF(AND(ISNUMBER($F21),$O21),$F21*J$3,"") | K21: =IF(AND(ISNUMBER($F21),$O21),$F21*K$3,"") | L21: =IF(AND(ISNUMBER($F21),$O21),$F21*L$3,"") | M21: =IF(AND(ISNUMBER($F21),$O21),$F21*M$3,"") | N21: =IF(AND(ISNUMBER($F21),$O21),$F21*N$3,"")
A22: 1 cage pour emplacement PCI | B22: HPE DL20 Gen10+ 2x8 LP FIO Riser Kit | C22: P46114-B21 | D22: 1 | H22: =IF(AND(ISNUMBER($F22),$O22),$F22*H$3,"") | I22: =IF(AND(ISNUMBER($F22),$O22),$F22*I$3,"") | J22: =IF(AND(ISNUMBER($F22),$O22),$F22*J$3,"") | K22: =IF(AND(ISNUMBER($F22),$O22),$F22*K$3,"") | L22: =IF(AND(ISNUMBER($F22),$O22),$F22*L$3,"") | M22: =IF(AND(ISNUMBER($F22),$O22),$F22*M$3,"") | N22: =IF(AND(ISNUMBER($F22),$O22),$F22*N$3,"")
A23: Alimentation Titanium 800W | B23: HPE 800W FS Ti Ht Plg LH Pwr Sply Kit | C23: 865438-B21 | D23: 1 | H23: =IF(AND(ISNUMBER($F23),$O23),$F23*H$3,"") | I23: =IF(AND(ISNUMBER($F23),$O23),$F23*I$3,"") | J23: =IF(AND(ISNUMBER($F23),$O23),$F23*J$3,"") | K23: =IF(AND(ISNUMBER($F23),$O23),$F23*K$3,"") | L23: =IF(AND(ISNUMBER($F23),$O23),$F23*L$3,"") | M23: =IF(AND(ISNUMBER($F23),$O23),$F23*M$3,"") | N23: =IF(AND(ISNUMBER($F23),$O23),$F23*N$3,"")
A24: Activation Alimentation redondante | B24: HPE ProLiant DL20 Gen10 Plus RPS FIO Enablement Kit | C24: P45948-B21 | D24: Cat | H24: =IF(AND(ISNUMBER($F24),$O24),$F24*H$3,"") | I24: =IF(AND(ISNUMBER($F24),$O24),$F24*I$3,"") | J24: =IF(AND(ISNUMBER($F24),$O24),$F24*J$3,"") | K24: =IF(AND(ISNUMBER($F24),$O24),$F24*K$3,"") | L24: =IF(AND(ISNUMBER($F24),$O24),$F24*L$3,"") | M24: =IF(AND(ISNUMBER($F24),$O24),$F24*M$3,"") | N24: =IF(AND(ISNUMBER($F24),$O24),$F24*N$3,"")
A25: Licence iLO en version Advanced avec toutes les options activées | B25: HPE iLO Adv 1-svr Lic 1yr Support | C25: 512485-B21 | D25: 1 | H25: =IF(AND(ISNUMBER($F25),$O25),$F25*H$3,"") | I25: =IF(AND(ISNUMBER($F25),$O25),$F25*I$3,"") | J25: =IF(AND(ISNUMBER($F25),$O25),$F25*J$3,"") | K25: =IF(AND(ISNUMBER($F25),$O25),$F25*K$3,"") | L25: =IF(AND(ISNUMBER($F25),$O25),$F25*L$3,"") | M25: =IF(AND(ISNUMBER($F25),$O25),$F25*M$3,"") | N25: =IF(AND(ISNUMBER($F25),$O25),$F25*N$3,"")
A26: Suppression des câbles électriques par défaut | B26: HPE Remove Standard Power Cords | C26: 469774-409 | D26: 1 | H26: =IF(AND(ISNUMBER($F26),$O26),$F26*H$3,"") | I26: =IF(AND(ISNUMBER($F26),$O26),$F26*I$3,"") | J26: =IF(AND(ISNUMBER($F26),$O26),$F26*J$3,"") | K26: =IF(AND(ISNUMBER($F26),$O26),$F26*K$3,"") | L26: =IF(AND(ISNUMBER($F26),$O26),$F26*L$3,"") | M26: =IF(AND(ISNUMBER($F26),$O26),$F26*M$3,"") | N26: =IF(AND(ISNUMBER($F26),$O26),$F26*N$3,"")
A27: 1 kit de rail pour rack | B27: HPE 1U Short Friction Rail Kit | C27: 775612-B21 | D27: 1 | H27: =IF(AND(ISNUMBER($F27),$O27),$F27*H$3,"") | I27: =IF(AND(ISNUMBER($F27),$O27),$F27*I$3,"") | J27: =IF(AND(ISNUMBER($F27),$O27),$F27*J$3,"") | K27: =IF(AND(ISNUMBER($F27),$O27),$F27*K$3,"") | L27: =IF(AND(ISNUMBER($F27),$O27),$F27*L$3,"") | M27: =IF(AND(ISNUMBER($F27),$O27),$F27*M$3,"") | N27: =IF(AND(ISNUMBER($F27),$O27),$F27*N$3,"")
A28: Livraison devant la porte | B28: HPE Door/dock Small Delivery SVC | C28: AC111A | D28: 1 | H28: =IF(AND(ISNUMBER($F28),$O28),$F28*H$3,"") | I28: =IF(AND(ISNUMBER($F28),$O28),$F28*I$3,"") | J28: =IF(AND(ISNUMBER($F28),$O28),$F28*J$3,"") | K28: =IF(AND(ISNUMBER($F28),$O28),$F28*K$3,"") | L28: =IF(AND(ISNUMBER($F28),$O28),$F28*L$3,"") | M28: =IF(AND(ISNUMBER($F28),$O28),$F28*M$3,"") | N28: =IF(AND(ISNUMBER($F28),$O28),$F28*N$3,"")
A29: Support 5 ans H+4 ILO | B29: HPE 5Y TC Ess iLO Adv Non BL SVC | C29: HW2P1E | D29: 1 | H29: =IF(AND(ISNUMBER($F29),$O29),$F29*H$3,"") | I29: =IF(AND(ISNUMBER($F29),$O29),$F29*I$3,"") | J29: =IF(AND(ISNUMBER($F29),$O29),$F29*J$3,"") | K29: =IF(AND(ISNUMBER($F29),$O29),$F29*K$3,"") | L29: =IF(AND(ISNUMBER($F29),$O29),$F29*L$3,"") | M29: =IF(AND(ISNUMBER($F29),$O29),$F29*M$3,"") | N29: =IF(AND(ISNUMBER($F29),$O29),$F29*N$3,"")
A30: Garantie 5 ans J+1 châssis | B30: HPE 5Y TC Bas DL20 Gen10 Plus HW SVC | C30: H32ZWE | D30: 1 | H30: =IF(AND(ISNUMBER($F30),$O30),$F30*H$3,"") | I30: =IF(AND(ISNUMBER($F30),$O30),$F30*I$3,"") | J30: =IF(AND(ISNUMBER($F30),$O30),$F30*J$3,"") | K30: =IF(AND(ISNUMBER($F30),$O30),$F30*K$3,"") | L30: =IF(AND(ISNUMBER($F30),$O30),$F30*L$3,"") | M30: =IF(AND(ISNUMBER($F30),$O30),$F30*M$3,"") | N30: =IF(AND(ISNUMBER($F30),$O30),$F30*N$3,"")
H31: =IF(AND(ISNUMBER($F31),$O31),$F31*H$3,"") | I31: =IF(AND(ISNUMBER($F31),$O31),$F31*I$3,"") | J31: =IF(AND(ISNUMBER($F31),$O31),$F31*J$3,"") | K31: =IF(AND(ISNUMBER($F31),$O31),$F31*K$3,"") | L31: =IF(AND(ISNUMBER($F31),$O31),$F31*L$3,"") | M31: =IF(AND(ISNUMBER($F31),$O31),$F31*M$3,"") | N31: =IF(AND(ISNUMBER($F31),$O31),$F31*N$3,"")
H32: =IF(AND(ISNUMBER($F32),$O32),$F32*H$3,"") | I32: =IF(AND(ISNUMBER($F32),$O32),$F32*I$3,"") | J32: =IF(AND(ISNUMBER($F32),$O32),$F32*J$3,"") | K32: =IF(AND(ISNUMBER($F32),$O32),$F32*K$3,"") | L32: =IF(AND(ISNUMBER($F32),$O32),$F32*L$3,"") | M32: =IF(AND(ISNUMBER($F32),$O32),$F32*M$3,"") | N32: =IF(AND(ISNUMBER($F32),$O32),$F32*N$3,"")
A33: Cat1 Conf10 DL325 Gen10 plus v2 | B33: HPE ProLiant DL325 Gen10 plus V2 | C33: P38471-B21 | F33: 969.28 | H33: =IF(AND(ISNUMBER($F33),$O33),$F33*H$3,"") -> 341.76813 | I33: =IF(AND(ISNUMBER($F33),$O33),$F33*I$3,"") -> 341.76813 | J33: =IF(AND(ISNUMBER($F33),$O33),$F33*J$3,"") -> 449.06742 | K33: =IF(AND(ISNUMBER($F33),$O33),$F33*K$3,"") -> 311.96277 | L33: =IF(AND(ISNUMBER($F33),$O33),$F33*L$3,"") -> 495.76249 | M33: =IF(AND(ISNUMBER($F33),$O33),$F33*M$3,"") -> 427.21016 | N33: =IF(AND(ISNUMBER($F33),$O33),$F33*N$3,"") -> 479.8663 | O33: TRUE
A34: Serveur rack standard 1U mono-socket AMD | B34: HPE DL325 G10+ v2 8SFF CTO Svr | C34: P38471-B21 | D34: 1 | H34: =IF(AND(ISNUMBER($F34),$O34),$F34*H$3,"") | I34: =IF(AND(ISNUMBER($F34),$O34),$F34*I$3,"") | J34: =IF(AND(ISNUMBER($F34),$O34),$F34*J$3,"") | K34: =IF(AND(ISNUMBER($F34),$O34),$F34*K$3,"") | L34: =IF(AND(ISNUMBER($F34),$O34),$F34*L$3,"") | M34: =IF(AND(ISNUMBER($F34),$O34),$F34*M$3,"") | N34: =IF(AND(ISNUMBER($F34),$O34),$F34*N$3,"")
A35: Processeur 64 bits AMD EPYC 7232P (3,1 GHz de base 8 cœurs / 16 threads) | B35: AMD EPYC 7232P Kit for DL325 Gen10+ v2 | C35: P39738-B21 | D35: 1 | H35: =IF(AND(ISNUMBER($F35),$O35),$F35*H$3,"") | I35: =IF(AND(ISNUMBER($F35),$O35),$F35*I$3,"") | J35: =IF(AND(ISNUMBER($F35),$O35),$F35*J$3,"") | K35: =IF(AND(ISNUMBER($F35),$O35),$F35*K$3,"") | L35: =IF(AND(ISNUMBER($F35),$O35),$F35*L$3,"") | M35: =IF(AND(ISNUMBER($F35),$O35),$F35*M$3,"") | N35: =IF(AND(ISNUMBER($F35),$O35),$F35*N$3,"")
A36: Barrette mémoire de 32GB HPE DDR4-3200 RDIMM | B36: HPE 32GB 2Rx4 PC4-3200AA-R Smart Kit | C36: P07646-B21 | D36: 1 | H36: =IF(AND(ISNUMBER($F36),$O36),$F36*H$3,"") | I36: =IF(AND(ISNUMBER($F36),$O36),$F36*I$3,"") | J36: =IF(AND(ISNUMBER($F36),$O36),$F36*J$3,"") | K36: =IF(AND(ISNUMBER($F36),$O36),$F36*K$3,"") | L36: =IF(AND(ISNUMBER($F36),$O36),$F36*L$3,"") | M36: =IF(AND(ISNUMBER($F36),$O36),$F36*M$3,"") | N36: =IF(AND(ISNUMBER($F36),$O36),$F36*N$3,"")
A37: Cage disque 8SFF | B37: HPE ProLiant DL325 Gen10 Plus v2 8SFF SAS/SATA BC FIO Backplane Kit | C37: P38473-B21 | D37: 1 | H37: =IF(AND(ISNUMBER($F37),$O37),$F37*H$3,"") | I37: =IF(AND(ISNUMBER($F37),$O37),$F37*I$3,"") | J37: =IF(AND(ISNUMBER($F37),$O37),$F37*J$3,"") | K37: =IF(AND(ISNUMBER($F37),$O37),$F37*K$3,"") | L37: =IF(AND(ISNUMBER($F37),$O37),$F37*L$3,"") | M37: =IF(AND(ISNUMBER($F37),$O37),$F37*M$3,"") | N37: =IF(AND(ISNUMBER($F37),$O37),$F37*N$3,"")
A38: 2 ports Ethernet 10GbE Base-T OCP (intégré) | B38: BCM 57416 10GbE 2p BASE-T OCP3 Adptr | C38: P10097-B21 | D38: 1 | H38: =IF(AND(ISNUMBER($F38),$O38),$F38*H$3,"") | I38: =IF(AND(ISNUMBER($F38),$O38),$F38*I$3,"") | J38: =IF(AND(ISNUMBER($F38),$O38),$F38*J$3,"") | K38: =IF(AND(ISNUMBER($F38),$O38),$F38*K$3,"") | L38: =IF(AND(ISNUMBER($F38),$O38),$F38*L$3,"") | M38: =IF(AND(ISNUMBER($F38),$O38),$F38*M$3,"") | N38: =IF(AND(ISNUMBER($F38),$O38),$F38*N$3,"")
A39: Alimentation Titanium 800W | B39: HPE 800W FS Ti Ht Plg LH Pwr Sply Kit | C39: 865438-B21 | D39: 1 | H39: =IF(AND(ISNUMBER($F39),$O39),$F39*H$3,"") | I39: =IF(AND(ISNUMBER($F39),$O39),$F39*I$3,"") | J39: =IF(AND(ISNUMBER($F39),$O39),$F39*J$3,"") | K39: =IF(AND(ISNUMBER($F39),$O39),$F39*K$3,"") | L39: =IF(AND(ISNUMBER($F39),$O39),$F39*L$3,"") | M39: =IF(AND(ISNUMBER($F39),$O39),$F39*M$3,"") | N39: =IF(AND(ISNUMBER($F39),$O39),$F39*N$3,"")
A40: Licence iLO en version Advanced avec toutes les options activées | B40: HPE iLO Adv 1-svr Lic 1yr Support | C40: 512485-B21 | D40: 1 | H40: =IF(AND(ISNUMBER($F40),$O40),$F40*H$3,"") | I40: =IF(AND(ISNUMBER($F40),$O40),$F40*I$3,"") | J40: =IF(AND(ISNUMBER($F40),$O40),$F40*J$3,"") | K40: =IF(AND(ISNUMBER($F40),$O40),$F40*K$3,"") | L40: =IF(AND(ISNUMBER($F40),$O40),$F40*L$3,"") | M40: =IF(AND(ISNUMBER($F40),$O40),$F40*M$3,"") | N40: =IF(AND(ISNUMBER($F40),$O40),$F40*N$3,"")
A41: Outil d'administration | B41: HPE GreenLake COM En 5y Up ProLiant aaS | C41: R7A12AAE | D41: 1 | H41: =IF(AND(ISNUMBER($F41),$O41),$F41*H$3,"") | I41: =IF(AND(ISNUMBER($F41),$O41),$F41*I$3,"") | J41: =IF(AND(ISNUMBER($F41),$O41),$F41*J$3,"") | K41: =IF(AND(ISNUMBER($F41),$O41),$F41*K$3,"") | L41: =IF(AND(ISNUMBER($F41),$O41),$F41*L$3,"") | M41: =IF(AND(ISNUMBER($F41),$O41),$F41*M$3,"") | N41: =IF(AND(ISNUMBER($F41),$O41),$F41*N$3,"")
A42: Kit de câble SATA | B42: HPE DL325 G10+ v2 SATA FIO Cbl Kit | C42: P39134-B21 | D42: 1 | H42: =IF(AND(ISNUMBER($F42),$O42),$F42*H$3,"") | I42: =IF(AND(ISNUMBER($F42),$O42),$F42*I$3,"") | J42: =IF(AND(ISNUMBER($F42),$O42),$F42*J$3,"") | K42: =IF(AND(ISNUMBER($F42),$O42),$F42*K$3,"") | L42: =IF(AND(ISNUMBER($F42),$O42),$F42*L$3,"") | M42: =IF(AND(ISNUMBER($F42),$O42),$F42*M$3,"") | N42: =IF(AND(ISNUMBER($F42),$O42),$F42*N$3,"")
A43: Kit Ventilateurs Standard | B43: HPE DL325 G10+ v2 Stnd FIO Fan Kit | C43: P41471-B21 | D43: 1 | H43: =IF(AND(ISNUMBER($F43),$O43),$F43*H$3,"") | I43: =IF(AND(ISNUMBER($F43),$O43),$F43*I$3,"") | J43: =IF(AND(ISNUMBER($F43),$O43),$F43*J$3,"") | K43: =IF(AND(ISNUMBER($F43),$O43),$F43*K$3,"") | L43: =IF(AND(ISNUMBER($F43),$O43),$F43*L$3,"") | M43: =IF(AND(ISNUMBER($F43),$O43),$F43*M$3,"") | N43: =IF(AND(ISNUMBER($F43),$O43),$F43*N$3,"")
A44: Dissipateurs thermiques Haute Performance | B44: HPE DL325 G10+ v2 High Perf FIO HS Kit | C44: P41197-B21 | D44: 1 | H44: =IF(AND(ISNUMBER($F44),$O44),$F44*H$3,"") | I44: =IF(AND(ISNUMBER($F44),$O44),$F44*I$3,"") | J44: =IF(AND(ISNUMBER($F44),$O44),$F44*J$3,"") | K44: =IF(AND(ISNUMBER($F44),$O44),$F44*K$3,"") | L44: =IF(AND(ISNUMBER($F44),$O44),$F44*L$3,"") | M44: =IF(AND(ISNUMBER($F44),$O44),$F44*M$3,"") | N44: =IF(AND(ISNUMBER($F44),$O44),$F44*N$3,"")
A45: Suppression des câbles électriques par défaut | B45: HPE Remove Standard Power Cords | C45: 469774-409 | D45: 1 | H45: =IF(AND(ISNUMBER($F45),$O45),$F45*H$3,"") | I45: =IF(AND(ISNUMBER($F45),$O45),$F45*I$3,"") | J45: =IF(AND(ISNUMBER($F45),$O45),$F45*J$3,"") | K45: =IF(AND(ISNUMBER($F45),$O45),$F45*K$3,"") | L45: =IF(AND(ISNUMBER($F45),$O45),$F45*L$3,"") | M45: =IF(AND(ISNUMBER($F45),$O45),$F45*M$3,"") | N45: =IF(AND(ISNUMBER($F45),$O45),$F45*N$3,"")
... A49: Garantie 5 ans J+1 châssis | B49: HPE 5Y TC Bas DL325G10+V2 SVC | C49: HY5G1E | D49: 1 | H49: =IF(AND(ISNUMBER($F49),$O49),$F49*H$3,"") | I49: =IF(AND(ISNUMBER($F49),$O49),$F49*I$3,"") | J49: =IF(AND(ISNUMBER($F49),$O49),$F49*J$3,"") | K49: =IF(AND(ISNUMBER($F49),$O49),$F49*K$3,"") | L49: =IF(AND(ISNUMBER($F49),$O49),$F49*L$3,"") | M49: =IF(AND(ISNUMBER($F49),$O49),$F49*M$3,"") | N49: =IF(AND(ISNUMBER($F49),$O49),$F49*N$3,"")
H50: =IF(AND(ISNUMBER($F50),$O50),$F50*H$3,"") | I50: =IF(AND(ISNUMBER($F50),$O50),$F50*I$3,"") | J50: =IF(AND(ISNUMBER($F50),$O50),$F50*J$3,"") | K50: =IF(AND(ISNUMBER($F50),$O50),$F50*K$3,"") | L50: =IF(AND(ISNUMBER($F50),$O50),$F50*L$3,"") | M50: =IF(AND(ISNUMBER($F50),$O50),$F50*M$3,"") | N50: =IF(AND(ISNUMBER($F50),$O50),$F50*N$3,"")
H51: =IF(AND(ISNUMBER($F51),$O51),$F51*H$3,"") | I51: =IF(AND(ISNUMBER($F51),$O51),$F51*I$3,"") | J51: =IF(AND(ISNUMBER($F51),$O51),$F51*J$3,"") | K51: =IF(AND(ISNUMBER($F51),$O51),$F51*K$3,"") | L51: =IF(AND(ISNUMBER($F51),$O51),$F51*L$3,"") | M51: =IF(AND(ISNUMBER($F51),$O51),$F51*M$3,"") | N51: =IF(AND(ISNUMBER($F51),$O51),$F51*N$3,"")
A52: Cat1 Conf6 Tour ML30 Gen10 plus | B52: HPE ProLiant ML30 Gen10 plus | C52: P44723-B21 | F52: 757.93 | H52: =IF(AND(ISNUMBER($F52),$O52),$F52*H$3,"") -> 267.24612 | I52: =IF(AND(ISNUMBER($F52),$O52),$F52*I$3,"") -> 267.24612 | J52: =IF(AND(ISNUMBER($F52),$O52),$F52*J$3,"") -> 351.14897 | K52: =IF(AND(ISNUMBER($F52),$O52),$F52*K$3,"") -> 243.93977 | L52: =IF(AND(ISNUMBER($F52),$O52),$F52*L$3,"") -> 387.66225 | M52: =IF(AND(ISNUMBER($F52),$O52),$F52*M$3,"") -> 334.05765 | N52: =IF(AND(ISNUMBER($F52),$O52),$F52*N$3,"") -> 375.23219 | O52: TRUE
A53: Serveur de type tour ML30 Gen10 plus | B53: HPE ML30 Gen10+ 4LFF NHP CTO Svr | C53: P44723-B21 | D53: 1 | H53: =IF(AND(ISNUMBER($F53),$O53),$F53*H$3,"") | I53: =IF(AND(ISNUMBER($F53),$O53),$F53*I$3,"") | J53: =IF(AND(ISNUMBER($F53),$O53),$F53*J$3,"") | K53: =IF(AND(ISNUMBER($F53),$O53),$F53*K$3,"") | L53: =IF(AND(ISNUMBER($F53),$O53),$F53*L$3,"") | M53: =IF(AND(ISNUMBER($F53),$O53),$F53*M$3,"") | N53: =IF(AND(ISNUMBER($F53),$O53),$F53*N$3,"")
A54: Processeur 64 bits Intel Xeon E-2314 (2,8 GHz de base / 4,50 Ghz Turbo / 4 cœurs / 4 threads / 8 Mo Smart Cache / 65W TDP) | B54: Intel Xeon E-2314 FIO CPU for HPE | C54: P45248-B21 | D54: 1 | H54: =IF(AND(ISNUMBER($F54),$O54),$F54*H$3,"") | I54: =IF(AND(ISNUMBER($F54),$O54),$F54*I$3,"") | J54: =IF(AND(ISNUMBER($F54),$O54),$F54*J$3,"") | K54: =IF(AND(ISNUMBER($F54),$O54),$F54*K$3,"") | L54: =IF(AND(ISNUMBER($F54),$O54),$F54*L$3,"") | M54: =IF(AND(ISNUMBER($F54),$O54),$F54*M$3,"") | N54: =IF(AND(ISNUMBER($F54),$O54),$F54*N$3,"")
A55: Barrette mémoire de 16GB HPE Standard DDR4-3200 UDIMM | B55: HPE 16GB 1Rx8 PC4-3200AA-E STND Kit | C55: P43019-B21 | D55: 1 | H55: =IF(AND(ISNUMBER($F55),$O55),$F55*H$3,"") | I55: =IF(AND(ISNUMBER($F55),$O55),$F55*I$3,"") | J55: =IF(AND(ISNUMBER($F55),$O55),$F55*J$3,"") | K55: =IF(AND(ISNUMBER($F55),$O55),$F55*K$3,"") | L55: =IF(AND(ISNUMBER($F55),$O55),$F55*L$3,"") | M55: =IF(AND(ISNUMBER($F55),$O55),$F55*M$3,"") | N55: =IF(AND(ISNUMBER($F55),$O55),$F55*N$3,"")
A56: Alimentation Titanium 800W | B56: HPE 800W FS Ti Ht Plg LH Pwr Sply Kit | C56: 865438-B21 | D56: 1 | H56: =IF(AND(ISNUMBER($F56),$O56),$F56*H$3,"") | I56: =IF(AND(ISNUMBER($F56),$O56),$F56*I$3,"") | J56: =IF(AND(ISNUMBER($F56),$O56),$F56*J$3,"") | K56: =IF(AND(ISNUMBER($F56),$O56),$F56*K$3,"") | L56: =IF(AND(ISNUMBER($F56),$O56),$F56*L$3,"") | M56: =IF(AND(ISNUMBER($F56),$O56),$F56*M$3,"") | N56: =IF(AND(ISNUMBER($F56),$O56),$F56*N$3,"")
A57: Licence iLO en version Advanced avec toutes les options activées | B57: HPE iLO Adv 1-svr Lic 1yr Support | C57: 512485-B21 | D57: 1 | H57: =IF(AND(ISNUMBER($F57),$O57),$F57*H$3,"") | I57: =IF(AND(ISNUMBER($F57),$O57),$F57*I$3,"") | J57: =IF(AND(ISNUMBER($F57),$O57),$F57*J$3,"") | K57: =IF(AND(ISNUMBER($F57),$O57),$F57*K$3,"") | L57: =IF(AND(ISNUMBER($F57),$O57),$F57*L$3,"") | M57: =IF(AND(ISNUMBER($F57),$O57),$F57*M$3,"") | N57: =IF(AND(ISNUMBER($F57),$O57),$F57*N$3,"")
A58: Outil d'administration | B58: HPE GreenLake COM En 5y Up ProLiant aaS | C58: R7A12AAE | D58: 1 | H58: =IF(AND(ISNUMBER($F58),$O58),$F58*H$3,"") | I58: =IF(AND(ISNUMBER($F58),$O58),$F58*I$3,"") | J58: =IF(AND(ISNUMBER($F58),$O58),$F58*J$3,"") | K58: =IF(AND(ISNUMBER($F58),$O58),$F58*K$3,"") | L58: =IF(AND(ISNUMBER($F58),$O58),$F58*L$3,"") | M58: =IF(AND(ISNUMBER($F58),$O58),$F58*M$3,"") | N58: =IF(AND(ISNUMBER($F58),$O58),$F58*N$3,"")
A59: Kit d'Alimentation redondante | B59: HPE ML30 Gen10+ 4U RPS Enable Kit | C59: P45209-B21 | D59: 1 | H59: =IF(AND(ISNUMBER($F59),$O59),$F59*H$3,"") | I59: =IF(AND(ISNUMBER($F59),$O59),$F59*I$3,"") | J59: =IF(AND(ISNUMBER($F59),$O59),$F59*J$3,"") | K59: =IF(AND(ISNUMBER($F59),$O59),$F59*K$3,"") | L59: =IF(AND(ISNUMBER($F59),$O59),$F59*L$3,"") | M59: =IF(AND(ISNUMBER($F59),$O59),$F59*M$3,"") | N59: =IF(AND(ISNUMBER($F59),$O59),$F59*N$3,"")
A60: Kit Ventilateur | B60: HPE ML30 Gen10 PCI Fan and Baffle Kit | C60: P06303-B21 | D60: 1 | H60: =IF(AND(ISNUMBER($F60),$O60),$F60*H$3,"") | I60: =IF(AND(ISNUMBER($F60),$O60),$F60*I$3,"") | J60: =IF(AND(ISNUMBER($F60),$O60),$F60*J$3,"") | K60: =IF(AND(ISNUMBER($F60),$O60),$F60*K$3,"") | L60: =IF(AND(ISNUMBER($F60),$O60),$F60*L$3,"") | M60: =IF(AND(ISNUMBER($F60),$O60),$F60*M$3,"") | N60: =IF(AND(ISNUMBER($F60),$O60),$F60*N$3,"")
A61: Suppression des câbles électriques par défaut | B61: HPE Remove Standard Power Cords | C61: 469774-409 | D61: 1 | H61: =IF(AND(ISNUMBER($F61),$O61),$F61*H$3,"") | I61: =IF(AND(ISNUMBER($F61),$O61),$F61*I$3,"") | J61: =IF(AND(ISNUMBER($F61),$O61),$F61*J$3,"") | K61: =IF(AND(ISNUMBER($F61),$O61),$F61*K$3,"") | L61: =IF(AND(ISNUMBER($F61),$O61),$F61*L$3,"") | M61: =IF(AND(ISNUMBER($F61),$O61),$F61*M$3,"") | N61: =IF(AND(ISNUMBER($F61),$O61),$F61*N$3,"")
A62: Livraison devant la porte | B62: HPE Door/dock Small Delivery SVC | C62: AC111A | D62: 1 | H62: =IF(AND(ISNUMBER($F62),$O62),$F62*H$3,"") | I62: =IF(AND(ISNUMBER($F62),$O62),$F62*I$3,"") | J62: =IF(AND(ISNUMBER($F62),$O62),$F62*J$3,"") | K62: =IF(AND(ISNUMBER($F62),$O62),$F62*K$3,"") | L62: =IF(AND(ISNUMBER($F62),$O62),$F62*L$3,"") | M62: =IF(AND(ISNUMBER($F62),$O62),$F62*M$3,"") | N62: =IF(AND(ISNUMBER($F62),$O62),$F62*N$3,"")
A63: Support 5 ans H+4 ILO | B63: HPE 5Y TC Ess iLO Adv Non BL SVC | C63: HW2P1E | D63: 1 | H63: =IF(AND(ISNUMBER($F63),$O63),$F63*H$3,"") | I63: =IF(AND(ISNUMBER($F63),$O63),$F63*I$3,"") | J63: =IF(AND(ISNUMBER($F63),$O63),$F63*J$3,"") | K63: =IF(AND(ISNUMBER($F63),$O63),$F63*K$3,"") | L63: =IF(AND(ISNUMBER($F63),$O63),$F63*L$3,"") | M63: =IF(AND(ISNUMBER($F63),$O63),$F63*M$3,"") | N63: =IF(AND(ISNUMBER($F63),$O63),$F63*N$3,"")
A64: Garantie 5 ans J+1 châssis | B64: HPE 5Y TC Bas ML30 Gen10 Plus SVC | C64: HS8G6E | D64: 1 | H64: =IF(AND(ISNUMBER($F64),$O64),$F64*H$3,"") | I64: =IF(AND(ISNUMBER($F64),$O64),$F64*I$3,"") | J64: =IF(AND(ISNUMBER($F64),$O64),$F64*J$3,"") | K64: =IF(AND(ISNUMBER($F64),$O64),$F64*K$3,"") | L64: =IF(AND(ISNUMBER($F64),$O64),$F64*L$3,"") | M64: =IF(AND(ISNUMBER($F64),$O64),$F64*M$3,"") | N64: =IF(AND(ISNUMBER($F64),$O64),$F64*N$3,"")
H65: =IF(AND(ISNUMBER($F65),$O65),$F65*H$3,"") | I65: =IF(AND(ISNUMBER($F65),$O65),$F65*I$3,"") | J65: =IF(AND(ISNUMBER($F65),$O65),$F65*J$3,"") | K65: =IF(AND(ISNUMBER($F65),$O65),$F65*K$3,"") | L65: =IF(AND(ISNUMBER($F65),$O65),$F65*L$3,"") | M65: =IF(AND(ISNUMBER($F65),$O65),$F65*M$3,"") | N65: =IF(AND(ISNUMBER($F65),$O65),$F65*N$3,"")
A66: Cat1 Conf7 DL160 Gen10 | B66: HPE ProLiant DL160 Gen10 | C66: 878973-B21 | F66: 872.07 | H66: =IF(AND(ISNUMBER($F66),$O66),$F66*H$3,"") -> 307.49188 | I66: =IF(AND(ISNUMBER($F66),$O66),$F66*I$3,"") -> 307.49188 | J66: =IF(AND(ISNUMBER($F66),$O66),$F66*J$3,"") -> 404.03003 | K66: =IF(AND(ISNUMBER($F66),$O66),$F66*K$3,"") -> 280.67573 | L66: =IF(AND(ISNUMBER($F66),$O66),$F66*L$3,"") -> 446.042 | M66: =IF(AND(ISNUMBER($F66),$O66),$F66*M$3,"") -> 384.36485 | N66: =IF(AND(ISNUMBER($F66),$O66),$F66*N$3,"") -> 431.74006 | O66: TRUE
A67: Serveur rack 1U évolutif bi-socket INTEL DL160 Gen10 | B67: HPE DL160 Gen10 8SFF CTO Server | C67: 878973-B21 | D67: 1 | H67: =IF(AND(ISNUMBER($F67),$O67),$F67*H$3,"") | I67: =IF(AND(ISNUMBER($F67),$O67),$F67*I$3,"") | J67: =IF(AND(ISNUMBER($F67),$O67),$F67*J$3,"") | K67: =IF(AND(ISNUMBER($F67),$O67),$F67*K$3,"") | L67: =IF(AND(ISNUMBER($F67),$O67),$F67*L$3,"") | M67: =IF(AND(ISNUMBER($F67),$O67),$F67*M$3,"") | N67: =IF(AND(ISNUMBER($F67),$O67),$F67*N$3,"")
A68: Processeur 64 bits Intel Xeon Silver 4210R (2,40 GHz de base / 3,20 Ghz Turbo / 10 cœurs / 20 threads / 13,75 Mo Smart Cache / 100W TDP) | B68: Intel Xeon-S 4210R FIO Kit for DL160 G10 | C68: P21191-L21 | D68: 1 | H68: =IF(AND(ISNUMBER($F68),$O68),$F68*H$3,"") | I68: =IF(AND(ISNUMBER($F68),$O68),$F68*I$3,"") | J68: =IF(AND(ISNUMBER($F68),$O68),$F68*J$3,"") | K68: =IF(AND(ISNUMBER($F68),$O68),$F68*K$3,"") | L68: =IF(AND(ISNUMBER($F68),$O68),$F68*L$3,"") | M68: =IF(AND(ISNUMBER($F68),$O68),$F68*M$3,"") | N68: =IF(AND(ISNUMBER($F68),$O68),$F68*N$3,"")
A69: Barrette mémoire de 32GB HPE DDR4-2933 RDIMM | B69: HPE 32GB 2Rx4 PC4-2933Y-R Smart Kit | C69: P00924-B21 | D69: 2 | H69: =IF(AND(ISNUMBER($F69),$O69),$F69*H$3,"") | I69: =IF(AND(ISNUMBER($F69),$O69),$F69*I$3,"") | J69: =IF(AND(ISNUMBER($F69),$O69),$F69*J$3,"") | K69: =IF(AND(ISNUMBER($F69),$O69),$F69*K$3,"") | L69: =IF(AND(ISNUMBER($F69),$O69),$F69*L$3,"") | M69: =IF(AND(ISNUMBER($F69),$O69),$F69*M$3,"") | N69: =IF(AND(ISNUMBER($F69),$O69),$F69*N$3,"")
A70: 2 ports Ethernet 10Gb BASE-T | B70: HPE Eth 10Gb 2p 568T Mmt Adptr | C70: 866470-B21 | D70: 1 | H70: =IF(AND(ISNUMBER($F70),$O70),$F70*H$3,"") | I70: =IF(AND(ISNUMBER($F70),$O70),$F70*I$3,"") | J70: =IF(AND(ISNUMBER($F70),$O70),$F70*J$3,"") | K70: =IF(AND(ISNUMBER($F70),$O70),$F70*K$3,"") | L70: =IF(AND(ISNUMBER($F70),$O70),$F70*L$3,"") | M70: =IF(AND(ISNUMBER($F70),$O70),$F70*M$3,"") | N70: =IF(AND(ISNUMBER($F70),$O70),$F70*N$3,"")
A71: Alimentation Titanium 800W | B71: HPE 800W FS Ti Ht Plg LH Pwr Sply Kit | C71: 865438-B21 | D71: 1 | H71: =IF(AND(ISNUMBER($F71),$O71),$F71*H$3,"") | I71: =IF(AND(ISNUMBER($F71),$O71),$F71*I$3,"") | J71: =IF(AND(ISNUMBER($F71),$O71),$F71*J$3,"") | K71: =IF(AND(ISNUMBER($F71),$O71),$F71*K$3,"") | L71: =IF(AND(ISNUMBER($F71),$O71),$F71*L$3,"") | M71: =IF(AND(ISNUMBER($F71),$O71),$F71*M$3,"") | N71: =IF(AND(ISNUMBER($F71),$O71),$F71*N$3,"")
A72: Licence iLO en version Advanced avec toutes les options activées | B72: HPE iLO Adv 1-svr Lic 1yr Support | C72: 512485-B21 | D72: 1 | H72: =IF(AND(ISNUMBER($F72),$O72),$F72*H$3,"") | I72: =IF(AND(ISNUMBER($F72),$O72),$F72*I$3,"") | J72: =IF(AND(ISNUMBER($F72),$O72),$F72*J$3,"") | K72: =IF(AND(ISNUMBER($F72),$O72),$F72*K$3,"") | L72: =IF(AND(ISNUMBER($F72),$O72),$F72*L$3,"") | M72: =IF(AND(ISNUMBER($F72),$O72),$F72*M$3,"") | N72: =IF(AND(ISNUMBER($F72),$O72),$F72*N$3,"")
A73: Cable SATA | B73: HPE DL160 G10 8SFF Emb SATA FIO Cbl Kit | C73: 866446-B21 | D73: 1 | H73: =IF(AND(ISNUMBER($F73),$O73),$F73*H$3,"") | I73: =IF(AND(ISNUMBER($F73),$O73),$F73*I$3,"") | J73: =IF(AND(ISNUMBER($F73),$O73),$F73*J$3,"") | K73: =IF(AND(ISNUMBER($F73),$O73),$F73*K$3,"") | L73: =IF(AND(ISNUMBER($F73),$O73),$F73*L$3,"") | M73: =IF(AND(ISNUMBER($F73),$O73),$F73*M$3,"") | N73: =IF(AND(ISNUMBER($F73),$O73),$F73*N$3,"")
A74: Kit d'Alimentation redondante | B74: HPE DL160/180 Gen10 RPS Enablement Kit | C74: 866442-B21 | D74: 1 | H74: =IF(AND(ISNUMBER($F74),$O74),$F74*H$3,"") | I74: =IF(AND(ISNUMBER($F74),$O74),$F74*I$3,"") | J74: =IF(AND(ISNUMBER($F74),$O74),$F74*J$3,"") | K74: =IF(AND(ISNUMBER($F74),$O74),$F74*K$3,"") | L74: =IF(AND(ISNUMBER($F74),$O74),$F74*L$3,"") | M74: =IF(AND(ISNUMBER($F74),$O74),$F74*M$3,"") | N74: =IF(AND(ISNUMBER($F74),$O74),$F74*N$3,"")
A75: 1 kit de rail pour rack | B75: HPE 1U SFF Easy Install Rail Kit | C75: 734807-B21 | D75: 1 | H75: =IF(AND(ISNUMBER($F75),$O75),$F75*H$3,"") | I75: =IF(AND(ISNUMBER($F75),$O75),$F75*I$3,"") | J75: =IF(AND(ISNUMBER($F75),$O75),$F75*J$3,"") | K75: =IF(AND(ISNUMBER($F75),$O75),$F75*K$3,"") | L75: =IF(AND(ISNUMBER($F75),$O75),$F75*L$3,"") | M75: =IF(AND(ISNUMBER($F75),$O75),$F75*M$3,"") | N75: =IF(AND(ISNUMBER($F75),$O75),$F75*N$3,"")
A76: Suppression des câbles électriques par défaut | B76: HPE Remove Standard Power Cords | C76: 469774-409 | D76: 1 | H76: =IF(AND(ISNUMBER($F76),$O76),$F76*H$3,"") | I76: =IF(AND(ISNUMBER($F76),$O76),$F76*I$3,"") | J76: =IF(AND(ISNUMBER($F76),$O76),$F76*J$3,"") | K76: =IF(AND(ISNUMBER($F76),$O76),$F76*K$3,"") | L76: =IF(AND(ISNUMBER($F76),$O76),$F76*L$3,"") | M76: =IF(AND(ISNUMBER($F76),$O76),$F76*M$3,"") | N76: =IF(AND(ISNUMBER($F76),$O76),$F76*N$3,"")
A77: Livraison devant la porte | B77: HPE Door/dock Small Delivery SVC | C77: AC111A | D77: 1 | H77: =IF(AND(ISNUMBER($F77),$O77),$F77*H$3,"") | I77: =IF(AND(ISNUMBER($F77),$O77),$F77*I$3,"") | J77: =IF(AND(ISNUMBER($F77),$O77),$F77*J$3,"") | K77: =IF(AND(ISNUMBER($F77),$O77),$F77*K$3,"") | L77: =IF(AND(ISNUMBER($F77),$O77),$F77*L$3,"") | M77: =IF(AND(ISNUMBER($F77),$O77),$F77*M$3,"") | N77: =IF(AND(ISNUMBER($F77),$O77),$F77*N$3,"")
A78: Support 5 ans H+4 ILO | B78: HPE 5Y TC Ess iLO Adv Non BL SVC | C78: HW2P1E | D78: 1 | H78: =IF(AND(ISNUMBER($F78),$O78),$F78*H$3,"") | I78: =IF(AND(ISNUMBER($F78),$O78),$F78*I$3,"") | J78: =IF(AND(ISNUMBER($F78),$O78),$F78*J$3,"") | K78: =IF(AND(ISNUMBER($F78),$O78),$F78*K$3,"") | L78: =IF(AND(ISNUMBER($F78),$O78),$F78*L$3,"") | M78: =IF(AND(ISNUMBER($F78),$O78),$F78*M$3,"") | N78: =IF(AND(ISNUMBER($F78),$O78),$F78*N$3,"")
A79: Garantie 5 ans J+1 châssis | B79: HPE 5Y TC Bas DL160 Gen10 SVC | C79: HV6T5E | D79: 1 | H79: =IF(AND(ISNUMBER($F79),$O79),$F79*H$3,"") | I79: =IF(AND(ISNUMBER($F79),$O79),$F79*I$3,"") | J79: =IF(AND(ISNUMBER($F79),$O79),$F79*J$3,"") | K79: =IF(AND(ISNUMBER($F79),$O79),$F79*K$3,"") | L79: =IF(AND(ISNUMBER($F79),$O79),$F79*L$3,"") | M79: =IF(AND(ISNUMBER($F79),$O79),$F79*M$3,"") | N79: =IF(AND(ISNUMBER($F79),$O79),$F79*N$3,"")
H80: =IF(AND(ISNUMBER($F80),$O80),$F80*H$3,"") | I80: =IF(AND(ISNUMBER($F80),$O80),$F80*I$3,"") | J80: =IF(AND(ISNUMBER($F80),$O80),$F80*J$3,"") | K80: =IF(AND(ISNUMBER($F80),$O80),$F80*K$3,"") | L80: =IF(AND(ISNUMBER($F80),$O80),$F80*L$3,"") | M80: =IF(AND(ISNUMBER($F80),$O80),$F80*M$3,"") | N80: =IF(AND(ISNUMBER($F80),$O80),$F80*N$3,"")
A81: Cat1 Conf9 DL180 Gen10 Intel | B81: HPE ProLiant DL180 Gen10 | C81: 879517-B21 | F81: 947.04 | H81: =IF(AND(ISNUMBER($F81),$O81),$F81*H$3,"") -> 333.9263 | I81: =IF(AND(ISNUMBER($F81),$O81),$F81*I$3,"") -> 333.9263 | J81: =IF(AND(ISNUMBER($F81),$O81),$F81*J$3,"") -> 438.76363 | K81: =IF(AND(ISNUMBER($F81),$O81),$F81*K$3,"") -> 304.80482 | L81: =IF(AND(ISNUMBER($F81),$O81),$F81*L$3,"") -> 484.38728 | M81: =IF(AND(ISNUMBER($F81),$O81),$F81*M$3,"") -> 417.40788 | N81: =IF(AND(ISNUMBER($F81),$O81),$F81*N$3,"") -> 468.85583 | O81: TRUE
A82: Serveur rack 2U évolutif bi-socket INTEL | B82: HPE DL180 Gen10 8SFF CTO Server | C82: 879517-B21 | D82: 1 | H82: =IF(AND(ISNUMBER($F82),$O82),$F82*H$3,"") | I82: =IF(AND(ISNUMBER($F82),$O82),$F82*I$3,"") | J82: =IF(AND(ISNUMBER($F82),$O82),$F82*J$3,"") | K82: =IF(AND(ISNUMBER($F82),$O82),$F82*K$3,"") | L82: =IF(AND(ISNUMBER($F82),$O82),$F82*L$3,"") | M82: =IF(AND(ISNUMBER($F82),$O82),$F82*M$3,"") | N82: =IF(AND(ISNUMBER($F82),$O82),$F82*N$3,"")
A83: Processeur 64 bits Intel Xeon Silver 4210R (2,40 GHz de base / 3,20 Ghz Turbo / 10 cœurs / 20 threads / 13,75 Mo Smart Cache / 100W TDP) | B83: Intel Xeon-S 4210R FIO Kit for DL180 G10 | C83: P21198-L21 | D83: 1 | H83: =IF(AND(ISNUMBER($F83),$O83),$F83*H$3,"") | I83: =IF(AND(ISNUMBER($F83),$O83),$F83*I$3,"") | J83: =IF(AND(ISNUMBER($F83),$O83),$F83*J$3,"") | K83: =IF(AND(ISNUMBER($F83),$O83),$F83*K$3,"") | L83: =IF(AND(ISNUMBER($F83),$O83),$F83*L$3,"") | M83: =IF(AND(ISNUMBER($F83),$O83),$F83*M$3,"") | N83: =IF(AND(ISNUMBER($F83),$O83),$F83*N$3,"")
A84: Barrette mémoire de 32GB HPE DDR4-2933 RDIMM | B84: HPE 32GB 2Rx4 PC4-2933Y-R Smart Kit | C84: P00924-B21 | D84: 2 | H84: =IF(AND(ISNUMBER($F84),$O84),$F84*H$3,"") | I84: =IF(AND(ISNUMBER($F84),$O84),$F84*I$3,"") | J84: =IF(AND(ISNUMBER($F84),$O84),$F84*J$3,"") | K84: =IF(AND(ISNUMBER($F84),$O84),$F84*K$3,"") | L84: =IF(AND(ISNUMBER($F84),$O84),$F84*L$3,"") | M84: =IF(AND(ISNUMBER($F84),$O84),$F84*M$3,"") | N84: =IF(AND(ISNUMBER($F84),$O84),$F84*N$3,"")
A85: Kit pour emplacement Processeur | B85: HPE DL180 Gen10 CPU1 x8x8x8 Riser Kit | C85: 878484-B21 | D85: 1 | H85: =IF(AND(ISNUMBER($F85),$O85),$F85*H$3,"") | I85: =IF(AND(ISNUMBER($F85),$O85),$F85*I$3,"") | J85: =IF(AND(ISNUMBER($F85),$O85),$F85*J$3,"") | K85: =IF(AND(ISNUMBER($F85),$O85),$F85*K$3,"") | L85: =IF(AND(ISNUMBER($F85),$O85),$F85*L$3,"") | M85: =IF(AND(ISNUMBER($F85),$O85),$F85*M$3,"") | N85: =IF(AND(ISNUMBER($F85),$O85),$F85*N$3,"")
A86: 2 ports Ethernet 10Gb BASE-T | B86: HPE Eth 10Gb 2p 568T Mmt Adptr | C86: 866470-B21 | D86: 1 | H86: =IF(AND(ISNUMBER($F86),$O86),$F86*H$3,"") | I86: =IF(AND(ISNUMBER($F86),$O86),$F86*I$3,"") | J86: =IF(AND(ISNUMBER($F86),$O86),$F86*J$3,"") | K86: =IF(AND(ISNUMBER($F86),$O86),$F86*K$3,"") | L86: =IF(AND(ISNUMBER($F86),$O86),$F86*L$3,"") | M86: =IF(AND(ISNUMBER($F86),$O86),$F86*M$3,"") | N86: =IF(AND(ISNUMBER($F86),$O86),$F86*N$3,"")
A87: Alimentation Titanium 800W | B87: HPE 800W FS Ti Ht Plg LH Pwr Sply Kit | C87: 865438-B21 | D87: 1 | H87: =IF(AND(ISNUMBER($F87),$O87),$F87*H$3,"") | I87: =IF(AND(ISNUMBER($F87),$O87),$F87*I$3,"") | J87: =IF(AND(ISNUMBER($F87),$O87),$F87*J$3,"") | K87: =IF(AND(ISNUMBER($F87),$O87),$F87*K$3,"") | L87: =IF(AND(ISNUMBER($F87),$O87),$F87*L$3,"") | M87: =IF(AND(ISNUMBER($F87),$O87),$F87*M$3,"") | N87: =IF(AND(ISNUMBER($F87),$O87),$F87*N$3,"")
A88: Licence iLO en version Advanced avec toutes les options activées | B88: HPE iLO Adv 1-svr Lic 1yr Support | C88: 512485-B21 | D88: 1 | H88: =IF(AND(ISNUMBER($F88),$O88),$F88*H$3,"") | I88: =IF(AND(ISNUMBER($F88),$O88),$F88*I$3,"") | J88: =IF(AND(ISNUMBER($F88),$O88),$F88*J$3,"") | K88: =IF(AND(ISNUMBER($F88),$O88),$F88*K$3,"") | L88: =IF(AND(ISNUMBER($F88),$O88),$F88*L$3,"") | M88: =IF(AND(ISNUMBER($F88),$O88),$F88*M$3,"") | N88: =IF(AND(ISNUMBER($F88),$O88),$F88*N$3,"")
A89: Cable | B89: HPE DL180 G10 SFF Box3 MB/-p FIO Cbl Kit | C89: 879752-B21 | D89: 1 | H89: =IF(AND(ISNUMBER($F89),$O89),$F89*H$3,"") | I89: =IF(AND(ISNUMBER($F89),$O89),$F89*I$3,"") | J89: =IF(AND(ISNUMBER($F89),$O89),$F89*J$3,"") | K89: =IF(AND(ISNUMBER($F89),$O89),$F89*K$3,"") | L89: =IF(AND(ISNUMBER($F89),$O89),$F89*L$3,"") | M89: =IF(AND(ISNUMBER($F89),$O89),$F89*M$3,"") | N89: =IF(AND(ISNUMBER($F89),$O89),$F89*N$3,"")
A90: Cage pour Alimentation | B90: HPE DL160/180 Gen10 RPS Enablement Kit | C90: 866442-B21 | D90: 1 | H90: =IF(AND(ISNUMBER($F90),$O90),$F90*H$3,"") | I90: =IF(AND(ISNUMBER($F90),$O90),$F90*I$3,"") | J90: =IF(AND(ISNUMBER($F90),$O90),$F90*J$3,"") | K90: =IF(AND(ISNUMBER($F90),$O90),$F90*K$3,"") | L90: =IF(AND(ISNUMBER($F90),$O90),$F90*L$3,"") | M90: =IF(AND(ISNUMBER($F90),$O90),$F90*M$3,"") | N90: =IF(AND(ISNUMBER($F90),$O90),$F90*N$3,"")
A91: Suppression des câbles électriques par défaut | B91: HPE Remove Standard Power Cords | C91: 469774-409 | D91: 1 | H91: =IF(AND(ISNUMBER($F91),$O91),$F91*H$3,"") | I91: =IF(AND(ISNUMBER($F91),$O91),$F91*I$3,"") | J91: =IF(AND(ISNUMBER($F91),$O91),$F91*J$3,"") | K91: =IF(AND(ISNUMBER($F91),$O91),$F91*K$3,"") | L91: =IF(AND(ISNUMBER($F91),$O91),$F91*L$3,"") | M91: =IF(AND(ISNUMBER($F91),$O91),$F91*M$3,"") | N91: =IF(AND(ISNUMBER($F91),$O91),$F91*N$3,"")
A92: 1 kit de rail pour rack | B92: HPE 2U SFF Easy Install Rail Kit | C92: 733660-B21 | D92: 1 | H92: =IF(AND(ISNUMBER($F92),$O92),$F92*H$3,"") | I92: =IF(AND(ISNUMBER($F92),$O92),$F92*I$3,"") | J92: =IF(AND(ISNUMBER($F92),$O92),$F92*J$3,"") | K92: =IF(AND(ISNUMBER($F92),$O92),$F92*K$3,"") | L92: =IF(AND(ISNUMBER($F92),$O92),$F92*L$3,"") | M92: =IF(AND(ISNUMBER($F92),$O92),$F92*M$3,"") | N92: =IF(AND(ISNUMBER($F92),$O92),$F92*N$3,"")
A93: Livraison devant la porte | B93: HPE Door/dock Medium Delivery SVC | C93: AC114A | D93: 1 | H93: =IF(AND(ISNUMBER($F93),$O93),$F93*H$3,"") | I93: =IF(AND(ISNUMBER($F93),$O93),$F93*I$3,"") | J93: =IF(AND(ISNUMBER($F93),$O93),$F93*J$3,"") | K93: =IF(AND(ISNUMBER($F93),$O93),$F93*K$3,"") | L93: =IF(AND(ISNUMBER($F93),$O93),$F93*L$3,"") | M93: =IF(AND(ISNUMBER($F93),$O93),$F93*M$3,"") | N93: =IF(AND(ISNUMBER($F93),$O93),$F93*N$3,"")
... A95: Garantie 5 ans J+1 châssis | B95: HPE 5Y TC Bas DL180 Gen10 SVC | C95: HV6W2E | D95: 1 | H95: =IF(AND(ISNUMBER($F95),$O95),$F95*H$3,"") | I95: =IF(AND(ISNUMBER($F95),$O95),$F95*I$3,"") | J95: =IF(AND(ISNUMBER($F95),$O95),$F95*J$3,"") | K95: =IF(AND(ISNUMBER($F95),$O95),$F95*K$3,"") | L95: =IF(AND(ISNUMBER($F95),$O95),$F95*L$3,"") | M95: =IF(AND(ISNUMBER($F95),$O95),$F95*M$3,"") | N95: =IF(AND(ISNUMBER($F95),$O95),$F95*N$3,"")
H96: =IF(AND(ISNUMBER($F96),$O96),$F96*H$3,"") | I96: =IF(AND(ISNUMBER($F96),$O96),$F96*I$3,"") | J96: =IF(AND(ISNUMBER($F96),$O96),$F96*J$3,"") | K96: =IF(AND(ISNUMBER($F96),$O96),$F96*K$3,"") | L96: =IF(AND(ISNUMBER($F96),$O96),$F96*L$3,"") | M96: =IF(AND(ISNUMBER($F96),$O96),$F96*M$3,"") | N96: =IF(AND(ISNUMBER($F96),$O96),$F96*N$3,"")
A97: Cat1 Conf8 Tour ML350 Gen11 | B97: HPE ProLiant ML350 Gen11 | C97: P48405-B21 | F97: 1672.91 | H97: =IF(AND(ISNUMBER($F97),$O97),$F97*H$3,"") -> 589.86807 | I97: =IF(AND(ISNUMBER($F97),$O97),$F97*I$3,"") -> 589.86807 | J97: =IF(AND(ISNUMBER($F97),$O97),$F97*J$3,"") -> 775.0592 | K97: =IF(AND(ISNUMBER($F97),$O97),$F97*K$3,"") -> 538.42608 | L97: =IF(AND(ISNUMBER($F97),$O97),$F97*L$3,"") -> 855.65164 | M97: =IF(AND(ISNUMBER($F97),$O97),$F97*M$3,"") -> 737.33508 | N97: =IF(AND(ISNUMBER($F97),$O97),$F97*N$3,"") -> 828.21592 | O97: TRUE
A98: Serveur de type tour ML30 Gen10+ | B98: HPE ML350 Gen11 SFF CTO Server | C98: P48405-B21 | D98: 1 | H98: =IF(AND(ISNUMBER($F98),$O98),$F98*H$3,"") | I98: =IF(AND(ISNUMBER($F98),$O98),$F98*I$3,"") | J98: =IF(AND(ISNUMBER($F98),$O98),$F98*J$3,"") | K98: =IF(AND(ISNUMBER($F98),$O98),$F98*K$3,"") | L98: =IF(AND(ISNUMBER($F98),$O98),$F98*L$3,"") | M98: =IF(AND(ISNUMBER($F98),$O98),$F98*M$3,"") | N98: =IF(AND(ISNUMBER($F98),$O98),$F98*N$3,"")
A99: Processeur 64 bits Intel Xeon Silver 4410Y (2,0 GHz de base / 12 cœurs / 150W TDP) | B99: INT Xeon-S 4410Y CPU for HPE | C99: P49610-B21 | D99: 1 | H99: =IF(AND(ISNUMBER($F99),$O99),$F99*H$3,"") | I99: =IF(AND(ISNUMBER($F99),$O99),$F99*I$3,"") | J99: =IF(AND(ISNUMBER($F99),$O99),$F99*J$3,"") | K99: =IF(AND(ISNUMBER($F99),$O99),$F99*K$3,"") | L99: =IF(AND(ISNUMBER($F99),$O99),$F99*L$3,"") | M99: =IF(AND(ISNUMBER($F99),$O99),$F99*M$3,"") | N99: =IF(AND(ISNUMBER($F99),$O99),$F99*N$3,"")
A100: Barrette mémoire de 32GB HPE DDR5-4800 RDIMM | B100: HPE 32GB 2Rx8 PC5-4800B-R Smart Kit | C100: P43328-B21 | D100: 2 | H100: =IF(AND(ISNUMBER($F100),$O100),$F100*H$3,"") | I100: =IF(AND(ISNUMBER($F100),$O100),$F100*I$3,"") | J100: =IF(AND(ISNUMBER($F100),$O100),$F100*J$3,"") | K100: =IF(AND(ISNUMBER($F100),$O100),$F100*K$3,"") | L100: =IF(AND(ISNUMBER($F100),$O100),$F100*L$3,"") | M100: =IF(AND(ISNUMBER($F100),$O100),$F100*M$3,"") | N100: =IF(AND(ISNUMBER($F100),$O100),$F100*N$3,"")
A101: 2 ports Ethernet 10GbE Base-T OCP (intégré) | B101: BCM 57416 10GbE 2p BASE-T OCP3 Adptr | C101: P10097-B21 | D101: 1 | H101: =IF(AND(ISNUMBER($F101),$O101),$F101*H$3,"") | I101: =IF(AND(ISNUMBER($F101),$O101),$F101*I$3,"") | J101: =IF(AND(ISNUMBER($F101),$O101),$F101*J$3,"") | K101: =IF(AND(ISNUMBER($F101),$O101),$F101*K$3,"") | L101: =IF(AND(ISNUMBER($F101),$O101),$F101*L$3,"") | M101: =IF(AND(ISNUMBER($F101),$O101),$F101*M$3,"") | N101: =IF(AND(ISNUMBER($F101),$O101),$F101*N$3,"")
A102: Alimentation Titanium 1000W | B102: HPE 1000W FS Ti Ht Plg PS Kit | C102: P03178-B21 | D102: 1 | H102: =IF(AND(ISNUMBER($F102),$O102),$F102*H$3,"") | I102: =IF(AND(ISNUMBER($F102),$O102),$F102*I$3,"") | J102: =IF(AND(ISNUMBER($F102),$O102),$F102*J$3,"") | K102: =IF(AND(ISNUMBER($F102),$O102),$F102*K$3,"") | L102: =IF(AND(ISNUMBER($F102),$O102),$F102*L$3,"") | M102: =IF(AND(ISNUMBER($F102),$O102),$F102*M$3,"") | N102: =IF(AND(ISNUMBER($F102),$O102),$F102*N$3,"")
A103: Licence iLO en version Advanced avec toutes les options activées | B103: HPE iLO Adv 1-svr Lic 1yr Support | C103: 512485-B21 | D103: 1 | H103: =IF(AND(ISNUMBER($F103),$O103),$F103*H$3,"") | I103: =IF(AND(ISNUMBER($F103),$O103),$F103*I$3,"") | J103: =IF(AND(ISNUMBER($F103),$O103),$F103*J$3,"") | K103: =IF(AND(ISNUMBER($F103),$O103),$F103*K$3,"") | L103: =IF(AND(ISNUMBER($F103),$O103),$F103*L$3,"") | M103: =IF(AND(ISNUMBER($F103),$O103),$F103*M$3,"") | N103: =IF(AND(ISNUMBER($F103),$O103),$F103*N$3,"")
A104: Kit d’activation HPE ProLiant ML350 Gen11 OCP2 | B104: HPE ML350 Gen11 OCP2 Enable Kit | C104: P47231-B21 | D104: 1 | H104: =IF(AND(ISNUMBER($F104),$O104),$F104*H$3,"") | I104: =IF(AND(ISNUMBER($F104),$O104),$F104*I$3,"") | J104: =IF(AND(ISNUMBER($F104),$O104),$F104*J$3,"") | K104: =IF(AND(ISNUMBER($F104),$O104),$F104*K$3,"") | L104: =IF(AND(ISNUMBER($F104),$O104),$F104*L$3,"") | M104: =IF(AND(ISNUMBER($F104),$O104),$F104*M$3,"") | N104: =IF(AND(ISNUMBER($F104),$O104),$F104*N$3,"")
A105: Cable SATA | B105: HPE ML350 Gen11 SFF Emb SATA Cbl Kit | C105: P47232-B21 | D105: 1 | H105: =IF(AND(ISNUMBER($F105),$O105),$F105*H$3,"") | I105: =IF(AND(ISNUMBER($F105),$O105),$F105*I$3,"") | J105: =IF(AND(ISNUMBER($F105),$O105),$F105*J$3,"") | K105: =IF(AND(ISNUMBER($F105),$O105),$F105*K$3,"") | L105: =IF(AND(ISNUMBER($F105),$O105),$F105*L$3,"") | M105: =IF(AND(ISNUMBER($F105),$O105),$F105*M$3,"") | N105: =IF(AND(ISNUMBER($F105),$O105),$F105*N$3,"")
...

Sheet Lot4 - BPU Location
G1: Coefficients en Crédit-Bail | H1: 0.26888624 | I1: 0.13836099 | J1: 0.095025056
A2: Désignation Description des matériels | B2: Référence constructeur (le cas échéant) | C2: HPE SKU | D2: Quantités | E2: Tag | F2: TARIFS en €HT | G2: Références de Location | H2: Crédit Bail 1 An Loyer Trimestriel €HT (4 Trimestres) | I2: Crédit Bail 2 Ans Loyer Trimestriel €HT (8 Trimestres) | J2: Crédit Bail 3 Ans Loyer Trimestriel €HT (12 Trimestres) | K2: Coefficient Locatif 1 An (4 Trimestres) | L2: Loyer Trimestriel 1 An (4 Trimestres) €HT | M2: Coefficient Locatif 2 Ans (8 Trimestres) | N2: Loyer Trimestriel 2 Ans (8 Trimestres) €HT | O2: Coefficient Locatif 3 Ans (12 Trimestres) | P2: Loyer Trimestriel 3 Ans (12 Trimestres) €HT
A3: CATEGORIE 1 : Serveurs Edge ou Standard | H3: =IF(ISNUMBER($F3),ROUND($F3*H$1,2),"") | I3: =IF(ISNUMBER($F3),ROUND($F3*I$1,2),"") | J3: =IF(ISNUMBER($F3),ROUND($F3*J$1,2),"") | K3: =IF(ISNUMBER(F3),IF(G3="",VLOOKUP($A3,'Loc Coefficients Config'!$A:$G,7,FALSE),VLOOKUP(G3,'Loc Coefficients Location'!A:D,4,FALSE)),"") | L3: =IF(ISNUMBER(K3),ROUND($F3*K3,2),"") | M3: =IF(ISNUMBER(F3),IF(G3="",VLOOKUP($A3,'Loc Coefficients Config'!$A:$H,8,FALSE),VLOOKUP(G3,'Loc Coefficients Location'!A:E,5,FALSE)),"") | N3: =IF(ISNUMBER(M3),ROUND($F3*M3,2),"") | O3: =IF(ISNUMBER(F3),IF(G3="",VLOOKUP($A3,'Loc Coefficients Config'!$A:$I,9,FALSE),VLOOKUP(G3,'Loc Coefficients Location'!A:F,6,FALSE)),"") | P3: =IF(ISNUMBER(O3),ROUND($F3*O3,2),"")
A4: Désignation/Description des matériels | B4: Référence constructeur (le cas échéant) | C4: Numéro de référence | D4: Quantités | F4: TARIFS en €HT | H4: =IF(ISNUMBER($F4),ROUND($F4*H$1,2),"") | I4: =IF(ISNUMBER($F4),ROUND($F4*I$1,2),"") | J4: =IF(ISNUMBER($F4),ROUND($F4*J$1,2),"") | K4: =IF(ISNUMBER(F4),IF(G4="",VLOOKUP($A4,'Loc Coefficients Config'!$A:$G,7,FALSE),VLOOKUP(G4,'Loc Coefficients Location'!A:D,4,FALSE)),"") | L4: =IF(ISNUMBER(K4),ROUND($F4*K4,2),"") | M4: =IF(ISNUMBER(F4),IF(G4="",VLOOKUP($A4,'Loc Coefficients Config'!$A:$H,8,FALSE),VLOOKUP(G4,'Loc Coefficients Location'!A:E,5,FALSE)),"") | N4: =IF(ISNUMBER(M4),ROUND($F4*M4,2),"") | O4: =IF(ISNUMBER(F4),IF(G4="",VLOOKUP($A4,'Loc Coefficients Config'!$A:$I,9,FALSE),VLOOKUP(G4,'Loc Coefficients Location'!A:F,6,FALSE)),"") | P4: =IF(ISNUMBER(O4),ROUND($F4*O4,2),"")
H5: =IF(ISNUMBER($F5),ROUND($F5*H$1,2),"") | I5: =IF(ISNUMBER($F5),ROUND($F5*I$1,2),"") | J5: =IF(ISNUMBER($F5),ROUND($F5*J$1,2),"") | K5: =IF(ISNUMBER(F5),IF(G5="",VLOOKUP($A5,'Loc Coefficients Config'!$A:$G,7,FALSE),VLOOKUP(G5,'Loc Coefficients Location'!A:D,4,FALSE)),"") | L5: =IF(ISNUMBER(K5),ROUND($F5*K5,2),"") | M5: =IF(ISNUMBER(F5),IF(G5="",VLOOKUP($A5,'Loc Coefficients Config'!$A:$H,8,FALSE),VLOOKUP(G5,'Loc Coefficients Location'!A:E,5,FALSE)),"") | N5: =IF(ISNUMBER(M5),ROUND($F5*M5,2),"") | O5: =IF(ISNUMBER(F5),IF(G5="",VLOOKUP($A5,'Loc Coefficients Config'!$A:$I,9,FALSE),VLOOKUP(G5,'Loc Coefficients Location'!A:F,6,FALSE)),"") | P5: =IF(ISNUMBER(O5),ROUND($F5*O5,2),"")
A6: Cat1 Conf4 Microserver Gen10 Plus v2 | B6: HPE ProLiant MicroServer Gen10 plus v2 | C6: P54644-421 | F6: 573.47 | H6: =IF(ISNUMBER($F6),ROUND($F6*H$1,2),"") -> 154.2 | I6: =IF(ISNUMBER($F6),ROUND($F6*I$1,2),"") -> 79.35 | J6: =IF(ISNUMBER($F6),ROUND($F6*J$1,2),"") -> 54.49 | K6: =IF(ISNUMBER(F6),IF(G6="",VLOOKUP($A6,'Loc Coefficients Config'!$A:$G,7,FALSE),VLOOKUP(G6,'Loc Coefficients Location'!A:D,4,FALSE)),"") -> 0.19408936 | L6: =IF(ISNUMBER(K6),ROUND($F6*K6,2),"") -> 111.3 | M6: =IF(ISNUMBER(F6),IF(G6="",VLOOKUP($A6,'Loc Coefficients Config'!$A:$H,8,FALSE),VLOOKUP(G6,'Loc Coefficients Location'!A:E,5,FALSE)),"") -> 0.10502487 | N6: =IF(ISNUMBER(M6),ROUND($F6*M6,2),"") -> 60.23 | O6: =IF(ISNUMBER(F6),IF(G6="",VLOOKUP($A6,'Loc Coefficients Config'!$A:$I,9,FALSE),VLOOKUP(G6,'Loc Coefficients Location'!A:F,6,FALSE)),"") -> 0.080002776 | P6: =IF(ISNUMBER(O6),ROUND($F6*O6,2),"") -> 45.88
A7: Serveur tour Ultra Micro mono-socket | B7: HPE ProLiant MicroServer Gen10 Plus v2 G6405 2-core 16GB-U VROC 4LFF-NHP 180W External PS Server | C7: P54644-421 | D7: 1 | G7: PC_SE/PLX86 | H7: =IF(ISNUMBER($F7),ROUND($F7*H$1,2),"") | I7: =IF(ISNUMBER($F7),ROUND($F7*I$1,2),"") | J7: =IF(ISNUMBER($F7),ROUND($F7*J$1,2),"") | K7: =IF(ISNUMBER(F7),IF(G7="",VLOOKUP($A7,'Loc Coefficients Config'!$A:$G,7,FALSE),VLOOKUP(G7,'Loc Coefficients Location'!A:D,4,FALSE)),"") | L7: =IF(ISNUMBER(K7),ROUND($F7*K7,2),"") | M7: =IF(ISNUMBER(F7),IF(G7="",VLOOKUP($A7,'Loc Coefficients Config'!$A:$H,8,FALSE),VLOOKUP(G7,'Loc Coefficients Location'!A:E,5,FALSE)),"") | N7: =IF(ISNUMBER(M7),ROUND($F7*M7,2),"") | O7: =IF(ISNUMBER(F7),IF(G7="",VLOOKUP($A7,'Loc Coefficients Config'!$A:$I,9,FALSE),VLOOKUP(G7,'Loc Coefficients Location'!A:F,6,FALSE)),"") | P7: =IF(ISNUMBER(O7),ROUND($F7*O7,2),"")
A8: 1 disque de 1 To 6G SATA 7.2K 3,5 pouces (LFF) Non Hot Plug | B8: HPE 1TB SATA 6G Business Critical 7.2K LFF RW 1-year Warranty Multi Vendor HDD | C8: 801882-B21 | D8: 1 | G8: PC_SE/PLX86 | H8: =IF(ISNUMBER($F8),ROUND($F8*H$1,2),"") | I8: =IF(ISNUMBER($F8),ROUND($F8*I$1,2),"") | J8: =IF(ISNUMBER($F8),ROUND($F8*J$1,2),"") | K8: =IF(ISNUMBER(F8),IF(G8="",VLOOKUP($A8,'Loc Coefficients Config'!$A:$G,7,FALSE),VLOOKUP(G8,'Loc Coefficients Location'!A:D,4,FALSE)),"") | L8: =IF(ISNUMBER(K8),ROUND($F8*K8,2),"") | M8: =IF(ISNUMBER(F8),IF(G8="",VLOOKUP($A8,'Loc Coefficients Config'!$A:$H,8,FALSE),VLOOKUP(G8,'Loc Coefficients Location'!A:E,5,FALSE)),"") | N8: =IF(ISNUMBER(M8),ROUND($F8*M8,2),"") | O8: =IF(ISNUMBER(F8),IF(G8="",VLOOKUP($A8,'Loc Coefficients Config'!$A:$I,9,FALSE),VLOOKUP(G8,'Loc Coefficients Location'!A:F,6,FALSE)),"") | P8: =IF(ISNUMBER(O8),ROUND($F8*O8,2),"")
A9: Kit pour carte d'administration HPE iLO | B9: HPE MicroServer Gen10 Plus iLO Enablement Kit | C9: P13788-B21 | D9: 1 | G9: PC_SE/PLX86 | H9: =IF(ISNUMBER($F9),ROUND($F9*H$1,2),"") | I9: =IF(ISNUMBER($F9),ROUND($F9*I$1,2),"") | J9: =IF(ISNUMBER($F9),ROUND($F9*J$1,2),"") | K9: =IF(ISNUMBER(F9),IF(G9="",VLOOKUP($A9,'Loc Coefficients Config'!$A:$G,7,FALSE),VLOOKUP(G9,'Loc Coefficients Location'!A:D,4,FALSE)),"") | L9: =IF(ISNUMBER(K9),ROUND($F9*K9,2),"") | M9: =IF(ISNUMBER(F9),IF(G9="",VLOOKUP($A9,'Loc Coefficients Config'!$A:$H,8,FALSE),VLOOKUP(G9,'Loc Coefficients Location'!A:E,5,FALSE)),"") | N9: =IF(ISNUMBER(M9),ROUND($F9*M9,2),"") | O9: =IF(ISNUMBER(F9),IF(G9="",VLOOKUP($A9,'Loc Coefficients Config'!$A:$I,9,FALSE),VLOOKUP(G9,'Loc Coefficients Location'!A:F,6,FALSE)),"") | P9: =IF(ISNUMBER(O9),ROUND($F9*O9,2),"")
A10: Carte d'administration HPE iLO avec API RESTful compatible IPMI v2.0 et Redfish. Licence en version Advanced avec toutes les options activées | B10: HPE iLO Advanced 1-server License with 1yr Support on iLO Licensed Features | C10: 512485-B21 | D10: 1 | G10: SOFTCOST | H10: =IF(ISNUMBER($F10),ROUND($F10*H$1,2),"") | I10: =IF(ISNUMBER($F10),ROUND($F10*I$1,2),"") | J10: =IF(ISNUMBER($F10),ROUND($F10*J$1,2),"") | K10: =IF(ISNUMBER(F10),IF(G10="",VLOOKUP($A10,'Loc Coefficients Config'!$A:$G,7,FALSE),VLOOKUP(G10,'Loc Coefficients Location'!A:D,4,FALSE)),"") | L10: =IF(ISNUMBER(K10),ROUND($F10*K10,2),"") | M10: =IF(ISNUMBER(F10),IF(G10="",VLOOKUP($A10,'Loc Coefficients Config'!$A:$H,8,FALSE),VLOOKUP(G10,'Loc Coefficients Location'!A:E,5,FALSE)),"") | N10: =IF(ISNUMBER(M10),ROUND($F10*M10,2),"") | O10: =IF(ISNUMBER(F10),IF(G10="",VLOOKUP($A10,'Loc Coefficients Config'!$A:$I,9,FALSE),VLOOKUP(G10,'Loc Coefficients Location'!A:F,6,FALSE)),"") | P10: =IF(ISNUMBER(O10),ROUND($F10*O10,2),"")
A11: Livraison devant la porte | B11: Livraison devant la porte | C11: AC114A | D11: 1 | G11: SOFTCOST | H11: =IF(ISNUMBER($F11),ROUND($F11*H$1,2),"") | I11: =IF(ISNUMBER($F11),ROUND($F11*I$1,2),"") | J11: =IF(ISNUMBER($F11),ROUND($F11*J$1,2),"") | K11: =IF(ISNUMBER(F11),IF(G11="",VLOOKUP($A11,'Loc Coefficients Config'!$A:$G,7,FALSE),VLOOKUP(G11,'Loc Coefficients Location'!A:D,4,FALSE)),"") | L11: =IF(ISNUMBER(K11),ROUND($F11*K11,2),"") | M11: =IF(ISNUMBER(F11),IF(G11="",VLOOKUP($A11,'Loc Coefficients Config'!$A:$H,8,FALSE),VLOOKUP(G11,'Loc Coefficients Location'!A:E,5,FALSE)),"") | N11: =IF(ISNUMBER(M11),ROUND($F11*M11,2),"") | O11: =IF(ISNUMBER(F11),IF(G11="",VLOOKUP($A11,'Loc Coefficients Config'!$A:$I,9,FALSE),VLOOKUP(G11,'Loc Coefficients Location'!A:F,6,FALSE)),"") | P11: =IF(ISNUMBER(O11),ROUND($F11*O11,2),"")
A12: Garantie 5 ans J+1 | B12: HPE 5 Year Tech Care Basic Service | C12: HU4B2A5 | D12: 1 | G12: SOFT/MAINT | H12: =IF(ISNUMBER($F12),ROUND($F12*H$1,2),"") | I12: =IF(ISNUMBER($F12),ROUND($F12*I$1,2),"") | J12: =IF(ISNUMBER($F12),ROUND($F12*J$1,2),"") | K12: =IF(ISNUMBER(F12),IF(G12="",VLOOKUP($A12,'Loc Coefficients Config'!$A:$G,7,FALSE),VLOOKUP(G12,'Loc Coefficients Location'!A:D,4,FALSE)),"") | L12: =IF(ISNUMBER(K12),ROUND($F12*K12,2),"") | M12: =IF(ISNUMBER(F12),IF(G12="",VLOOKUP($A12,'Loc Coefficients Config'!$A:$H,8,FALSE),VLOOKUP(G12,'Loc Coefficients Location'!A:E,5,FALSE)),"") | N12: =IF(ISNUMBER(M12),ROUND($F12*M12,2),"") | O12: =IF(ISNUMBER(F12),IF(G12="",VLOOKUP($A12,'Loc Coefficients Config'!$A:$I,9,FALSE),VLOOKUP(G12,'Loc Coefficients Location'!A:F,6,FALSE)),"") | P12: =IF(ISNUMBER(O12),ROUND($F12*O12,2),"")
A13: Garantie 5 ans H+4 ILO | B13: HPE 5 Year Tech Care Essential iLO Advance Non Blade Service | C13: HU4B2A5#7X4 | D13: 1 | G13: SOFT/MAINT | H13: =IF(ISNUMBER($F13),ROUND($F13*H$1,2),"") | I13: =IF(ISNUMBER($F13),ROUND($F13*I$1,2),"") | J13: =IF(ISNUMBER($F13),ROUND($F13*J$1,2),"") | K13: =IF(ISNUMBER(F13),IF(G13="",VLOOKUP($A13,'Loc Coefficients Config'!$A:$G,7,FALSE),VLOOKUP(G13,'Loc Coefficients Location'!A:D,4,FALSE)),"") | L13: =IF(ISNUMBER(K13),ROUND($F13*K13,2),"") | M13: =IF(ISNUMBER(F13),IF(G13="",VLOOKUP($A13,'Loc Coefficients Config'!$A:$H,8,FALSE),VLOOKUP(G13,'Loc Coefficients Location'!A:E,5,FALSE)),"") | N13: =IF(ISNUMBER(M13),ROUND($F13*M13,2),"") | O13: =IF(ISNUMBER(F13),IF(G13="",VLOOKUP($A13,'Loc Coefficients Config'!$A:$I,9,FALSE),VLOOKUP(G13,'Loc Coefficients Location'!A:F,6,FALSE)),"") | P13: =IF(ISNUMBER(O13),ROUND($F13*O13,2),"")
A14: Garantie 5 ans J+1 châssis | B14: HPE Microserver Gen10 Plus Support | C14: HU4B2A5#YKX | D14: 1 | G14: SOFT/MAINT | H14: =IF(ISNUMBER($F14),ROUND($F14*H$1,2),"") | I14: =IF(ISNUMBER($F14),ROUND($F14*I$1,2),"") | J14: =IF(ISNUMBER($F14),ROUND($F14*J$1,2),"") | K14: =IF(ISNUMBER(F14),IF(G14="",VLOOKUP($A14,'Loc Coefficients Config'!$A:$G,7,FALSE),VLOOKUP(G14,'Loc Coefficients Location'!A:D,4,FALSE)),"") | L14: =IF(ISNUMBER(K14),ROUND($F14*K14,2),"") | M14: =IF(ISNUMBER(F14),IF(G14="",VLOOKUP($A14,'Loc Coefficients Config'!$A:$H,8,FALSE),VLOOKUP(G14,'Loc Coefficients Location'!A:E,5,FALSE)),"") | N14: =IF(ISNUMBER(M14),ROUND($F14*M14,2),"") | O14: =IF(ISNUMBER(F14),IF(G14="",VLOOKUP($A14,'Loc Coefficients Config'!$A:$I,9,FALSE),VLOOKUP(G14,'Loc Coefficients Location'!A:F,6,FALSE)),"") | P14: =IF(ISNUMBER(O14),ROUND($F14*O14,2),"")
H15: =IF(ISNUMBER($F15),ROUND($F15*H$1,2),"") | I15: =IF(ISNUMBER($F15),ROUND($F15*I$1,2),"") | J15: =IF(ISNUMBER($F15),ROUND($F15*J$1,2),"") | K15: =IF(ISNUMBER(F15),IF(G15="",VLOOKUP($A15,'Loc Coefficients Config'!$A:$G,7,FALSE),VLOOKUP(G15,'Loc Coefficients Location'!A:D,4,FALSE)),"") | L15: =IF(ISNUMBER(K15),ROUND($F15*K15,2),"") | M15: =IF(ISNUMBER(F15),IF(G15="",VLOOKUP($A15,'Loc Coefficients Config'!$A:$H,8,FALSE),VLOOKUP(G15,'Loc Coefficients Location'!A:E,5,FALSE)),"") | N15: =IF(ISNUMBER(M15),ROUND($F15*M15,2),"") | O15: =IF(ISNUMBER(F15),IF(G15="",VLOOKUP($A15,'Loc Coefficients Config'!$A:$I,9,FALSE),VLOOKUP(G15,'Loc Coefficients Location'!A:F,6,FALSE)),"") | P15: =IF(ISNUMBER(O15),ROUND($F15*O15,2),"")
A16: Cat1 Conf5 DL20 Gen10 plus | B16: HPE ProLiant DL20 Gen10 plus | C16: P44109-B21 | F16: 310.47 | H16: =IF(ISNUMBER($F16),ROUND($F16*H$1,2),"") -> 83.48 | I16: =IF(ISNUMBER($F16),ROUND($F16*I$1,2),"") -> 42.96 | J16: =IF(ISNUMBER($F16),ROUND($F16*J$1,2),"") -> 29.5 | K16: =IF(ISNUMBER(F16),IF(G16="",VLOOKUP($A16,'Loc Coefficients Config'!$A:$G,7,FALSE),VLOOKUP(G16,'Loc Coefficients Location'!A:D,4,FALSE)),"") -> 0.21791781 | L16: =IF(ISNUMBER(K16),ROUND($F16*K16,2),"") -> 67.66 | M16: =IF(ISNUMBER(F16),IF(G16="",VLOOKUP($A16,'Loc Coefficients Config'!$A:$H,8,FALSE),VLOOKUP(G16,'Loc Coefficients Location'!A:E,5,FALSE)),"") -> 0.11564498 | N16: =IF(ISNUMBER(M16),ROUND($F16*M16,2),"") -> 35.9 | O16: =IF(ISNUMBER(F16),IF(G16="",VLOOKUP($A16,'Loc Coefficients Config'!$A:$I,9,FALSE),VLOOKUP(G16,'Loc Coefficients Location'!A:F,6,FALSE)),"") -> 0.084788504 | P16: =IF(ISNUMBER(O16),ROUND($F16*O16,2),"") -> 26.32
A17: Serveur rack standard 1U DL20 Gen10+ mono-socket INTEL | B17: HPE DL20 Gen10+ 2LFF NHP CTO Svr | C17: P44109-B21 | D17: 1 | G17: PC_SE/PLX86 | H17: =IF(ISNUMBER($F17),ROUND($F17*H$1,2),"") | I17: =IF(ISNUMBER($F17),ROUND($F17*I$1,2),"") | J17: =IF(ISNUMBER($F17),ROUND($F17*J$1,2),"") | K17: =IF(ISNUMBER(F17),IF(G17="",VLOOKUP($A17,'Loc Coefficients Config'!$A:$G,7,FALSE),VLOOKUP(G17,'Loc Coefficients Location'!A:D,4,FALSE)),"") | L17: =IF(ISNUMBER(K17),ROUND($F17*K17,2),"") | M17: =IF(ISNUMBER(F17),IF(G17="",VLOOKUP($A17,'Loc Coefficients Config'!$A:$H,8,FALSE),VLOOKUP(G17,'Loc Coefficients Location'!A:E,5,FALSE)),"") | N17: =IF(ISNUMBER(M17),ROUND($F17*M17,2),"") | O17: =IF(ISNUMBER(F17),IF(G17="",VLOOKUP($A17,'Loc Coefficients Config'!$A:$I,9,FALSE),VLOOKUP(G17,'Loc Coefficients Location'!A:F,6,FALSE)),"") | P17: =IF(ISNUMBER(O17),ROUND($F17*O17,2),"")
A18: Processeur 64 bits Intel Xeon E-2314 (2,8 GHz de base / 4,50 Ghz Turbo / 4 cœurs / 4 threads / 8 Mo Smart Cache / 65W TDP) | B18: Intel Xeon E-2314 FIO CPU for HPE | C18: P45248-B21 | D18: 1 | G18: PC_SE/PLX86 | H18: =IF(ISNUMBER($F18),ROUND($F18*H$1,2),"") | I18: =IF(ISNUMBER($F18),ROUND($F18*I$1,2),"") | J18: =IF(ISNUMBER($F18),ROUND($F18*J$1,2),"") | K18: =IF(ISNUMBER(F18),IF(G18="",VLOOKUP($A18,'Loc Coefficients Config'!$A:$G,7,FALSE),VLOOKUP(G18,'Loc Coefficients Location'!A:D,4,FALSE)),"") | L18: =IF(ISNUMBER(K18),ROUND($F18*K18,2),"") | M18: =IF(ISNUMBER(F18),IF(G18="",VLOOKUP($A18,'Loc Coefficients Config'!$A:$H,8,FALSE),VLOOKUP(G18,'Loc Coefficients Location'!A:E,5,FALSE)),"") | N18: =IF(ISNUMBER(M18),ROUND($F18*M18,2),"") | O18: =IF(ISNUMBER(F18),IF(G18="",VLOOKUP($A18,'Loc Coefficients Config'!$A:$I,9,FALSE),VLOOKUP(G18,'Loc Coefficients Location'!A:F,6,FALSE)),"") | P18: =IF(ISNUMBER(O18),ROUND($F18*O18,2),"")
A19: Barrette mémoire de 16GB HPE Standard DDR4-3200 UDIMM | B19: HPE 16GB 1Rx8 PC4-3200AA-E STND Kit | C19: P43019-B21 | D19: 1 | G19: PC_SE/PLX86 | H19: =IF(ISNUMBER($F19),ROUND($F19*H$1,2),"") | I19: =IF(ISNUMBER($F19),ROUND($F19*I$1,2),"") | J19: =IF(ISNUMBER($F19),ROUND($F19*J$1,2),"") | K19: =IF(ISNUMBER(F19),IF(G19="",VLOOKUP($A19,'Loc Coefficients Config'!$A:$G,7,FALSE),VLOOKUP(G19,'Loc Coefficients Location'!A:D,4,FALSE)),"") | L19: =IF(ISNUMBER(K19),ROUND($F19*K19,2),"") | M19: =IF(ISNUMBER(F19),IF(G19="",VLOOKUP($A19,'Loc Coefficients Config'!$A:$H,8,FALSE),VLOOKUP(G19,'Loc Coefficients Location'!A:E,5,FALSE)),"") | N19: =IF(ISNUMBER(M19),ROUND($F19*M19,2),"") | O19: =IF(ISNUMBER(F19),IF(G19="",VLOOKUP($A19,'Loc Coefficients Config'!$A:$I,9,FALSE),VLOOKUP(G19,'Loc Coefficients Location'!A:F,6,FALSE)),"") | P19: =IF(ISNUMBER(O19),ROUND($F19*O19,2),"")
A20: 1 cage pour emplacement PCI | B20: HPE DL20 Gen10+ 2x8 LP FIO Riser Kit | C20: P46114-B21 | D20: 1 | G20: PC_SE/PLX86 | H20: =IF(ISNUMBER($F20),ROUND($F20*H$1,2),"") | I20: =IF(ISNUMBER($F20),ROUND($F20*I$1,2),"") | J20: =IF(ISNUMBER($F20),ROUND($F20*J$1,2),"") | K20: =IF(ISNUMBER(F20),IF(G20="",VLOOKUP($A20,'Loc Coefficients Config'!$A:$G,7,FALSE),VLOOKUP(G20,'Loc Coefficients Location'!A:D,4,FALSE)),"") | L20: =IF(ISNUMBER(K20),ROUND($F20*K20,2),"") | M20: =IF(ISNUMBER(F20),IF(G20="",VLOOKUP($A20,'Loc Coefficients Config'!$A:$H,8,FALSE),VLOOKUP(G20,'Loc Coefficients Location'!A:E,5,FALSE)),"") | N20: =IF(ISNUMBER(M20),ROUND($F20*M20,2),"") | O20: =IF(ISNUMBER(F20),IF(G20="",VLOOKUP($A20,'Loc Coefficients Config'!$A:$I,9,FALSE),VLOOKUP(G20,'Loc Coefficients Location'!A:F,6,FALSE)),"") | P20: =IF(ISNUMBER(O20),ROUND($F20*O20,2),"")
A21: Alimentation Titanium 800W | B21: HPE 800W FS Ti Ht Plg LH Pwr Sply Kit | C21: 865438-B21 | D21: 1 | G21: PC_SE/PLX86 | H21: =IF(ISNUMBER($F21),ROUND($F21*H$1,2),"") | I21: =IF(ISNUMBER($F21),ROUND($F21*I$1,2),"") | J21: =IF(ISNUMBER($F21),ROUND($F21*J$1,2),"") | K21: =IF(ISNUMBER(F21),IF(G21="",VLOOKUP($A21,'Loc Coefficients Config'!$A:$G,7,FALSE),VLOOKUP(G21,'Loc Coefficients Location'!A:D,4,FALSE)),"") | L21: =IF(ISNUMBER(K21),ROUND($F21*K21,2),"") | M21: =IF(ISNUMBER(F21),IF(G21="",VLOOKUP($A21,'Loc Coefficients Config'!$A:$H,8,FALSE),VLOOKUP(G21,'Loc Coefficients Location'!A:E,5,FALSE)),"") | N21: =IF(ISNUMBER(M21),ROUND($F21*M21,2),"") | O21: =IF(ISNUMBER(F21),IF(G21="",VLOOKUP($A21,'Loc Coefficients Config'!$A:$I,9,FALSE),VLOOKUP(G21,'Loc Coefficients Location'!A:F,6,FALSE)),"") | P21: =IF(ISNUMBER(O21),ROUND($F21*O21,2),"")
A22: Activation Alimentation redondante | B22: HPE ProLiant DL20 Gen10 Plus RPS FIO Enablement Kit | C22: P45948-B21 | D22: Cat | H22: =IF(ISNUMBER($F22),ROUND($F22*H$1,2),"") | I22: =IF(ISNUMBER($F22),ROUND($F22*I$1,2),"") | J22: =IF(ISNUMBER($F22),ROUND($F22*J$1,2),"") | K22: =IF(ISNUMBER(F22),IF(G22="",VLOOKUP($A22,'Loc Coefficients Config'!$A:$G,7,FALSE),VLOOKUP(G22,'Loc Coefficients Location'!A:D,4,FALSE)),"") | L22: =IF(ISNUMBER(K22),ROUND($F22*K22,2),"") | M22: =IF(ISNUMBER(F22),IF(G22="",VLOOKUP($A22,'Loc Coefficients Config'!$A:$H,8,FALSE),VLOOKUP(G22,'Loc Coefficients Location'!A:E,5,FALSE)),"") | N22: =IF(ISNUMBER(M22),ROUND($F22*M22,2),"") | O22: =IF(ISNUMBER(F22),IF(G22="",VLOOKUP($A22,'Loc Coefficients Config'!$A:$I,9,FALSE),VLOOKUP(G22,'Loc Coefficients Location'!A:F,6,FALSE)),"") | P22: =IF(ISNUMBER(O22),ROUND($F22*O22,2),"")
A23: Licence iLO en version Advanced avec toutes les options activées | B23: HPE iLO Adv 1-svr Lic 1yr Support | C23: 512485-B21 | D23: 1 | G23: SOFTCOST | H23: =IF(ISNUMBER($F23),ROUND($F23*H$1,2),"") | I23: =IF(ISNUMBER($F23),ROUND($F23*I$1,2),"") | J23: =IF(ISNUMBER($F23),ROUND($F23*J$1,2),"") | K23: =IF(ISNUMBER(F23),IF(G23="",VLOOKUP($A23,'Loc Coefficients Config'!$A:$G,7,FALSE),VLOOKUP(G23,'Loc Coefficients Location'!A:D,4,FALSE)),"") | L23: =IF(ISNUMBER(K23),ROUND($F23*K23,2),"") | M23: =IF(ISNUMBER(F23),IF(G23="",VLOOKUP($A23,'Loc Coefficients Config'!$A:$H,8,FALSE),VLOOKUP(G23,'Loc Coefficients Location'!A:E,5,FALSE)),"") | N23: =IF(ISNUMBER(M23),ROUND($F23*M23,2),"") | O23: =IF(ISNUMBER(F23),IF(G23="",VLOOKUP($A23,'Loc Coefficients Config'!$A:$I,9,FALSE),VLOOKUP(G23,'Loc Coefficients Location'!A:F,6,FALSE)),"") | P23: =IF(ISNUMBER(O23),ROUND($F23*O23,2),"")
A24: Suppression des câbles électriques par défaut | B24: HPE Remove Standard Power Cords | C24: 469774-409 | D24: 1 | G24: SOFTCOST | H24: =IF(ISNUMBER($F24),ROUND($F24*H$1,2),"") | I24: =IF(ISNUMBER($F24),ROUND($F24*I$1,2),"") | J24: =IF(ISNUMBER($F24),ROUND($F24*J$1,2),"") | K24: =IF(ISNUMBER(F24),IF(G24="",VLOOKUP($A24,'Loc Coefficients Config'!$A:$G,7,FALSE),VLOOKUP(G24,'Loc Coefficients Location'!A:D,4,FALSE)),"") | L24: =IF(ISNUMBER(K24),ROUND($F24*K24,2),"") | M24: =IF(ISNUMBER(F24),IF(G24="",VLOOKUP($A24,'Loc Coefficients Config'!$A:$H,8,FALSE),VLOOKUP(G24,'Loc Coefficients Location'!A:E,5,FALSE)),"") | N24: =IF(ISNUMBER(M24),ROUND($F24*M24,2),"") | O24: =IF(ISNUMBER(F24),IF(G24="",VLOOKUP($A24,'Loc Coefficients Config'!$A:$I,9,FALSE),VLOOKUP(G24,'Loc Coefficients Location'!A:F,6,FALSE)),"") | P24: =IF(ISNUMBER(O24),ROUND($F24*O24,2),"")
A25: 1 kit de rail pour rack | B25: HPE 1U Short Friction Rail Kit | C25: 775612-B21 | D25: 1 | G25: PC_SE/PLX86 | H25: =IF(ISNUMBER($F25),ROUND($F25*H$1,2),"") | I25: =IF(ISNUMBER($F25),ROUND($F25*I$1,2),"") | J25: =IF(ISNUMBER($F25),ROUND($F25*J$1,2),"") | K25: =IF(ISNUMBER(F25),IF(G25="",VLOOKUP($A25,'Loc Coefficients Config'!$A:$G,7,FALSE),VLOOKUP(G25,'Loc Coefficients Location'!A:D,4,FALSE)),"") | L25: =IF(ISNUMBER(K25),ROUND($F25*K25,2),"") | M25: =IF(ISNUMBER(F25),IF(G25="",VLOOKUP($A25,'Loc Coefficients Config'!$A:$H,8,FALSE),VLOOKUP(G25,'Loc Coefficients Location'!A:E,5,FALSE)),"") | N25: =IF(ISNUMBER(M25),ROUND($F25*M25,2),"") | O25: =IF(ISNUMBER(F25),IF(G25="",VLOOKUP($A25,'Loc Coefficients Config'!$A:$I,9,FALSE),VLOOKUP(G25,'Loc Coefficients Location'!A:F,6,FALSE)),"") | P25: =IF(ISNUMBER(O25),ROUND($F25*O25,2),"")
A26: Livraison devant la porte | B26: HPE Door/dock Small Delivery SVC | C26: AC111A | D26: 1 | G26: SOFTCOST | H26: =IF(ISNUMBER($F26),ROUND($F26*H$1,2),"") | I26: =IF(ISNUMBER($F26),ROUND($F26*I$1,2),"") | J26: =IF(ISNUMBER($F26),ROUND($F26*J$1,2),"") | K26: =IF(ISNUMBER(F26),IF(G26="",VLOOKUP($A26,'Loc Coefficients Config'!$A:$G,7,FALSE),VLOOKUP(G26,'Loc Coefficients Location'!A:D,4,FALSE)),"") | L26: =IF(ISNUMBER(K26),ROUND($F26*K26,2),"") | M26: =IF(ISNUMBER(F26),IF(G26="",VLOOKUP($A26,'Loc Coefficients Config'!$A:$H,8,FALSE),VLOOKUP(G26,'Loc Coefficients Location'!A:E,5,FALSE)),"") | N26: =IF(ISNUMBER(M26),ROUND($F26*M26,2),"") | O26: =IF(ISNUMBER(F26),IF(G26="",VLOOKUP($A26,'Loc Coefficients Config'!$A:$I,9,FALSE),VLOOKUP(G26,'Loc Coefficients Location'!A:F,6,FALSE)),"") | P26: =IF(ISNUMBER(O26),ROUND($F26*O26,2),"")
A27: Support 5 ans H+4 ILO | B27: HPE 5Y TC Ess iLO Adv Non BL SVC | C27: HW2P1E | D27: 1 | G27: SOFT/MAINT | H27: =IF(ISNUMBER($F27),ROUND($F27*H$1,2),"") | I27: =IF(ISNUMBER($F27),ROUND($F27*I$1,2),"") | J27: =IF(ISNUMBER($F27),ROUND($F27*J$1,2),"") | K27: =IF(ISNUMBER(F27),IF(G27="",VLOOKUP($A27,'Loc Coefficients Config'!$A:$G,7,FALSE),VLOOKUP(G27,'Loc Coefficients Location'!A:D,4,FALSE)),"") | L27: =IF(ISNUMBER(K27),ROUND($F27*K27,2),"") | M27: =IF(ISNUMBER(F27),IF(G27="",VLOOKUP($A27,'Loc Coefficients Config'!$A:$H,8,FALSE),VLOOKUP(G27,'Loc Coefficients Location'!A:E,5,FALSE)),"") | N27: =IF(ISNUMBER(M27),ROUND($F27*M27,2),"") | O27: =IF(ISNUMBER(F27),IF(G27="",VLOOKUP($A27,'Loc Coefficients Config'!$A:$I,9,FALSE),VLOOKUP(G27,'Loc Coefficients Location'!A:F,6,FALSE)),"") | P27: =IF(ISNUMBER(O27),ROUND($F27*O27,2),"")
A28: Garantie 5 ans J+1 châssis | B28: HPE 5Y TC Bas DL20 Gen10 Plus HW SVC | C28: H32ZWE | D28: 1 | G28: SOFT/MAINT | H28: =IF(ISNUMBER($F28),ROUND($F28*H$1,2),"") | I28: =IF(ISNUMBER($F28),ROUND($F28*I$1,2),"") | J28: =IF(ISNUMBER($F28),ROUND($F28*J$1,2),"") | K28: =IF(ISNUMBER(F28),IF(G28="",VLOOKUP($A28,'Loc Coefficients Config'!$A:$G,7,FALSE),VLOOKUP(G28,'Loc Coefficients Location'!A:D,4,FALSE)),"") | L28: =IF(ISNUMBER(K28),ROUND($F28*K28,2),"") | M28: =IF(ISNUMBER(F28),IF(G28="",VLOOKUP($A28,'Loc Coefficients Config'!$A:$H,8,FALSE),VLOOKUP(G28,'Loc Coefficients Location'!A:E,5,FALSE)),"") | N28: =IF(ISNUMBER(M28),ROUND($F28*M28,2),"") | O28: =IF(ISNUMBER(F28),IF(G28="",VLOOKUP($A28,'Loc Coefficients Config'!$A:$I,9,FALSE),VLOOKUP(G28,'Loc Coefficients Location'!A:F,6,FALSE)),"") | P28: =IF(ISNUMBER(O28),ROUND($F28*O28,2),"")
H29: =IF(ISNUMBER($F29),ROUND($F29*H$1,2),"") | I29: =IF(ISNUMBER($F29),ROUND($F29*I$1,2),"") | J29: =IF(ISNUMBER($F29),ROUND($F29*J$1,2),"") | K29: =IF(ISNUMBER(F29),IF(G29="",VLOOKUP($A29,'Loc Coefficients Config'!$A:$G,7,FALSE),VLOOKUP(G29,'Loc Coefficients Location'!A:D,4,FALSE)),"") | L29: =IF(ISNUMBER(K29),ROUND($F29*K29,2),"") | M29: =IF(ISNUMBER(F29),IF(G29="",VLOOKUP($A29,'Loc Coefficients Config'!$A:$H,8,FALSE),VLOOKUP(G29,'Loc Coefficients Location'!A:E,5,FALSE)),"") | N29: =IF(ISNUMBER(M29),ROUND($F29*M29,2),"") | O29: =IF(ISNUMBER(F29),IF(G29="",VLOOKUP($A29,'Loc Coefficients Config'!$A:$I,9,FALSE),VLOOKUP(G29,'Loc Coefficients Location'!A:F,6,FALSE)),"") | P29: =IF(ISNUMBER(O29),ROUND($F29*O29,2),"")
H30: =IF(ISNUMBER($F30),ROUND($F30*H$1,2),"") | I30: =IF(ISNUMBER($F30),ROUND($F30*I$1,2),"") | J30: =IF(ISNUMBER($F30),ROUND($F30*J$1,2),"") | K30: =IF(ISNUMBER(F30),IF(G30="",VLOOKUP($A30,'Loc Coefficients Config'!$A:$G,7,FALSE),VLOOKUP(G30,'Loc Coefficients Location'!A:D,4,FALSE)),"") | L30: =IF(ISNUMBER(K30),ROUND($F30*K30,2),"") | M30: =IF(ISNUMBER(F30),IF(G30="",VLOOKUP($A30,'Loc Coefficients Config'!$A:$H,8,FALSE),VLOOKUP(G30,'Loc Coefficients Location'!A:E,5,FALSE)),"") | N30: =IF(ISNUMBER(M30),ROUND($F30*M30,2),"") | O30: =IF(ISNUMBER(F30),IF(G30="",VLOOKUP($A30,'Loc Coefficients Config'!$A:$I,9,FALSE),VLOOKUP(G30,'Loc Coefficients Location'!A:F,6,FALSE)),"") | P30: =IF(ISNUMBER(O30),ROUND($F30*O30,2),"")
A31: Cat1 Conf10 DL325 Gen10 plus v2 | B31: HPE ProLiant DL325 Gen10 plus V2 | C31: P38471-B21 | F31: 969.28 | H31: =IF(ISNUMBER($F31),ROUND($F31*H$1,2),"") -> 260.63 | I31: =IF(ISNUMBER($F31),ROUND($F31*I$1,2),"") -> 134.11 | J31: =IF(ISNUMBER($F31),ROUND($F31*J$1,2),"") -> 92.11 | K31: =IF(ISNUMBER(F31),IF(G31="",VLOOKUP($A31,'Loc Coefficients Config'!$A:$G,7,FALSE),VLOOKUP(G31,'Loc Coefficients Location'!A:D,4,FALSE)),"") -> 0.22717399 | L31: =IF(ISNUMBER(K31),ROUND($F31*K31,2),"") -> 220.2 | M31: =IF(ISNUMBER(F31),IF(G31="",VLOOKUP($A31,'Loc Coefficients Config'!$A:$H,8,FALSE),VLOOKUP(G31,'Loc Coefficients Location'!A:E,5,FALSE)),"") -> 0.11977037 | N31: =IF(ISNUMBER(M31),ROUND($F31*M31,2),"") -> 116.09 | O31: =IF(ISNUMBER(F31),IF(G31="",VLOOKUP($A31,'Loc Coefficients Config'!$A:$I,9,FALSE),VLOOKUP(G31,'Loc Coefficients Location'!A:F,6,FALSE)),"") -> 0.086647524 | P31: =IF(ISNUMBER(O31),ROUND($F31*O31,2),"") -> 83.99
A32: Serveur rack standard 1U mono-socket AMD | B32: HPE DL325 G10+ v2 8SFF CTO Svr | C32: P38471-B21 | D32: 1 | G32: PC_SE/PLX86 | H32: =IF(ISNUMBER($F32),ROUND($F32*H$1,2),"") | I32: =IF(ISNUMBER($F32),ROUND($F32*I$1,2),"") | J32: =IF(ISNUMBER($F32),ROUND($F32*J$1,2),"") | K32: =IF(ISNUMBER(F32),IF(G32="",VLOOKUP($A32,'Loc Coefficients Config'!$A:$G,7,FALSE),VLOOKUP(G32,'Loc Coefficients Location'!A:D,4,FALSE)),"") | L32: =IF(ISNUMBER(K32),ROUND($F32*K32,2),"") | M32: =IF(ISNUMBER(F32),IF(G32="",VLOOKUP($A32,'Loc Coefficients Config'!$A:$H,8,FALSE),VLOOKUP(G32,'Loc Coefficients Location'!A:E,5,FALSE)),"") | N32: =IF(ISNUMBER(M32),ROUND($F32*M32,2),"") | O32: =IF(ISNUMBER(F32),IF(G32="",VLOOKUP($A32,'Loc Coefficients Config'!$A:$I,9,FALSE),VLOOKUP(G32,'Loc Coefficients Location'!A:F,6,FALSE)),"") | P32: =IF(ISNUMBER(O32),ROUND($F32*O32,2),"")
A33: Processeur 64 bits AMD EPYC 7232P (3,1 GHz de base 8 cœurs / 16 threads) | B33: AMD EPYC 7232P Kit for DL325 Gen10+ v2 | C33: P39738-B21 | D33: 1 | G33: PC_SE/PLX86 | H33: =IF(ISNUMBER($F33),ROUND($F33*H$1,2),"") | I33: =IF(ISNUMBER($F33),ROUND($F33*I$1,2),"") | J33: =IF(ISNUMBER($F33),ROUND($F33*J$1,2),"") | K33: =IF(ISNUMBER(F33),IF(G33="",VLOOKUP($A33,'Loc Coefficients Config'!$A:$G,7,FALSE),VLOOKUP(G33,'Loc Coefficients Location'!A:D,4,FALSE)),"") | L33: =IF(ISNUMBER(K33),ROUND($F33*K33,2),"") | M33: =IF(ISNUMBER(F33),IF(G33="",VLOOKUP($A33,'Loc Coefficients Config'!$A:$H,8,FALSE),VLOOKUP(G33,'Loc Coefficients Location'!A:E,5,FALSE)),"") | N33: =IF(ISNUMBER(M33),ROUND($F33*M33,2),"") | O33: =IF(ISNUMBER(F33),IF(G33="",VLOOKUP($A33,'Loc Coefficients Config'!$A:$I,9,FALSE),VLOOKUP(G33,'Loc Coefficients Location'!A:F,6,FALSE)),"") | P33: =IF(ISNUMBER(O33),ROUND($F33*O33,2),"")
A34: Barrette mémoire de 32GB HPE DDR4-3200 RDIMM | B34: HPE 32GB 2Rx4 PC4-3200AA-R Smart Kit | C34: P07646-B21 | D34: 1 | G34: PC_SE/PLX86 | H34: =IF(ISNUMBER($F34),ROUND($F34*H$1,2),"") | I34: =IF(ISNUMBER($F34),ROUND($F34*I$1,2),"") | J34: =IF(ISNUMBER($F34),ROUND($F34*J$1,2),"") | K34: =IF(ISNUMBER(F34),IF(G34="",VLOOKUP($A34,'Loc Coefficients Config'!$A:$G,7,FALSE),VLOOKUP(G34,'Loc Coefficients Location'!A:D,4,FALSE)),"") | L34: =IF(ISNUMBER(K34),ROUND($F34*K34,2),"") | M34: =IF(ISNUMBER(F34),IF(G34="",VLOOKUP($A34,'Loc Coefficients Config'!$A:$H,8,FALSE),VLOOKUP(G34,'Loc Coefficients Location'!A:E,5,FALSE)),"") | N34: =IF(ISNUMBER(M34),ROUND($F34*M34,2),"") | O34: =IF(ISNUMBER(F34),IF(G34="",VLOOKUP($A34,'Loc Coefficients Config'!$A:$I,9,FALSE),VLOOKUP(G34,'Loc Coefficients Location'!A:F,6,FALSE)),"") | P34: =IF(ISNUMBER(O34),ROUND($F34*O34,2),"")
A35: Cage disque 8SFF | B35: HPE ProLiant DL325 Gen10 Plus v2 8SFF SAS/SATA BC FIO Backplane Kit | C35: P38473-B21 | D35: 1 | G35: PC_SE/PLX86 | H35: =IF(ISNUMBER($F35),ROUND($F35*H$1,2),"") | I35: =IF(ISNUMBER($F35),ROUND($F35*I$1,2),"") | J35: =IF(ISNUMBER($F35),ROUND($F35*J$1,2),"") | K35: =IF(ISNUMBER(F35),IF(G35="",VLOOKUP($A35,'Loc Coefficients Config'!$A:$G,7,FALSE),VLOOKUP(G35,'Loc Coefficients Location'!A:D,4,FALSE)),"") | L35: =IF(ISNUMBER(K35),ROUND($F35*K35,2),"") | M35: =IF(ISNUMBER(F35),IF(G35="",VLOOKUP($A35,'Loc Coefficients Config'!$A:$H,8,FALSE),VLOOKUP(G35,'Loc Coefficients Location'!A:E,5,FALSE)),"") | N35: =IF(ISNUMBER(M35),ROUND($F35*M35,2),"") | O35: =IF(ISNUMBER(F35),IF(G35="",VLOOKUP($A35,'Loc Coefficients Config'!$A:$I,9,FALSE),VLOOKUP(G35,'Loc Coefficients Location'!A:F,6,FALSE)),"") | P35: =IF(ISNUMBER(O35),ROUND($F35*O35,2),"")
A36: 2 ports Ethernet 10GbE Base-T OCP (intégré) | B36: BCM 57416 10GbE 2p BASE-T OCP3 Adptr | C36: P10097-B21 | D36: 1 | G36: PC_SE/PLX86 | H36: =IF(ISNUMBER($F36),ROUND($F36*H$1,2),"") | I36: =IF(ISNUMBER($F36),ROUND($F36*I$1,2),"") | J36: =IF(ISNUMBER($F36),ROUND($F36*J$1,2),"") | K36: =IF(ISNUMBER(F36),IF(G36="",VLOOKUP($A36,'Loc Coefficients Config'!$A:$G,7,FALSE),VLOOKUP(G36,'Loc Coefficients Location'!A:D,4,FALSE)),"") | L36: =IF(ISNUMBER(K36),ROUND($F36*K36,2),"") | M36: =IF(ISNUMBER(F36),IF(G36="",VLOOKUP($A36,'Loc Coefficients Config'!$A:$H,8,FALSE),VLOOKUP(G36,'Loc Coefficients Location'!A:E,5,FALSE)),"") | N36: =IF(ISNUMBER(M36),ROUND($F36*M36,2),"") | O36: =IF(ISNUMBER(F36),IF(G36="",VLOOKUP($A36,'Loc Coefficients Config'!$A:$I,9,FALSE),VLOOKUP(G36,'Loc Coefficients Location'!A:F,6,FALSE)),"") | P36: =IF(ISNUMBER(O36),ROUND($F36*O36,2),"")
A37: Alimentation Titanium 800W | B37: HPE 800W FS Ti Ht Plg LH Pwr Sply Kit | C37: 865438-B21 | D37: 1 | G37: PC_SE/PLX86 | H37: =IF(ISNUMBER($F37),ROUND($F37*H$1,2),"") | I37: =IF(ISNUMBER($F37),ROUND($F37*I$1,2),"") | J37: =IF(ISNUMBER($F37),ROUND($F37*J$1,2),"") | K37: =IF(ISNUMBER(F37),IF(G37="",VLOOKUP($A37,'Loc Coefficients Config'!$A:$G,7,FALSE),VLOOKUP(G37,'Loc Coefficients Location'!A:D,4,FALSE)),"") | L37: =IF(ISNUMBER(K37),ROUND($F37*K37,2),"") | M37: =IF(ISNUMBER(F37),IF(G37="",VLOOKUP($A37,'Loc Coefficients Config'!$A:$H,8,FALSE),VLOOKUP(G37,'Loc Coefficients Location'!A:E,5,FALSE)),"") | N37: =IF(ISNUMBER(M37),ROUND($F37*M37,2),"") | O37: =IF(ISNUMBER(F37),IF(G37="",VLOOKUP($A37,'Loc Coefficients Config'!$A:$I,9,FALSE),VLOOKUP(G37,'Loc Coefficients Location'!A:F,6,FALSE)),"") | P37: =IF(ISNUMBER(O37),ROUND($F37*O37,2),"")
A38: Licence iLO en version Advanced avec toutes les options activées | B38: HPE iLO Adv 1-svr Lic 1yr Support | C38: 512485-B21 | D38: 1 | G38: SOFTCOST | H38: =IF(ISNUMBER($F38),ROUND($F38*H$1,2),"") | I38: =IF(ISNUMBER($F38),ROUND($F38*I$1,2),"") | J38: =IF(ISNUMBER($F38),ROUND($F38*J$1,2),"") | K38: =IF(ISNUMBER(F38),IF(G38="",VLOOKUP($A38,'Loc Coefficients Config'!$A:$G,7,FALSE),VLOOKUP(G38,'Loc Coefficients Location'!A:D,4,FALSE)),"") | L38: =IF(ISNUMBER(K38),ROUND($F38*K38,2),"") | M38: =IF(ISNUMBER(F38),IF(G38="",VLOOKUP($A38,'Loc Coefficients Config'!$A:$H,8,FALSE),VLOOKUP(G38,'Loc Coefficients Location'!A:E,5,FALSE)),"") | N38: =IF(ISNUMBER(M38),ROUND($F38*M38,2),"") | O38: =IF(ISNUMBER(F38),IF(G38="",VLOOKUP($A38,'Loc Coefficients Config'!$A:$I,9,FALSE),VLOOKUP(G38,'Loc Coefficients Location'!A:F,6,FALSE)),"") | P38: =IF(ISNUMBER(O38),ROUND($F38*O38,2),"")
A39: Outil d'administration | B39: HPE GreenLake COM En 5y Up ProLiant aaS | C39: R7A12AAE | D39: 1 | G39: SOFT/SFT | H39: =IF(ISNUMBER($F39),ROUND($F39*H$1,2),"") | I39: =IF(ISNUMBER($F39),ROUND($F39*I$1,2),"") | J39: =IF(ISNUMBER($F39),ROUND($F39*J$1,2),"") | K39: =IF(ISNUMBER(F39),IF(G39="",VLOOKUP($A39,'Loc Coefficients Config'!$A:$G,7,FALSE),VLOOKUP(G39,'Loc Coefficients Location'!A:D,4,FALSE)),"") | L39: =IF(ISNUMBER(K39),ROUND($F39*K39,2),"") | M39: =IF(ISNUMBER(F39),IF(G39="",VLOOKUP($A39,'Loc Coefficients Config'!$A:$H,8,FALSE),VLOOKUP(G39,'Loc Coefficients Location'!A:E,5,FALSE)),"") | N39: =IF(ISNUMBER(M39),ROUND($F39*M39,2),"") | O39: =IF(ISNUMBER(F39),IF(G39="",VLOOKUP($A39,'Loc Coefficients Config'!$A:$I,9,FALSE),VLOOKUP(G39,'Loc Coefficients Location'!A:F,6,FALSE)),"") | P39: =IF(ISNUMBER(O39),ROUND($F39*O39,2),"")
A40: Kit de câble SATA | B40: HPE DL325 G10+ v2 SATA FIO Cbl Kit | C40: P39134-B21 | D40: 1 | G40: PC_SE/PLX86 | H40: =IF(ISNUMBER($F40),ROUND($F40*H$1,2),"") | I40: =IF(ISNUMBER($F40),ROUND($F40*I$1,2),"") | J40: =IF(ISNUMBER($F40),ROUND($F40*J$1,2),"") | K40: =IF(ISNUMBER(F40),IF(G40="",VLOOKUP($A40,'Loc Coefficients Config'!$A:$G,7,FALSE),VLOOKUP(G40,'Loc Coefficients Location'!A:D,4,FALSE)),"") | L40: =IF(ISNUMBER(K40),ROUND($F40*K40,2),"") | M40: =IF(ISNUMBER(F40),IF(G40="",VLOOKUP($A40,'Loc Coefficients Config'!$A:$H,8,FALSE),VLOOKUP(G40,'Loc Coefficients Location'!A:E,5,FALSE)),"") | N40: =IF(ISNUMBER(M40),ROUND($F40*M40,2),"") | O40: =IF(ISNUMBER(F40),IF(G40="",VLOOKUP($A40,'Loc Coefficients Config'!$A:$I,9,FALSE),VLOOKUP(G40,'Loc Coefficients Location'!A:F,6,FALSE)),"") | P40: =IF(ISNUMBER(O40),ROUND($F40*O40,2),"")
A41: Kit Ventilateurs Standard | B41: HPE DL325 G10+ v2 Stnd FIO Fan Kit | C41: P41471-B21 | D41: 1 | G41: PC_SE/PLX86 | H41: =IF(ISNUMBER($F41),ROUND($F41*H$1,2),"") | I41: =IF(ISNUMBER($F41),ROUND($F41*I$1,2),"") | J41: =IF(ISNUMBER($F41),ROUND($F41*J$1,2),"") | K41: =IF(ISNUMBER(F41),IF(G41="",VLOOKUP($A41,'Loc Coefficients Config'!$A:$G,7,FALSE),VLOOKUP(G41,'Loc Coefficients Location'!A:D,4,FALSE)),"") | L41: =IF(ISNUMBER(K41),ROUND($F41*K41,2),"") | M41: =IF(ISNUMBER(F41),IF(G41="",VLOOKUP($A41,'Loc Coefficients Config'!$A:$H,8,FALSE),VLOOKUP(G41,'Loc Coefficients Location'!A:E,5,FALSE)),"") | N41: =IF(ISNUMBER(M41),ROUND($F41*M41,2),"") | O41: =IF(ISNUMBER(F41),IF(G41="",VLOOKUP($A41,'Loc Coefficients Config'!$A:$I,9,FALSE),VLOOKUP(G41,'Loc Coefficients Location'!A:F,6,FALSE)),"") | P41: =IF(ISNUMBER(O41),ROUND($F41*O41,2),"")
A42: Dissipateurs thermiques Haute Performance | B42: HPE DL325 G10+ v2 High Perf FIO HS Kit | C42: P41197-B21 | D42: 1 | G42: PC_SE/PLX86 | H42: =IF(ISNUMBER($F42),ROUND($F42*H$1,2),"") | I42: =IF(ISNUMBER($F42),ROUND($F42*I$1,2),"") | J42: =IF(ISNUMBER($F42),ROUND($F42*J$1,2),"") | K42: =IF(ISNUMBER(F42),IF(G42="",VLOOKUP($A42,'Loc Coefficients Config'!$A:$G,7,FALSE),VLOOKUP(G42,'Loc Coefficients Location'!A:D,4,FALSE)),"") | L42: =IF(ISNUMBER(K42),ROUND($F42*K42,2),"") | M42: =IF(ISNUMBER(F42),IF(G42="",VLOOKUP($A42,'Loc Coefficients Config'!$A:$H,8,FALSE),VLOOKUP(G42,'Loc Coefficients Location'!A:E,5,FALSE)),"") | N42: =IF(ISNUMBER(M42),ROUND($F42*M42,2),"") | O42: =IF(ISNUMBER(F42),IF(G42="",VLOOKUP($A42,'Loc Coefficients Config'!$A:$I,9,FALSE),VLOOKUP(G42,'Loc Coefficients Location'!A:F,6,FALSE)),"") | P42: =IF(ISNUMBER(O42),ROUND($F42*O42,2),"")
A43: Suppression des câbles électriques par défaut | B43: HPE Remove Standard Power Cords | C43: 469774-409 | D43: 1 | G43: SOFTCOST | H43: =IF(ISNUMBER($F43),ROUND($F43*H$1,2),"") | I43: =IF(ISNUMBER($F43),ROUND($F43*I$1,2),"") | J43: =IF(ISNUMBER($F43),ROUND($F43*J$1,2),"") | K43: =IF(ISNUMBER(F43),IF(G43="",VLOOKUP($A43,'Loc Coefficients Config'!$A:$G,7,FALSE),VLOOKUP(G43,'Loc Coefficients Location'!A:D,4,FALSE)),"") | L43: =IF(ISNUMBER(K43),ROUND($F43*K43,2),"") | M43: =IF(ISNUMBER(F43),IF(G43="",VLOOKUP($A43,'Loc Coefficients Config'!$A:$H,8,FALSE),VLOOKUP(G43,'Loc Coefficients Location'!A:E,5,FALSE)),"") | N43: =IF(ISNUMBER(M43),ROUND($F43*M43,2),"") | O43: =IF(ISNUMBER(F43),IF(G43="",VLOOKUP($A43,'Loc Coefficients Config'!$A:$I,9,FALSE),VLOOKUP(G43,'Loc Coefficients Location'!A:F,6,FALSE)),"") | P43: =IF(ISNUMBER(O43),ROUND($F43*O43,2),"")
... A47: Garantie 5 ans J+1 châssis | B47: HPE 5Y TC Bas DL325G10+V2 SVC | C47: HY5G1E | D47: 1 | G47: SOFT/MAINT | H47: =IF(ISNUMBER($F47),ROUND($F47*H$1,2),"") | I47: =IF(ISNUMBER($F47),ROUND($F47*I$1,2),"") | J47: =IF(ISNUMBER($F47),ROUND($F47*J$1,2),"") | K47: =IF(ISNUMBER(F47),IF(G47="",VLOOKUP($A47,'Loc Coefficients Config'!$A:$G,7,FALSE),VLOOKUP(G47,'Loc Coefficients Location'!A:D,4,FALSE)),"") | L47: =IF(ISNUMBER(K47),ROUND($F47*K47,2),"") | M47: =IF(ISNUMBER(F47),IF(G47="",VLOOKUP($A47,'Loc Coefficients Config'!$A:$H,8,FALSE),VLOOKUP(G47,'Loc Coefficients Location'!A:E,5,FALSE)),"") | N47: =IF(ISNUMBER(M47),ROUND($F47*M47,2),"") | O47: =IF(ISNUMBER(F47),IF(G47="",VLOOKUP($A47,'Loc Coefficients Config'!$A:$I,9,FALSE),VLOOKUP(G47,'Loc Coefficients Location'!A:F,6,FALSE)),"") | P47: =IF(ISNUMBER(O47),ROUND($F47*O47,2),"")
H48: =IF(ISNUMBER($F48),ROUND($F48*H$1,2),"") | I48: =IF(ISNUMBER($F48),ROUND($F48*I$1,2),"") | J48: =IF(ISNUMBER($F48),ROUND($F48*J$1,2),"") | K48: =IF(ISNUMBER(F48),IF(G48="",VLOOKUP($A48,'Loc Coefficients Config'!$A:$G,7,FALSE),VLOOKUP(G48,'Loc Coefficients Location'!A:D,4,FALSE)),"") | L48: =IF(ISNUMBER(K48),ROUND($F48*K48,2),"") | M48: =IF(ISNUMBER(F48),IF(G48="",VLOOKUP($A48,'Loc Coefficients Config'!$A:$H,8,FALSE),VLOOKUP(G48,'Loc Coefficients Location'!A:E,5,FALSE)),"") | N48: =IF(ISNUMBER(M48),ROUND($F48*M48,2),"") | O48: =IF(ISNUMBER(F48),IF(G48="",VLOOKUP($A48,'Loc Coefficients Config'!$A:$I,9,FALSE),VLOOKUP(G48,'Loc Coefficients Location'!A:F,6,FALSE)),"") | P48: =IF(ISNUMBER(O48),ROUND($F48*O48,2),"")
H49: =IF(ISNUMBER($F49),ROUND($F49*H$1,2),"") | I49: =IF(ISNUMBER($F49),ROUND($F49*I$1,2),"") | J49: =IF(ISNUMBER($F49),ROUND($F49*J$1,2),"") | K49: =IF(ISNUMBER(F49),IF(G49="",VLOOKUP($A49,'Loc Coefficients Config'!$A:$G,7,FALSE),VLOOKUP(G49,'Loc Coefficients Location'!A:D,4,FALSE)),"") | L49: =IF(ISNUMBER(K49),ROUND($F49*K49,2),"") | M49: =IF(ISNUMBER(F49),IF(G49="",VLOOKUP($A49,'Loc Coefficients Config'!$A:$H,8,FALSE),VLOOKUP(G49,'Loc Coefficients Location'!A:E,5,FALSE)),"") | N49: =IF(ISNUMBER(M49),ROUND($F49*M49,2),"") | O49: =IF(ISNUMBER(F49),IF(G49="",VLOOKUP($A49,'Loc Coefficients Config'!$A:$I,9,FALSE),VLOOKUP(G49,'Loc Coefficients Location'!A:F,6,FALSE)),"") | P49: =IF(ISNUMBER(O49),ROUND($F49*O49,2),"")
A50: Cat1 Conf6 Tour ML30 Gen10 plus | B50: HPE ProLiant ML30 Gen10 plus | C50: P44723-B21 | F50: 757.93 | H50: =IF(ISNUMBER($F50),ROUND($F50*H$1,2),"") -> 203.8 | I50: =IF(ISNUMBER($F50),ROUND($F50*I$1,2),"") -> 104.87 | J50: =IF(ISNUMBER($F50),ROUND($F50*J$1,2),"") -> 72.02 | K50: =IF(ISNUMBER(F50),IF(G50="",VLOOKUP($A50,'Loc Coefficients Config'!$A:$G,7,FALSE),VLOOKUP(G50,'Loc Coefficients Location'!A:D,4,FALSE)),"") -> 0.23286669 | L50: =IF(ISNUMBER(K50),ROUND($F50*K50,2),"") -> 176.5 | M50: =IF(ISNUMBER(F50),IF(G50="",VLOOKUP($A50,'Loc Coefficients Config'!$A:$H,8,FALSE),VLOOKUP(G50,'Loc Coefficients Location'!A:E,5,FALSE)),"") -> 0.12230755 | N50: =IF(ISNUMBER(M50),ROUND($F50*M50,2),"") -> 92.7 | O50: =IF(ISNUMBER(F50),IF(G50="",VLOOKUP($A50,'Loc Coefficients Config'!$A:$I,9,FALSE),VLOOKUP(G50,'Loc Coefficients Location'!A:F,6,FALSE)),"") -> 0.087790851 | P50: =IF(ISNUMBER(O50),ROUND($F50*O50,2),"") -> 66.54
A51: Serveur de type tour ML30 Gen10 plus | B51: HPE ML30 Gen10+ 4LFF NHP CTO Svr | C51: P44723-B21 | D51: 1 | G51: PC_SE/PLX86 | H51: =IF(ISNUMBER($F51),ROUND($F51*H$1,2),"") | I51: =IF(ISNUMBER($F51),ROUND($F51*I$1,2),"") | J51: =IF(ISNUMBER($F51),ROUND($F51*J$1,2),"") | K51: =IF(ISNUMBER(F51),IF(G51="",VLOOKUP($A51,'Loc Coefficients Config'!$A:$G,7,FALSE),VLOOKUP(G51,'Loc Coefficients Location'!A:D,4,FALSE)),"") | L51: =IF(ISNUMBER(K51),ROUND($F51*K51,2),"") | M51: =IF(ISNUMBER(F51),IF(G51="",VLOOKUP($A51,'Loc Coefficients Config'!$A:$H,8,FALSE),VLOOKUP(G51,'Loc Coefficients Location'!A:E,5,FALSE)),"") | N51: =IF(ISNUMBER(M51),ROUND($F51*M51,2),"") | O51: =IF(ISNUMBER(F51),IF(G51="",VLOOKUP($A51,'Loc Coefficients Config'!$A:$I,9,FALSE),VLOOKUP(G51,'Loc Coefficients Location'!A:F,6,FALSE)),"") | P51: =IF(ISNUMBER(O51),ROUND($F51*O51,2),"")
A52: Processeur 64 bits Intel Xeon E-2314 (2,8 GHz de base / 4,50 Ghz Turbo / 4 cœurs / 4 threads / 8 Mo Smart Cache / 65W TDP) | B52: Intel Xeon E-2314 FIO CPU for HPE | C52: P45248-B21 | D52: 1 | G52: PC_SE/PLX86 | H52: =IF(ISNUMBER($F52),ROUND($F52*H$1,2),"") | I52: =IF(ISNUMBER($F52),ROUND($F52*I$1,2),"") | J52: =IF(ISNUMBER($F52),ROUND($F52*J$1,2),"") | K52: =IF(ISNUMBER(F52),IF(G52="",VLOOKUP($A52,'Loc Coefficients Config'!$A:$G,7,FALSE),VLOOKUP(G52,'Loc Coefficients Location'!A:D,4,FALSE)),"") | L52: =IF(ISNUMBER(K52),ROUND($F52*K52,2),"") | M52: =IF(ISNUMBER(F52),IF(G52="",VLOOKUP($A52,'Loc Coefficients Config'!$A:$H,8,FALSE),VLOOKUP(G52,'Loc Coefficients Location'!A:E,5,FALSE)),"") | N52: =IF(ISNUMBER(M52),ROUND($F52*M52,2),"") | O52: =IF(ISNUMBER(F52),IF(G52="",VLOOKUP($A52,'Loc Coefficients Config'!$A:$I,9,FALSE),VLOOKUP(G52,'Loc Coefficients Location'!A:F,6,FALSE)),"") | P52: =IF(ISNUMBER(O52),ROUND($F52*O52,2),"")
A53: Barrette mémoire de 16GB HPE Standard DDR4-3200 UDIMM | B53: HPE 16GB 1Rx8 PC4-3200AA-E STND Kit | C53: P43019-B21 | D53: 1 | G53: PC_SE/PLX86 | H53: =IF(ISNUMBER($F53),ROUND($F53*H$1,2),"") | I53: =IF(ISNUMBER($F53),ROUND($F53*I$1,2),"") | J53: =IF(ISNUMBER($F53),ROUND($F53*J$1,2),"") | K53: =IF(ISNUMBER(F53),IF(G53="",VLOOKUP($A53,'Loc Coefficients Config'!$A:$G,7,FALSE),VLOOKUP(G53,'Loc Coefficients Location'!A:D,4,FALSE)),"") | L53: =IF(ISNUMBER(K53),ROUND($F53*K53,2),"") | M53: =IF(ISNUMBER(F53),IF(G53="",VLOOKUP($A53,'Loc Coefficients Config'!$A:$H,8,FALSE),VLOOKUP(G53,'Loc Coefficients Location'!A:E,5,FALSE)),"") | N53: =IF(ISNUMBER(M53),ROUND($F53*M53,2),"") | O53: =IF(ISNUMBER(F53),IF(G53="",VLOOKUP($A53,'Loc Coefficients Config'!$A:$I,9,FALSE),VLOOKUP(G53,'Loc Coefficients Location'!A:F,6,FALSE)),"") | P53: =IF(ISNUMBER(O53),ROUND($F53*O53,2),"")
A54: Alimentation Titanium 800W | B54: HPE 800W FS Ti Ht Plg LH Pwr Sply Kit | C54: 865438-B21 | D54: 1 | G54: PC_SE/PLX86 | H54: =IF(ISNUMBER($F54),ROUND($F54*H$1,2),"") | I54: =IF(ISNUMBER($F54),ROUND($F54*I$1,2),"") | J54: =IF(ISNUMBER($F54),ROUND($F54*J$1,2),"") | K54: =IF(ISNUMBER(F54),IF(G54="",VLOOKUP($A54,'Loc Coefficients Config'!$A:$G,7,FALSE),VLOOKUP(G54,'Loc Coefficients Location'!A:D,4,FALSE)),"") | L54: =IF(ISNUMBER(K54),ROUND($F54*K54,2),"") | M54: =IF(ISNUMBER(F54),IF(G54="",VLOOKUP($A54,'Loc Coefficients Config'!$A:$H,8,FALSE),VLOOKUP(G54,'Loc Coefficients Location'!A:E,5,FALSE)),"") | N54: =IF(ISNUMBER(M54),ROUND($F54*M54,2),"") | O54: =IF(ISNUMBER(F54),IF(G54="",VLOOKUP($A54,'Loc Coefficients Config'!$A:$I,9,FALSE),VLOOKUP(G54,'Loc Coefficients Location'!A:F,6,FALSE)),"") | P54: =IF(ISNUMBER(O54),ROUND($F54*O54,2),"")
A55: Licence iLO en version Advanced avec toutes les options activées | B55: HPE iLO Adv 1-svr Lic 1yr Support | C55: 512485-B21 | D55: 1 | G55: SOFTCOST | H55: =IF(ISNUMBER($F55),ROUND($F55*H$1,2),"") | I55: =IF(ISNUMBER($F55),ROUND($F55*I$1,2),"") | J55: =IF(ISNUMBER($F55),ROUND($F55*J$1,2),"") | K55: =IF(ISNUMBER(F55),IF(G55="",VLOOKUP($A55,'Loc Coefficients Config'!$A:$G,7,FALSE),VLOOKUP(G55,'Loc Coefficients Location'!A:D,4,FALSE)),"") | L55: =IF(ISNUMBER(K55),ROUND($F55*K55,2),"") | M55: =IF(ISNUMBER(F55),IF(G55="",VLOOKUP($A55,'Loc Coefficients Config'!$A:$H,8,FALSE),VLOOKUP(G55,'Loc Coefficients Location'!A:E,5,FALSE)),"") | N55: =IF(ISNUMBER(M55),ROUND($F55*M55,2),"") | O55: =IF(ISNUMBER(F55),IF(G55="",VLOOKUP($A55,'Loc Coefficients Config'!$A:$I,9,FALSE),VLOOKUP(G55,'Loc Coefficients Location'!A:F,6,FALSE)),"") | P55: =IF(ISNUMBER(O55),ROUND($F55*O55,2),"")
A56: Outil d'administration | B56: HPE GreenLake COM En 5y Up ProLiant aaS | C56: R7A12AAE | D56: 1 | G56: SOFT/SFT | H56: =IF(ISNUMBER($F56),ROUND($F56*H$1,2),"") | I56: =IF(ISNUMBER($F56),ROUND($F56*I$1,2),"") | J56: =IF(ISNUMBER($F56),ROUND($F56*J$1,2),"") | K56: =IF(ISNUMBER(F56),IF(G56="",VLOOKUP($A56,'Loc Coefficients Config'!$A:$G,7,FALSE),VLOOKUP(G56,'Loc Coefficients Location'!A:D,4,FALSE)),"") | L56: =IF(ISNUMBER(K56),ROUND($F56*K56,2),"") | M56: =IF(ISNUMBER(F56),IF(G56="",VLOOKUP($A56,'Loc Coefficients Config'!$A:$H,8,FALSE),VLOOKUP(G56,'Loc Coefficients Location'!A:E,5,FALSE)),"") | N56: =IF(ISNUMBER(M56),ROUND($F56*M56,2),"") | O56: =IF(ISNUMBER(F56),IF(G56="",VLOOKUP($A56,'Loc Coefficients Config'!$A:$I,9,FALSE),VLOOKUP(G56,'Loc Coefficients Location'!A:F,6,FALSE)),"") | P56: =IF(ISNUMBER(O56),ROUND($F56*O56,2),"")
A57: Kit d'Alimentation redondante | B57: HPE ML30 Gen10+ 4U RPS Enable Kit | C57: P45209-B21 | D57: 1 | G57: PC_SE/PLX86 | H57: =IF(ISNUMBER($F57),ROUND($F57*H$1,2),"") | I57: =IF(ISNUMBER($F57),ROUND($F57*I$1,2),"") | J57: =IF(ISNUMBER($F57),ROUND($F57*J$1,2),"") | K57: =IF(ISNUMBER(F57),IF(G57="",VLOOKUP($A57,'Loc Coefficients Config'!$A:$G,7,FALSE),VLOOKUP(G57,'Loc Coefficients Location'!A:D,4,FALSE)),"") | L57: =IF(ISNUMBER(K57),ROUND($F57*K57,2),"") | M57: =IF(ISNUMBER(F57),IF(G57="",VLOOKUP($A57,'Loc Coefficients Config'!$A:$H,8,FALSE),VLOOKUP(G57,'Loc Coefficients Location'!A:E,5,FALSE)),"") | N57: =IF(ISNUMBER(M57),ROUND($F57*M57,2),"") | O57: =IF(ISNUMBER(F57),IF(G57="",VLOOKUP($A57,'Loc Coefficients Config'!$A:$I,9,FALSE),VLOOKUP(G57,'Loc Coefficients Location'!A:F,6,FALSE)),"") | P57: =IF(ISNUMBER(O57),ROUND($F57*O57,2),"")
A58: Kit Ventilateur | B58: HPE ML30 Gen10 PCI Fan and Baffle Kit | C58: P06303-B21 | D58: 1 | G58: PC_SE/PLX86 | H58: =IF(ISNUMBER($F58),ROUND($F58*H$1,2),"") | I58: =IF(ISNUMBER($F58),ROUND($F58*I$1,2),"") | J58: =IF(ISNUMBER($F58),ROUND($F58*J$1,2),"") | K58: =IF(ISNUMBER(F58),IF(G58="",VLOOKUP($A58,'Loc Coefficients Config'!$A:$G,7,FALSE),VLOOKUP(G58,'Loc Coefficients Location'!A:D,4,FALSE)),"") | L58: =IF(ISNUMBER(K58),ROUND($F58*K58,2),"") | M58: =IF(ISNUMBER(F58),IF(G58="",VLOOKUP($A58,'Loc Coefficients Config'!$A:$H,8,FALSE),VLOOKUP(G58,'Loc Coefficients Location'!A:E,5,FALSE)),"") | N58: =IF(ISNUMBER(M58),ROUND($F58*M58,2),"") | O58: =IF(ISNUMBER(F58),IF(G58="",VLOOKUP($A58,'Loc Coefficients Config'!$A:$I,9,FALSE),VLOOKUP(G58,'Loc Coefficients Location'!A:F,6,FALSE)),"") | P58: =IF(ISNUMBER(O58),ROUND($F58*O58,2),"")
A59: Suppression des câbles électriques par défaut | B59: HPE Remove Standard Power Cords | C59: 469774-409 | D59: 1 | G59: SOFTCOST | H59: =IF(ISNUMBER($F59),ROUND($F59*H$1,2),"") | I59: =IF(ISNUMBER($F59),ROUND($F59*I$1,2),"") | J59: =IF(ISNUMBER($F59),ROUND($F59*J$1,2),"") | K59: =IF(ISNUMBER(F59),IF(G59="",VLOOKUP($A59,'Loc Coefficients Config'!$A:$G,7,FALSE),VLOOKUP(G59,'Loc Coefficients Location'!A:D,4,FALSE)),"") | L59: =IF(ISNUMBER(K59),ROUND($F59*K59,2),"") | M59: =IF(ISNUMBER(F59),IF(G59="",VLOOKUP($A59,'Loc Coefficients Config'!$A:$H,8,FALSE),VLOOKUP(G59,'Loc Coefficients Location'!A:E,5,FALSE)),"") | N59: =IF(ISNUMBER(M59),ROUND($F59*M59,2),"") | O59: =IF(ISNUMBER(F59),IF(G59="",VLOOKUP($A59,'Loc Coefficients Config'!$A:$I,9,FALSE),VLOOKUP(G59,'Loc Coefficients Location'!A:F,6,FALSE)),"") | P59: =IF(ISNUMBER(O59),ROUND($F59*O59,2),"")
A60: Livraison devant la porte | B60: HPE Door/dock Small Delivery SVC | C60: AC111A | D60: 1 | G60: SOFTCOST | H60: =IF(ISNUMBER($F60),ROUND($F60*H$1,2),"") | I60: =IF(ISNUMBER($F60),ROUND($F60*I$1,2),"") | J60: =IF(ISNUMBER($F60),ROUND($F60*J$1,2),"") | K60: =IF(ISNUMBER(F60),IF(G60="",VLOOKUP($A60,'Loc Coefficients Config'!$A:$G,7,FALSE),VLOOKUP(G60,'Loc Coefficients Location'!A:D,4,FALSE)),"") | L60: =IF(ISNUMBER(K60),ROUND($F60*K60,2),"") | M60: =IF(ISNUMBER(F60),IF(G60="",VLOOKUP($A60,'Loc Coefficients Config'!$A:$H,8,FALSE),VLOOKUP(G60,'Loc Coefficients Location'!A:E,5,FALSE)),"") | N60: =IF(ISNUMBER(M60),ROUND($F60*M60,2),"") | O60: =IF(ISNUMBER(F60),IF(G60="",VLOOKUP($A60,'Loc Coefficients Config'!$A:$I,9,FALSE),VLOOKUP(G60,'Loc Coefficients Location'!A:F,6,FALSE)),"") | P60: =IF(ISNUMBER(O60),ROUND($F60*O60,2),"")
A61: Support 5 ans H+4 ILO | B61: HPE 5Y TC Ess iLO Adv Non BL SVC | C61: HW2P1E | D61: 1 | G61: SOFT/MAINT | H61: =IF(ISNUMBER($F61),ROUND($F61*H$1,2),"") | I61: =IF(ISNUMBER($F61),ROUND($F61*I$1,2),"") | J61: =IF(ISNUMBER($F61),ROUND($F61*J$1,2),"") | K61: =IF(ISNUMBER(F61),IF(G61="",VLOOKUP($A61,'Loc Coefficients Config'!$A:$G,7,FALSE),VLOOKUP(G61,'Loc Coefficients Location'!A:D,4,FALSE)),"") | L61: =IF(ISNUMBER(K61),ROUND($F61*K61,2),"") | M61: =IF(ISNUMBER(F61),IF(G61="",VLOOKUP($A61,'Loc Coefficients Config'!$A:$H,8,FALSE),VLOOKUP(G61,'Loc Coefficients Location'!A:E,5,FALSE)),"") | N61: =IF(ISNUMBER(M61),ROUND($F61*M61,2),"") | O61: =IF(ISNUMBER(F61),IF(G61="",VLOOKUP($A61,'Loc Coefficients Config'!$A:$I,9,FALSE),VLOOKUP(G61,'Loc Coefficients Location'!A:F,6,FALSE)),"") | P61: =IF(ISNUMBER(O61),ROUND($F61*O61,2),"")
A62: Garantie 5 ans J+1 châssis | B62: HPE 5Y TC Bas ML30 Gen10 Plus SVC | C62: HS8G6E | D62: 1 | G62: SOFT/MAINT | H62: =IF(ISNUMBER($F62),ROUND($F62*H$1,2),"") | I62: =IF(ISNUMBER($F62),ROUND($F62*I$1,2),"") | J62: =IF(ISNUMBER($F62),ROUND($F62*J$1,2),"") | K62: =IF(ISNUMBER(F62),IF(G62="",VLOOKUP($A62,'Loc Coefficients Config'!$A:$G,7,FALSE),VLOOKUP(G62,'Loc Coefficients Location'!A:D,4,FALSE)),"") | L62: =IF(ISNUMBER(K62),ROUND($F62*K62,2),"") | M62: =IF(ISNUMBER(F62),IF(G62="",VLOOKUP($A62,'Loc Coefficients Config'!$A:$H,8,FALSE),VLOOKUP(G62,'Loc Coefficients Location'!A:E,5,FALSE)),"") | N62: =IF(ISNUMBER(M62),ROUND($F62*M62,2),"") | O62: =IF(ISNUMBER(F62),IF(G62="",VLOOKUP($A62,'Loc Coefficients Config'!$A:$I,9,FALSE),VLOOKUP(G62,'Loc Coefficients Location'!A:F,6,FALSE)),"") | P62: =IF(ISNUMBER(O62),ROUND($F62*O62,2),"")
H63: =IF(ISNUMBER($F63),ROUND($F63*H$1,2),"") | I63: =IF(ISNUMBER($F63),ROUND($F63*I$1,2),"") | J63: =IF(ISNUMBER($F63),ROUND($F63*J$1,2),"") | K63: =IF(ISNUMBER(F63),IF(G63="",VLOOKUP($A63,'Loc Coefficients Config'!$A:$G,7,FALSE),VLOOKUP(G63,'Loc Coefficients Location'!A:D,4,FALSE)),"") | L63: =IF(ISNUMBER(K63),ROUND($F63*K63,2),"") | M63: =IF(ISNUMBER(F63),IF(G63="",VLOOKUP($A63,'Loc Coefficients Config'!$A:$H,8,FALSE),VLOOKUP(G63,'Loc Coefficients Location'!A:E,5,FALSE)),"") | N63: =IF(ISNUMBER(M63),ROUND($F63*M63,2),"") | O63: =IF(ISNUMBER(F63),IF(G63="",VLOOKUP($A63,'Loc Coefficients Config'!$A:$I,9,FALSE),VLOOKUP(G63,'Loc Coefficients Location'!A:F,6,FALSE)),"") | P63: =IF(ISNUMBER(O63),ROUND($F63*O63,2),"")
A64: Cat1 Conf7 DL160 Gen10 | B64: HPE ProLiant DL160 Gen10 | C64: 878973-B21 | F64: 872.07 | H64: =IF(ISNUMBER($F64),ROUND($F64*H$1,2),"") -> 234.49 | I64: =IF(ISNUMBER($F64),ROUND($F64*I$1,2),"") -> 120.66 | J64: =IF(ISNUMBER($F64),ROUND($F64*J$1,2),"") -> 82.87 | K64: =IF(ISNUMBER(F64),IF(G64="",VLOOKUP($A64,'Loc Coefficients Config'!$A:$G,7,FALSE),VLOOKUP(G64,'Loc Coefficients Location'!A:D,4,FALSE)),"") -> 0.2124378 | L64: =IF(ISNUMBER(K64),ROUND($F64*K64,2),"") -> 185.26 | M64: =IF(ISNUMBER(F64),IF(G64="",VLOOKUP($A64,'Loc Coefficients Config'!$A:$H,8,FALSE),VLOOKUP(G64,'Loc Coefficients Location'!A:E,5,FALSE)),"") -> 0.11320259 | N64: =IF(ISNUMBER(M64),ROUND($F64*M64,2),"") -> 98.72 | O64: =IF(ISNUMBER(F64),IF(G64="",VLOOKUP($A64,'Loc Coefficients Config'!$A:$I,9,FALSE),VLOOKUP(G64,'Loc Coefficients Location'!A:F,6,FALSE)),"") -> 0.083687894 | P64: =IF(ISNUMBER(O64),ROUND($F64*O64,2),"") -> 72.98
A65: Serveur rack 1U évolutif bi-socket INTEL DL160 Gen10 | B65: HPE DL160 Gen10 8SFF CTO Server | C65: 878973-B21 | D65: 1 | G65: PC_SE/PLX86 | H65: =IF(ISNUMBER($F65),ROUND($F65*H$1,2),"") | I65: =IF(ISNUMBER($F65),ROUND($F65*I$1,2),"") | J65: =IF(ISNUMBER($F65),ROUND($F65*J$1,2),"") | K65: =IF(ISNUMBER(F65),IF(G65="",VLOOKUP($A65,'Loc Coefficients Config'!$A:$G,7,FALSE),VLOOKUP(G65,'Loc Coefficients Location'!A:D,4,FALSE)),"") | L65: =IF(ISNUMBER(K65),ROUND($F65*K65,2),"") | M65: =IF(ISNUMBER(F65),IF(G65="",VLOOKUP($A65,'Loc Coefficients Config'!$A:$H,8,FALSE),VLOOKUP(G65,'Loc Coefficients Location'!A:E,5,FALSE)),"") | N65: =IF(ISNUMBER(M65),ROUND($F65*M65,2),"") | O65: =IF(ISNUMBER(F65),IF(G65="",VLOOKUP($A65,'Loc Coefficients Config'!$A:$I,9,FALSE),VLOOKUP(G65,'Loc Coefficients Location'!A:F,6,FALSE)),"") | P65: =IF(ISNUMBER(O65),ROUND($F65*O65,2),"")
A66: Processeur 64 bits Intel Xeon Silver 4210R (2,40 GHz de base / 3,20 Ghz Turbo / 10 cœurs / 20 threads / 13,75 Mo Smart Cache / 100W TDP) | B66: Intel Xeon-S 4210R FIO Kit for DL160 G10 | C66: P21191-L21 | D66: 1 | G66: PC_SE/PLX86 | H66: =IF(ISNUMBER($F66),ROUND($F66*H$1,2),"") | I66: =IF(ISNUMBER($F66),ROUND($F66*I$1,2),"") | J66: =IF(ISNUMBER($F66),ROUND($F66*J$1,2),"") | K66: =IF(ISNUMBER(F66),IF(G66="",VLOOKUP($A66,'Loc Coefficients Config'!$A:$G,7,FALSE),VLOOKUP(G66,'Loc Coefficients Location'!A:D,4,FALSE)),"") | L66: =IF(ISNUMBER(K66),ROUND($F66*K66,2),"") | M66: =IF(ISNUMBER(F66),IF(G66="",VLOOKUP($A66,'Loc Coefficients Config'!$A:$H,8,FALSE),VLOOKUP(G66,'Loc Coefficients Location'!A:E,5,FALSE)),"") | N66: =IF(ISNUMBER(M66),ROUND($F66*M66,2),"") | O66: =IF(ISNUMBER(F66),IF(G66="",VLOOKUP($A66,'Loc Coefficients Config'!$A:$I,9,FALSE),VLOOKUP(G66,'Loc Coefficients Location'!A:F,6,FALSE)),"") | P66: =IF(ISNUMBER(O66),ROUND($F66*O66,2),"")
A67: Barrette mémoire de 32GB HPE DDR4-2933 RDIMM | B67: HPE 32GB 2Rx4 PC4-2933Y-R Smart Kit | C67: P00924-B21 | D67: 2 | G67: PC_SE/PLX86 | H67: =IF(ISNUMBER($F67),ROUND($F67*H$1,2),"") | I67: =IF(ISNUMBER($F67),ROUND($F67*I$1,2),"") | J67: =IF(ISNUMBER($F67),ROUND($F67*J$1,2),"") | K67: =IF(ISNUMBER(F67),IF(G67="",VLOOKUP($A67,'Loc Coefficients Config'!$A:$G,7,FALSE),VLOOKUP(G67,'Loc Coefficients Location'!A:D,4,FALSE)),"") | L67: =IF(ISNUMBER(K67),ROUND($F67*K67,2),"") | M67: =IF(ISNUMBER(F67),IF(G67="",VLOOKUP($A67,'Loc Coefficients Config'!$A:$H,8,FALSE),VLOOKUP(G67,'Loc Coefficients Location'!A:E,5,FALSE)),"") | N67: =IF(ISNUMBER(M67),ROUND($F67*M67,2),"") | O67: =IF(ISNUMBER(F67),IF(G67="",VLOOKUP($A67,'Loc Coefficients Config'!$A:$I,9,FALSE),VLOOKUP(G67,'Loc Coefficients Location'!A:F,6,FALSE)),"") | P67: =IF(ISNUMBER(O67),ROUND($F67*O67,2),"")
A68: 2 ports Ethernet 10Gb BASE-T | B68: HPE Eth 10Gb 2p 568T Mmt Adptr | C68: 866470-B21 | D68: 1 | G68: PC_SE/PLX86 | H68: =IF(ISNUMBER($F68),ROUND($F68*H$1,2),"") | I68: =IF(ISNUMBER($F68),ROUND($F68*I$1,2),"") | J68: =IF(ISNUMBER($F68),ROUND($F68*J$1,2),"") | K68: =IF(ISNUMBER(F68),IF(G68="",VLOOKUP($A68,'Loc Coefficients Config'!$A:$G,7,FALSE),VLOOKUP(G68,'Loc Coefficients Location'!A:D,4,FALSE)),"") | L68: =IF(ISNUMBER(K68),ROUND($F68*K68,2),"") | M68: =IF(ISNUMBER(F68),IF(G68="",VLOOKUP($A68,'Loc Coefficients Config'!$A:$H,8,FALSE),VLOOKUP(G68,'Loc Coefficients Location'!A:E,5,FALSE)),"") | N68: =IF(ISNUMBER(M68),ROUND($F68*M68,2),"") | O68: =IF(ISNUMBER(F68),IF(G68="",VLOOKUP($A68,'Loc Coefficients Config'!$A:$I,9,FALSE),VLOOKUP(G68,'Loc Coefficients Location'!A:F,6,FALSE)),"") | P68: =IF(ISNUMBER(O68),ROUND($F68*O68,2),"")
A69: Alimentation Titanium 800W | B69: HPE 800W FS Ti Ht Plg LH Pwr Sply Kit | C69: 865438-B21 | D69: 1 | G69: PC_SE/PLX86 | H69: =IF(ISNUMBER($F69),ROUND($F69*H$1,2),"") | I69: =IF(ISNUMBER($F69),ROUND($F69*I$1,2),"") | J69: =IF(ISNUMBER($F69),ROUND($F69*J$1,2),"") | K69: =IF(ISNUMBER(F69),IF(G69="",VLOOKUP($A69,'Loc Coefficients Config'!$A:$G,7,FALSE),VLOOKUP(G69,'Loc Coefficients Location'!A:D,4,FALSE)),"") | L69: =IF(ISNUMBER(K69),ROUND($F69*K69,2),"") | M69: =IF(ISNUMBER(F69),IF(G69="",VLOOKUP($A69,'Loc Coefficients Config'!$A:$H,8,FALSE),VLOOKUP(G69,'Loc Coefficients Location'!A:E,5,FALSE)),"") | N69: =IF(ISNUMBER(M69),ROUND($F69*M69,2),"") | O69: =IF(ISNUMBER(F69),IF(G69="",VLOOKUP($A69,'Loc Coefficients Config'!$A:$I,9,FALSE),VLOOKUP(G69,'Loc Coefficients Location'!A:F,6,FALSE)),"") | P69: =IF(ISNUMBER(O69),ROUND($F69*O69,2),"")
A70: Licence iLO en version Advanced avec toutes les options activées | B70: HPE iLO Adv 1-svr Lic 1yr Support | C70: 512485-B21 | D70: 1 | G70: SOFTCOST | H70: =IF(ISNUMBER($F70),ROUND($F70*H$1,2),"") | I70: =IF(ISNUMBER($F70),ROUND($F70*I$1,2),"") | J70: =IF(ISNUMBER($F70),ROUND($F70*J$1,2),"") | K70: =IF(ISNUMBER(F70),IF(G70="",VLOOKUP($A70,'Loc Coefficients Config'!$A:$G,7,FALSE),VLOOKUP(G70,'Loc Coefficients Location'!A:D,4,FALSE)),"") | L70: =IF(ISNUMBER(K70),ROUND($F70*K70,2),"") | M70: =IF(ISNUMBER(F70),IF(G70="",VLOOKUP($A70,'Loc Coefficients Config'!$A:$H,8,FALSE),VLOOKUP(G70,'Loc Coefficients Location'!A:E,5,FALSE)),"") | N70: =IF(ISNUMBER(M70),ROUND($F70*M70,2),"") | O70: =IF(ISNUMBER(F70),IF(G70="",VLOOKUP($A70,'Loc Coefficients Config'!$A:$I,9,FALSE),VLOOKUP(G70,'Loc Coefficients Location'!A:F,6,FALSE)),"") | P70: =IF(ISNUMBER(O70),ROUND($F70*O70,2),"")
A71: Cable SATA | B71: HPE DL160 G10 8SFF Emb SATA FIO Cbl Kit | C71: 866446-B21 | D71: 1 | G71: PC_SE/PLX86 | H71: =IF(ISNUMBER($F71),ROUND($F71*H$1,2),"") | I71: =IF(ISNUMBER($F71),ROUND($F71*I$1,2),"") | J71: =IF(ISNUMBER($F71),ROUND($F71*J$1,2),"") | K71: =IF(ISNUMBER(F71),IF(G71="",VLOOKUP($A71,'Loc Coefficients Config'!$A:$G,7,FALSE),VLOOKUP(G71,'Loc Coefficients Location'!A:D,4,FALSE)),"") | L71: =IF(ISNUMBER(K71),ROUND($F71*K71,2),"") | M71: =IF(ISNUMBER(F71),IF(G71="",VLOOKUP($A71,'Loc Coefficients Config'!$A:$H,8,FALSE),VLOOKUP(G71,'Loc Coefficients Location'!A:E,5,FALSE)),"") | N71: =IF(ISNUMBER(M71),ROUND($F71*M71,2),"") | O71: =IF(ISNUMBER(F71),IF(G71="",VLOOKUP($A71,'Loc Coefficients Config'!$A:$I,9,FALSE),VLOOKUP(G71,'Loc Coefficients Location'!A:F,6,FALSE)),"") | P71: =IF(ISNUMBER(O71),ROUND($F71*O71,2),"")
A72: Kit d'Alimentation redondante | B72: HPE DL160/180 Gen10 RPS Enablement Kit | C72: 866442-B21 | D72: 1 | G72: PC_SE/PLX86 | H72: =IF(ISNUMBER($F72),ROUND($F72*H$1,2),"") | I72: =IF(ISNUMBER($F72),ROUND($F72*I$1,2),"") | J72: =IF(ISNUMBER($F72),ROUND($F72*J$1,2),"") | K72: =IF(ISNUMBER(F72),IF(G72="",VLOOKUP($A72,'Loc Coefficients Config'!$A:$G,7,FALSE),VLOOKUP(G72,'Loc Coefficients Location'!A:D,4,FALSE)),"") | L72: =IF(ISNUMBER(K72),ROUND($F72*K72,2),"") | M72: =IF(ISNUMBER(F72),IF(G72="",VLOOKUP($A72,'Loc Coefficients Config'!$A:$H,8,FALSE),VLOOKUP(G72,'Loc Coefficients Location'!A:E,5,FALSE)),"") | N72: =IF(ISNUMBER(M72),ROUND($F72*M72,2),"") | O72: =IF(ISNUMBER(F72),IF(G72="",VLOOKUP($A72,'Loc Coefficients Config'!$A:$I,9,FALSE),VLOOKUP(G72,'Loc Coefficients Location'!A:F,6,FALSE)),"") | P72: =IF(ISNUMBER(O72),ROUND($F72*O72,2),"")
A73: 1 kit de rail pour rack | B73: HPE 1U SFF Easy Install Rail Kit | C73: 734807-B21 | D73: 1 | G73: PC_SE/PLX86 | H73: =IF(ISNUMBER($F73),ROUND($F73*H$1,2),"") | I73: =IF(ISNUMBER($F73),ROUND($F73*I$1,2),"") | J73: =IF(ISNUMBER($F73),ROUND($F73*J$1,2),"") | K73: =IF(ISNUMBER(F73),IF(G73="",VLOOKUP($A73,'Loc Coefficients Config'!$A:$G,7,FALSE),VLOOKUP(G73,'Loc Coefficients Location'!A:D,4,FALSE)),"") | L73: =IF(ISNUMBER(K73),ROUND($F73*K73,2),"") | M73: =IF(ISNUMBER(F73),IF(G73="",VLOOKUP($A73,'Loc Coefficients Config'!$A:$H,8,FALSE),VLOOKUP(G73,'Loc Coefficients Location'!A:E,5,FALSE)),"") | N73: =IF(ISNUMBER(M73),ROUND($F73*M73,2),"") | O73: =IF(ISNUMBER(F73),IF(G73="",VLOOKUP($A73,'Loc Coefficients Config'!$A:$I,9,FALSE),VLOOKUP(G73,'Loc Coefficients Location'!A:F,6,FALSE)),"") | P73: =IF(ISNUMBER(O73),ROUND($F73*O73,2),"")
A74: Suppression des câbles électriques par défaut | B74: HPE Remove Standard Power Cords | C74: 469774-409 | D74: 1 | G74: SOFTCOST | H74: =IF(ISNUMBER($F74),ROUND($F74*H$1,2),"") | I74: =IF(ISNUMBER($F74),ROUND($F74*I$1,2),"") | J74: =IF(ISNUMBER($F74),ROUND($F74*J$1,2),"") | K74: =IF(ISNUMBER(F74),IF(G74="",VLOOKUP($A74,'Loc Coefficients Config'!$A:$G,7,FALSE),VLOOKUP(G74,'Loc Coefficients Location'!A:D,4,FALSE)),"") | L74: =IF(ISNUMBER(K74),ROUND($F74*K74,2),"") | M74: =IF(ISNUMBER(F74),IF(G74="",VLOOKUP($A74,'Loc Coefficients Config'!$A:$H,8,FALSE),VLOOKUP(G74,'Loc Coefficients Location'!A:E,5,FALSE)),"") | N74: =IF(ISNUMBER(M74),ROUND($F74*M74,2),"") | O74: =IF(ISNUMBER(F74),IF(G74="",VLOOKUP($A74,'Loc Coefficients Config'!$A:$I,9,FALSE),VLOOKUP(G74,'Loc Coefficients Location'!A:F,6,FALSE)),"") | P74: =IF(ISNUMBER(O74),ROUND($F74*O74,2),"")
A75: Livraison devant la porte | B75: HPE Door/dock Small Delivery SVC | C75: AC111A | D75: 1 | G75: SOFTCOST | H75: =IF(ISNUMBER($F75),ROUND($F75*H$1,2),"") | I75: =IF(ISNUMBER($F75),ROUND($F75*I$1,2),"") | J75: =IF(ISNUMBER($F75),ROUND($F75*J$1,2),"") | K75: =IF(ISNUMBER(F75),IF(G75="",VLOOKUP($A75,'Loc Coefficients Config'!$A:$G,7,FALSE),VLOOKUP(G75,'Loc Coefficients Location'!A:D,4,FALSE)),"") | L75: =IF(ISNUMBER(K75),ROUND($F75*K75,2),"") | M75: =IF(ISNUMBER(F75),IF(G75="",VLOOKUP($A75,'Loc Coefficients Config'!$A:$H,8,FALSE),VLOOKUP(G75,'Loc Coefficients Location'!A:E,5,FALSE)),"") | N75: =IF(ISNUMBER(M75),ROUND($F75*M75,2),"") | O75: =IF(ISNUMBER(F75),IF(G75="",VLOOKUP($A75,'Loc Coefficients Config'!$A:$I,9,FALSE),VLOOKUP(G75,'Loc Coefficients Location'!A:F,6,FALSE)),"") | P75: =IF(ISNUMBER(O75),ROUND($F75*O75,2),"")
A76: Support 5 ans H+4 ILO | B76: HPE 5Y TC Ess iLO Adv Non BL SVC | C76: HW2P1E | D76: 1 | G76: SOFT/MAINT | H76: =IF(ISNUMBER($F76),ROUND($F76*H$1,2),"") | I76: =IF(ISNUMBER($F76),ROUND($F76*I$1,2),"") | J76: =IF(ISNUMBER($F76),ROUND($F76*J$1,2),"") | K76: =IF(ISNUMBER(F76),IF(G76="",VLOOKUP($A76,'Loc Coefficients Config'!$A:$G,7,FALSE),VLOOKUP(G76,'Loc Coefficients Location'!A:D,4,FALSE)),"") | L76: =IF(ISNUMBER(K76),ROUND($F76*K76,2),"") | M76: =IF(ISNUMBER(F76),IF(G76="",VLOOKUP($A76,'Loc Coefficients Config'!$A:$H,8,FALSE),VLOOKUP(G76,'Loc Coefficients Location'!A:E,5,FALSE)),"") | N76: =IF(ISNUMBER(M76),ROUND($F76*M76,2),"") | O76: =IF(ISNUMBER(F76),IF(G76="",VLOOKUP($A76,'Loc Coefficients Config'!$A:$I,9,FALSE),VLOOKUP(G76,'Loc Coefficients Location'!A:F,6,FALSE)),"") | P76: =IF(ISNUMBER(O76),ROUND($F76*O76,2),"")
A77: Garantie 5 ans J+1 châssis | B77: HPE 5Y TC Bas DL160 Gen10 SVC | C77: HV6T5E | D77: 1 | G77: SOFT/MAINT | H77: =IF(ISNUMBER($F77),ROUND($F77*H$1,2),"") | I77: =IF(ISNUMBER($F77),ROUND($F77*I$1,2),"") | J77: =IF(ISNUMBER($F77),ROUND($F77*J$1,2),"") | K77: =IF(ISNUMBER(F77),IF(G77="",VLOOKUP($A77,'Loc Coefficients Config'!$A:$G,7,FALSE),VLOOKUP(G77,'Loc Coefficients Location'!A:D,4,FALSE)),"") | L77: =IF(ISNUMBER(K77),ROUND($F77*K77,2),"") | M77: =IF(ISNUMBER(F77),IF(G77="",VLOOKUP($A77,'Loc Coefficients Config'!$A:$H,8,FALSE),VLOOKUP(G77,'Loc Coefficients Location'!A:E,5,FALSE)),"") | N77: =IF(ISNUMBER(M77),ROUND($F77*M77,2),"") | O77: =IF(ISNUMBER(F77),IF(G77="",VLOOKUP($A77,'Loc Coefficients Config'!$A:$I,9,FALSE),VLOOKUP(G77,'Loc Coefficients Location'!A:F,6,FALSE)),"") | P77: =IF(ISNUMBER(O77),ROUND($F77*O77,2),"")
H78: =IF(ISNUMBER($F78),ROUND($F78*H$1,2),"") | I78: =IF(ISNUMBER($F78),ROUND($F78*I$1,2),"") | J78: =IF(ISNUMBER($F78),ROUND($F78*J$1,2),"") | K78: =IF(ISNUMBER(F78),IF(G78="",VLOOKUP($A78,'Loc Coefficients Config'!$A:$G,7,FALSE),VLOOKUP(G78,'Loc Coefficients Location'!A:D,4,FALSE)),"") | L78: =IF(ISNUMBER(K78),ROUND($F78*K78,2),"") | M78: =IF(ISNUMBER(F78),IF(G78="",VLOOKUP($A78,'Loc Coefficients Config'!$A:$H,8,FALSE),VLOOKUP(G78,'Loc Coefficients Location'!A:E,5,FALSE)),"") | N78: =IF(ISNUMBER(M78),ROUND($F78*M78,2),"") | O78: =IF(ISNUMBER(F78),IF(G78="",VLOOKUP($A78,'Loc Coefficients Config'!$A:$I,9,FALSE),VLOOKUP(G78,'Loc Coefficients Location'!A:F,6,FALSE)),"") | P78: =IF(ISNUMBER(O78),ROUND($F78*O78,2),"")
A79: Cat1 Conf9 DL180 Gen10 Intel | B79: HPE ProLiant DL180 Gen10 | C79: 879517-B21 | F79: 947.04 | H79: =IF(ISNUMBER($F79),ROUND($F79*H$1,2),"") -> 254.65 | I79: =IF(ISNUMBER($F79),ROUND($F79*I$1,2),"") -> 131.03 | J79: =IF(ISNUMBER($F79),ROUND($F79*J$1,2),"") -> 89.99 | K79: =IF(ISNUMBER(F79),IF(G79="",VLOOKUP($A79,'Loc Coefficients Config'!$A:$G,7,FALSE),VLOOKUP(G79,'Loc Coefficients Location'!A:D,4,FALSE)),"") -> 0.21111232 | L79: =IF(ISNUMBER(K79),ROUND($F79*K79,2),"") -> 199.93 | M79: =IF(ISNUMBER(F79),IF(G79="",VLOOKUP($A79,'Loc Coefficients Config'!$A:$H,8,FALSE),VLOOKUP(G79,'Loc Coefficients Location'!A:E,5,FALSE)),"") -> 0.11261184 | N79: =IF(ISNUMBER(M79),ROUND($F79*M79,2),"") -> 106.65 | O79: =IF(ISNUMBER(F79),IF(G79="",VLOOKUP($A79,'Loc Coefficients Config'!$A:$I,9,FALSE),VLOOKUP(G79,'Loc Coefficients Location'!A:F,6,FALSE)),"") -> 0.083421684 | P79: =IF(ISNUMBER(O79),ROUND($F79*O79,2),"") -> 79
A80: Serveur rack 2U évolutif bi-socket INTEL | B80: HPE DL180 Gen10 8SFF CTO Server | C80: 879517-B21 | D80: 1 | G80: PC_SE/PLX86 | H80: =IF(ISNUMBER($F80),ROUND($F80*H$1,2),"") | I80: =IF(ISNUMBER($F80),ROUND($F80*I$1,2),"") | J80: =IF(ISNUMBER($F80),ROUND($F80*J$1,2),"") | K80: =IF(ISNUMBER(F80),IF(G80="",VLOOKUP($A80,'Loc Coefficients Config'!$A:$G,7,FALSE),VLOOKUP(G80,'Loc Coefficients Location'!A:D,4,FALSE)),"") | L80: =IF(ISNUMBER(K80),ROUND($F80*K80,2),"") | M80: =IF(ISNUMBER(F80),IF(G80="",VLOOKUP($A80,'Loc Coefficients Config'!$A:$H,8,FALSE),VLOOKUP(G80,'Loc Coefficients Location'!A:E,5,FALSE)),"") | N80: =IF(ISNUMBER(M80),ROUND($F80*M80,2),"") | O80: =IF(ISNUMBER(F80),IF(G80="",VLOOKUP($A80,'Loc Coefficients Config'!$A:$I,9,FALSE),VLOOKUP(G80,'Loc Coefficients Location'!A:F,6,FALSE)),"") | P80: =IF(ISNUMBER(O80),ROUND($F80*O80,2),"")
A81: Processeur 64 bits Intel Xeon Silver 4210R (2,40 GHz de base / 3,20 Ghz Turbo / 10 cœurs / 20 threads / 13,75 Mo Smart Cache / 100W TDP) | B81: Intel Xeon-S 4210R FIO Kit for DL180 G10 | C81: P21198-L21 | D81: 1 | G81: PC_SE/PLX86 | H81: =IF(ISNUMBER($F81),ROUND($F81*H$1,2),"") | I81: =IF(ISNUMBER($F81),ROUND($F81*I$1,2),"") | J81: =IF(ISNUMBER($F81),ROUND($F81*J$1,2),"") | K81: =IF(ISNUMBER(F81),IF(G81="",VLOOKUP($A81,'Loc Coefficients Config'!$A:$G,7,FALSE),VLOOKUP(G81,'Loc Coefficients Location'!A:D,4,FALSE)),"") | L81: =IF(ISNUMBER(K81),ROUND($F81*K81,2),"") | M81: =IF(ISNUMBER(F81),IF(G81="",VLOOKUP($A81,'Loc Coefficients Config'!$A:$H,8,FALSE),VLOOKUP(G81,'Loc Coefficients Location'!A:E,5,FALSE)),"") | N81: =IF(ISNUMBER(M81),ROUND($F81*M81,2),"") | O81: =IF(ISNUMBER(F81),IF(G81="",VLOOKUP($A81,'Loc Coefficients Config'!$A:$I,9,FALSE),VLOOKUP(G81,'Loc Coefficients Location'!A:F,6,FALSE)),"") | P81: =IF(ISNUMBER(O81),ROUND($F81*O81,2),"")
A82: Barrette mémoire de 32GB HPE DDR4-2933 RDIMM | B82: HPE 32GB 2Rx4 PC4-2933Y-R Smart Kit | C82: P00924-B21 | D82: 2 | G82: PC_SE/PLX86 | H82: =IF(ISNUMBER($F82),ROUND($F82*H$1,2),"") | I82: =IF(ISNUMBER($F82),ROUND($F82*I$1,2),"") | J82: =IF(ISNUMBER($F82),ROUND($F82*J$1,2),"") | K82: =IF(ISNUMBER(F82),IF(G82="",VLOOKUP($A82,'Loc Coefficients Config'!$A:$G,7,FALSE),VLOOKUP(G82,'Loc Coefficients Location'!A:D,4,FALSE)),"") | L82: =IF(ISNUMBER(K82),ROUND($F82*K82,2),"") | M82: =IF(ISNUMBER(F82),IF(G82="",VLOOKUP($A82,'Loc Coefficients Config'!$A:$H,8,FALSE),VLOOKUP(G82,'Loc Coefficients Location'!A:E,5,FALSE)),"") | N82: =IF(ISNUMBER(M82),ROUND($F82*M82,2),"") | O82: =IF(ISNUMBER(F82),IF(G82="",VLOOKUP($A82,'Loc Coefficients Config'!$A:$I,9,FALSE),VLOOKUP(G82,'Loc Coefficients Location'!A:F,6,FALSE)),"") | P82: =IF(ISNUMBER(O82),ROUND($F82*O82,2),"")
A83: Kit pour emplacement Processeur | B83: HPE DL180 Gen10 CPU1 x8x8x8 Riser Kit | C83: 878484-B21 | D83: 1 | G83: PC_SE/PLX86 | H83: =IF(ISNUMBER($F83),ROUND($F83*H$1,2),"") | I83: =IF(ISNUMBER($F83),ROUND($F83*I$1,2),"") | J83: =IF(ISNUMBER($F83),ROUND($F83*J$1,2),"") | K83: =IF(ISNUMBER(F83),IF(G83="",VLOOKUP($A83,'Loc Coefficients Config'!$A:$G,7,FALSE),VLOOKUP(G83,'Loc Coefficients Location'!A:D,4,FALSE)),"") | L83: =IF(ISNUMBER(K83),ROUND($F83*K83,2),"") | M83: =IF(ISNUMBER(F83),IF(G83="",VLOOKUP($A83,'Loc Coefficients Config'!$A:$H,8,FALSE),VLOOKUP(G83,'Loc Coefficients Location'!A:E,5,FALSE)),"") | N83: =IF(ISNUMBER(M83),ROUND($F83*M83,2),"") | O83: =IF(ISNUMBER(F83),IF(G83="",VLOOKUP($A83,'Loc Coefficients Config'!$A:$I,9,FALSE),VLOOKUP(G83,'Loc Coefficients Location'!A:F,6,FALSE)),"") | P83: =IF(ISNUMBER(O83),ROUND($F83*O83,2),"")
A84: 2 ports Ethernet 10Gb BASE-T | B84: HPE Eth 10Gb 2p 568T Mmt Adptr | C84: 866470-B21 | D84: 1 | G84: PC_SE/PLX86 | H84: =IF(ISNUMBER($F84),ROUND($F84*H$1,2),"") | I84: =IF(ISNUMBER($F84),ROUND($F84*I$1,2),"") | J84: =IF(ISNUMBER($F84),ROUND($F84*J$1,2),"") | K84: =IF(ISNUMBER(F84),IF(G84="",VLOOKUP($A84,'Loc Coefficients Config'!$A:$G,7,FALSE),VLOOKUP(G84,'Loc Coefficients Location'!A:D,4,FALSE)),"") | L84: =IF(ISNUMBER(K84),ROUND($F84*K84,2),"") | M84: =IF(ISNUMBER(F84),IF(G84="",VLOOKUP($A84,'Loc Coefficients Config'!$A:$H,8,FALSE),VLOOKUP(G84,'Loc Coefficients Location'!A:E,5,FALSE)),"") | N84: =IF(ISNUMBER(M84),ROUND($F84*M84,2),"") | O84: =IF(ISNUMBER(F84),IF(G84="",VLOOKUP($A84,'Loc Coefficients Config'!$A:$I,9,FALSE),VLOOKUP(G84,'Loc Coefficients Location'!A:F,6,FALSE)),"") | P84: =IF(ISNUMBER(O84),ROUND($F84*O84,2),"")
A85: Alimentation Titanium 800W | B85: HPE 800W FS Ti Ht Plg LH Pwr Sply Kit | C85: 865438-B21 | D85: 1 | G85: PC_SE/PLX86 | H85: =IF(ISNUMBER($F85),ROUND($F85*H$1,2),"") | I85: =IF(ISNUMBER($F85),ROUND($F85*I$1,2),"") | J85: =IF(ISNUMBER($F85),ROUND($F85*J$1,2),"") | K85: =IF(ISNUMBER(F85),IF(G85="",VLOOKUP($A85,'Loc Coefficients Config'!$A:$G,7,FALSE),VLOOKUP(G85,'Loc Coefficients Location'!A:D,4,FALSE)),"") | L85: =IF(ISNUMBER(K85),ROUND($F85*K85,2),"") | M85: =IF(ISNUMBER(F85),IF(G85="",VLOOKUP($A85,'Loc Coefficients Config'!$A:$H,8,FALSE),VLOOKUP(G85,'Loc Coefficients Location'!A:E,5,FALSE)),"") | N85: =IF(ISNUMBER(M85),ROUND($F85*M85,2),"") | O85: =IF(ISNUMBER(F85),IF(G85="",VLOOKUP($A85,'Loc Coefficients Config'!$A:$I,9,FALSE),VLOOKUP(G85,'Loc Coefficients Location'!A:F,6,FALSE)),"") | P85: =IF(ISNUMBER(O85),ROUND($F85*O85,2),"")
A86: Licence iLO en version Advanced avec toutes les options activées | B86: HPE iLO Adv 1-svr Lic 1yr Support | C86: 512485-B21 | D86: 1 | G86: SOFTCOST | H86: =IF(ISNUMBER($F86),ROUND($F86*H$1,2),"") | I86: =IF(ISNUMBER($F86),ROUND($F86*I$1,2),"") | J86: =IF(ISNUMBER($F86),ROUND($F86*J$1,2),"") | K86: =IF(ISNUMBER(F86),IF(G86="",VLOOKUP($A86,'Loc Coefficients Config'!$A:$G,7,FALSE),VLOOKUP(G86,'Loc Coefficients Location'!A:D,4,FALSE)),"") | L86: =IF(ISNUMBER(K86),ROUND($F86*K86,2),"") | M86: =IF(ISNUMBER(F86),IF(G86="",VLOOKUP($A86,'Loc Coefficients Config'!$A:$H,8,FALSE),VLOOKUP(G86,'Loc Coefficients Location'!A:E,5,FALSE)),"") | N86: =IF(ISNUMBER(M86),ROUND($F86*M86,2),"") | O86: =IF(ISNUMBER(F86),IF(G86="",VLOOKUP($A86,'Loc Coefficients Config'!$A:$I,9,FALSE),VLOOKUP(G86,'Loc Coefficients Location'!A:F,6,FALSE)),"") | P86: =IF(ISNUMBER(O86),ROUND($F86*O86,2),"")
A87: Cable | B87: HPE DL180 G10 SFF Box3 MB/-p FIO Cbl Kit | C87: 879752-B21 | D87: 1 | G87: PC_SE/PLX86 | H87: =IF(ISNUMBER($F87),ROUND($F87*H$1,2),"") | I87: =IF(ISNUMBER($F87),ROUND($F87*I$1,2),"") | J87: =IF(ISNUMBER($F87),ROUND($F87*J$1,2),"") | K87: =IF(ISNUMBER(F87),IF(G87="",VLOOKUP($A87,'Loc Coefficients Config'!$A:$G,7,FALSE),VLOOKUP(G87,'Loc Coefficients Location'!A:D,4,FALSE)),"") | L87: =IF(ISNUMBER(K87),ROUND($F87*K87,2),"") | M87: =IF(ISNUMBER(F87),IF(G87="",VLOOKUP($A87,'Loc Coefficients Config'!$A:$H,8,FALSE),VLOOKUP(G87,'Loc Coefficients Location'!A:E,5,FALSE)),"") | N87: =IF(ISNUMBER(M87),ROUND($F87*M87,2),"") | O87: =IF(ISNUMBER(F87),IF(G87="",VLOOKUP($A87,'Loc Coefficients Config'!$A:$I,9,FALSE),VLOOKUP(G87,'Loc Coefficients Location'!A:F,6,FALSE)),"") | P87: =IF(ISNUMBER(O87),ROUND($F87*O87,2),"")
A88: Cage pour Alimentation | B88: HPE DL160/180 Gen10 RPS Enablement Kit | C88: 866442-B21 | D88: 1 | G88: PC_SE/PLX86 | H88: =IF(ISNUMBER($F88),ROUND($F88*H$1,2),"") | I88: =IF(ISNUMBER($F88),ROUND($F88*I$1,2),"") | J88: =IF(ISNUMBER($F88),ROUND($F88*J$1,2),"") | K88: =IF(ISNUMBER(F88),IF(G88="",VLOOKUP($A88,'Loc Coefficients Config'!$A:$G,7,FALSE),VLOOKUP(G88,'Loc Coefficients Location'!A:D,4,FALSE)),"") | L88: =IF(ISNUMBER(K88),ROUND($F88*K88,2),"") | M88: =IF(ISNUMBER(F88),IF(G88="",VLOOKUP($A88,'Loc Coefficients Config'!$A:$H,8,FALSE),VLOOKUP(G88,'Loc Coefficients Location'!A:E,5,FALSE)),"") | N88: =IF(ISNUMBER(M88),ROUND($F88*M88,2),"") | O88: =IF(ISNUMBER(F88),IF(G88="",VLOOKUP($A88,'Loc Coefficients Config'!$A:$I,9,FALSE),VLOOKUP(G88,'Loc Coefficients Location'!A:F,6,FALSE)),"") | P88: =IF(ISNUMBER(O88),ROUND($F88*O88,2),"")
A89: Suppression des câbles électriques par défaut | B89: HPE Remove Standard Power Cords | C89: 469774-409 | D89: 1 | G89: SOFTCOST | H89: =IF(ISNUMBER($F89),ROUND($F89*H$1,2),"") | I89: =IF(ISNUMBER($F89),ROUND($F89*I$1,2),"") | J89: =IF(ISNUMBER($F89),ROUND($F89*J$1,2),"") | K89: =IF(ISNUMBER(F89),IF(G89="",VLOOKUP($A89,'Loc Coefficients Config'!$A:$G,7,FALSE),VLOOKUP(G89,'Loc Coefficients Location'!A:D,4,FALSE)),"") | L89: =IF(ISNUMBER(K89),ROUND($F89*K89,2),"") | M89: =IF(ISNUMBER(F89),IF(G89="",VLOOKUP($A89,'Loc Coefficients Config'!$A:$H,8,FALSE),VLOOKUP(G89,'Loc Coefficients Location'!A:E,5,FALSE)),"") | N89: =IF(ISNUMBER(M89),ROUND($F89*M89,2),"") | O89: =IF(ISNUMBER(F89),IF(G89="",VLOOKUP($A89,'Loc Coefficients Config'!$A:$I,9,FALSE),VLOOKUP(G89,'Loc Coefficients Location'!A:F,6,FALSE)),"") | P89: =IF(ISNUMBER(O89),ROUND($F89*O89,2),"")
A90: 1 kit de rail pour rack | B90: HPE 2U SFF Easy Install Rail Kit | C90: 733660-B21 | D90: 1 | G90: PC_SE/PLX86 | H90: =IF(ISNUMBER($F90),ROUND($F90*H$1,2),"") | I90: =IF(ISNUMBER($F90),ROUND($F90*I$1,2),"") | J90: =IF(ISNUMBER($F90),ROUND($F90*J$1,2),"") | K90: =IF(ISNUMBER(F90),IF(G90="",VLOOKUP($A90,'Loc Coefficients Config'!$A:$G,7,FALSE),VLOOKUP(G90,'Loc Coefficients Location'!A:D,4,FALSE)),"") | L90: =IF(ISNUMBER(K90),ROUND($F90*K90,2),"") | M90: =IF(ISNUMBER(F90),IF(G90="",VLOOKUP($A90,'Loc Coefficients Config'!$A:$H,8,FALSE),VLOOKUP(G90,'Loc Coefficients Location'!A:E,5,FALSE)),"") | N90: =IF(ISNUMBER(M90),ROUND($F90*M90,2),"") | O90: =IF(ISNUMBER(F90),IF(G90="",VLOOKUP($A90,'Loc Coefficients Config'!$A:$I,9,FALSE),VLOOKUP(G90,'Loc Coefficients Location'!A:F,6,FALSE)),"") | P90: =IF(ISNUMBER(O90),ROUND($F90*O90,2),"")
A91: Livraison devant la porte | B91: HPE Door/dock Medium Delivery SVC | C91: AC114A | D91: 1 | G91: SOFTCOST | H91: =IF(ISNUMBER($F91),ROUND($F91*H$1,2),"") | I91: =IF(ISNUMBER($F91),ROUND($F91*I$1,2),"") | J91: =IF(ISNUMBER($F91),ROUND($F91*J$1,2),"") | K91: =IF(ISNUMBER(F91),IF(G91="",VLOOKUP($A91,'Loc Coefficients Config'!$A:$G,7,FALSE),VLOOKUP(G91,'Loc Coefficients Location'!A:D,4,FALSE)),"") | L91: =IF(ISNUMBER(K91),ROUND($F91*K91,2),"") | M91: =IF(ISNUMBER(F91),IF(G91="",VLOOKUP($A91,'Loc Coefficients Config'!$A:$H,8,FALSE),VLOOKUP(G91,'Loc Coefficients Location'!A:E,5,FALSE)),"") | N91: =IF(ISNUMBER(M91),ROUND($F91*M91,2),"") | O91: =IF(ISNUMBER(F91),IF(G91="",VLOOKUP($A91,'Loc Coefficients Config'!$A:$I,9,FALSE),VLOOKUP(G91,'Loc Coefficients Location'!A:F,6,FALSE)),"") | P91: =IF(ISNUMBER(O91),ROUND($F91*O91,2),"")
... A93: Garantie 5 ans J+1 châssis | B93: HPE 5Y TC Bas DL180 Gen10 SVC | C93: HV6W2E | D93: 1 | G93: SOFT/MAINT | H93: =IF(ISNUMBER($F93),ROUND($F93*H$1,2),"") | I93: =IF(ISNUMBER($F93),ROUND($F93*I$1,2),"") | J93: =IF(ISNUMBER($F93),ROUND($F93*J$1,2),"") | K93: =IF(ISNUMBER(F93),IF(G93="",VLOOKUP($A93,'Loc Coefficients Config'!$A:$G,7,FALSE),VLOOKUP(G93,'Loc Coefficients Location'!A:D,4,FALSE)),"") | L93: =IF(ISNUMBER(K93),ROUND($F93*K93,2),"") | M93: =IF(ISNUMBER(F93),IF(G93="",VLOOKUP($A93,'Loc Coefficients Config'!$A:$H,8,FALSE),VLOOKUP(G93,'Loc Coefficients Location'!A:E,5,FALSE)),"") | N93: =IF(ISNUMBER(M93),ROUND($F93*M93,2),"") | O93: =IF(ISNUMBER(F93),IF(G93="",VLOOKUP($A93,'Loc Coefficients Config'!$A:$I,9,FALSE),VLOOKUP(G93,'Loc Coefficients Location'!A:F,6,FALSE)),"") | P93: =IF(ISNUMBER(O93),ROUND($F93*O93,2),"")
H94: =IF(ISNUMBER($F94),ROUND($F94*H$1,2),"") | I94: =IF(ISNUMBER($F94),ROUND($F94*I$1,2),"") | J94: =IF(ISNUMBER($F94),ROUND($F94*J$1,2),"") | K94: =IF(ISNUMBER(F94),IF(G94="",VLOOKUP($A94,'Loc Coefficients Config'!$A:$G,7,FALSE),VLOOKUP(G94,'Loc Coefficients Location'!A:D,4,FALSE)),"") | L94: =IF(ISNUMBER(K94),ROUND($F94*K94,2),"") | M94: =IF(ISNUMBER(F94),IF(G94="",VLOOKUP($A94,'Loc Coefficients Config'!$A:$H,8,FALSE),VLOOKUP(G94,'Loc Coefficients Location'!A:E,5,FALSE)),"") | N94: =IF(ISNUMBER(M94),ROUND($F94*M94,2),"") | O94: =IF(ISNUMBER(F94),IF(G94="",VLOOKUP($A94,'Loc Coefficients Config'!$A:$I,9,FALSE),VLOOKUP(G94,'Loc Coefficients Location'!A:F,6,FALSE)),"") | P94: =IF(ISNUMBER(O94),ROUND($F94*O94,2),"")
A95: Cat1 Conf8 Tour ML350 Gen11 | B95: HPE ProLiant ML350 Gen11 | C95: P48405-B21 | F95: 1672.91 | H95: =IF(ISNUMBER($F95),ROUND($F95*H$1,2),"") -> 449.82 | I95: =IF(ISNUMBER($F95),ROUND($F95*I$1,2),"") -> 231.47 | J95: =IF(ISNUMBER($F95),ROUND($F95*J$1,2),"") -> 158.97 | K95: =IF(ISNUMBER(F95),IF(G95="",VLOOKUP($A95,'Loc Coefficients Config'!$A:$G,7,FALSE),VLOOKUP(G95,'Loc Coefficients Location'!A:D,4,FALSE)),"") -> 0.21829031 | L95: =IF(ISNUMBER(K95),ROUND($F95*K95,2),"") -> 365.18 | M95: =IF(ISNUMBER(F95),IF(G95="",VLOOKUP($A95,'Loc Coefficients Config'!$A:$H,8,FALSE),VLOOKUP(G95,'Loc Coefficients Location'!A:E,5,FALSE)),"") -> 0.115811 | N95: =IF(ISNUMBER(M95),ROUND($F95*M95,2),"") -> 193.74 | O95: =IF(ISNUMBER(F95),IF(G95="",VLOOKUP($A95,'Loc Coefficients Config'!$A:$I,9,FALSE),VLOOKUP(G95,'Loc Coefficients Location'!A:F,6,FALSE)),"") -> 0.084863318 | P95: =IF(ISNUMBER(O95),ROUND($F95*O95,2),"") -> 141.97
A96: Serveur de type tour ML30 Gen10+ | B96: HPE ML350 Gen11 SFF CTO Server | C96: P48405-B21 | D96: 1 | G96: PC_SE/PLX86 | H96: =IF(ISNUMBER($F96),ROUND($F96*H$1,2),"") | I96: =IF(ISNUMBER($F96),ROUND($F96*I$1,2),"") | J96: =IF(ISNUMBER($F96),ROUND($F96*J$1,2),"") | K96: =IF(ISNUMBER(F96),IF(G96="",VLOOKUP($A96,'Loc Coefficients Config'!$A:$G,7,FALSE),VLOOKUP(G96,'Loc Coefficients Location'!A:D,4,FALSE)),"") | L96: =IF(ISNUMBER(K96),ROUND($F96*K96,2),"") | M96: =IF(ISNUMBER(F96),IF(G96="",VLOOKUP($A96,'Loc Coefficients Config'!$A:$H,8,FALSE),VLOOKUP(G96,'Loc Coefficients Location'!A:E,5,FALSE)),"") | N96: =IF(ISNUMBER(M96),ROUND($F96*M96,2),"") | O96: =IF(ISNUMBER(F96),IF(G96="",VLOOKUP($A96,'Loc Coefficients Config'!$A:$I,9,FALSE),VLOOKUP(G96,'Loc Coefficients Location'!A:F,6,FALSE)),"") | P96: =IF(ISNUMBER(O96),ROUND($F96*O96,2),"")
A97: Processeur 64 bits Intel Xeon Silver 4410Y (2,0 GHz de base / 12 cœurs / 150W TDP) | B97: INT Xeon-S 4410Y CPU for HPE | C97: P49610-B21 | D97: 1 | G97: PC_SE/PLX86 | H97: =IF(ISNUMBER($F97),ROUND($F97*H$1,2),"") | I97: =IF(ISNUMBER($F97),ROUND($F97*I$1,2),"") | J97: =IF(ISNUMBER($F97),ROUND($F97*J$1,2),"") | K97: =IF(ISNUMBER(F97),IF(G97="",VLOOKUP($A97,'Loc Coefficients Config'!$A:$G,7,FALSE),VLOOKUP(G97,'Loc Coefficients Location'!A:D,4,FALSE)),"") | L97: =IF(ISNUMBER(K97),ROUND($F97*K97,2),"") | M97: =IF(ISNUMBER(F97),IF(G97="",VLOOKUP($A97,'Loc Coefficients Config'!$A:$H,8,FALSE),VLOOKUP(G97,'Loc Coefficients Location'!A:E,5,FALSE)),"") | N97: =IF(ISNUMBER(M97),ROUND($F97*M97,2),"") | O97: =IF(ISNUMBER(F97),IF(G97="",VLOOKUP($A97,'Loc Coefficients Config'!$A:$I,9,FALSE),VLOOKUP(G97,'Loc Coefficients Location'!A:F,6,FALSE)),"") | P97: =IF(ISNUMBER(O97),ROUND($F97*O97,2),"")
A98: Barrette mémoire de 32GB HPE DDR5-4800 RDIMM | B98: HPE 32GB 2Rx8 PC5-4800B-R Smart Kit | C98: P43328-B21 | D98: 2 | G98: PC_SE/PLX86 | H98: =IF(ISNUMBER($F98),ROUND($F98*H$1,2),"") | I98: =IF(ISNUMBER($F98),ROUND($F98*I$1,2),"") | J98: =IF(ISNUMBER($F98),ROUND($F98*J$1,2),"") | K98: =IF(ISNUMBER(F98),IF(G98="",VLOOKUP($A98,'Loc Coefficients Config'!$A:$G,7,FALSE),VLOOKUP(G98,'Loc Coefficients Location'!A:D,4,FALSE)),"") | L98: =IF(ISNUMBER(K98),ROUND($F98*K98,2),"") | M98: =IF(ISNUMBER(F98),IF(G98="",VLOOKUP($A98,'Loc Coefficients Config'!$A:$H,8,FALSE),VLOOKUP(G98,'Loc Coefficients Location'!A:E,5,FALSE)),"") | N98: =IF(ISNUMBER(M98),ROUND($F98*M98,2),"") | O98: =IF(ISNUMBER(F98),IF(G98="",VLOOKUP($A98,'Loc Coefficients Config'!$A:$I,9,FALSE),VLOOKUP(G98,'Loc Coefficients Location'!A:F,6,FALSE)),"") | P98: =IF(ISNUMBER(O98),ROUND($F98*O98,2),"")
A99: 2 ports Ethernet 10GbE Base-T OCP (intégré) | B99: BCM 57416 10GbE 2p BASE-T OCP3 Adptr | C99: P10097-B21 | D99: 1 | G99: PC_SE/PLX86 | H99: =IF(ISNUMBER($F99),ROUND($F99*H$1,2),"") | I99: =IF(ISNUMBER($F99),ROUND($F99*I$1,2),"") | J99: =IF(ISNUMBER($F99),ROUND($F99*J$1,2),"") | K99: =IF(ISNUMBER(F99),IF(G99="",VLOOKUP($A99,'Loc Coefficients Config'!$A:$G,7,FALSE),VLOOKUP(G99,'Loc Coefficients Location'!A:D,4,FALSE)),"") | L99: =IF(ISNUMBER(K99),ROUND($F99*K99,2),"") | M99: =IF(ISNUMBER(F99),IF(G99="",VLOOKUP($A99,'Loc Coefficients Config'!$A:$H,8,FALSE),VLOOKUP(G99,'Loc Coefficients Location'!A:E,5,FALSE)),"") | N99: =IF(ISNUMBER(M99),ROUND($F99*M99,2),"") | O99: =IF(ISNUMBER(F99),IF(G99="",VLOOKUP($A99,'Loc Coefficients Config'!$A:$I,9,FALSE),VLOOKUP(G99,'Loc Coefficients Location'!A:F,6,FALSE)),"") | P99: =IF(ISNUMBER(O99),ROUND($F99*O99,2),"")
A100: Alimentation Titanium 1000W | B100: HPE 1000W FS Ti Ht Plg PS Kit | C100: P03178-B21 | D100: 1 | G100: PC_SE/PLX86 | H100: =IF(ISNUMBER($F100),ROUND($F100*H$1,2),"") | I100: =IF(ISNUMBER($F100),ROUND($F100*I$1,2),"") | J100: =IF(ISNUMBER($F100),ROUND($F100*J$1,2),"") | K100: =IF(ISNUMBER(F100),IF(G100="",VLOOKUP($A100,'Loc Coefficients Config'!$A:$G,7,FALSE),VLOOKUP(G100,'Loc Coefficients Location'!A:D,4,FALSE)),"") | L100: =IF(ISNUMBER(K100),ROUND($F100*K100,2),"") | M100: =IF(ISNUMBER(F100),IF(G100="",VLOOKUP($A100,'Loc Coefficients Config'!$A:$H,8,FALSE),VLOOKUP(G100,'Loc Coefficients Location'!A:E,5,FALSE)),"") | N100: =IF(ISNUMBER(M100),ROUND($F100*M100,2),"") | O100: =IF(ISNUMBER(F100),IF(G100="",VLOOKUP($A100,'Loc Coefficients Config'!$A:$I,9,FALSE),VLOOKUP(G100,'Loc Coefficients Location'!A:F,6,FALSE)),"") | P100: =IF(ISNUMBER(O100),ROUND($F100*O100,2),"")
A101: Licence iLO en version Advanced avec toutes les options activées | B101: HPE iLO Adv 1-svr Lic 1yr Support | C101: 512485-B21 | D101: 1 | G101: SOFTCOST | H101: =IF(ISNUMBER($F101),ROUND($F101*H$1,2),"") | I101: =IF(ISNUMBER($F101),ROUND($F101*I$1,2),"") | J101: =IF(ISNUMBER($F101),ROUND($F101*J$1,2),"") | K101: =IF(ISNUMBER(F101),IF(G101="",VLOOKUP($A101,'Loc Coefficients Config'!$A:$G,7,FALSE),VLOOKUP(G101,'Loc Coefficients Location'!A:D,4,FALSE)),"") | L101: =IF(ISNUMBER(K101),ROUND($F101*K101,2),"") | M101: =IF(ISNUMBER(F101),IF(G101="",VLOOKUP($A101,'Loc Coefficients Config'!$A:$H,8,FALSE),VLOOKUP(G101,'Loc Coefficients Location'!A:E,5,FALSE)),"") | N101: =IF(ISNUMBER(M101),ROUND($F101*M101,2),"") | O101: =IF(ISNUMBER(F101),IF(G101="",VLOOKUP($A101,'Loc Coefficients Config'!$A:$I,9,FALSE),VLOOKUP(G101,'Loc Coefficients Location'!A:F,6,FALSE)),"") | P101: =IF(ISNUMBER(O101),ROUND($F101*O101,2),"")
A102: Kit d’activation HPE ProLiant ML350 Gen11 OCP2 | B102: HPE ML350 Gen11 OCP2 Enable Kit | C102: P47231-B21 | D102: 1 | G102: PC_SE/PLX86 | H102: =IF(ISNUMBER($F102),ROUND($F102*H$1,2),"") | I102: =IF(ISNUMBER($F102),ROUND($F102*I$1,2),"") | J102: =IF(ISNUMBER($F102),ROUND($F102*J$1,2),"") | K102: =IF(ISNUMBER(F102),IF(G102="",VLOOKUP($A102,'Loc Coefficients Config'!$A:$G,7,FALSE),VLOOKUP(G102,'Loc Coefficients Location'!A:D,4,FALSE)),"") | L102: =IF(ISNUMBER(K102),ROUND($F102*K102,2),"") | M102: =IF(ISNUMBER(F102),IF(G102="",VLOOKUP($A102,'Loc Coefficients Config'!$A:$H,8,FALSE),VLOOKUP(G102,'Loc Coefficients Location'!A:E,5,FALSE)),"") | N102: =IF(ISNUMBER(M102),ROUND($F102*M102,2),"") | O102: =IF(ISNUMBER(F102),IF(G102="",VLOOKUP($A102,'Loc Coefficients Config'!$A:$I,9,FALSE),VLOOKUP(G102,'Loc Coefficients Location'!A:F,6,FALSE)),"") | P102: =IF(ISNUMBER(O102),ROUND($F102*O102,2),"")
A103: Cable SATA | B103: HPE ML350 Gen11 SFF Emb SATA Cbl Kit | C103: P47232-B21 | D103: 1 | G103: PC_SE/PLX86 | H103: =IF(ISNUMBER($F103),ROUND($F103*H$1,2),"") | I103: =IF(ISNUMBER($F103),ROUND($F103*I$1,2),"") | J103: =IF(ISNUMBER($F103),ROUND($F103*J$1,2),"") | K103: =IF(ISNUMBER(F103),IF(G103="",VLOOKUP($A103,'Loc Coefficients Config'!$A:$G,7,FALSE),VLOOKUP(G103,'Loc Coefficients Location'!A:D,4,FALSE)),"") | L103: =IF(ISNUMBER(K103),ROUND($F103*K103,2),"") | M103: =IF(ISNUMBER(F103),IF(G103="",VLOOKUP($A103,'Loc Coefficients Config'!$A:$H,8,FALSE),VLOOKUP(G103,'Loc Coefficients Location'!A:E,5,FALSE)),"") | N103: =IF(ISNUMBER(M103),ROUND($F103*M103,2),"") | O103: =IF(ISNUMBER(F103),IF(G103="",VLOOKUP($A103,'Loc Coefficients Config'!$A:$I,9,FALSE),VLOOKUP(G103,'Loc Coefficients Location'!A:F,6,FALSE)),"") | P103: =IF(ISNUMBER(O103),ROUND($F103*O103,2),"")
A104: Kit de dissipateurs thermiques Standard | B104: HPE ML350 Gen11 Stnd Heat Sink Kit | C104: P47223-B21 | D104: 1 | G104: PC_SE/PLX86 | H104: =IF(ISNUMBER($F104),ROUND($F104*H$1,2),"") | I104: =IF(ISNUMBER($F104),ROUND($F104*I$1,2),"") | J104: =IF(ISNUMBER($F104),ROUND($F104*J$1,2),"") | K104: =IF(ISNUMBER(F104),IF(G104="",VLOOKUP($A104,'Loc Coefficients Config'!$A:$G,7,FALSE),VLOOKUP(G104,'Loc Coefficients Location'!A:D,4,FALSE)),"") | L104: =IF(ISNUMBER(K104),ROUND($F104*K104,2),"") | M104: =IF(ISNUMBER(F104),IF(G104="",VLOOKUP($A104,'Loc Coefficients Config'!$A:$H,8,FALSE),VLOOKUP(G104,'Loc Coefficients Location'!A:E,5,FALSE)),"") | N104: =IF(ISNUMBER(M104),ROUND($F104*M104,2),"") | O104: =IF(ISNUMBER(F104),IF(G104="",VLOOKUP($A104,'Loc Coefficients Config'!$A:$I,9,FALSE),VLOOKUP(G104,'Loc Coefficients Location'!A:F,6,FALSE)),"") | P104: =IF(ISNUMBER(O104),ROUND($F104*O104,2),"")
...

Sheet Loc Coefficients Crédit-Bail
A1: Category | B1: Equipment | C1: Type | D1: LRF12 | E1: LRF24 | F1: LRF36 | G1: LRF48
A2: PC_SE/PLX86 | B2: HPE ISS Servers (Apollo; SGI; Synergy; Superdome Flex; StoreEasy; Non Stop, Cloudline) | C2: Server | D2: 0.26888624 | E2: 0.13836099 | F2: 0.095025056 | G2: n/a
A3: PC_SE/EDGE | B3: Edgeline/Moonshot | C3: Server | D3: 0.26888624 | E3: 0.13836099 | F3: 0.095025056 | G3: n/a
A4: Store/PRIMERA | B4: Primera, Nimble and Alletra Storage Hardware; and Store SAN; includes MSA, Store Virtual, IAP(RISS), Storeonce, BX(VLS) | C4: Storage | D4: 0.26888624 | E4: 0.13836099 | F4: 0.095025056 | G4: n/a
A5: Store/DTL | B5: StoreEver MSL and ESL Tape Libraries | C5: Storage | D5: 0.26888624 | E5: 0.13836099 | F5: 0.095025056 | G5: n/a
A6: Store/Other | B6: 3rd Party Storage (EMC Storage, IBM, Lenovo, Pure Storage, Net App) & NAS Storage Appliance (Cisco NSS, QNAP) | C6: Storage | D6: 0.26888624 | E6: 0.13836099 | F6: 0.095025056 | G6: n/a
A7: Netwo/HPEN | B7: Aruba Data Center Networking, Cisco & Arista | C7: Networking | D7: 0.26888624 | E7: 0.13836099 | F7: 0.095025056 | G7: n/a
A8: Netwo/ARUBA | B8: Aruba Wireless | C8: Networking | D8: 0.26888624 | E8: 0.13836099 | F8: 0.095025056 | G8: n/a
A9: SOFTCOST | B9: soft cost | C9: SOFT | D9: 0.26888624 | E9: 0.13836099 | F9: 0.095025056 | G9: n/a
A10: SOFT/MAINT | B10: soft cost | C10: SOFT | D10: =D9 -> 0.26888624 | E10: =E9 -> 0.13836099 | F10: =F9 -> 0.095025056 | G10: =G9 -> n/a

Sheet Loc Coefficients Location
A1: Category | B1: Equipment | C1: Type | D1: LRF12 | E1: LRF24 | F1: LRF36 | G1: LRF48
A2: PC_SE/PLX86 | B2: HPE ISS Servers (Apollo; SGI; Synergy; Superdome Flex; StoreEasy; Non Stop, Cloudline) | C2: Server | D2: 0.192537 | E2: 0.104333 | F2: 0.079691 | G2: n/a
A3: PC_SE/CLX86 | B3: HPE ISS Servers (Apollo; SGI; Synergy; Superdome Flex; StoreEasy; Non Stop, Cloudline) | C3: Server | D3: 0.192537 | E3: 0.104333 | F3: 0.079691 | G3: n/a
A4: Store/CRAY | B4: HPE ISS Servers (Apollo; SGI; Synergy; Superdome Flex; StoreEasy; Non Stop, Cloudline) | C4: Server | D4: 0.192537 | E4: 0.104333 | F4: 0.079691 | G4: n/a
A5: PC_SE/DSERV | B5: Edgeline/Moonshot | C5: Server | D5: 0.217214 | E5: 0.116469 | F5: 0.087329 | G5: n/a
A6: PC_SE/EDGE | B6: Edgeline/Moonshot | C6: Server | D6: 0.217214 | E6: 0.116469 | F6: 0.087329 | G6: n/a
A7: Store/SAN | B7: Primera, Nimble and Alletra Storage Hardware; and Store SAN; includes MSA, Store Virtual, IAP(RISS), Storeonce, BX(VLS) | C7: Storage | D7: 0.198014 | E7: 0.107415 | F7: 0.081879 | G7: n/a
A8: Store/PRIMERA | B8: Primera, Nimble and Alletra Storage Hardware; and Store SAN; includes MSA, Store Virtual, IAP(RISS), Storeonce, BX(VLS) | C8: Storage | D8: 0.198014 | E8: 0.107415 | F8: 0.081879 | G8: n/a
A9: Store/DTL | B9: StoreEver MSL and ESL Tape Libraries | C9: Storage | D9: 0.189968 | E9: 0.103552 | F9: 0.081179 | G9: n/a
A10: Store/Other | B10: 3rd Party Storage (EMC Storage, IBM, Lenovo, Pure Storage, Net App) & NAS Storage Appliance (Cisco NSS, QNAP) | C10: Storage | D10: 0.230766 | E10: 0.123132 | F10: 0.088102 | G10: n/a
A11: Netwo/HPEN | B11: Aruba Data Center Networking, Cisco & Arista | C11: Networking | D11: 0.196073 | E11: 0.107189 | F11: 0.080737 | G11: n/a
A12: Netwo/ARUBA | B12: Aruba Wireless | C12: Networking | D12: 0.196073 | E12: 0.107189 | F12: 0.080737 | G12: n/a
A13: SOFTCOST | B13: soft cost | C13: SOFT | D13: 0.268886 | E13: 0.138361 | F13: 0.095025 | G13: n/a
A14: SOFT/SFT | B14: soft cost | C14: SOFT | D14: 0.268886 | E14: 0.138361 | F14: 0.095025 | G14: n/a
A15: FEES/CONS | B15: Maintenance | C15: Support | D15: =D13 -> 0.268886 | E15: =E13 -> 0.138361 | F15: =F13 -> 0.095025 | G15: =G13 -> n/a
A16: SOFT/MAINT | B16: Maintenance | C16: Support | D16: =D14 -> 0.268886 | E16: =E14 -> 0.138361 | F16: =F14 -> 0.095025 | G16: =G14 -> n/a
A17: Mapping | B17: Equipement
A18: Netwo/ARUBA | B18: Aruba Wireless
A19: Netwo/HPEN | B19: Aruba Data Center Networking, Cisco & Arista
A20: Other/Essen | B20: use parent HW lease rate factor
A21: PC_SE/EDGE | B21: Edgeline/Moonshot
A22: PC_SE/PLX86 | B22: HPE ISS Servers (Apollo; SGI; Synergy; Superdome Flex; StoreEasy; Non Stop, Cloudline)
A23: Store/BURA | B23: Primera, Nimble and Alletra Storage Hardware; and Store SAN; includes MSA, Store Virtual, IAP(RISS), Storeonce, BX(VLS)
A24: Store/DTL | B24: StoreEver MSL and ESL Tape Libraries
A25: Store/DTL2 | B25: StoreEver MSL and ESL Tape Libraries
A26: Store/NAS | B26: 3rd Party Storage (EMC Storage, IBM, Lenovo, Pure Storage, Net App) & NAS Storage Appliance (Cisco NSS, QNAP)
A27: Store/Other | B27: 3rd Party Storage (EMC Storage, IBM, Lenovo, Pure Storage, Net App) & NAS Storage Appliance (Cisco NSS, QNAP)
A28: Store/P10000 | B28: Primera, Nimble and Alletra Storage Hardware; and Store SAN; includes MSA, Store Virtual, IAP(RISS), Storeonce, BX(VLS)
... A31: Store/SAN | B31: Primera, Nimble and Alletra Storage Hardware; and Store SAN; includes MSA, Store Virtual, IAP(RISS), Storeonce, BX(VLS)

Sheet Loc Coefficients Config
A2: Désignation Description des matériels | B2: Référence constructeur (le cas échéant) | C2: HPE SKU | D2: Quantités | E2: Tag | F2: TARIFS en €HT | G2: Coefficient Locatif 1 An (4 Trimestres) | H2: Coefficient Locatif 2 Ans (8 Trimestres) | I2: Coefficient Locatif 3 Ans (12 Trimestres)
A3: Cat1 Conf4 Microserver Gen10 Plus v2 | B3: HPE ProLiant MicroServer Gen10 plus v2 | C3: P54644-421 | F3: =VLOOKUP(A3,'Lot4 - BPU'!A:F,6,FALSE) -> 573.47 | G3: 0.19408936 | H3: 0.10502487 | I3: 0.080002776
A4: Cat1 Conf5 DL20 Gen10 plus | B4: HPE ProLiant DL20 Gen10 plus | C4: P44109-B21 | F4: =VLOOKUP(A4,'Lot4 - BPU'!A:F,6,FALSE) -> 310.47 | G4: 0.21791781 | H4: 0.11564498 | I4: 0.084788504
A5: Cat1 Conf10 DL325 Gen10 plus v2 | B5: HPE ProLiant DL325 Gen10 plus V2 | C5: P38471-B21 | F5: =VLOOKUP(A5,'Lot4 - BPU'!A:F,6,FALSE) -> 969.28 | G5: 0.22717399 | H5: 0.11977037 | I5: 0.086647524
A6: Cat1 Conf6 Tour ML30 Gen10 plus | B6: HPE ProLiant ML30 Gen10 plus | C6: P44723-B21 | F6: =VLOOKUP(A6,'Lot4 - BPU'!A:F,6,FALSE) -> 757.93 | G6: 0.23286669 | H6: 0.12230755 | I6: 0.087790851
A7: Cat1 Conf7 DL160 Gen10 | B7: HPE ProLiant DL160 Gen10 | C7: 878973-B21 | F7: =VLOOKUP(A7,'Lot4 - BPU'!A:F,6,FALSE) -> 872.07 | G7: 0.2124378 | H7: 0.11320259 | I7: 0.083687894
A8: Cat1 Conf9 DL180 Gen10 Intel | B8: HPE ProLiant DL180 Gen10 | C8: 879517-B21 | F8: =VLOOKUP(A8,'Lot4 - BPU'!A:F,6,FALSE) -> 947.04 | G8: 0.21111232 | H8: 0.11261184 | I8: 0.083421684
A9: Cat1 Conf8 Tour ML350 Gen11 | B9: HPE ProLiant ML350 Gen11 | C9: P48405-B21 | F9: =VLOOKUP(A9,'Lot4 - BPU'!A:F,6,FALSE) -> 1672.91 | G9: 0.21829031 | H9: 0.115811 | I9: 0.084863318
A10: Cat2 Conf7 DL365 Gen10 plus | B10: HPE ProLiant DL365 Gen10 plus | C10: P38578-B21 | F10: =VLOOKUP(A10,'Lot4 - BPU'!A:F,6,FALSE) -> 1541.3 | G10: 0.21853123 | H10: 0.11591837 | I10: 0.084911703
A11: Cat2 Conf19 DL365 Gen11 | B11: HPE ProLiant DL365 Gen11 | C11: P53933-B21 | F11: =VLOOKUP(A11,'Lot4 - BPU'!A:F,6,FALSE) -> 2237.87 | G11: 0.21123711 | H11: 0.11266746 | I11: 0.083446746
A12: Cat2 Conf10 DL360 Gen10 plus | B12: HPE Proliant DL360 Gen10 plus | C12: P28948-B21 | F12: =VLOOKUP(A12,'Lot4 - BPU'!A:F,6,FALSE) -> 1506.22 | G12: 0.21722717 | H12: 0.11533717 | I12: 0.084649796
A13: Cat2 Conf17 DL360 Gen11 | B13: HPE ProLiant DL360 Gen11 | C13: P52499-B21 | F13: =VLOOKUP(A13,'Lot4 - BPU'!A:F,6,FALSE) -> 1621.7 | G13: 0.2182354 | H13: 0.11578653 | I13: 0.08485229
A14: Cat2 Conf20 DL325 Gen11 | B14: HPE ProLiant DL325 Gen11 | C14: P54199-B21 | F14: =VLOOKUP(A14,'Lot4 - BPU'!A:F,6,FALSE) -> 2295.44 | G14: 0.21057153 | H14: 0.11237081 | I14: 0.083313072
... A54: Cat5 Conf11 StorEver MSL 3040 | B54: StoreEver MSL 3040 | C54: Q6Q62C | F54: =VLOOKUP(A54,'Lot4 - BPU'!A:F,6,FALSE) -> 6025.89 | G54: 0.14369896 | H54: 0.076791451 | I54: 0.057679907
